Workbook

Sheet Names
A5: Country Name | B5: % World GDP | C5: GDP y/y | D5: GDP q/q | E5: Key Rate | F5: Inflation | G5: PMI | H5: Summary | K5: Country Name | L5: % World GDP | M5: Jun-26 | N5: May-26 | O5: Change | P5: Trend | Q5: Summary
A6: United States | B6: =VLOOKUP(A6,Data!$A$51:$L$275,2,FALSE)/SUM(Data!$B$53:$B$275) -> 0.19182681 | C6: =VLOOKUP($A6,Data!$A$51:$L$275,COLUMN(C5),FALSE) -> 0.022 | D6: =VLOOKUP($A6,Data!$A$51:$L$275,COLUMN(D5),FALSE) -> 0 | E6: =VLOOKUP($A6,Data!$A$51:$L$275,COLUMN(E5),FALSE) -> 0.0363 | F6: =VLOOKUP($A6,Data!$A$51:$L$275,COLUMN(F5),FALSE) -> 0.043 | G6: =Tabs!F27 -> 53.9 | H6: =VLOOKUP(A6,$K$6:$Q$28,7,FALSE) -> Growing, slower | K6: Ireland | L6: =VLOOKUP(K6,$A$6:$B$28,2,FALSE) -> 0.0024891812 | M6: =Tabs!AP27 -> 54.9 | N6: =Tabs!AP26 -> 55.9 | O6: =M6-N6 -> -1 | P6: 18 | Q6: Growing, slower
A7: Euro Area | B7: =VLOOKUP(A7,Data!$A$51:$L$275,2,FALSE)/SUM(Data!$B$53:$B$275) -> 0.14558285 | C7: =VLOOKUP($A7,Data!$A$51:$L$275,COLUMN(C6),FALSE) -> 0.003 | D7: =VLOOKUP($A7,Data!$A$51:$L$275,COLUMN(D6),FALSE) -> 0 | E7: =VLOOKUP($A7,Data!$A$51:$L$275,COLUMN(E6),FALSE) -> 0.0193 | F7: =VLOOKUP($A7,Data!$A$51:$L$275,COLUMN(F6),FALSE) -> 0.0314 | G7: =Tabs!N27 -> 51.4 | H7: =VLOOKUP(A7,$K$6:$Q$28,7,FALSE) -> Growing, slower | K7: Czech Republic | L7: =VLOOKUP(K7,$A$6:$B$28,2,FALSE) -> 0.0022608159 | M7: =Tabs!CL27 -> 53.9 | N7: =Tabs!CL26 -> 52.2 | O7: =M7-N7 -> 1.7 | P7: 19 | Q7: Growing, faster
A8: China | B8: =VLOOKUP(A8,Data!$A$51:$L$275,2,FALSE)/SUM(Data!$B$53:$B$275) -> 0.10550474 | C8: =VLOOKUP($A8,Data!$A$51:$L$275,COLUMN(C7),FALSE) -> 0.0446 | D8: =VLOOKUP($A8,Data!$A$51:$L$275,COLUMN(D7),FALSE) -> 0 | E8: =VLOOKUP($A8,Data!$A$51:$L$275,COLUMN(E7),FALSE) -> 0.03 | F8: =VLOOKUP($A8,Data!$A$51:$L$275,COLUMN(F7),FALSE) -> -0.001 | G8: =Tabs!AT27 -> 51.7 | H8: =VLOOKUP(A8,$K$6:$Q$28,7,FALSE) -> Growing, slower | K8: Canada | L8: =VLOOKUP(K8,$A$6:$B$28,2,FALSE) -> 0.020838329 | M8: =Tabs!J27 -> 53 | N8: =Tabs!J26 -> 52.9 | O8: =M8-N8 -> 0.1 | P8: 19 | Q8: Growing, at same rate
A9: Japan | B9: =VLOOKUP(A9,Data!$A$51:$L$275,2,FALSE)/SUM(Data!$B$53:$B$275) -> 0.055960904 | C9: =VLOOKUP($A9,Data!$A$51:$L$275,COLUMN(C8),FALSE) -> 0.0143 | D9: =VLOOKUP($A9,Data!$A$51:$L$275,COLUMN(D8),FALSE) -> 0 | E9: =VLOOKUP($A9,Data!$A$51:$L$275,COLUMN(E8),FALSE) -> 0.0075 | F9: =VLOOKUP($A9,Data!$A$51:$L$275,COLUMN(F8),FALSE) -> 0.0192 | G9: =Tabs!AX27 -> 54.8 | H9: =VLOOKUP(A9,$K$6:$Q$28,7,FALSE) -> Growing, slower | K9: United States | L9: =VLOOKUP(K9,$A$6:$B$28,2,FALSE) -> 0.19182681 | M9: =Tabs!F27 -> 53.9 | N9: =Tabs!F26 -> 55.1 | O9: =M9-N9 -> -1.2 | P9: 49 | Q9: Growing, slower
A10: Germany | B10: =VLOOKUP(A10,Data!$A$51:$L$275,2,FALSE)/SUM(Data!$B$53:$B$275) -> 0.041505384 | C10: =VLOOKUP($A10,Data!$A$51:$L$275,COLUMN(C9),FALSE) -> 0.0072 | D10: =VLOOKUP($A10,Data!$A$51:$L$275,COLUMN(D9),FALSE) -> 0 | E10: =VLOOKUP($A10,Data!$A$51:$L$275,COLUMN(E9),FALSE) -> 0.0238 | F10: =VLOOKUP($A10,Data!$A$51:$L$275,COLUMN(F9),FALSE) -> 0.0202 | G10: =Tabs!V27 -> 50.3 | H10: =VLOOKUP(A10,$K$6:$Q$28,7,FALSE) -> Contracting, from Growing | K10: Spain | L10: =VLOOKUP(K10,$A$6:$B$28,2,FALSE) -> 0.015506 | M10: =Tabs!AH27 -> 49.7 | N10: =Tabs!AH26 -> 51.2 | O10: =M10-N10 -> -1.5 | P10: 12 | Q10: Growing, faster
A11: France | B11: =VLOOKUP(A11,Data!$A$51:$L$275,2,FALSE)/SUM(Data!$B$53:$B$275) -> 0.031228948 | C11: =VLOOKUP($A11,Data!$A$51:$L$275,COLUMN(C10),FALSE) -> 0.009 | D11: =VLOOKUP($A11,Data!$A$51:$L$275,COLUMN(D10),FALSE) -> 0 | E11: =VLOOKUP($A11,Data!$A$51:$L$275,COLUMN(E10),FALSE) -> 0.0238 | F11: =VLOOKUP($A11,Data!$A$51:$L$275,COLUMN(F10),FALSE) -> 0.016 | G11: =Tabs!Z27 -> 51.2 | H11: =VLOOKUP(A11,$K$6:$Q$28,7,FALSE) -> Contracting, faster | K11: Mexico | L11: =VLOOKUP(K11,$A$6:$B$28,2,FALSE) -> 0.014398429 | M11: =Tabs!BN27 -> 51.3 | N11: =Tabs!BN26 -> 49.6 | O11: =M11-N11 -> 1.7 | P11: 15 | Q11: Growing, faster
A12: United Kingdom | B12: =VLOOKUP(A12,Data!$A$51:$L$275,2,FALSE)/SUM(Data!$B$53:$B$275) -> 0.028796858 | C12: =VLOOKUP($A12,Data!$A$51:$L$275,COLUMN(C11),FALSE) -> 0.0169 | D12: =VLOOKUP($A12,Data!$A$51:$L$275,COLUMN(D11),FALSE) -> 0 | E12: =VLOOKUP($A12,Data!$A$51:$L$275,COLUMN(E11),FALSE) -> 0.0373 | F12: =VLOOKUP($A12,Data!$A$51:$L$275,COLUMN(F11),FALSE) -> 0.028 | G12: =Tabs!R27 -> 52.5 | H12: =VLOOKUP(A12,$K$6:$Q$28,7,FALSE) -> Growing, faster | K12: United Kingdom | L12: =VLOOKUP(K12,$A$6:$B$28,2,FALSE) -> 0.028796858 | M12: =Tabs!R27 -> 52.5 | N12: =Tabs!R26 -> 53.9 | O12: =M12-N12 -> -1.4 | P12: 20 | Q12: Growing, faster
A13: Brazil | B13: =VLOOKUP(A13,Data!$A$51:$L$275,2,FALSE)/SUM(Data!$B$53:$B$275) -> 0.025645417 | C13: =VLOOKUP($A13,Data!$A$51:$L$275,COLUMN(C12),FALSE) -> 0.0233 | D13: =VLOOKUP($A13,Data!$A$51:$L$275,COLUMN(D12),FALSE) -> 0 | E13: =VLOOKUP($A13,Data!$A$51:$L$275,COLUMN(E12),FALSE) -> 0.15 | F13: =VLOOKUP($A13,Data!$A$51:$L$275,COLUMN(F12),FALSE) -> 0.0424 | G13: =Tabs!BB27 -> 50.8 | H13: =VLOOKUP(A13,$K$6:$Q$28,7,FALSE) -> Contracting, faster | K13: India | L13: =VLOOKUP(K13,$A$6:$B$28,2,FALSE) -> 0.021432078 | M13: =Tabs!BF27 -> 54.2 | N13: =Tabs!BF26 -> 55 | O13: =M13-N13 -> -0.8 | P13: 13 | Q13: Growing, faster
A14: Russia | B14: =VLOOKUP(A14,Data!$A$51:$L$275,2,FALSE)/SUM(Data!$B$53:$B$275) -> 0.023944096 | C14: =VLOOKUP($A14,Data!$A$51:$L$275,COLUMN(C13),FALSE) -> 0.0113 | D14: =VLOOKUP($A14,Data!$A$51:$L$275,COLUMN(D13),FALSE) -> 0 | E14: =VLOOKUP($A14,Data!$A$51:$L$275,COLUMN(E13),FALSE) -> 0.16 | F14: =VLOOKUP($A14,Data!$A$51:$L$275,COLUMN(F13),FALSE) -> 0.0704 | G14: =Tabs!BJ27 -> 50.3 | H14: =VLOOKUP(A14,$K$6:$Q$28,7,FALSE) -> Growing, faster | K14: Poland | L14: =VLOOKUP(K14,$A$6:$B$28,2,FALSE) -> 0.0059146599 | M14: =Tabs!CP27 -> 46.1 | N14: =Tabs!CP26 -> 49.4 | O14: =M14-N14 -> -3.3 | P14: 2 | Q14: Growing, faster
A15: Italy | B15: =VLOOKUP(A15,Data!$A$51:$L$275,2,FALSE)/SUM(Data!$B$53:$B$275) -> 0.023647221 | C15: =VLOOKUP($A15,Data!$A$51:$L$275,COLUMN(C14),FALSE) -> 0.009 | D15: =VLOOKUP($A15,Data!$A$51:$L$275,COLUMN(D14),FALSE) -> 0 | E15: =VLOOKUP($A15,Data!$A$51:$L$275,COLUMN(E14),FALSE) -> 0.0238 | F15: =VLOOKUP($A15,Data!$A$51:$L$275,COLUMN(F14),FALSE) -> 0.0206 | G15: =Tabs!AD27 -> 52.2 | H15: =VLOOKUP(A15,$K$6:$Q$28,7,FALSE) -> Contracting, at same rate | K15: Turkey | L15: =VLOOKUP(K15,$A$6:$B$28,2,FALSE) -> 0.0093629751 | M15: =Tabs!CH27 -> 47.1 | N15: =Tabs!CH26 -> 49.8 | O15: =M15-N15 -> -2.7 | P15: 4 | Q15: Growing, faster
A16: India | B16: =VLOOKUP(A16,Data!$A$51:$L$275,2,FALSE)/SUM(Data!$B$53:$B$275) -> 0.021432078 | C16: =VLOOKUP($A16,Data!$A$51:$L$275,COLUMN(C15),FALSE) -> 0.0667 | D16: =VLOOKUP($A16,Data!$A$51:$L$275,COLUMN(D15),FALSE) -> 0 | E16: =VLOOKUP($A16,Data!$A$51:$L$275,COLUMN(E15),FALSE) -> 0.0525 | F16: =VLOOKUP($A16,Data!$A$51:$L$275,COLUMN(F15),FALSE) -> 0.042 | G16: =Tabs!BF27 -> 54.2 | H16: =VLOOKUP(A16,$K$6:$Q$28,7,FALSE) -> Growing, faster | K16: Japan | L16: =VLOOKUP(K16,$A$6:$B$28,2,FALSE) -> 0.055960904 | M16: =Tabs!AX27 -> 54.8 | N16: =Tabs!AX26 -> 54.5 | O16: =M16-N16 -> 0.3 | P16: 6 | Q16: Growing, slower
A17: Canada | B17: =VLOOKUP(A17,Data!$A$51:$L$275,2,FALSE)/SUM(Data!$B$53:$B$275) -> 0.020838329 | C17: =VLOOKUP($A17,Data!$A$51:$L$275,COLUMN(C16),FALSE) -> 0.0195 | D17: =VLOOKUP($A17,Data!$A$51:$L$275,COLUMN(D16),FALSE) -> 0 | E17: =VLOOKUP($A17,Data!$A$51:$L$275,COLUMN(E16),FALSE) -> 0.0225 | F17: =VLOOKUP($A17,Data!$A$51:$L$275,COLUMN(F16),FALSE) -> 0.0199 | G17: =Tabs!J27 -> 53 | H17: =VLOOKUP(A17,$K$6:$Q$28,7,FALSE) -> Growing, at same rate | K17: Russia | L17: =VLOOKUP(K17,$A$6:$B$28,2,FALSE) -> 0.023944096 | M17: =Tabs!BJ27 -> 50.3 | N17: =Tabs!BJ26 -> 48.8 | O17: =M17-N17 -> 1.5 | P17: 5 | Q17: Growing, faster
A18: Australia | B18: =VLOOKUP(A18,Data!$A$51:$L$275,2,FALSE)/SUM(Data!$B$53:$B$275) -> 0.017823908 | C18: =VLOOKUP($A18,Data!$A$51:$L$275,COLUMN(C17),FALSE) -> 0.0189 | D18: =VLOOKUP($A18,Data!$A$51:$L$275,COLUMN(D17),FALSE) -> 0 | E18: =VLOOKUP($A18,Data!$A$51:$L$275,COLUMN(E17),FALSE) -> 0.0431 | F18: =VLOOKUP($A18,Data!$A$51:$L$275,COLUMN(F17),FALSE) -> 0.024 | G18: =Tabs!BR27 -> 51.5 | H18: =VLOOKUP(A18,$K$6:$Q$28,7,FALSE) -> Growing, from Contracting | K18: Taiwan | L18: =VLOOKUP(K18,$A$6:$B$28,2,FALSE) -> 0.0055835303 | M18: =Tabs!CD27 -> 55.2 | N18: =Tabs!CD26 -> 56.1 | O18: =M18-N18 -> -0.9 | P18: 15 | Q18: Growing, slower
A19: Spain | B19: =VLOOKUP(A19,Data!$A$51:$L$275,2,FALSE)/SUM(Data!$B$53:$B$275) -> 0.015506 | C19: =VLOOKUP($A19,Data!$A$51:$L$275,COLUMN(C18),FALSE) -> 0.0228 | D19: =VLOOKUP($A19,Data!$A$51:$L$275,COLUMN(D18),FALSE) -> 0 | E19: =VLOOKUP($A19,Data!$A$51:$L$275,COLUMN(E18),FALSE) -> 0.0238 | F19: =VLOOKUP($A19,Data!$A$51:$L$275,COLUMN(F18),FALSE) -> 0.0206 | G19: =Tabs!AH27 -> 49.7 | H19: =VLOOKUP(A19,$K$6:$Q$28,7,FALSE) -> Growing, faster | K19: China | L19: =VLOOKUP(K19,$A$6:$B$28,2,FALSE) -> 0.10550474 | M19: =Tabs!AT27 -> 51.7 | N19: =Tabs!AT26 -> 51.8 | O19: =M19-N19 -> -0.1 | P19: 6 | Q19: Growing, slower
A20: South Korea | B20: =VLOOKUP(A20,Data!$A$51:$L$275,2,FALSE)/SUM(Data!$B$53:$B$275) -> 0.014900832 | C20: =VLOOKUP($A20,Data!$A$51:$L$275,COLUMN(C19),FALSE) -> 0.023 | D20: =VLOOKUP($A20,Data!$A$51:$L$275,COLUMN(D19),FALSE) -> 0 | E20: =VLOOKUP($A20,Data!$A$51:$L$275,COLUMN(E19),FALSE) -> 0.025 | F20: =VLOOKUP($A20,Data!$A$51:$L$275,COLUMN(F19),FALSE) -> 0.0184 | G20: =Tabs!BV27 -> 52.1 | H20: =VLOOKUP(A20,$K$6:$Q$28,7,FALSE) -> Contracting, slower | K20: Australia | L20: =VLOOKUP(K20,$A$6:$B$28,2,FALSE) -> 0.017823908 | M20: =Tabs!BR27 -> 51.5 | N20: =Tabs!BR26 -> 50.7 | O20: =M20-N20 -> 0.8 | P20: 1 | Q20: Growing, from Contracting
A21: Mexico | B21: =VLOOKUP(A21,Data!$A$51:$L$275,2,FALSE)/SUM(Data!$B$53:$B$275) -> 0.014398429 | C21: =VLOOKUP($A21,Data!$A$51:$L$275,COLUMN(C20),FALSE) -> 0.0141 | D21: =VLOOKUP($A21,Data!$A$51:$L$275,COLUMN(D20),FALSE) -> 0 | E21: =VLOOKUP($A21,Data!$A$51:$L$275,COLUMN(E20),FALSE) -> 0.07 | F21: =VLOOKUP($A21,Data!$A$51:$L$275,COLUMN(F20),FALSE) -> 0.0334 | G21: =Tabs!BN27 -> 51.3 | H21: =VLOOKUP(A21,$K$6:$Q$28,7,FALSE) -> Growing, faster | K21: Euro Area | L21: =VLOOKUP(K21,$A$6:$B$28,2,FALSE) -> 0.14558285 | M21: =Tabs!N27 -> 51.4 | N21: =Tabs!N26 -> 51.6 | O21: =M21-N21 -> -0.2 | P21: 17 | Q21: Growing, slower
A22: Indonesia | B22: =VLOOKUP(A22,Data!$A$51:$L$275,2,FALSE)/SUM(Data!$B$53:$B$275) -> 0.0099110517 | C22: =VLOOKUP($A22,Data!$A$51:$L$275,COLUMN(C21),FALSE) -> 0.0482 | D22: =VLOOKUP($A22,Data!$A$51:$L$275,COLUMN(D21),FALSE) -> 0 | E22: =VLOOKUP($A22,Data!$A$51:$L$275,COLUMN(E21),FALSE) -> 0.0475 | F22: =VLOOKUP($A22,Data!$A$51:$L$275,COLUMN(F21),FALSE) -> 0.0224 | G22: =Tabs!BZ27 -> 46.9 | H22: =VLOOKUP(A22,$K$6:$Q$28,7,FALSE) -> Contracting, faster | K22: Germany | L22: =VLOOKUP(K22,$A$6:$B$28,2,FALSE) -> 0.041505384 | M22: =Tabs!V27 -> 50.3 | N22: =Tabs!V26 -> 50.1 | O22: =M22-N22 -> 0.2 | P22: 1 | Q22: Contracting, from Growing
A23: Turkey | B23: =VLOOKUP(A23,Data!$A$51:$L$275,2,FALSE)/SUM(Data!$B$53:$B$275) -> 0.0093629751 | C23: =VLOOKUP($A23,Data!$A$51:$L$275,COLUMN(C22),FALSE) -> 0.0259 | D23: =VLOOKUP($A23,Data!$A$51:$L$275,COLUMN(D22),FALSE) -> 0 | E23: =VLOOKUP($A23,Data!$A$51:$L$275,COLUMN(E22),FALSE) -> 0.38 | F23: =VLOOKUP($A23,Data!$A$51:$L$275,COLUMN(F22),FALSE) -> 0.3067 | G23: =Tabs!CH27 -> 47.1 | H23: =VLOOKUP(A23,$K$6:$Q$28,7,FALSE) -> Growing, faster | K23: Greece | L23: =VLOOKUP(K23,$A$6:$B$28,2,FALSE) -> 0.0027632195 | M23: =Tabs!AL27 -> 53.8 | N23: =Tabs!AL26 -> 53.3 | O23: =M23-N23 -> 0.5 | P23: 3 | Q23: Contracting, slower
A24: Poland | B24: =VLOOKUP(A24,Data!$A$51:$L$275,2,FALSE)/SUM(Data!$B$53:$B$275) -> 0.0059146599 | C24: =VLOOKUP($A24,Data!$A$51:$L$275,COLUMN(C23),FALSE) -> 0.0336 | D24: =VLOOKUP($A24,Data!$A$51:$L$275,COLUMN(D23),FALSE) -> 0 | E24: =VLOOKUP($A24,Data!$A$51:$L$275,COLUMN(E23),FALSE) -> 0.04 | F24: =VLOOKUP($A24,Data!$A$51:$L$275,COLUMN(F23),FALSE) -> 0.0503 | G24: =Tabs!CP27 -> 46.1 | H24: =VLOOKUP(A24,$K$6:$Q$28,7,FALSE) -> Growing, faster | K24: South Korea | L24: =VLOOKUP(K24,$A$6:$B$28,2,FALSE) -> 0.014900832 | M24: =Tabs!BV27 -> 52.1 | N24: =Tabs!BV26 -> 54.8 | O24: =M24-N24 -> -2.7 | P24: 3 | Q24: Contracting, slower
A25: Taiwan | B25: =VLOOKUP(A25,Data!$A$51:$L$275,2,FALSE)/SUM(Data!$B$53:$B$275) -> 0.0055835303 | C25: =VLOOKUP($A25,Data!$A$51:$L$275,COLUMN(C24),FALSE) -> 0.087 | D25: =VLOOKUP($A25,Data!$A$51:$L$275,COLUMN(D24),FALSE) -> 0 | E25: =VLOOKUP($A25,Data!$A$51:$L$275,COLUMN(E24),FALSE) -> 0.0111 | F25: =VLOOKUP($A25,Data!$A$51:$L$275,COLUMN(F24),FALSE) -> 0.0166 | G25: =Tabs!CD27 -> 55.2 | H25: =VLOOKUP(A25,$K$6:$Q$28,7,FALSE) -> Growing, slower | K25: Italy | L25: =VLOOKUP(K25,$A$6:$B$28,2,FALSE) -> 0.023647221 | M25: =Tabs!AD27 -> 52.2 | N25: =Tabs!AD26 -> 52.9 | O25: =M25-N25 -> -0.7 | P25: 2 | Q25: Contracting, at same rate
A26: Greece | B26: =VLOOKUP(A26,Data!$A$51:$L$275,2,FALSE)/SUM(Data!$B$53:$B$275) -> 0.0027632195 | C26: =VLOOKUP($A26,Data!$A$51:$L$275,COLUMN(C25),FALSE) -> 0.0217 | D26: =VLOOKUP($A26,Data!$A$51:$L$275,COLUMN(D25),FALSE) -> 0 | E26: =VLOOKUP($A26,Data!$A$51:$L$275,COLUMN(E25),FALSE) -> 0.0238 | F26: =VLOOKUP($A26,Data!$A$51:$L$275,COLUMN(F25),FALSE) -> 0.0274 | G26: =Tabs!AL27 -> 53.8 | H26: =VLOOKUP(A26,$K$6:$Q$28,7,FALSE) -> Contracting, slower | K26: Brazil | L26: =VLOOKUP(K26,$A$6:$B$28,2,FALSE) -> 0.025645417 | M26: =Tabs!BB27 -> 50.8 | N26: =Tabs!BB26 -> 49.1 | O26: =M26-N26 -> 1.7 | P26: 3 | Q26: Contracting, faster
A27: Ireland | B27: =VLOOKUP(A27,Data!$A$51:$L$275,2,FALSE)/SUM(Data!$B$53:$B$275) -> 0.0024891812 | C27: =VLOOKUP($A27,Data!$A$51:$L$275,COLUMN(C26),FALSE) -> 0.0366 | D27: =VLOOKUP($A27,Data!$A$51:$L$275,COLUMN(D26),FALSE) -> 0 | E27: =VLOOKUP($A27,Data!$A$51:$L$275,COLUMN(E26),FALSE) -> 0.0238 | F27: =VLOOKUP($A27,Data!$A$51:$L$275,COLUMN(F26),FALSE) -> 0.0186 | G27: =Tabs!AP27 -> 54.9 | H27: =VLOOKUP(A27,$K$6:$Q$28,7,FALSE) -> Growing, slower | K27: France | L27: =VLOOKUP(K27,$A$6:$B$28,2,FALSE) -> 0.031228948 | M27: =Tabs!Z27 -> 51.2 | N27: =Tabs!Z26 -> 49.7 | O27: =M27-N27 -> 1.5 | P27: 7 | Q27: Contracting, faster
A28: Czech Republic | B28: =VLOOKUP(A28,Data!$A$51:$L$275,2,FALSE)/SUM(Data!$B$53:$B$275) -> 0.0022608159 | C28: =VLOOKUP($A28,Data!$A$51:$L$275,COLUMN(C27),FALSE) -> 0.0236 | D28: =VLOOKUP($A28,Data!$A$51:$L$275,COLUMN(D27),FALSE) -> 0 | E28: =VLOOKUP($A28,Data!$A$51:$L$275,COLUMN(E27),FALSE) -> 0.035 | F28: =VLOOKUP($A28,Data!$A$51:$L$275,COLUMN(F27),FALSE) -> 0.0233 | G28: =Tabs!CL27 -> 53.9 | H28: =VLOOKUP(A28,$K$6:$Q$28,7,FALSE) -> Growing, faster | K28: Indonesia | L28: =VLOOKUP(K28,$A$6:$B$28,2,FALSE) -> 0.0099110517 | M28: =Tabs!BZ27 -> 46.9 | N28: =Tabs!BZ26 -> 50 | O28: =M28-N28 -> -3.1 | P28: 2 | Q28: Contracting, faster

Sheet Tabs
A1: Rows 26-27 REFRESHED to May/Jun-2026 (S&P Global press releases via web, fetched 2026-07-03; China block = Caixin/RatingDog, HSBC lineage). Rows 4-25 remain the 2012-14 teaching corpus. May row Change left blank (Apr-2026 not tracked). Cross-checks: US ISM Jun 53.3 (May 54.0); China NBS official Jun 50.3 (May 50.0).
A2: Global | E2: US | I2: CA | M2: EZ | Q2: UK | U2: DE | Y2: FR | AC2: IT | AG2: ES | AK2: EL | AO2: IR | AS2: CH | AW2: JP | BA2: BRL | BE2: IND | BI2: RS | BM2: MX | BQ2: AU | BU2: SK | BY2: INS | CC2: TW | CG2: TUR | CK2: CZ | CO2: PL
A3: Date | B3: Index | C3: Change | E3: Date | F3: Index | G3: Change | I3: Date | J3: Index | K3: Change | M3: Date | N3: Index | O3: Change | Q3: Date | R3: Index | S3: Change | U3: Date | V3: Index | W3: Change | Y3: Date | Z3: Index | AA3: Change | AC3: Date | AD3: Index | AE3: Change | AG3: Date | AH3: Index | AI3: Change | AK3: Date | AL3: Index | AM3: Change | AO3: Date | AP3: Index | AQ3: Change | AS3: Date | AT3: Index | AU3: Change | AW3: Date | AX3: Index | AY3: Change | BA3: Date | BB3: Index | BC3: Change | BE3: Date | BF3: Index | BG3: Change | BI3: Date | BJ3: Index | BK3: Change | BM3: Date | BN3: Index | BO3: Change | BQ3: Date | BR3: Index | BS3: Change | BU3: Date | BV3: Index | BW3: Change | BY3: Date | BZ3: Index | CA3: Change | CC3: Date | CD3: Index | CE3: Change | CG3: Date | CH3: Index | CI3: Change | CK3: Date | CL3: Index | CM3: Change | CO3: Date | CP3: Index | CQ3: Change
A4: =Global!A98 -> 41244 | B4: =Global!B98 -> 50 | C4: =Global!C98 -> 0.4 | E4: =US!A98 -> 41244 | F4: =US!B98 -> 54 | G4: =US!C98 -> 1.2 | I4: =CA!A98 -> 41244 | J4: =CA!B98 -> 50.4 | K4: =CA!C98 -> 0 | M4: =EZ!A98 -> 41244 | N4: =EZ!B98 -> 46.1 | O4: =EZ!C98 -> -0.1 | Q4: =UK!A98 -> 41244 | R4: =UK!B98 -> 50.7 | S4: =UK!C98 -> 2.3 | U4: =DE!A98 -> 41244 | V4: =DE!B98 -> 46 | W4: =DE!C98 -> -0.8 | Y4: =FR!A98 -> 41244 | Z4: =FR!B98 -> 44.6 | AA4: =FR!C98 -> 0.1 | AC4: =IT!A98 -> 41244 | AD4: =IT!B98 -> 46.7 | AE4: =IT!C98 -> 1.6 | AG4: =ES!A98 -> 41244 | AH4: =ES!B98 -> 44.6 | AI4: =ES!C98 -> -0.7 | AK4: =ES!A98 -> 41244 | AL4: =EL!B98 -> 41.4 | AM4: =EL!C98 -> -0.4 | AO4: =IR!A98 -> 41244 | AP4: =IR!B98 -> 51.4 | AQ4: =IR!C98 -> -1 | AS4: =CH!A98 -> 41252 | AT4: =CH!B98 -> 51.5 | AU4: =CH!C98 -> 1 | AW4: =JP!A98 -> 41244 | AX4: =JP!B98 -> 45 | AY4: =JP!C98 -> -1.5 | BA4: =BRL!A98 -> 41244 | BB4: =BRL!B98 -> 51.1 | BC4: =BRL!C98 -> -1.1 | BE4: =IND!A98 -> 41244 | BF4: =IND!B98 -> 54.7 | BG4: =IND!C98 -> 1 | BI4: =RS!A98 -> 41244 | BJ4: =RS!B98 -> 50 | BK4: =RS!C98 -> -2.2 | BM4: =MX!A98 -> 41244 | BN4: =MX!B98 -> 57.1 | BO4: =MX!C98 -> 1.5 | BQ4: =AU!A98 -> 41244 | BR4: =AU!B98 -> 44.3 | BS4: =AU!C98 -> 0.7 | BU4: =SK!A98 -> 41244 | BV4: =SK!B98 -> 50.1 | BW4: =SK!C98 -> 1.9 | BY4: =INS!A98 -> 41244 | BZ4: =INS!B98 -> 51.5 | CA4: =INS!C98 -> -0.4 | CC4: =TW!A98 -> 41244 | CD4: =TW!B98 -> 47.4 | CE4: =TW!C98 -> -0.4 | CG4: =TUR!A98 -> 41244 | CH4: =TUR!B98 -> 53.1 | CI4: =TUR!C98 -> 1.5 | CK4: =CZ!A98 -> 41244 | CL4: =CZ!B98 -> 46 | CM4: =CZ!C98 -> -2.2 | CO4: =PL!A98 -> 41244 | CP4: =PL!B98 -> 48.3 | CQ4: =PL!C98 -> 0.1
A5: =Global!A99 -> 41275 | B5: =Global!B99 -> 51.5 | C5: =Global!C99 -> 1.5 | E5: =US!A99 -> 41275 | F5: =US!B99 -> 55.8 | G5: =US!C99 -> 1.8 | I5: =CA!A99 -> 41275 | J5: =CA!B99 -> 50.5 | K5: =CA!C99 -> 0.1 | M5: =EZ!A99 -> 41275 | N5: =EZ!B99 -> 47.9 | O5: =EZ!C99 -> 1.8 | Q5: =UK!A99 -> 41275 | R5: =UK!B99 -> 50.9 | S5: =UK!C99 -> 0.2 | U5: =DE!A99 -> 41275 | V5: =DE!B99 -> 49.8 | W5: =DE!C99 -> 3.8 | Y5: =FR!A99 -> 41275 | Z5: =FR!B99 -> 42.9 | AA5: =FR!C99 -> -1.7 | AC5: =IT!A99 -> 41275 | AD5: =IT!B99 -> 47.8 | AE5: =IT!C99 -> 1.1 | AG5: =ES!A99 -> 41275 | AH5: =ES!B99 -> 46.1 | AI5: =ES!C99 -> 1.5 | AK5: =ES!A99 -> 41275 | AL5: =EL!B99 -> 41.7 | AM5: =EL!C99 -> 0.3 | AO5: =IR!A99 -> 41275 | AP5: =IR!B99 -> 50.3 | AQ5: =IR!C99 -> -1.1 | AS5: =CH!A99 -> 41275 | AT5: =CH!B99 -> 52.3 | AU5: =CH!C99 -> 0.8 | AW5: =JP!A99 -> 41275 | AX5: =JP!B99 -> 47.7 | AY5: =JP!C99 -> 2.7 | BA5: =BRL!A99 -> 41275 | BB5: =BRL!B99 -> 53.2 | BC5: =BRL!C99 -> 2.1 | BE5: =IND!A99 -> 41275 | BF5: =IND!B99 -> 53.2 | BG5: =IND!C99 -> -1.5 | BI5: =RS!A99 -> 41275 | BJ5: =RS!B99 -> 52 | BK5: =RS!C99 -> 2 | BM5: =MX!A99 -> 41275 | BN5: =MX!B99 -> 55 | BO5: =MX!C99 -> -2.1 | BQ5: =AU!A99 -> 41275 | BR5: =AU!B99 -> 40.2 | BS5: =AU!C99 -> -4.1 | BU5: =SK!A99 -> 41275 | BV5: =SK!B99 -> 49.9 | BW5: =SK!C99 -> -0.2 | BY5: =INS!A99 -> 41275 | BZ5: =INS!B99 -> 49.7 | CA5: =INS!C99 -> -1.8 | CC5: =TW!A99 -> 41275 | CD5: =TW!B99 -> 51.5 | CE5: =TW!C99 -> 4.1 | CG5: =TUR!A99 -> 41275 | CH5: =TUR!B99 -> 54 | CI5: =TUR!C99 -> 0.9 | CK5: =CZ!A99 -> 41275 | CL5: =CZ!B99 -> 48.3 | CM5: =CZ!C99 -> 2.3 | CO5: =PL!A99 -> 41275 | CP5: =PL!B99 -> 48.6 | CQ5: =PL!C99 -> 0.3
A6: =Global!A100 -> 41306 | B6: =Global!B100 -> 50.9 | C6: =Global!C100 -> -0.6 | E6: =US!A100 -> 41306 | F6: =US!B100 -> 54.3 | G6: =US!C100 -> -1.5 | I6: =CA!A100 -> 41306 | J6: =CA!B100 -> 51.7 | K6: =CA!C100 -> 1.2 | M6: =EZ!A100 -> 41306 | N6: =EZ!B100 -> 47.9 | O6: =EZ!C100 -> 0 | Q6: =UK!A100 -> 41306 | R6: =UK!B100 -> 48.2 | S6: =UK!C100 -> -2.7 | U6: =DE!A100 -> 41306 | V6: =DE!B100 -> 50.3 | W6: =DE!C100 -> 0.5 | Y6: =FR!A100 -> 41306 | Z6: =FR!B100 -> 43.9 | AA6: =FR!C100 -> 1 | AC6: =IT!A100 -> 41306 | AD6: =IT!B100 -> 45.8 | AE6: =IT!C100 -> -2 | AG6: =ES!A100 -> 41306 | AH6: =ES!B100 -> 46.8 | AI6: =ES!C100 -> 0.7 | AK6: =ES!A100 -> 41306 | AL6: =EL!B100 -> 43 | AM6: =EL!C100 -> 1.3 | AO6: =IR!A100 -> 41306 | AP6: =IR!B100 -> 51.5 | AQ6: =IR!C100 -> 1.2 | AS6: =CH!A100 -> 41307 | AT6: =CH!B100 -> 50.4 | AU6: =CH!C100 -> -1.9 | AW6: =JP!A100 -> 41306 | AX6: =JP!B100 -> 48.5 | AY6: =JP!C100 -> 0.8 | BA6: =BRL!A100 -> 41306 | BB6: =BRL!B100 -> 52.5 | BC6: =BRL!C100 -> -0.7 | BE6: =IND!A100 -> 41306 | BF6: =IND!B100 -> 54.2 | BG6: =IND!C100 -> 1 | BI6: =RS!A100 -> 41306 | BJ6: =RS!B100 -> 52 | BK6: =RS!C100 -> 0 | BM6: =MX!A100 -> 41306 | BN6: =MX!B100 -> 53.4 | BO6: =MX!C100 -> -1.6 | BQ6: =AU!A100 -> 41306 | BR6: =AU!B100 -> 45.6 | BS6: =AU!C100 -> 5.4 | BU6: =SK!A100 -> 41306 | BV6: =SK!B100 -> 50.9 | BW6: =SK!C100 -> 1 | BY6: =INS!A100 -> 41306 | BZ6: =INS!B100 -> 50.5 | CA6: =INS!C100 -> 0.8 | CC6: =TW!A100 -> 41306 | CD6: =TW!B100 -> 51.5 | CE6: =TW!C100 -> 0 | CG6: =TUR!A100 -> 41306 | CH6: =TUR!B100 -> 53.5 | CI6: =TUR!C100 -> -0.5 | CK6: =CZ!A100 -> 41306 | CL6: =CZ!B100 -> 49.9 | CM6: =CZ!C100 -> 1.6 | CO6: =PL!A100 -> 41306 | CP6: =PL!B100 -> 48.9 | CQ6: =PL!C100 -> 0.3
A7: =Global!A101 -> 41334 | B7: =Global!B101 -> 51.2 | C7: =Global!C101 -> 0.3 | E7: =US!A101 -> 41334 | F7: =US!B101 -> 54.6 | G7: =US!C101 -> 0.3 | I7: =CA!A101 -> 41334 | J7: =CA!B101 -> 49.3 | K7: =CA!C101 -> -2.4 | M7: =EZ!A101 -> 41334 | N7: =EZ!B101 -> 46.8 | O7: =EZ!C101 -> -1.1 | Q7: =UK!A101 -> 41334 | R7: =UK!B101 -> 49.3 | S7: =UK!C101 -> 1.1 | U7: =DE!A101 -> 41334 | V7: =DE!B101 -> 49 | W7: =DE!C101 -> -1.3 | Y7: =FR!A101 -> 41334 | Z7: =FR!B101 -> 44 | AA7: =FR!C101 -> 0.1 | AC7: =IT!A101 -> 41334 | AD7: =IT!B101 -> 44.5 | AE7: =IT!C101 -> -1.3 | AG7: =ES!A101 -> 41334 | AH7: =ES!B101 -> 44.2 | AI7: =ES!C101 -> -2.6 | AK7: =ES!A101 -> 41334 | AL7: =EL!B101 -> 42.1 | AM7: =EL!C101 -> -0.9 | AO7: =IR!A101 -> 41334 | AP7: =IR!B101 -> 48.6 | AQ7: =IR!C101 -> -2.9 | AS7: =CH!A101 -> 41336 | AT7: =CH!B101 -> 51.6 | AU7: =CH!C101 -> 1.2 | AW7: =JP!A101 -> 41334 | AX7: =JP!B101 -> 50.4 | AY7: =JP!C101 -> 1.9 | BA7: =BRL!A101 -> 41334 | BB7: =BRL!B101 -> 51.8 | BC7: =BRL!C101 -> -0.7 | BE7: =IND!A101 -> 41334 | BF7: =IND!B101 -> 52 | BG7: =IND!C101 -> -2.2 | BI7: =RS!A101 -> 41334 | BJ7: =RS!B101 -> 50.8 | BK7: =RS!C101 -> -1.2 | BM7: =MX!A101 -> 41334 | BN7: =MX!B101 -> 52.2 | BO7: =MX!C101 -> -1.2 | BQ7: =AU!A101 -> 41334 | BR7: =AU!B101 -> 44.4 | BS7: =AU!C101 -> -1.2 | BU7: =SK!A101 -> 41334 | BV7: =SK!B101 -> 52 | BW7: =SK!C101 -> 1.1 | BY7: =INS!A101 -> 41334 | BZ7: =INS!B101 -> 51.3 | CA7: =INS!C101 -> 0.8 | CC7: =TW!A101 -> 41334 | CD7: =TW!B101 -> 50.2 | CE7: =TW!C101 -> -1.3 | CG7: =TUR!A101 -> 41334 | CH7: =TUR!B101 -> 52.3 | CI7: =TUR!C101 -> -1.2 | CK7: =CZ!A101 -> 41334 | CL7: =CZ!B101 -> 49.1 | CM7: =CZ!C101 -> -0.8 | CO7: =PL!A101 -> 41334 | CP7: =PL!B101 -> 48 | CQ7: =PL!C101 -> -0.9
A8: =Global!A102 -> 41365 | B8: =Global!B102 -> 50.4 | C8: =Global!C102 -> -0.8 | E8: =US!A102 -> 41365 | F8: =US!B102 -> 52.1 | G8: =US!C102 -> -2.5 | I8: =CA!A102 -> 41365 | J8: =CA!B102 -> 50.1 | K8: =CA!C102 -> 0.8 | M8: =EZ!A102 -> 41365 | N8: =EZ!B102 -> 46.7 | O8: =EZ!C102 -> -0.1 | Q8: =UK!A102 -> 41365 | R8: =UK!B102 -> 50.6 | S8: =UK!C102 -> 1.3 | U8: =DE!A102 -> 41365 | V8: =DE!B102 -> 48.1 | W8: =DE!C102 -> -0.9 | Y8: =FR!A102 -> 41365 | Z8: =FR!B102 -> 44.4 | AA8: =FR!C102 -> 0.4 | AC8: =IT!A102 -> 41365 | AD8: =IT!B102 -> 45.5 | AE8: =IT!C102 -> 1 | AG8: =ES!A102 -> 41365 | AH8: =ES!B102 -> 44.7 | AI8: =ES!C102 -> 0.5 | AK8: =ES!A102 -> 41365 | AL8: =EL!B102 -> 45 | AM8: =EL!C102 -> 2.9 | AO8: =IR!A102 -> 41365 | AP8: =IR!B102 -> 48 | AQ8: =IR!C102 -> -0.6 | AS8: =CH!A102 -> 41368 | AT8: =CH!B102 -> 50.4 | AU8: =CH!C102 -> -1.2 | AW8: =JP!A102 -> 41365 | AX8: =JP!B102 -> 51.1 | AY8: =JP!C102 -> 0.7 | BA8: =BRL!A102 -> 41365 | BB8: =BRL!B102 -> 50.8 | BC8: =BRL!C102 -> -1 | BE8: =IND!A102 -> 41365 | BF8: =IND!B102 -> 51 | BG8: =IND!C102 -> -1 | BI8: =RS!A102 -> 41365 | BJ8: =RS!B102 -> 50.6 | BK8: =RS!C102 -> -0.2 | BM8: =MX!A102 -> 41365 | BN8: =MX!B102 -> 51.7 | BO8: =MX!C102 -> -0.5 | BQ8: =AU!A102 -> 41365 | BR8: =AU!B102 -> 36.7 | BS8: =AU!C102 -> -7.7 | BU8: =SK!A102 -> 41365 | BV8: =SK!B102 -> 52.6 | BW8: =SK!C102 -> 0.6 | BY8: =INS!A102 -> 41365 | BZ8: =INS!B102 -> 51.7 | CA8: =INS!C102 -> 0.4 | CC8: =TW!A102 -> 41365 | CD8: =TW!B102 -> 51.2 | CE8: =TW!C102 -> 1 | CG8: =TUR!A102 -> 41365 | CH8: =TUR!B102 -> 51.3 | CI8: =TUR!C102 -> -1 | CK8: =CZ!A102 -> 41365 | CL8: =CZ!B102 -> 49.5 | CM8: =CZ!C102 -> 0.4 | CO8: =PL!A102 -> 41365 | CP8: =PL!B102 -> 48 | CQ8: =PL!C102 -> 0
A9: =Global!A103 -> 41395 | B9: =Global!B103 -> 50.6 | C9: =Global!C103 -> 0.2 | E9: =US!A103 -> 41395 | F9: =US!B103 -> 52.3 | G9: =US!C103 -> 0.2 | I9: =CA!A103 -> 41395 | J9: =CA!B103 -> 53.2 | K9: =CA!C103 -> 3.1 | M9: =EZ!A103 -> 41395 | N9: =EZ!B103 -> 48.3 | O9: =EZ!C103 -> 1.6 | Q9: =UK!A103 -> 41395 | R9: =UK!B103 -> 52.1 | S9: =UK!C103 -> 1.5 | U9: =DE!A103 -> 41395 | V9: =DE!B103 -> 49.4 | W9: =DE!C103 -> 1.3 | Y9: =FR!A103 -> 41395 | Z9: =FR!B103 -> 46.4 | AA9: =FR!C103 -> 2 | AC9: =IT!A103 -> 41395 | AD9: =IT!B103 -> 47.3 | AE9: =IT!C103 -> 1.8 | AG9: =ES!A103 -> 41395 | AH9: =ES!B103 -> 48.1 | AI9: =ES!C103 -> 3.4 | AK9: =ES!A103 -> 41395 | AL9: =EL!B103 -> 45.3 | AM9: =EL!C103 -> 0.3 | AO9: =IR!A103 -> 41395 | AP9: =IR!B103 -> 49.7 | AQ9: =IR!C103 -> 1.7 | AS9: =CH!A103 -> 41399 | AT9: =CH!B103 -> 49.2 | AU9: =CH!C103 -> -1.2 | AW9: =JP!A103 -> 41395 | AX9: =JP!B103 -> 51.5 | AY9: =JP!C103 -> 0.4 | BA9: =BRL!A103 -> 41395 | BB9: =BRL!B103 -> 50.4 | BC9: =BRL!C103 -> -0.4 | BE9: =IND!A103 -> 41395 | BF9: =IND!B103 -> 50.1 | BG9: =IND!C103 -> -0.9 | BI9: =RS!A103 -> 41395 | BJ9: =RS!B103 -> 50.4 | BK9: =RS!C103 -> -0.2 | BM9: =MX!A103 -> 41395 | BN9: =MX!B103 -> 51.8 | BO9: =MX!C103 -> 0.1 | BQ9: =AU!A103 -> 41395 | BR9: =AU!B103 -> 43.8 | BS9: =AU!C103 -> 7.1 | BU9: =SK!A103 -> 41395 | BV9: =SK!B103 -> 51.1 | BW9: =SK!C103 -> -1.5 | BY9: =INS!A103 -> 41395 | BZ9: =INS!B103 -> 51.6 | CA9: =INS!C103 -> -0.1 | CC9: =TW!A103 -> 41395 | CD9: =TW!B103 -> 50.7 | CE9: =TW!C103 -> -0.5 | CG9: =TUR!A103 -> 41395 | CH9: =TUR!B103 -> 51.1 | CI9: =TUR!C103 -> -0.2 | CK9: =CZ!A103 -> 41395 | CL9: =CZ!B103 -> 50.1 | CM9: =CZ!C103 -> 0.6 | CO9: =PL!A103 -> 41395 | CP9: =PL!B103 -> 46.9 | CQ9: =PL!C103 -> -1.1
A10: =Global!A104 -> 41426 | B10: =Global!B104 -> 50.6 | C10: =Global!C104 -> 0 | E10: =US!A104 -> 41426 | F10: =US!B104 -> 51.9 | G10: =US!C104 -> -0.4 | I10: =CA!A104 -> 41426 | J10: =CA!B104 -> 52.4 | K10: =CA!C104 -> -0.8 | M10: =EZ!A104 -> 41426 | N10: =EZ!B104 -> 48.8 | O10: =EZ!C104 -> 0.5 | Q10: =UK!A104 -> 41426 | R10: =UK!B104 -> 53 | S10: =UK!C104 -> 0.9 | U10: =DE!A104 -> 41426 | V10: =DE!B104 -> 48.6 | W10: =DE!C104 -> -0.8 | Y10: =FR!A104 -> 41426 | Z10: =FR!B104 -> 48.4 | AA10: =FR!C104 -> 2 | AC10: =IT!A104 -> 41426 | AD10: =IT!B104 -> 49.1 | AE10: =IT!C104 -> 1.8 | AG10: =ES!A104 -> 41426 | AH10: =ES!B104 -> 50 | AI10: =ES!C104 -> 1.9 | AK10: =ES!A104 -> 41426 | AL10: =EL!B104 -> 45.4 | AM10: =EL!C104 -> 0.1 | AO10: =IR!A104 -> 41426 | AP10: =IR!B104 -> 50.3 | AQ10: =IR!C104 -> 0.6 | AS10: =CH!A104 -> 41431 | AT10: =CH!B104 -> 48.2 | AU10: =CH!C104 -> -1 | AW10: =JP!A104 -> 41426 | AX10: =JP!B104 -> 52.3 | AY10: =JP!C104 -> 0.8 | BA10: =BRL!A104 -> 41426 | BB10: =BRL!B104 -> 50.4 | BC10: =BRL!C104 -> 0 | BE10: =IND!A104 -> 41426 | BF10: =IND!B104 -> 50.3 | BG10: =IND!C104 -> 0.2 | BI10: =RS!A104 -> 41426 | BJ10: =RS!B104 -> 51.7 | BK10: =RS!C104 -> 1.3 | BM10: =MX!A104 -> 41426 | BN10: =MX!B104 -> 51.3 | BO10: =MX!C104 -> -0.5 | BQ10: =AU!A104 -> 41426 | BR10: =AU!B104 -> 49.6 | BS10: =AU!C104 -> 5.8 | BU10: =SK!A104 -> 41426 | BV10: =SK!B104 -> 49.4 | BW10: =SK!C104 -> -1.7 | BY10: =INS!A104 -> 41426 | BZ10: =INS!B104 -> 51 | CA10: =INS!C104 -> -0.6 | CC10: =TW!A104 -> 41426 | CD10: =TW!B104 -> 47.1 | CE10: =TW!C104 -> -3.6 | CG10: =TUR!A104 -> 41426 | CH10: =TUR!B104 -> 51.2 | CI10: =TUR!C104 -> 0.1 | CK10: =CZ!A104 -> 41426 | CL10: =CZ!B104 -> 51 | CM10: =CZ!C104 -> 0.9 | CO10: =PL!A104 -> 41426 | CP10: =PL!B104 -> 48 | CQ10: =PL!C104 -> 1.1
A11: =Global!A105 -> 41456 | B11: =Global!B105 -> 50.8 | C11: =Global!C105 -> 0.2 | E11: =US!A105 -> 41456 | F11: =US!B105 -> 53.7 | G11: =US!C105 -> 1.8 | I11: =CA!A105 -> 41456 | J11: =CA!B105 -> 52 | K11: =CA!C105 -> -0.4 | M11: =EZ!A105 -> 41456 | N11: =EZ!B105 -> 50.3 | O11: =EZ!C105 -> 1.5 | Q11: =UK!A105 -> 41456 | R11: =UK!B105 -> 54.7 | S11: =UK!C105 -> 1.7 | U11: =DE!A105 -> 41456 | V11: =DE!B105 -> 50.7 | W11: =DE!C105 -> 2.1 | Y11: =FR!A105 -> 41456 | Z11: =FR!B105 -> 49.7 | AA11: =FR!C105 -> 1.3 | AC11: =IT!A105 -> 41456 | AD11: =IT!B105 -> 50.4 | AE11: =IT!C105 -> 1.3 | AG11: =ES!A105 -> 41456 | AH11: =ES!B105 -> 49.8 | AI11: =ES!C105 -> -0.2 | AK11: =ES!A105 -> 41456 | AL11: =EL!B105 -> 47 | AM11: =EL!C105 -> 1.6 | AO11: =IR!A105 -> 41456 | AP11: =IR!B105 -> 51 | AQ11: =IR!C105 -> 0.7 | AS11: =CH!A105 -> 41462 | AT11: =CH!B105 -> 47.7 | AU11: =CH!C105 -> -0.5 | AW11: =JP!A105 -> 41456 | AX11: =JP!B105 -> 50.7 | AY11: =JP!C105 -> -1.6 | BA11: =BRL!A105 -> 41456 | BB11: =BRL!B105 -> 48.5 | BC11: =BRL!C105 -> -1.9 | BE11: =IND!A105 -> 41456 | BF11: =IND!B105 -> 50.1 | BG11: =IND!C105 -> -0.2 | BI11: =RS!A105 -> 41456 | BJ11: =RS!B105 -> 49.2 | BK11: =RS!C105 -> -2.5 | BM11: =MX!A105 -> 41456 | BN11: =MX!B105 -> 49.7 | BO11: =MX!C105 -> -1.6 | BQ11: =AU!A105 -> 41456 | BR11: =AU!B105 -> 42 | BS11: =AU!C105 -> -7.6 | BU11: =SK!A105 -> 41456 | BV11: =SK!B105 -> 47.2 | BW11: =SK!C105 -> -2.2 | BY11: =INS!A105 -> 41456 | BZ11: =INS!B105 -> 50.7 | CA11: =INS!C105 -> -0.3 | CC11: =TW!A105 -> 41456 | CD11: =TW!B105 -> 49.5 | CE11: =TW!C105 -> 2.4 | CG11: =TUR!A105 -> 41456 | CH11: =TUR!B105 -> 49.8 | CI11: =TUR!C105 -> -1.4 | CK11: =CZ!A105 -> 41456 | CL11: =CZ!B105 -> 52 | CM11: =CZ!C105 -> 1 | CO11: =PL!A105 -> 41456 | CP11: =PL!B105 -> 49.3 | CQ11: =PL!C105 -> 1.3
A12: =Global!A106 -> 41487 | B12: =Global!B106 -> 51.6 | C12: =Global!C106 -> 0.8 | E12: =US!A106 -> 41487 | F12: =US!B106 -> 53.7 | G12: =US!C106 -> 0 | I12: =CA!A106 -> 41487 | J12: =CA!B106 -> 52.1 | K12: =CA!C106 -> 0.1 | M12: =EZ!A106 -> 41487 | N12: =EZ!B106 -> 51.4 | O12: =EZ!C106 -> 1.1 | Q12: =UK!A106 -> 41487 | R12: =UK!B106 -> 57.3 | S12: =UK!C106 -> 2.6 | U12: =DE!A106 -> 41487 | V12: =DE!B106 -> 51.8 | W12: =DE!C106 -> 1.1 | Y12: =FR!A106 -> 41487 | Z12: =FR!B106 -> 49.7 | AA12: =FR!C106 -> 0 | AC12: =IT!A106 -> 41487 | AD12: =IT!B106 -> 51.3 | AE12: =IT!C106 -> 0.9 | AG12: =ES!A106 -> 41487 | AH12: =ES!B106 -> 51.1 | AI12: =ES!C106 -> 1.3 | AK12: =ES!A106 -> 41487 | AL12: =EL!B106 -> 48.7 | AM12: =EL!C106 -> 1.7 | AO12: =IR!A106 -> 41487 | AP12: =IR!B106 -> 52 | AQ12: =IR!C106 -> 1 | AS12: =CH!A106 -> 41493 | AT12: =CH!B106 -> 50.1 | AU12: =CH!C106 -> 2.4 | AW12: =JP!A106 -> 41487 | AX12: =JP!B106 -> 52.2 | AY12: =JP!C106 -> 1.5 | BA12: =BRL!A106 -> 41487 | BB12: =BRL!B106 -> 49.4 | BC12: =BRL!C106 -> 0.9 | BE12: =IND!A106 -> 41487 | BF12: =IND!B106 -> 48.5 | BG12: =IND!C106 -> -1.6 | BI12: =RS!A106 -> 41487 | BJ12: =RS!B106 -> 49.4 | BK12: =RS!C106 -> 0.2 | BM12: =MX!A106 -> 41487 | BN12: =MX!B106 -> 50.8 | BO12: =MX!C106 -> 1.1 | BQ12: =AU!A106 -> 41487 | BR12: =AU!B106 -> 46.4 | BS12: =AU!C106 -> 4.4 | BU12: =SK!A106 -> 41487 | BV12: =SK!B106 -> 47.5 | BW12: =SK!C106 -> 0.3 | BY12: =INS!A106 -> 41487 | BZ12: =INS!B106 -> 48.5 | CA12: =INS!C106 -> -2.2 | CC12: =TW!A106 -> 41487 | CD12: =TW!B106 -> 48.6 | CE12: =TW!C106 -> -0.9 | CG12: =TUR!A106 -> 41487 | CH12: =TUR!B106 -> 50.9 | CI12: =TUR!C106 -> 1.1 | CK12: =CZ!A106 -> 41487 | CL12: =CZ!B106 -> 53.9 | CM12: =CZ!C106 -> 1.9 | CO12: =PL!A106 -> 41487 | CP12: =PL!B106 -> 51.1 | CQ12: =PL!C106 -> 1.8
A13: =Global!A107 -> 41518 | B13: =Global!B107 -> 51.8 | C13: =Global!C107 -> 0.2 | E13: =US!A107 -> 41518 | F13: =US!B107 -> 52.8 | G13: =US!C107 -> -0.9 | I13: =CA!A107 -> 41518 | J13: =CA!B107 -> 54.2 | K13: =CA!C107 -> 2.1 | M13: =EZ!A107 -> 41518 | N13: =EZ!B107 -> 51.1 | O13: =EZ!C107 -> -0.3 | Q13: =UK!A107 -> 41518 | R13: =UK!B107 -> 56.7 | S13: =UK!C107 -> -0.6 | U13: =DE!A107 -> 41518 | V13: =DE!B107 -> 51.1 | W13: =DE!C107 -> -0.7 | Y13: =FR!A107 -> 41518 | Z13: =FR!B107 -> 49.8 | AA13: =FR!C107 -> 0.1 | AC13: =IT!A107 -> 41518 | AD13: =IT!B107 -> 50.8 | AE13: =IT!C107 -> -0.5 | AG13: =ES!A107 -> 41518 | AH13: =ES!B107 -> 50.7 | AI13: =ES!C107 -> -0.4 | AK13: =ES!A107 -> 41518 | AL13: =EL!B107 -> 47.5 | AM13: =EL!C107 -> -1.2 | AO13: =IR!A107 -> 41518 | AP13: =IR!B107 -> 52.7 | AQ13: =IR!C107 -> 0.7 | AS13: =CH!A107 -> 41524 | AT13: =CH!B107 -> 50.2 | AU13: =CH!C107 -> 0.1 | AW13: =JP!A107 -> 41518 | AX13: =JP!B107 -> 52.5 | AY13: =JP!C107 -> 0.3 | BA13: =BRL!A107 -> 41518 | BB13: =BRL!B107 -> 49.9 | BC13: =BRL!C107 -> 0.5 | BE13: =IND!A107 -> 41518 | BF13: =IND!B107 -> 49.6 | BG13: =IND!C107 -> 1.1 | BI13: =RS!A107 -> 41518 | BJ13: =RS!B107 -> 49.4 | BK13: =RS!C107 -> 0 | BM13: =MX!A107 -> 41518 | BN13: =MX!B107 -> 50 | BO13: =MX!C107 -> -0.8 | BQ13: =AU!A107 -> 41518 | BR13: =AU!B107 -> 51.7 | BS13: =AU!C107 -> 5.3 | BU13: =SK!A107 -> 41518 | BV13: =SK!B107 -> 49.7 | BW13: =SK!C107 -> 2.2 | BY13: =INS!A107 -> 41518 | BZ13: =INS!B107 -> 50.2 | CA13: =INS!C107 -> 1.7 | CC13: =TW!A107 -> 41518 | CD13: =TW!B107 -> 50 | CE13: =TW!C107 -> 1.4 | CG13: =TUR!A107 -> 41518 | CH13: =TUR!B107 -> 54 | CI13: =TUR!C107 -> 3.1 | CK13: =CZ!A107 -> 41518 | CL13: =CZ!B107 -> 53.4 | CM13: =CZ!C107 -> -0.5 | CO13: =PL!A107 -> 41518 | CP13: =PL!B107 -> 52.6 | CQ13: =PL!C107 -> 1.5
A14: =Global!A108 -> 41548 | B14: =Global!B108 -> 52.1 | C14: =Global!C108 -> 0.3 | E14: =US!A108 -> 41548 | F14: =US!B108 -> 51.8 | G14: =US!C108 -> -1 | I14: =CA!A108 -> 41548 | J14: =CA!B108 -> 55.6 | K14: =CA!C108 -> 1.4 | M14: =EZ!A108 -> 41548 | N14: =EZ!B108 -> 51.3 | O14: =EZ!C108 -> 0.2 | Q14: =UK!A108 -> 41548 | R14: =UK!B108 -> 56.5 | S14: =UK!C108 -> -0.2 | U14: =DE!A108 -> 41548 | V14: =DE!B108 -> 51.7 | W14: =DE!C108 -> 0.6 | Y14: =FR!A108 -> 41548 | Z14: =FR!B108 -> 49.1 | AA14: =FR!C108 -> -0.7 | AC14: =IT!A108 -> 41548 | AD14: =IT!B108 -> 50.7 | AE14: =IT!C108 -> -0.1 | AG14: =ES!A108 -> 41548 | AH14: =ES!B108 -> 50.9 | AI14: =ES!C108 -> 0.2 | AK14: =ES!A108 -> 41548 | AL14: =EL!B108 -> 47.3 | AM14: =EL!C108 -> -0.2 | AO14: =IR!A108 -> 41548 | AP14: =IR!B108 -> 54.9 | AQ14: =IR!C108 -> 2.2 | AS14: =CH!A108 -> 41554 | AT14: =CH!B108 -> 50.9 | AU14: =CH!C108 -> 0.7 | AW14: =JP!A108 -> 41548 | AX14: =JP!B108 -> 54.2 | AY14: =JP!C108 -> 1.7 | BA14: =BRL!A108 -> 41548 | BB14: =BRL!B108 -> 50.2 | BC14: =BRL!C108 -> 0.3 | BE14: =IND!A108 -> 41548 | BF14: =IND!B108 -> 49.6 | BG14: =IND!C108 -> 0 | BI14: =RS!A108 -> 41548 | BJ14: =RS!B108 -> 51.8 | BK14: =RS!C108 -> 2.4 | BM14: =MX!A108 -> 41548 | BN14: =MX!B108 -> 50.2 | BO14: =MX!C108 -> 0.2 | BQ14: =AU!A108 -> 41548 | BR14: =AU!B108 -> 53.2 | BS14: =AU!C108 -> 1.5 | BU14: =SK!A108 -> 41548 | BV14: =SK!B108 -> 50.2 | BW14: =SK!C108 -> 0.5 | BY14: =INS!A108 -> 41548 | BZ14: =INS!B108 -> 50.9 | CA14: =INS!C108 -> 0.7 | CC14: =TW!A108 -> 41548 | CD14: =TW!B108 -> 52 | CE14: =TW!C108 -> 2 | CG14: =TUR!A108 -> 41548 | CH14: =TUR!B108 -> 53.3 | CI14: =TUR!C108 -> -0.7 | CK14: =CZ!A108 -> 41548 | CL14: =CZ!B108 -> 54.5 | CM14: =CZ!C108 -> 1.1 | CO14: =PL!A108 -> 41548 | CP14: =PL!B108 -> 53.4 | CQ14: =PL!C108 -> 0.8
A15: =Global!A109 -> 41579 | B15: =Global!B109 -> 53.1 | C15: =Global!C109 -> 1 | E15: =US!A109 -> 41579 | F15: =US!B109 -> 54.7 | G15: =US!C109 -> 2.9 | I15: =CA!A109 -> 41579 | J15: =CA!B109 -> 55.3 | K15: =CA!C109 -> -0.3 | M15: =EZ!A109 -> 41579 | N15: =EZ!B109 -> 51.6 | O15: =EZ!C109 -> 0.3 | Q15: =UK!A109 -> 41579 | R15: =UK!B109 -> 58.1 | S15: =UK!C109 -> 1.6 | U15: =DE!A109 -> 41579 | V15: =DE!B109 -> 52.7 | W15: =DE!C109 -> 1 | Y15: =FR!A109 -> 41579 | Z15: =FR!B109 -> 48.4 | AA15: =FR!C109 -> -0.7 | AC15: =IT!A109 -> 41579 | AD15: =IT!B109 -> 51.4 | AE15: =IT!C109 -> 0.7 | AG15: =ES!A109 -> 41579 | AH15: =ES!B109 -> 48.6 | AI15: =ES!C109 -> -2.3 | AK15: =ES!A109 -> 41579 | AL15: =EL!B109 -> 49.2 | AM15: =EL!C109 -> 1.9 | AO15: =IR!A109 -> 41579 | AP15: =IR!B109 -> 52.4 | AQ15: =IR!C109 -> -2.5 | AS15: =CH!A109 -> 41585 | AT15: =CH!B109 -> 50.8 | AU15: =CH!C109 -> -0.1 | AW15: =JP!A109 -> 41579 | AX15: =JP!B109 -> 55.1 | AY15: =JP!C109 -> 0.9 | BA15: =BRL!A109 -> 41579 | BB15: =BRL!B109 -> 49.7 | BC15: =BRL!C109 -> -0.5 | BE15: =IND!A109 -> 41579 | BF15: =IND!B109 -> 51.3 | BG15: =IND!C109 -> 1.7 | BI15: =RS!A109 -> 41579 | BJ15: =RS!B109 -> 49.4 | BK15: =RS!C109 -> -2.4 | BM15: =MX!A109 -> 41579 | BN15: =MX!B109 -> 51.9 | BO15: =MX!C109 -> 1.7 | BQ15: =AU!A109 -> 41579 | BR15: =AU!B109 -> 47.7 | BS15: =AU!C109 -> -5.5 | BU15: =SK!A109 -> 41579 | BV15: =SK!B109 -> 50.4 | BW15: =SK!C109 -> 0.2 | BY15: =INS!A109 -> 41579 | BZ15: =INS!B109 -> 50.3 | CA15: =INS!C109 -> -0.6 | CC15: =TW!A109 -> 41579 | CD15: =TW!B109 -> 53 | CE15: =TW!C109 -> 1 | CG15: =TUR!A109 -> 41579 | CH15: =TUR!B109 -> 55 | CI15: =TUR!C109 -> 1.7 | CK15: =CZ!A109 -> 41579 | CL15: =CZ!B109 -> 55.4 | CM15: =CZ!C109 -> 0.9 | CO15: =PL!A109 -> 41579 | CP15: =PL!B109 -> 54.4 | CQ15: =PL!C109 -> 1
... A25: =Global!A119 -> 41883 | B25: =Global!B119 -> 52.2 | C25: =Global!C119 -> -0.4 | E25: =US!A119 -> 41883 | F25: =US!B119 -> 57.5 | G25: =US!C119 -> -0.4 | I25: =CA!A119 -> 41883 | J25: =CA!B119 -> 53.5 | K25: =CA!C119 -> -1.3 | M25: =EZ!A119 -> 41883 | N25: =EZ!B119 -> 50.3 | O25: =EZ!C119 -> -0.4 | Q25: =UK!A119 -> 41883 | R25: =UK!B119 -> 51.6 | S25: =UK!C119 -> -0.9 | U25: =DE!A119 -> 41883 | V25: =DE!B119 -> 49.9 | W25: =DE!C119 -> -1.5 | Y25: =FR!A119 -> 41883 | Z25: =FR!B119 -> 48.8 | AA25: =FR!C119 -> 1.9 | AC25: =IT!A119 -> 41883 | AD25: =IT!B119 -> 50.7 | AE25: =IT!C119 -> 0.9 | AG25: =ES!A119 -> 41883 | AH25: =ES!B119 -> 52.6 | AI25: =ES!C119 -> -0.2 | AK25: =ES!A119 -> 41883 | AL25: =EL!B119 -> 48.4 | AM25: =EL!C119 -> -1.7 | AO25: =IR!A119 -> 41883 | AP25: =IR!B119 -> 55.7 | AQ25: =IR!C119 -> -1.6 | AS25: =CH!A119 -> 41883 | AT25: =CH!B119 -> 51.1 | AU25: =CH!C119 -> 0.9 | AW25: =JP!A119 -> 41883 | AX25: =JP!B119 -> 51.7 | AY25: =JP!C119 -> -0.5 | BA25: =BRL!A119 -> 41883 | BB25: =BRL!B119 -> 49.3 | BC25: =BRL!C119 -> -0.9 | BE25: =IND!A119 -> 41883 | BF25: =IND!B119 -> 51 | BG25: =IND!C119 -> -1.4 | BI25: =RS!A119 -> 41883 | BJ25: =RS!B119 -> 50.4 | BK25: =RS!C119 -> -0.6 | BM25: =MX!A119 -> 41883 | BN25: =MX!B119 -> 52.6 | BO25: =MX!C119 -> 0.5 | BQ25: =AU!A119 -> 41883 | BR25: =AU!B119 -> 46.5 | BS25: =AU!C119 -> -0.8 | BU25: =SK!A119 -> 41883 | BV25: =SK!B119 -> 48.8 | BW25: =SK!C119 -> -1.5 | BY25: =INS!A119 -> 41883 | BZ25: =INS!B119 -> 50.7 | CA25: =INS!C119 -> 1.2 | CC25: =TW!A119 -> 41883 | CD25: =TW!B119 -> 53.3 | CE25: =TW!C119 -> -2.8 | CG25: =TUR!A119 -> 41883 | CH25: =TUR!B119 -> 50.4 | CI25: =TUR!C119 -> 0.4 | CK25: =CZ!A119 -> 41883 | CL25: =CZ!B119 -> 55.6 | CM25: =CZ!C119 -> 1.3 | CO25: =PL!A119 -> 41883 | CP25: =PL!B119 -> 49.5 | CQ25: =PL!C119 -> 0.5
A26: 46143 | B26: 52.7 | E26: 46143 | F26: 55.1 | I26: 46143 | J26: 52.9 | M26: 46143 | N26: 51.6 | Q26: 46143 | R26: 53.9 | U26: 46143 | V26: 50.1 | Y26: 46143 | Z26: 49.7 | AC26: 46143 | AD26: 52.9 | AG26: 46143 | AH26: 51.2 | AK26: 46143 | AL26: 53.3 | AO26: 46143 | AP26: 55.9 | AS26: 46143 | AT26: 51.8 | AW26: 46143 | AX26: 54.5 | BA26: 46143 | BB26: 49.1 | BE26: 46143 | BF26: 55 | BI26: 46143 | BJ26: 48.8 | BM26: 46143 | BN26: 49.6 | BQ26: 46143 | BR26: 50.7 | BU26: 46143 | BV26: 54.8 | BY26: 46143 | BZ26: 50 | CC26: 46143 | CD26: 56.1 | CG26: 46143 | CH26: 49.8 | CK26: 46143 | CL26: 52.2 | CO26: 46143 | CP26: 49.4
A27: 46174 | B27: 52.2 | C27: -0.5 | E27: 46174 | F27: 53.9 | G27: -1.2 | I27: 46174 | J27: 53 | K27: 0.1 | M27: 46174 | N27: 51.4 | O27: -0.2 | Q27: 46174 | R27: 52.5 | S27: -1.4 | U27: 46174 | V27: 50.3 | W27: 0.2 | Y27: 46174 | Z27: 51.2 | AA27: 1.5 | AC27: 46174 | AD27: 52.2 | AE27: -0.7 | AG27: 46174 | AH27: 49.7 | AI27: -1.5 | AK27: 46174 | AL27: 53.8 | AM27: 0.5 | AO27: 46174 | AP27: 54.9 | AQ27: -1 | AS27: 46174 | AT27: 51.7 | AU27: -0.1 | AW27: 46174 | AX27: 54.8 | AY27: 0.3 | BA27: 46174 | BB27: 50.8 | BC27: 1.7 | BE27: 46174 | BF27: 54.2 | BG27: -0.8 | BI27: 46174 | BJ27: 50.3 | BK27: 1.5 | BM27: 46174 | BN27: 51.3 | BO27: 1.7 | BQ27: 46174 | BR27: 51.5 | BS27: 0.8 | BU27: 46174 | BV27: 52.1 | BW27: -2.7 | BY27: 46174 | BZ27: 46.9 | CA27: -3.1 | CC27: 46174 | CD27: 55.2 | CE27: -0.9 | CG27: 46174 | CH27: 47.1 | CI27: -2.7 | CK27: 46174 | CL27: 53.9 | CM27: 1.7 | CO27: 46174 | CP27: 46.1 | CQ27: -3.3

Sheet Global
A71: Date | B71: Global Manufacturing PMI | C71: Change
A72: 40452 | B72: 53.7
A73: 40483 | B73: 54 | C73: =B73-B72 -> 0.3
A74: 40513 | B74: 54.9 | C74: =B74-B73 -> 0.9
A75: 40544 | B75: 57.2 | C75: =B75-B74 -> 2.3
A76: 40575 | B76: 58.2 | C76: =B76-B75 -> 1
A77: 40603 | B77: 56 | C77: =B77-B76 -> -2.2
A78: 40634 | B78: 55.5 | C78: =B78-B77 -> -0.5
A79: 40664 | B79: 53.1 | C79: =B79-B78 -> -2.4
A80: 40695 | B80: 52.8 | C80: =B80-B79 -> -0.3
A81: 40725 | B81: 50.9 | C81: =B81-B80 -> -1.9
A82: 40756 | B82: 50.4 | C82: =B82-B81 -> -0.5
A83: 40787 | B83: 50.1 | C83: =B83-B82 -> -0.3
A84: 40817 | B84: 49.5 | C84: =B84-B83 -> -0.6
A85: 40848 | B85: 49.6 | C85: =B85-B84 -> 0.1 | G85: Global | H85: Reading | I85: Points
A86: 40878 | B86: 50.4 | C86: =B86-B85 -> 0.8 | G86: Previous | H86: =B114 -> 51.9
A87: 40909 | B87: 51 | C87: =B87-B86 -> 0.6 | G87: Latest | H87: =B115 -> 52.2 | I87: =(H87-H86) -> 0.3
A88: 40940 | B88: 51.2 | C88: =B88-B87 -> 0.2
A89: 40969 | B89: 51.6 | C89: =B89-B88 -> 0.4
A90: 41000 | B90: 51.3 | C90: =B90-B89 -> -0.3
A91: 41030 | B91: 50.3 | C91: =B91-B90 -> -1
A92: 41061 | B92: 49.7 | C92: =B92-B91 -> -0.6
A93: 41091 | B93: 48.8 | C93: =B93-B92 -> -0.9
A94: 41122 | B94: 48.7 | C94: =B94-B93 -> -0.1
A95: 41153 | B95: 48.7 | C95: =B95-B94 -> 0
A96: 41183 | B96: 48.9 | C96: =B96-B95 -> 0.2
A97: 41214 | B97: 49.6 | C97: =B97-B96 -> 0.7
A98: 41244 | B98: 50 | C98: =B98-B97 -> 0.4
A99: 41275 | B99: 51.5 | C99: =B99-B98 -> 1.5
... A121: 41944 | B121: 51.8 | C121: =B121-B120 -> -0.4
A122: 41974 | C122: =B122-B121 -> -51.8
A123: 42005 | C123: =B123-B122 -> 0
A124: 42036 | C124: =B124-B123 -> 0
A125: 42064 | C125: =B125-B124 -> 0
A126: 42095 | C126: =B126-B125 -> 0
A127: 42125 | C127: =B127-B126 -> 0
A128: 42156 | C128: =B128-B127 -> 0
A129: 42186 | C129: =B129-B128 -> 0
A130: 42217 | C130: =B130-B129 -> 0
A131: 42248 | C131: =B131-B130 -> 0
A132: 42278 | C132: =B132-B131 -> 0
A133: 42309 | C133: =B133-B132 -> 0
... A154: 42948 | C154: =B154-B153 -> 0
A155: 46143 | B155: 52.7 | C155: =B155-B154 -> 52.7 | E155: gap 2015-Apr26: S&P Global licensed
A156: 46174 | B156: 52.2 | C156: -0.5

Sheet US
A71: Date | B71: US Manufactung PMI | C71: Change | D71: US GDP Growth q/q | E71: SPY ETF
A72: 40452 | B72: 56.9 | E72: 109.7
A73: 40483 | B73: 56.6 | C73: =B73-B72 -> -0.3 | E73: 109.7
A74: 40513 | B74: 57 | C74: =B74-B73 -> 0.4 | D74: 0.039 | E74: 117.03
A75: 40544 | B75: 60.8 | C75: =B75-B74 -> 3.8 | E75: 119.76
A76: 40575 | B76: 61.4 | C76: =B76-B75 -> 0.6 | E76: 123.92
A77: 40603 | B77: 61.2 | C77: =B77-B76 -> -0.2 | D77: -0.015 | E77: 123.93
A78: 40634 | B78: 60.4 | C78: =B78-B77 -> -0.8 | E78: 127.52
A79: 40664 | B79: 53.5 | C79: =B79-B78 -> -6.9 | E79: 126.09
A80: 40695 | B80: 55.3 | C80: =B80-B79 -> 1.8 | D80: 0.029 | E80: 123.96
A81: 40725 | B81: 50.9 | C81: =B81-B80 -> -4.4 | E81: 121.48
A82: 40756 | B82: 50.6 | C82: =B82-B81 -> -0.3 | E82: 114.8
A83: 40787 | B83: 51.6 | C83: =B83-B82 -> 1 | D83: 0.008 | E83: 106.83
A84: 40817 | B84: 50.8 | C84: =B84-B83 -> -0.8 | E84: 118.5
A85: 40848 | B85: 52.7 | C85: =B85-B84 -> 1.9 | E85: 118.01 | H85: US | I85: United States
A86: 40878 | B86: 53.2 | C86: =B86-B85 -> 0.5 | D86: 0.046 | E86: 119.25
A87: 40909 | B87: 54.3 | C87: =B87-B86 -> 1.1 | E87: 124.78
A88: 40940 | B88: 53.6 | C88: =B88-B87 -> -0.7 | E88: 130.19
A89: 40969 | B89: 56 | C89: =B89-B88 -> 2.4 | D89: 0.023 | E89: 134.38
A90: 41000 | B90: 56 | C90: =B90-B89 -> 0 | E90: 133.48
A91: 41030 | B91: 54 | C91: =B91-B90 -> -2 | E91: 125.47
A92: 41061 | B92: 52.5 | C92: =B92-B91 -> -1.5 | D92: 0.016 | E92: 130.56
A93: 41091 | B93: 51.4 | C93: =B93-B92 -> -1.1 | E93: 132.1
A94: 41122 | B94: 51.5 | C94: =B94-B93 -> 0.1 | E94: 135.41
A95: 41153 | B95: 51.1 | C95: =B95-B94 -> -0.4 | D95: 0.025 | E95: 138.85
A96: 41183 | B96: 51 | C96: =B96-B95 -> -0.1 | E96: 136.32
A97: 41214 | B97: 52.8 | C97: =B97-B96 -> 1.8 | E97: 137.09
A98: 41244 | B98: 54 | C98: =B98-B97 -> 1.2 | D98: 0.001 | E98: 138.32
A99: 41275 | B99: 55.8 | C99: =B99-B98 -> 1.8 | E99: 145.4
A100: 41306 | B100: 54.3 | C100: =B100-B99 -> -1.5 | E100: 147.25
A101: 41334 | B101: 54.6 | C101: =B101-B100 -> 0.3 | D101: 0.027 | E101: 152.84
A102: 41365 | B102: 52.1 | C102: =B102-B101 -> -2.5 | E102: 155.78
A103: 41395 | B103: 52.3 | C103: =B103-B102 -> 0.2 | E103: 159.46
A104: 41426 | B104: 51.9 | C104: =B104-B103 -> -0.4 | D104: 0.018 | E104: 157.33
A105: 41456 | B105: 53.7 | C105: =B105-B104 -> 1.8 | E105: 165.46
A106: 41487 | B106: 53.7 | C106: =B106-B105 -> 0 | E106: 160.5
A107: 41518 | B107: 52.8 | C107: =B107-B106 -> -0.9 | D107: 0.045 | E107: 165.58
A108: 41548 | B108: 51.8 | C108: =B108-B107 -> -1 | E108: 173.24
A109: 41579 | B109: 54.7 | C109: =B109-B108 -> 2.9 | E109: 178.38
A110: 41609 | B110: 55 | C110: =B110-B109 -> 0.3 | D110: 0.035 | E110: 183
A111: 41640 | B111: 53.7 | C111: =B111-B110 -> -1.3 | E111: 176.55
A112: 41671 | B112: 57.1 | C112: =B112-B111 -> 3.4 | E112: 184.59
A113: 41699 | B113: 55.5 | C113: =B113-B112 -> -1.6 | D113: -0.021 | E113: 186.12
A114: 41730 | B114: 55.4 | C114: =B114-B113 -> -0.1 | E114: 187.41
A115: 41760 | B115: 56.4 | C115: =B115-B114 -> 1 | E115: 191.76
A116: 41791 | B116: 57.3 | C116: =B116-B115 -> 0.9 | D116: 0.046 | E116: 195.72
A117: 41821 | B117: 55.8 | C117: =B117-B116 -> -1.5 | E117: 193.09
A118: 41852 | B118: 57.9 | C118: =B118-B117 -> 2.1 | E118: 199.19
A119: 41883 | B119: 57.5 | C119: =IFERROR(B119-B118,"") -> -0.4 | D119: =IF(VLOOKUP(I85,Data!$O$51:$V$152,7,FALSE)=A118,VLOOKUP(I85,Data!$O$51:$V$152,2,FALSE)/100,"") -> 0.039 | E119: 197.02
A120: 41913 | B120: 55.9 | C120: -1.6 | E120: 201.66
A121: 41944 | B121: =IF(A121=Data!$C$1,VLOOKUP($H$85,Data!$A$2:$C$36,3,FALSE),"N/A") -> 54.8 | C121: =B121-B120 -> -1.1 | E121: 207.2
A122: 41974
A123: 42005
A124: 42036
A125: 42064
A126: 42095
A127: 42125
A128: 42156
A129: 42186
A130: 42217
A131: 42248
A132: 42278
A133: 42309
... A154: 42948
A155: 46143 | B155: 55.1 | E155: gap 2015-Apr26: S&P Global licensed
A156: 46174 | B156: 53.9 | C156: -1.2

Sheet CA
A77: Date | B77: Canada PMI | C77: Change | D77: Canada GDP Growth q/q | E77: EWC ETF
A78: 40634 | B78: 56.3 | E78: 31.27
A79: 40664 | B79: 54.8 | C79: =B79-B78 -> -1.5 | E79: 30.53
A80: 40695 | B80: 52.8 | C80: =B80-B79 -> -2 | D80: -0.001 | E80: 29.58
A81: 40725 | B81: 53.1 | C81: =B81-B80 -> 0.3 | E81: 28.9
A82: 40756 | B82: 54.9 | C82: =B82-B81 -> 1.8 | E82: 27.92
A83: 40787 | B83: 55 | C83: =B83-B82 -> 0.1 | D83: 0.014 | E83: 23.81
A84: 40817 | B84: 53.7 | C84: =B84-B83 -> -1.3 | E84: 26.38
A85: 40848 | B85: 53.3 | C85: =B85-B84 -> -0.4 | E85: 25.65 | H85: CA | I85: Canada
A86: 40878 | B86: 54 | C86: =B86-B85 -> 0.7 | D86: 0.005 | E86: 25.2
A87: 40909 | B87: 50.6 | C87: =B87-B86 -> -3.4 | E87: 26.63
A88: 40940 | B88: 51.8 | C88: =B88-B87 -> 1.2 | E88: 27.49
A89: 40969 | B89: 52.4 | C89: =B89-B88 -> 0.6 | D89: 0.002 | E89: 26.84
A90: 41000 | B90: 53.3 | C90: =B90-B89 -> 0.9 | E90: 26.86
A91: 41030 | B91: 54.7 | C91: =B91-B90 -> 1.4 | E91: 23.98
A92: 41061 | B92: 54.8 | C92: =B92-B91 -> 0.1 | D92: 0.004 | E92: 24.68
A93: 41091 | B93: 53 | C93: =B93-B92 -> -1.8 | E93: 25.11
A94: 41122 | B94: 53 | C94: =B94-B93 -> 0 | E94: 26.26
A95: 41153 | B95: 52.4 | C95: =B95-B94 -> -0.6 | D95: 0.002 | E95: 27.21
A96: 41183 | B96: 51.4 | C96: =B96-B95 -> -1 | E96: 27.21
A97: 41214 | B97: 50.4 | C97: =B97-B96 -> -1 | E97: 26.85
A98: 41244 | B98: 50.4 | C98: =B98-B97 -> 0 | D98: 0.002 | E98: 27.49
A99: 41275 | B99: 50.5 | C99: =B99-B98 -> 0.1 | E99: 27.94
A100: 41306 | B100: 51.7 | C100: =B100-B99 -> 1.2 | E100: 27.31
A101: 41334 | B101: 49.3 | C101: =B101-B100 -> -2.4 | D101: 0.009 | E101: 27.59
A102: 41365 | B102: 50.1 | C102: =B102-B101 -> 0.8 | E102: 27.12
A103: 41395 | B103: 53.2 | C103: =B103-B102 -> 3.1 | E103: 26.84
A104: 41426 | B104: 52.4 | C104: =B104-B103 -> -0.8 | D104: 0.005 | E104: 25.6
A105: 41456 | B105: 52 | C105: =B105-B104 -> -0.4 | E105: 27.05
A106: 41487 | B106: 52.1 | C106: =B106-B105 -> 0.1 | E106: 26.82
A107: 41518 | B107: 54.2 | C107: =B107-B106 -> 2.1 | D107: 0.007 | E107: 27.72
A108: 41548 | B108: 55.6 | C108: =B108-B107 -> 1.4 | E108: 28.75
A109: 41579 | B109: 55.3 | C109: =B109-B108 -> -0.3 | E109: 28.48
A110: 41609 | B110: 53.5 | C110: =B110-B109 -> -1.8 | D110: 0.007 | E110: 28.94
A111: 41640 | B111: 51.7 | C111: =B111-B110 -> -1.8 | E111: 27.72
A112: 41671 | B112: 52.9 | C112: =B112-B111 -> 1.2 | E112: 28.96
A113: 41699 | B113: 53.3 | C113: =B113-B112 -> 0.4 | D113: 0.003 | E113: 29.33
A114: 41730 | B114: 52.9 | C114: =B114-B113 -> -0.4 | E114: 30.31
A115: 41760 | B115: 52.2 | C115: =B115-B114 -> -0.7 | E115: 30.47
A116: 41791 | B116: 53.5 | C116: =B116-B115 -> 1.3 | D116: 0.008 | E116: 32.21
A117: 41821 | B117: 54.3 | C117: =B117-B116 -> 0.8 | E117: 32.16
A118: 41852 | B118: 54.8 | C118: =B118-B117 -> 0.5 | E118: 32.44
A119: 41883 | B119: 53.5 | C119: =IFERROR(B119-B118,"") -> -1.3 | D119: =IF(VLOOKUP(I85,Data!$O$51:$V$152,7,FALSE)=A118,VLOOKUP(I85,Data!$O$51:$V$152,2,FALSE)/100,"") -> 0.007 | E119: 30.69
A120: 41913 | B120: 55.3 | C120: 1.8 | E120: 29.92
A121: 41944 | B121: =IF(A121=Data!$C$1,VLOOKUP($H$85,Data!$A$2:$C$36,3,FALSE),"N/A") -> 55.3 | C121: =B121-B120 -> 0 | E121: 29.94
A122: 41974
A123: 42005
A124: 42036
A125: 42064
A126: 42095
A127: 42125
A128: 42156
A129: 42186
A130: 42217
A131: 42248
A132: 42278
A133: 42309
... A154: 42948
A155: 46143 | B155: 52.9 | E155: gap 2015-Apr26: S&P Global licensed
A156: 46174 | B156: 53 | C156: 0.1

Sheet UK
A1: Date | B1: UK PMI | C1: Change | D1: UK GDP Growth q/q | E1: UK ESI
A2: 38322 | B2: 53.7 | D2: =J8 -> 0.007 | E2: 110.4
A3: 38353 | B3: 51.8 | C3: =B3-B2 -> -1.9 | E3: 109.8
A4: 38384 | B4: 51.8 | C4: =B4-B3 -> 0 | E4: 109.8
A5: 38412 | B5: 52 | C5: =B5-B4 -> 0.2 | D5: =J9 -> 0.008 | E5: 105.4
A6: 38443 | B6: 49.5 | C6: =B6-B5 -> -2.5 | E6: 102.8
A7: 38473 | B7: 47.3 | C7: =B7-B6 -> -2.2 | E7: 100.8
A8: 38504 | B8: 49.6 | C8: =B8-B7 -> 2.3 | D8: =J10 -> 0.013 | E8: 96.3 | I8: 0.7 | J8: =I8/100 -> 0.007
A9: 38534 | B9: 49.2 | C9: =B9-B8 -> -0.4 | E9: 101.7 | I9: 0.8 | J9: =I9/100 -> 0.008
A10: 38565 | B10: 50.1 | C10: =B10-B9 -> 0.9 | E10: 98 | I10: 1.3 | J10: =I10/100 -> 0.013
A11: 38596 | B11: 51.5 | C11: =B11-B10 -> 1.4 | D11: =J11 -> 0.01 | E11: 102 | I11: 1 | J11: =I11/100 -> 0.01
A12: 38626 | B12: 51.7 | C12: =B12-B11 -> 0.2 | E12: 101.5 | I12: 1.3 | J12: =I12/100 -> 0.013
A13: 38657 | B13: 51 | C13: =B13-B12 -> -0.7 | E13: 98.4 | I13: 0.4 | J13: =I13/100 -> 0.004
A14: 38687 | B14: 51.1 | C14: =B14-B13 -> 0.1 | D14: =J12 -> 0.013 | E14: 97.5 | I14: 0.3 | J14: =I14/100 -> 0.003
A15: 38718 | B15: 51.7 | C15: =B15-B14 -> 0.6 | E15: 95.9 | I15: 0.2 | J15: =I15/100 -> 0.002
A16: 38749 | B16: 51.7 | C16: =B16-B15 -> 0 | E16: 103.5 | I16: 0.8 | J16: =I16/100 -> 0.008
A17: 38777 | B17: 50.8 | C17: =B17-B16 -> -0.9 | D17: =J13 -> 0.004 | E17: 100.9 | I17: 1 | J17: =I17/100 -> 0.01
A18: 38808 | B18: 54.1 | C18: =B18-B17 -> 3.3 | E18: 110.3 | I18: 1.3 | J18: =I18/100 -> 0.013
A19: 38838 | B19: 53.2 | C19: =B19-B18 -> -0.9 | E19: 107.6 | I19: 1.2 | J19: =I19/100 -> 0.012
A20: 38869 | B20: 55.1 | C20: =B20-B19 -> 1.9 | D20: =J14 -> 0.003 | E20: 108.4 | I20: 0.1 | J20: =I20/100 -> 0.001
A21: 38899 | B21: 53.8 | C21: =B21-B20 -> -1.3 | E21: 109.4 | I21: 0.1 | J21: =I21/100 -> 0.001
A22: 38930 | B22: 53.1 | C22: =B22-B21 -> -0.7 | E22: 106.1 | I22: -0.9 | J22: =I22/100 -> -0.009
A23: 38961 | B23: 54.4 | C23: =B23-B22 -> 1.3 | D23: =J15 -> 0.002 | E23: 109.4 | I23: -1.4 | J23: =I23/100 -> -0.014
A24: 38991 | B24: 53.7 | C24: =B24-B23 -> -0.7 | E24: 107.9 | I24: -2.1 | J24: =I24/100 -> -0.021
A25: 39022 | B25: 53.6 | C25: =B25-B24 -> -0.1 | E25: 111.7 | I25: -2.5 | J25: =I25/100 -> -0.025
A26: 39052 | B26: 51.9 | C26: =B26-B25 -> -1.7 | D26: =J16 -> 0.008 | E26: 112.6 | I26: -0.4 | J26: =I26/100 -> -0.004
A27: 39083 | B27: 52.8 | C27: =B27-B26 -> 0.9 | E27: 110.7 | I27: 0 | J27: =I27/100 -> 0
A28: 39114 | B28: 55.4 | C28: =B28-B27 -> 2.6 | E28: 110.8 | I28: 0.4 | J28: =I28/100 -> 0.004
A29: 39142 | B29: 54.4 | C29: =B29-B28 -> -1 | D29: =J17 -> 0.01 | E29: 113.3 | I29: 0.5 | J29: =I29/100 -> 0.005
A30: 39173 | B30: 53.9 | C30: =B30-B29 -> -0.5 | E30: 109.9 | I30: 1 | J30: =I30/100 -> 0.01
A31: 39203 | B31: 54.9 | C31: =B31-B30 -> 1 | E31: 113.7 | I31: 0.4 | J31: =I31/100 -> 0.004
A32: 39234 | B32: 54.3 | C32: =B32-B31 -> -0.6 | D32: =J18 -> 0.013 | E32: 115 | I32: -0.2 | J32: =I32/100 -> -0.002
A33: 39264 | B33: 55.7 | C33: =B33-B32 -> 1.4 | E33: 109.5 | I33: 0.5 | J33: =I33/100 -> 0.005
A34: 39295 | B34: 56.3 | C34: =B34-B33 -> 0.6 | E34: 110 | I34: 0.1 | J34: =I34/100 -> 0.001
A35: 39326 | B35: 55.1 | C35: =B35-B34 -> -1.2 | D35: =J19 -> 0.012 | E35: 113.1 | I35: 0.6 | J35: =I35/100 -> 0.006
A36: 39356 | B36: 52.9 | C36: =B36-B35 -> -2.2 | E36: 112.4 | I36: -0.1 | J36: =I36/100 -> -0.001
A37: 39387 | B37: 54.4 | C37: =B37-B36 -> 1.5 | E37: 108.1 | I37: 0 | J37: =I37/100 -> 0
A38: 39417 | B38: 52.9 | C38: =B38-B37 -> -1.5 | D38: =J21 -> 0.001 | E38: 107.7 | I38: -0.4 | J38: =I38/100 -> -0.004
A39: 39448 | B39: 50.6 | C39: =B39-B38 -> -2.3 | E39: 107.7 | I39: 0.8 | J39: =I39/100 -> 0.008
A40: 39479 | B40: 51.3 | C40: =B40-B39 -> 0.7 | E40: 99.7 | I40: -0.1 | J40: =I40/100 -> -0.001
A41: 39508 | B41: 51.3 | C41: =B41-B40 -> 0 | D41: 0.001 | E41: 106.5 | I41: 0.5 | J41: =I41/100 -> 0.005
A42: 39539 | B42: 51 | C42: =B42-B41 -> -0.3 | E42: 100 | I42: 0.8 | J42: =I42/100 -> 0.008
A43: 39569 | B43: 50 | C43: =B43-B42 -> -1 | E43: 94.3 | I43: 0.8 | J43: =I43/100 -> 0.008
A44: 39600 | B44: 45.8 | C44: =B44-B43 -> -4.2 | D44: =J22 -> -0.009 | E44: 95.1 | I44: 0.7 | J44: =I44/100 -> 0.007
A45: 39630 | B45: 44.3 | C45: =B45-B44 -> -1.5 | E45: 90.5
A46: 39661 | B46: 45.9 | C46: =B46-B45 -> 1.6 | E46: 88
A47: 39692 | B47: 41 | C47: =B47-B46 -> -4.9 | D47: =J23 -> -0.014 | E47: 85.6
A48: 39722 | B48: 41.5 | C48: =B48-B47 -> 0.5 | E48: 79
A49: 39753 | B49: 34.4 | C49: =B49-B48 -> -7.1 | E49: 77.5
A50: 39783 | B50: 34.9 | C50: =B50-B49 -> 0.5 | D50: =J24 -> -0.021 | E50: 73.6
A51: 39814 | B51: 35.8 | C51: =B51-B50 -> 0.9 | E51: 69.3
A52: 39845 | B52: 34.7 | C52: =B52-B51 -> -1.1 | E52: 66.2
A53: 39873 | B53: 39.1 | C53: =B53-B52 -> 4.4 | D53: =J25 -> -0.025 | E53: 64.3
A54: 39904 | B54: 42.9 | C54: =B54-B53 -> 3.8 | E54: 69.3
A55: 39934 | B55: 45.4 | C55: =B55-B54 -> 2.5 | E55: 74.5
A56: 39965 | B56: 47 | C56: =B56-B55 -> 1.6 | D56: =J26 -> -0.004 | E56: 76.7
A57: 39995 | B57: 50.8 | C57: =B57-B56 -> 3.8 | E57: 77.7
A58: 40026 | B58: 49.7 | C58: =B58-B57 -> -1.1 | E58: 86.9
A59: 40057 | B59: 49.5 | C59: =B59-B58 -> -0.2 | D59: =J27 -> 0 | E59: 87.8
A60: 40087 | B60: 53.7 | C60: =B60-B59 -> 4.2 | E60: 92.7
A61: 40118 | B61: 51.8 | C61: =B61-B60 -> -1.9 | E61: 93.3
A62: 40148 | B62: 54.1 | C62: =B62-B61 -> 2.3 | D62: =J28 -> 0.004 | E62: 95.2
A63: 40179 | B63: 56.7 | C63: =B63-B62 -> 2.6 | E63: 97.3
A64: 40210 | B64: 56.6 | C64: =B64-B63 -> -0.1 | E64: 102
A65: 40238 | B65: 57.2 | C65: =B65-B64 -> 0.6 | D65: =J29 -> 0.005 | E65: 103
A66: 40269 | B66: 58 | C66: =B66-B65 -> 0.8 | E66: 101.9
A67: 40299 | B67: 58 | C67: =B67-B66 -> 0 | E67: 102.9
A68: 40330 | B68: 57.5 | C68: =B68-B67 -> -0.5 | D68: =J30 -> 0.01 | E68: 100.1
A69: 40360 | B69: 57.3 | C69: =B69-B68 -> -0.2 | E69: 102.3
A70: 40391 | B70: 54.3 | C70: =B70-B69 -> -3 | E70: 103.4
A71: 40422 | B71: 53.4 | C71: =B71-B70 -> -0.9 | D71: =J31 -> 0.004 | E71: 100.9
A72: 40452 | B72: 54.9 | C72: =B72-B71 -> 1.5 | E72: 100.4
A73: 40483 | B73: 58 | C73: =B73-B72 -> 3.1 | E73: 101.3
A74: 40513 | B74: 58.3 | C74: =B74-B73 -> 0.3 | D74: =J32 -> -0.002 | E74: 102.5
A75: 40544 | B75: 62 | C75: =B75-B74 -> 3.7 | E75: 99.6
A76: 40575 | B76: 64.5 | C76: =B76-B75 -> 2.5 | E76: 102.8
A77: 40603 | B77: 57.1 | C77: =B77-B76 -> -7.4 | D77: =J33 -> 0.005 | E77: 105.5
A78: 40634 | B78: 54.6 | C78: =B78-B77 -> -2.5 | E78: 100.4
A79: 40664 | B79: 52.1 | C79: =B79-B78 -> -2.5 | E79: 102.9
A80: 40695 | B80: 51.3 | C80: =B80-B79 -> -0.8 | D80: =J34 -> 0.001 | E80: 100.6
A81: 40725 | B81: 49.1 | C81: =B81-B80 -> -2.2 | E81: 99.2
A82: 40756 | B82: 49 | C82: =B82-B81 -> -0.1 | E82: 93.6
A83: 40787 | B83: 51.1 | C83: =B83-B82 -> 2.1 | D83: =J35 -> 0.006 | E83: 90.2
A84: 40817 | B84: 47.4 | C84: =B84-B83 -> -3.7 | E84: 90.2
A85: 40848 | B85: 47.6 | C85: =B85-B84 -> 0.2 | E85: 89.5 | H85: UK | I85: United Kingdom
A86: 40878 | B86: 49.6 | C86: =B86-B85 -> 2 | D86: =J36 -> -0.001 | E86: 88.9
A87: 40909 | B87: 50.8 | C87: =B87-B86 -> 1.2 | E87: 94
A88: 40940 | B88: 51.1 | C88: =B88-B87 -> 0.3 | E88: 94.3
A89: 40969 | B89: 52 | C89: =B89-B88 -> 0.9 | D89: =J37 -> 0 | E89: 91.8
A90: 41000 | B90: 50.2 | C90: =B90-B89 -> -1.8 | E90: 96.1
A91: 41030 | B91: 46.8 | C91: =B91-B90 -> -3.4 | E91: 91.3
A92: 41061 | B92: 48.8 | C92: =B92-B91 -> 2 | D92: =J38 -> -0.004 | E92: 93.3
A93: 41091 | B93: 45.5 | C93: =B93-B92 -> -3.3 | E93: 95
A94: 41122 | B94: 49.1 | C94: =B94-B93 -> 3.6 | E94: 91.8
A95: 41153 | B95: 48.2 | C95: =B95-B94 -> -0.9 | D95: =J39 -> 0.008 | E95: 92.3
A96: 41183 | B96: 48 | C96: =B96-B95 -> -0.2 | E96: 97.6
A97: 41214 | B97: 48.4 | C97: =B97-B96 -> 0.4 | E97: 100.6
A98: 41244 | B98: 50.7 | C98: =B98-B97 -> 2.3 | D98: =J40 -> -0.001 | E98: 97.1
A99: 41275 | B99: 50.9 | C99: =B99-B98 -> 0.2 | E99: 97.6
A100: 41306 | B100: 48.2 | C100: =B100-B99 -> -2.7 | E100: 97.1
...

Sheet EZ
A32: Date | B32: Euro Area PMI | C32: Change | D32: Euro Area GDP q/q % | E32: Column1
A33: 39264 | B33: 55.6
A34: 39295 | B34: 54.3 | C34: =B34-B33 -> -1.3
A35: 39326 | B35: 53.2 | C35: =B35-B34 -> -1.1 | D35: 0.006
A36: 39356 | B36: 51.5 | C36: =B36-B35 -> -1.7
A37: 39387 | B37: 52.8 | C37: =B37-B36 -> 1.3
A38: 39417 | B38: 52.6 | C38: =B38-B37 -> -0.2 | D38: 0.004
A39: 39448 | B39: 52.8 | C39: =B39-B38 -> 0.2
A40: 39479 | B40: 52.3 | C40: =B40-B39 -> -0.5
A41: 39508 | B41: 52 | C41: =B41-B40 -> -0.3 | D41: 0.006
A42: 39539 | B42: 50.7 | C42: =B42-B41 -> -1.3
A43: 39569 | B43: 50.6 | C43: =B43-B42 -> -0.1
A44: 39600 | B44: 49.2 | C44: =B44-B43 -> -1.4 | D44: -0.004
A45: 39630 | B45: 47.4 | C45: =B45-B44 -> -1.8
A46: 39661 | B46: 47.6 | C46: =B46-B45 -> 0.2
A47: 39692 | B47: 45 | C47: =B47-B46 -> -2.6 | D47: -0.006
A48: 39722 | B48: 38.9 | C48: =B48-B47 -> -6.1
A49: 39753 | B49: 35.6 | C49: =B49-B48 -> -3.3
A50: 39783 | B50: 33.9 | C50: =B50-B49 -> -1.7 | D50: -0.017
A51: 39814 | B51: 34.4 | C51: =B51-B50 -> 0.5
A52: 39845 | B52: 33.5 | C52: =B52-B51 -> -0.9
A53: 39873 | B53: 33.9 | C53: =B53-B52 -> 0.4 | D53: -0.028
A54: 39904 | B54: 36.8 | C54: =B54-B53 -> 2.9 | K54: 0.007
A55: 39934 | B55: 40.7 | C55: =B55-B54 -> 3.9 | K55: -0.002
A56: 39965 | B56: 42.6 | C56: =B56-B55 -> 1.9 | D56: -0.003 | K56: -0.002
A57: 39995 | B57: 46.3 | C57: =B57-B56 -> 3.7 | K57: -0.015
A58: 40026 | B58: 48.2 | C58: =B58-B57 -> 1.9 | K58: -0.025
A59: 40057 | B59: 49.3 | C59: =B59-B58 -> 1.1 | D59: 0.004 | K59: -0.001
A60: 40087 | B60: 50.7 | C60: =B60-B59 -> 1.4 | K60: 0.004
A61: 40118 | B61: 51.2 | C61: =B61-B60 -> 0.5 | K61: 0.001
A62: 40148 | B62: 51.6 | C62: =B62-B61 -> 0.4 | D62: 0.005 | K62: 0.002
A63: 40179 | B63: 52.4 | C63: =B63-B62 -> 0.8 | K63: 0.01
A64: 40210 | B64: 54.2 | C64: =B64-B63 -> 1.8 | K64: 0.004
A65: 40238 | B65: 56.6 | C65: =B65-B64 -> 2.4 | D65: 0.004 | K65: 0.003
A66: 40269 | B66: 57.6 | C66: =B66-B65 -> 1 | K66: 0.008
A67: 40299 | B67: 55.8 | C67: =B67-B66 -> -1.8 | K67: 0.002
A68: 40330 | B68: 55.6 | C68: =B68-B67 -> -0.2 | D68: 0.009 | K68: 0.002
A69: 40360 | B69: 56.7 | C69: =B69-B68 -> 1.1 | K69: -0.003
A70: 40391 | B70: 55.1 | C70: =B70-B69 -> -1.6 | K70: 0
A71: 40422 | B71: 53.7 | C71: =B71-B70 -> -1.4 | D71: =K64 -> 0.004 | K71: -0.002
A72: 40452 | B72: 54.6 | C72: =B72-B71 -> 0.9 | K72: -0.001
A73: 40483 | B73: 55.3 | C73: =B73-B72 -> 0.7 | K73: -0.006
A74: 40513 | B74: 57.1 | C74: =B74-B73 -> 1.8 | D74: 0.005 | K74: -0.002
A75: 40544 | B75: 57.3 | C75: =B75-B74 -> 0.2 | K75: 0.003
A76: 40575 | B76: 59 | C76: =B76-B75 -> 1.7 | K76: 0.001
A77: 40603 | B77: 57.5 | C77: =B77-B76 -> -1.5 | D77: =K66 -> 0.008
A78: 40634 | B78: 58 | C78: =B78-B77 -> 0.5
A79: 40664 | B79: 54.6 | C79: =B79-B78 -> -3.4
A80: 40695 | B80: 52 | C80: =B80-B79 -> -2.6 | D80: =K67 -> 0.002
A81: 40725 | B81: 50.4 | C81: =B81-B80 -> -1.6
A82: 40756 | B82: 49 | C82: =B82-B81 -> -1.4
A83: 40787 | B83: 48.5 | C83: =B83-B82 -> -0.5 | D83: =K68 -> 0.002
A84: 40817 | B84: 47.1 | C84: =B84-B83 -> -1.4
A85: 40848 | B85: 46.4 | C85: =B85-B84 -> -0.7 | H85: EZ | I85: Euro Area
A86: 40878 | B86: 46.9 | C86: =B86-B85 -> 0.5 | D86: -0.002
A87: 40909 | B87: 48.8 | C87: =B87-B86 -> 1.9
A88: 40940 | B88: 49 | C88: =B88-B87 -> 0.2
A89: 40969 | B89: 47.7 | C89: =B89-B88 -> -1.3 | D89: -0.001
A90: 41000 | B90: 45.9 | C90: =B90-B89 -> -1.8
A91: 41030 | B91: 45.1 | C91: =B91-B90 -> -0.8
A92: 41061 | B92: 45.1 | C92: =B92-B91 -> 0 | D92: -0.003
A93: 41091 | B93: 44 | C93: =B93-B92 -> -1.1
A94: 41122 | B94: 45.1 | C94: =B94-B93 -> 1.1
A95: 41153 | B95: 46.1 | C95: =B95-B94 -> 1 | D95: -0.002
A96: 41183 | B96: 45.4 | C96: =B96-B95 -> -0.7
A97: 41214 | B97: 46.2 | C97: =B97-B96 -> 0.8
A98: 41244 | B98: 46.1 | C98: =B98-B97 -> -0.1 | D98: -0.005
A99: 41275 | B99: 47.9 | C99: =B99-B98 -> 1.8
A100: 41306 | B100: 47.9 | C100: =B100-B99 -> 0
A101: 41334 | B101: 46.8 | C101: =B101-B100 -> -1.1 | D101: =K74 -> -0.002
A102: 41365 | B102: 46.7 | C102: =B102-B101 -> -0.1
A103: 41395 | B103: 48.3 | C103: =B103-B102 -> 1.6
A104: 41426 | B104: 48.8 | C104: =B104-B103 -> 0.5 | D104: =K75 -> 0.003
A105: 41456 | B105: 50.3 | C105: =B105-B104 -> 1.5
A106: 41487 | B106: 51.4 | C106: =B106-B105 -> 1.1
A107: 41518 | B107: 51.1 | C107: =B107-B106 -> -0.3 | D107: =K76 -> 0.001
A108: 41548 | B108: 51.3 | C108: =B108-B107 -> 0.2
A109: 41579 | B109: 51.6 | C109: =B109-B108 -> 0.3
A110: 41609 | B110: 52.7 | C110: =B110-B109 -> 1.1 | D110: 0.002
A111: 41640 | B111: 54 | C111: =B111-B110 -> 1.3
A112: 41671 | B112: 53.2 | C112: =B112-B111 -> -0.8
A113: 41699 | B113: 53 | C113: =B113-B112 -> -0.2 | D113: 0.002
A114: 41730 | B114: 54 | C114: =B114-B113 -> 1
A115: 41760 | B115: 52.2 | C115: =B115-B114 -> -1.8
A116: 41791 | B116: 51.8 | C116: =B116-B115 -> -0.4 | D116: 0
A117: 41821 | B117: 51.8 | C117: =B117-B116 -> 0
A118: 41852 | B118: 50.7 | C118: =B118-B117 -> -1.1
A119: 41883 | B119: 50.3 | C119: =IFERROR(B119-B118,"") -> -0.4 | D119: =IF(VLOOKUP(I85,Data!$O$51:$V$152,7,FALSE)=A118,VLOOKUP(I85,Data!$O$51:$V$152,2,FALSE)/100,"") -> 0.002
A120: 41913 | B120: 50.6 | C120: 0.3
A121: 41944 | B121: =IF(A121=Data!$C$1,VLOOKUP($H$85,Data!$A$2:$C$36,3,FALSE),"N/A") -> 50.1 | C121: =B121-B120 -> -0.5
A122: 41974
A123: 42005
A124: 42036
A125: 42064
A126: 42095
A127: 42125
A128: 42156
A129: 42186
A130: 42217
A131: 42248
...

Sheet DE
A38: Date | B38: Germany PMI | C38: Change | D38: Germany GDP q/q | E38: Column1
A39: 39478 | B39: 54.4
A40: 39479 | B40: 54.3 | C40: =B40-B39 -> -0.1
A41: 39508 | B41: 54.9 | C41: =B41-B40 -> 0.6 | D41: 0.016
A42: 39539 | B42: 53.6 | C42: =B42-B41 -> -1.3
A43: 39569 | B43: 53.5 | C43: =B43-B42 -> -0.1
A44: 39600 | B44: 52.3 | C44: =B44-B43 -> -1.2 | D44: -0.006
A45: 39630 | B45: 50.9 | C45: =B45-B44 -> -1.4
A46: 39661 | B46: 49.9 | C46: =B46-B45 -> -1
A47: 39692 | B47: 48.1 | C47: =B47-B46 -> -1.8 | D47: -0.003
A48: 39722 | B48: 43.3 | C48: =B48-B47 -> -4.8
A49: 39753 | B49: 36.7 | C49: =B49-B48 -> -6.6
A50: 39783 | B50: 33.5 | C50: =B50-B49 -> -3.2 | D50: -0.024
A51: 39814 | B51: 32 | C51: =B51-B50 -> -1.5
A52: 39845 | B52: 32.2 | C52: =B52-B51 -> 0.2
A53: 39873 | B53: 32.4 | C53: =B53-B52 -> 0.2 | D53: -0.037
A54: 39904 | B54: 35 | C54: =B54-B53 -> 2.6
A55: 39934 | B55: 39.6 | C55: =B55-B54 -> 4.6 | J55: 0.015
A56: 39965 | B56: 40.9 | C56: =B56-B55 -> 1.3 | D56: 0.005 | J56: -0.005
A57: 39995 | B57: 45.2 | C57: =B57-B56 -> 4.3 | J57: -0.005
A58: 40026 | B58: 49 | C58: =B58-B57 -> 3.8 | J58: -0.021
A59: 40057 | B59: 49.6 | C59: =B59-B58 -> 0.6 | D59: 0.008 | J59: -0.038
A60: 40087 | B60: 51.1 | C60: =B60-B59 -> 1.5 | J60: 0.003
A61: 40118 | B61: 52.4 | C61: =B61-B60 -> 1.3 | J61: 0.007
A62: 40148 | B62: 53.1 | C62: =B62-B61 -> 0.7 | D62: 0.005 | J62: 0
A63: 40179 | B63: 53.4 | C63: =B63-B62 -> 0.3 | J63: 0.002
A64: 40210 | B64: 57.2 | C64: =B64-B63 -> 3.8 | J64: 0.022
A65: 40238 | B65: 59.6 | C65: =B65-B64 -> 2.4 | D65: 0.005 | J65: 0.007
A66: 40269 | B66: 61.5 | C66: =B66-B65 -> 1.9 | J66: 0.004
A67: 40299 | B67: 58.4 | C67: =B67-B66 -> -3.1 | J67: 0.015
A68: 40330 | B68: 58.1 | C68: =B68-B67 -> -0.3 | D68: 0.021 | J68: 0.001
A69: 40360 | B69: 61.2 | C69: =B69-B68 -> 3.1 | J69: 0.005
A70: 40391 | B70: 58.2 | C70: =B70-B69 -> -3 | J70: -0.002
A71: 40422 | B71: 55.3 | C71: =B71-B70 -> -2.9 | D71: 0.008 | J71: 0.005
A72: 40452 | B72: 56.6 | C72: =B72-B71 -> 1.3 | J72: 0.003
A73: 40483 | B73: 58.1 | C73: =B73-B72 -> 1.5 | J73: 0.002
A74: 40513 | B74: 60.9 | C74: =B74-B73 -> 2.8 | D74: =J66 -> 0.004 | J74: -0.006
A75: 40544 | B75: 60.5 | C75: =B75-B74 -> -0.4 | J75: 0.001
A76: 40575 | B76: 62.7 | C76: =B76-B75 -> 2.2 | J76: 0.007
A77: 40603 | B77: 60.9 | C77: =B77-B76 -> -1.8 | D77: =J67 -> 0.015 | J77: 0.003
A78: 40634 | B78: 62 | C78: =B78-B77 -> 1.1
A79: 40664 | B79: 57.7 | C79: =B79-B78 -> -4.3
A80: 40695 | B80: 54.9 | C80: =B80-B79 -> -2.8 | D80: =J68 -> 0.001
A81: 40725 | B81: 52 | C81: =B81-B80 -> -2.9
A82: 40756 | B82: 50.9 | C82: =B82-B81 -> -1.1
A83: 40787 | B83: 50.3 | C83: =B83-B82 -> -0.6 | D83: 0.004
A84: 40817 | B84: 49.1 | C84: =B84-B83 -> -1.2
A85: 40848 | B85: 47.9 | C85: =B85-B84 -> -1.2 | H85: DE | I85: Germany
A86: 40878 | B86: 48.4 | C86: =B86-B85 -> 0.5 | D86: 0.001
A87: 40909 | B87: 51 | C87: =B87-B86 -> 2.6
A88: 40940 | B88: 50.2 | C88: =B88-B87 -> -0.8
A89: 40969 | B89: 48.4 | C89: =B89-B88 -> -1.8 | D89: 0.007
A90: 41000 | B90: 46.2 | C90: =B90-B89 -> -2.2
A91: 41030 | B91: 45.2 | C91: =B91-B90 -> -1
A92: 41061 | B92: 45 | C92: =B92-B91 -> -0.2 | D92: -0.001
A93: 41091 | B93: 43 | C93: =B93-B92 -> -2
A94: 41122 | B94: 44.7 | C94: =B94-B93 -> 1.7
A95: 41153 | B95: 47.4 | C95: =B95-B94 -> 2.7 | D95: =J73 -> 0.002
A96: 41183 | B96: 46 | C96: =B96-B95 -> -1.4
A97: 41214 | B97: 46.8 | C97: =B97-B96 -> 0.8
A98: 41244 | B98: 46 | C98: =B98-B97 -> -0.8 | D98: -0.005
A99: 41275 | B99: 49.8 | C99: =B99-B98 -> 3.8
A100: 41306 | B100: 50.3 | C100: =B100-B99 -> 0.5
A101: 41334 | B101: 49 | C101: =B101-B100 -> -1.3 | D101: =J75 -> 0.001
A102: 41365 | B102: 48.1 | C102: =B102-B101 -> -0.9
A103: 41395 | B103: 49.4 | C103: =B103-B102 -> 1.3
A104: 41426 | B104: 48.6 | C104: =B104-B103 -> -0.8 | D104: =J76 -> 0.007
A105: 41456 | B105: 50.7 | C105: =B105-B104 -> 2.1
A106: 41487 | B106: 51.8 | C106: =B106-B105 -> 1.1
A107: 41518 | B107: 51.1 | C107: =B107-B106 -> -0.7 | D107: =J77 -> 0.003
A108: 41548 | B108: 51.7 | C108: =B108-B107 -> 0.6
A109: 41579 | B109: 52.7 | C109: =B109-B108 -> 1
A110: 41609 | B110: 54.3 | C110: =B110-B109 -> 1.6 | D110: 0.004
A111: 41640 | B111: 56.6 | C111: =B111-B110 -> 2.3
A112: 41671 | B112: 54.8 | C112: =B112-B111 -> -1.8
A113: 41699 | B113: 53.7 | C113: =B113-B112 -> -1.1 | D113: 0.007
A114: 41730 | B114: 54.1 | C114: =B114-B113 -> 0.4
A115: 41760 | B115: 52.3 | C115: =B115-B114 -> -1.8
A116: 41791 | B116: 52 | C116: =B116-B115 -> -0.3 | D116: -0.002
A117: 41821 | B117: 52.4 | C117: =B117-B116 -> 0.4
A118: 41852 | B118: 51.4 | C118: =B118-B117 -> -1
A119: 41883 | B119: 49.9 | C119: =IFERROR(B119-B118,"") -> -1.5 | D119: =IF(VLOOKUP(I85,Data!$O$51:$V$152,7,FALSE)=A118,VLOOKUP(I85,Data!$O$51:$V$152,2,FALSE)/100,"") -> 0.001
A120: 41913 | B120: 51.4 | C120: 1.5
A121: 41944 | B121: =IF(A121=Data!$C$1,VLOOKUP($H$85,Data!$A$2:$C$36,3,FALSE),"N/A") -> 49.5 | C121: =B121-B120 -> -1.9
A122: 41974
A123: 42005
A124: 42036
A125: 42064
A126: 42095
A127: 42125
A128: 42156
A129: 42186
A130: 42217
A131: 42248
A132: 42278
A133: 42309
... A154: 42948
A155: 46143 | B155: 50.1 | E155: gap 2015-Apr26: S&P Global licensed
A156: 46174 | B156: 50.3 | C156: 0.2

Sheet FR
A45: Date | B45: France PMI | C45: Change | D45: French GDP q/q | E45: ESI
A46: 39661 | B46: 45.1
A47: 39692 | B47: 43.6 | C47: =B47-B46 -> -1.5 | D47: -0.004
A48: 39722 | B48: 40.8 | C48: =B48-B47 -> -2.8
A49: 39753 | B49: 37.9 | C49: =B49-B48 -> -2.9
A50: 39783 | B50: 35.9 | C50: =B50-B49 -> -2 | D50: -0.016
A51: 39814 | B51: 38.1 | C51: =B51-B50 -> 2.2
A52: 39845 | B52: 32.3 | C52: =B52-B51 -> -5.8
A53: 39873 | B53: 36.3 | C53: =B53-B52 -> 4 | D53: -0.017
A54: 39904 | B54: 40 | C54: =B54-B53 -> 3.7
A55: 39934 | B55: 43.1 | C55: =B55-B54 -> 3.1
A56: 39965 | B56: 45.9 | C56: =B56-B55 -> 2.8 | D56: 0 | I56: 0.001
A57: 39995 | B57: 50.2 | C57: =B57-B56 -> 4.3 | I57: -0.012
A58: 40026 | B58: 52.5 | C58: =B58-B57 -> 2.3 | I58: -0.012
A59: 40057 | B59: 53 | C59: =B59-B58 -> 0.5 | D59: 0.001 | I59: 0.003
A60: 40087 | B60: 54.2 | C60: =B60-B59 -> 1.2 | I60: 0.003
A61: 40118 | B61: 54.4 | C61: =B61-B60 -> 0.2 | I61: 0.006
A62: 40148 | B62: 54.7 | C62: =B62-B61 -> 0.3 | D62: 0.007 | I62: 0.001
A63: 40179 | B63: 54.6 | C63: =B63-B62 -> -0.1 | I63: 0.006
A64: 40210 | B64: 56.3 | C64: =B64-B63 -> 1.7 | I64: 0.004
A65: 40238 | B65: 56.7 | C65: =B65-B64 -> 0.4 | D65: 0.003 | I65: 0.003
A66: 40269 | B66: 56.6 | C66: =B66-B65 -> -0.1 | I66: 0.01
A67: 40299 | B67: 55.8 | C67: =B67-B66 -> -0.8 | I67: 0
A68: 40330 | B68: 53.7 | C68: =B68-B67 -> -2.1 | D68: 0.006 | I68: 0.004
A69: 40360 | B69: 54.7 | C69: =B69-B68 -> 1 | I69: 0.002
A70: 40391 | B70: 55.4 | C70: =B70-B69 -> 0.7 | I70: 0
A71: 40422 | B71: 55.2 | C71: =B71-B70 -> -0.2 | D71: 0.005 | I71: 0
A72: 40452 | B72: 57.5 | C72: =B72-B71 -> 2.3 | I72: 0.002
A73: 40483 | B73: 56.3 | C73: =B73-B72 -> -1.2 | I73: -0.003
A74: 40513 | B74: 54.3 | C74: =B74-B73 -> -2 | D74: 0.005 | I74: -0.002
A75: 40544 | B75: 54.9 | C75: =B75-B74 -> 0.6 | E75: 110 | I75: 0.005
A76: 40575 | B76: 56.6 | C76: =B76-B75 -> 1.7 | E76: 110.6 | I76: -0.001
A77: 40603 | B77: 56.9 | C77: =B77-B76 -> 0.3 | D77: 0.011 | E77: 109.8
A78: 40634 | B78: 57.5 | C78: =B78-B77 -> 0.6 | E78: 107.9
A79: 40664 | B79: 54.9 | C79: =B79-B78 -> -2.6 | E79: 107.7
A80: 40695 | B80: 50.1 | C80: =B80-B79 -> -4.8 | D80: -0.001 | E80: 106.2
A81: 40725 | B81: 50.5 | C81: =B81-B80 -> 0.4 | E81: 100.2
A82: 40756 | B82: 49.1 | C82: =B82-B81 -> -1.4 | E82: 98.4
A83: 40787 | B83: 48.2 | C83: =B83-B82 -> -0.9 | D83: 0.003 | E83: 96.7
A84: 40817 | B84: 48.5 | C84: =B84-B83 -> 0.3 | E84: 97
A85: 40848 | B85: 47.3 | C85: =B85-B84 -> -1.2 | E85: 94.5 | H85: FR | I85: France
A86: 40878 | B86: 48.9 | C86: =B86-B85 -> 1.6 | D86: 0.001 | E86: 94.7
A87: 40909 | B87: 48.5 | C87: =B87-B86 -> -0.4 | E87: 93.2
A88: 40940 | B88: 50 | C88: =B88-B87 -> 1.5 | E88: 95.3
A89: 40969 | B89: 46.7 | C89: =B89-B88 -> -3.3 | D89: 0.001 | E89: 96.6
A90: 41000 | B90: 46.9 | C90: =B90-B89 -> 0.2 | E90: 96.7
A91: 41030 | B91: 44.7 | C91: =B91-B90 -> -2.2 | E91: 95
A92: 41061 | B92: 45.2 | C92: =B92-B91 -> 0.5 | D92: -0.003 | E92: 93.3
A93: 41091 | B93: 43.4 | C93: =B93-B92 -> -1.8 | E93: 90.9
A94: 41122 | B94: 46 | C94: =B94-B93 -> 2.6 | E94: 90.8
A95: 41153 | B95: 42.7 | C95: =B95-B94 -> -3.3 | D95: 0.002 | E95: 89.7
A96: 41183 | B96: 43.7 | C96: =B96-B95 -> 1 | E96: 87.3
A97: 41214 | B97: 44.5 | C97: =B97-B96 -> 0.8 | E97: 88.8
A98: 41244 | B98: 44.6 | C98: =B98-B97 -> 0.1 | D98: -0.002 | E98: 89.5
A99: 41275 | B99: 42.9 | C99: =B99-B98 -> -1.7 | E99: 89.8
A100: 41306 | B100: 43.9 | C100: =B100-B99 -> 1 | E100: 90.3
A101: 41334 | B101: 44 | C101: =B101-B100 -> 0.1 | D101: 0 | E101: 88.8
A102: 41365 | B102: 44.4 | C102: =B102-B101 -> 0.4 | E102: 86.4
A103: 41395 | B103: 46.4 | C103: =B103-B102 -> 2 | E103: 87.4
A104: 41426 | B104: 48.4 | C104: =B104-B103 -> 2 | D104: 0.006 | E104: 88.7
A105: 41456 | B105: 49.7 | C105: =B105-B104 -> 1.3 | E105: 89.9
A106: 41487 | B106: 49.7 | C106: =B106-B105 -> 0 | E106: 91.6
A107: 41518 | B107: 49.8 | C107: =B107-B106 -> 0.1 | D107: -0.001 | E107: 93.5
A108: 41548 | B108: 49.1 | C108: =B108-B107 -> -0.7 | E108: 96.4
A109: 41579 | B109: 48.4 | C109: =B109-B108 -> -0.7 | E109: 95.2
A110: 41609 | B110: 47 | C110: =B110-B109 -> -1.4 | D110: 0.002 | E110: 96
A111: 41640 | B111: 49.3 | C111: =B111-B110 -> 2.3 | E111: 97.5
A112: 41671 | B112: 49.7 | C112: =B112-B111 -> 0.4 | E112: 95.9
A113: 41699 | B113: 52.1 | C113: =B113-B112 -> 2.4 | D113: 0 | E113: 97.1
A114: 41730 | B114: 51.2 | C114: =B114-B113 -> -0.9 | E114: 96.8
A115: 41760 | B115: 49.6 | C115: =B115-B114 -> -1.6 | E115: 96.3
A116: 41791 | B116: 48.2 | C116: =B116-B115 -> -1.4 | D116: 0 | E116: 95.3
A117: 41821 | B117: 47.8 | C117: =B117-B116 -> -0.4 | E117: 95.7
A118: 41852 | B118: 46.9 | C118: =B118-B117 -> -0.9 | E118: 95.1
A119: 41883 | B119: 48.8 | C119: =IFERROR(B119-B118,"") -> 1.9 | D119: =IF(VLOOKUP(I85,Data!$O$51:$V$152,7,FALSE)=A118,VLOOKUP(I85,Data!$O$51:$V$152,2,FALSE)/100,"") -> 0.003 | E119: 95.3
A120: 41913 | B120: 48.5 | C120: -0.3 | E120: 96.6
A121: 41944 | B121: =IF(A121=Data!$C$1,VLOOKUP($H$85,Data!$A$2:$C$36,3,FALSE),"N/A") -> 48.4 | C121: =B121-B120 -> -0.1 | E121: 98.1
A122: 41974
A123: 42005
A124: 42036
A125: 42064
A126: 42095
A127: 42125
A128: 42156
A129: 42186
A130: 42217
A131: 42248
A132: 42278
A133: 42309
... A154: 42948
A155: 46143 | B155: 49.7 | E155: gap 2015-Apr26: S&P Global licensed
A156: 46174 | B156: 51.2 | C156: 1.5

Sheet IT
A25: Date | B25: Italy PMI | C25: Change | D25: Italy GDP q/q | E25: Column1
A26: 39052 | B26: 55 | D26: 0.011
A27: 39083 | B27: 53.5 | C27: =B27-B26 -> -1.5
A28: 39114 | B28: 54.2 | C28: =B28-B27 -> 0.7
A29: 39142 | B29: 53.8 | C29: =B29-B28 -> -0.4 | D29: 0
A30: 39173 | B30: 53.9 | C30: =B30-B29 -> 0.1
A31: 39203 | B31: 55 | C31: =B31-B30 -> 1.1
A32: 39234 | B32: 54 | C32: =B32-B31 -> -1 | D32: 0.002
A33: 39264 | B33: 53.3 | C33: =B33-B32 -> -0.7
A34: 39295 | B34: 53.6 | C34: =B34-B33 -> 0.3
A35: 39326 | B35: 52.4 | C35: =B35-B34 -> -1.2 | D35: 0.003
A36: 39356 | B36: 51.3 | C36: =B36-B35 -> -1.1
A37: 39387 | B37: 51.3 | C37: =B37-B36 -> 0
A38: 39417 | B38: 50.7 | C38: =B38-B37 -> -0.6 | D38: -0.004
A39: 39448 | B39: 50.8 | C39: =B39-B38 -> 0.1
A40: 39479 | B40: 50.6 | C40: =B40-B39 -> -0.2
A41: 39508 | B41: 49.4 | C41: =B41-B40 -> -1.2 | D41: 0.004
A42: 39539 | B42: 48.2 | C42: =B42-B41 -> -1.2
A43: 39569 | B43: 48 | C43: =B43-B42 -> -0.2
A44: 39600 | B44: 46.9 | C44: =B44-B43 -> -1.1 | D44: -0.005
A45: 39630 | B45: 45.3 | C45: =B45-B44 -> -1.6
A46: 39661 | B46: 47.1 | C46: =B46-B45 -> 1.8
A47: 39692 | B47: 44.4 | C47: =B47-B46 -> -2.7 | D47: -0.011
A48: 39722 | B48: 39.7 | C48: =B48-B47 -> -4.7
A49: 39753 | B49: 34.9 | C49: =B49-B48 -> -4.8
A50: 39783 | B50: 35.5 | C50: =B50-B49 -> 0.6 | D50: -0.019
A51: 39814 | B51: 36.1 | C51: =B51-B50 -> 0.6
A52: 39845 | B52: 35 | C52: =B52-B51 -> -1.1
A53: 39873 | B53: 34.6 | C53: =B53-B52 -> -0.4 | D53: -0.035
A54: 39904 | B54: 37.2 | C54: =B54-B53 -> 2.6
A55: 39934 | B55: 41.1 | C55: =B55-B54 -> 3.9
A56: 39965 | B56: 42.7 | C56: =B56-B55 -> 1.6 | D56: -0.003
A57: 39995 | B57: 45.4 | C57: =B57-B56 -> 2.7
A58: 40026 | B58: 44.2 | C58: =B58-B57 -> -1.2
A59: 40057 | B59: 47.6 | C59: =B59-B58 -> 3.4 | D59: 0.004
A60: 40087 | B60: 49.2 | C60: =B60-B59 -> 1.6
A61: 40118 | B61: 50.1 | C61: =B61-B60 -> 0.9
A62: 40148 | B62: 50.8 | C62: =B62-B61 -> 0.7 | D62: -0.001
A63: 40179 | B63: 51.7 | C63: =B63-B62 -> 0.9
A64: 40210 | B64: 51.6 | C64: =B64-B63 -> -0.1
A65: 40238 | B65: 53.7 | C65: =B65-B64 -> 2.1 | D65: 0.008
A66: 40269 | B66: 54.3 | C66: =B66-B65 -> 0.6
A67: 40299 | B67: 54 | C67: =B67-B66 -> -0.3
A68: 40330 | B68: 54.3 | C68: =B68-B67 -> 0.3 | D68: 0.006
A69: 40360 | B69: 54.4 | C69: =B69-B68 -> 0.1
A70: 40391 | B70: 52.8 | C70: =B70-B69 -> -1.6
A71: 40422 | B71: 52.6 | C71: =B71-B70 -> -0.2 | D71: 0.004
A72: 40452 | B72: 53 | C72: =B72-B71 -> 0.4
A73: 40483 | B73: 52 | C73: =B73-B72 -> -1
A74: 40513 | B74: 54.7 | C74: =B74-B73 -> 2.7 | D74: 0.003
A75: 40544 | B75: 56.6 | C75: =B75-B74 -> 1.9
A76: 40575 | B76: 59 | C76: =B76-B75 -> 2.4
A77: 40603 | B77: 56.2 | C77: =B77-B76 -> -2.8 | D77: 0.001
A78: 40634 | B78: 55.5 | C78: =B78-B77 -> -0.7
A79: 40664 | B79: 52.8 | C79: =B79-B78 -> -2.7
A80: 40695 | B80: 49.9 | C80: =B80-B79 -> -2.9 | D80: 0.002
A81: 40725 | B81: 50.1 | C81: =B81-B80 -> 0.2
A82: 40756 | B82: 47 | C82: =B82-B81 -> -3.1
A83: 40787 | B83: 48.3 | C83: =B83-B82 -> 1.3 | D83: -0.002
A84: 40817 | B84: 43.3 | C84: =B84-B83 -> -5
A85: 40848 | B85: 44 | C85: =B85-B84 -> 0.7 | H85: IT | I85: Italy
A86: 40878 | B86: 44.3 | C86: =B86-B85 -> 0.3 | D86: -0.007
A87: 40909 | B87: 46.8 | C87: =B87-B86 -> 2.5
A88: 40940 | B88: 47.8 | C88: =B88-B87 -> 1
A89: 40969 | B89: 47.9 | C89: =B89-B88 -> 0.1 | D89: -0.011
A90: 41000 | B90: 43.8 | C90: =B90-B89 -> -4.1
A91: 41030 | B91: 44.8 | C91: =B91-B90 -> 1
A92: 41061 | B92: 44.6 | C92: =B92-B91 -> -0.2 | D92: 0.005
A93: 41091 | B93: 44.3 | C93: =B93-B92 -> -0.3
A94: 41122 | B94: 43.6 | C94: =B94-B93 -> -0.7
A95: 41153 | B95: 45.7 | C95: =B95-B94 -> 2.1 | D95: -0.004
A96: 41183 | B96: 45.5 | C96: =B96-B95 -> -0.2
A97: 41214 | B97: 45.1 | C97: =B97-B96 -> -0.4
A98: 41244 | B98: 46.7 | C98: =B98-B97 -> 1.6 | D98: -0.009
A99: 41275 | B99: 47.8 | C99: =B99-B98 -> 1.1
A100: 41306 | B100: 45.8 | C100: =B100-B99 -> -2
A101: 41334 | B101: 44.5 | C101: =B101-B100 -> -1.3 | D101: -0.006
A102: 41365 | B102: 45.5 | C102: =B102-B101 -> 1
A103: 41395 | B103: 47.3 | C103: =B103-B102 -> 1.8
A104: 41426 | B104: 49.1 | C104: =B104-B103 -> 1.8 | D104: -0.003
A105: 41456 | B105: 50.4 | C105: =B105-B104 -> 1.3
A106: 41487 | B106: 51.3 | C106: =B106-B105 -> 0.9
A107: 41518 | B107: 50.8 | C107: =B107-B106 -> -0.5 | D107: -0.001
A108: 41548 | B108: 50.7 | C108: =B108-B107 -> -0.1
A109: 41579 | B109: 51.4 | C109: =B109-B108 -> 0.7
A110: 41609 | B110: 53.3 | C110: =B110-B109 -> 1.9 | D110: 0.001
A111: 41640 | B111: 53.1 | C111: =B111-B110 -> -0.2
A112: 41671 | B112: 52.3 | C112: =B112-B111 -> -0.8
A113: 41699 | B113: 52.4 | C113: =B113-B112 -> 0.1 | D113: -0.001
A114: 41730 | B114: 54 | C114: =B114-B113 -> 1.6
A115: 41760 | B115: 53.2 | C115: =B115-B114 -> -0.8
A116: 41791 | B116: 52.6 | C116: =B116-B115 -> -0.6 | D116: -0.002
A117: 41821 | B117: 51.9 | C117: =B117-B116 -> -0.7
A118: 41852 | B118: 49.8 | C118: =B118-B117 -> -2.1
A119: 41883 | B119: 50.7 | C119: =IFERROR(B119-B118,"") -> 0.9 | D119: =IF(VLOOKUP(I85,Data!$O$51:$V$152,7,FALSE)=A118,VLOOKUP(I85,Data!$O$51:$V$152,2,FALSE)/100,"") -> -0.001
A120: 41913 | B120: 49 | C120: -1.7
A121: 41944 | B121: =IF(A121=Data!$C$1,VLOOKUP($H$85,Data!$A$2:$C$36,3,FALSE),"N/A") -> 49 | C121: =B121-B120 -> 0
A122: 41974
A123: 42005
A124: 42036
...

Sheet ES
A25: Date | B25: Spanish PMI | C25: Change | D25: Spanish GDP q/q | E25: Column1
A26: 39052 | B26: 57.2
A27: 39083 | B27: 56.2 | C27: =B27-B26 -> -1
A28: 39114 | B28: 56.2 | C28: =B28-B27 -> 0
A29: 39142 | B29: 55.4 | C29: =B29-B28 -> -0.8 | D29: 0.011
A30: 39173 | B30: 56 | C30: =B30-B29 -> 0.6
A31: 39203 | B31: 53.3 | C31: =B31-B30 -> -2.7
A32: 39234 | B32: 55.1 | C32: =B32-B31 -> 1.8 | D32: 0.008
A33: 39264 | B33: 53.2 | C33: =B33-B32 -> -1.9
A34: 39295 | B34: 52.2 | C34: =B34-B33 -> -1 | I34: 0.01
A35: 39326 | B35: 50.8 | C35: =B35-B34 -> -1.4 | D35: 0.007 | I35: 0.008
A36: 39356 | B36: 49.6 | C36: =B36-B35 -> -1.2 | I36: 0.007
A37: 39387 | B37: 50.7 | C37: =B37-B36 -> 1.1 | I37: 0.008
A38: 39417 | B38: 49.5 | C38: =B38-B37 -> -1.2 | D38: 0.008 | I38: 0.003
A39: 39448 | B39: 49.8 | C39: =B39-B38 -> 0.3 | I39: 0.001
A40: 39479 | B40: 46.7 | C40: =B40-B39 -> -3.1 | I40: -0.002
A41: 39508 | B41: 46.4 | C41: =B41-B40 -> -0.3 | D41: 0.003 | I41: -0.01
A42: 39539 | B42: 45.2 | C42: =B42-B41 -> -1.2 | I42: -0.018
A43: 39569 | B43: 43.8 | C43: =B43-B42 -> -1.4 | I43: -0.01
A44: 39600 | B44: 40.6 | C44: =B44-B43 -> -3.2 | D44: 0.001 | I44: -0.003
A45: 39630 | B45: 39.2 | C45: =B45-B44 -> -1.4 | I45: -0.001
A46: 39661 | B46: 42.4 | C46: =B46-B45 -> 3.2 | I46: 0.001
A47: 39692 | B47: 38.3 | C47: =B47-B46 -> -4.1 | D47: -0.002 | I47: 0.002
A48: 39722 | B48: 34.6 | C48: =B48-B47 -> -3.7 | I48: 0
A49: 39753 | B49: 29.4 | C49: =B49-B48 -> -5.2 | I49: 0.002
A50: 39783 | B50: 28.5 | C50: =B50-B49 -> -0.9 | D50: -0.01 | I50: 0.003
A51: 39814 | B51: 31.5 | C51: =B51-B50 -> 3 | I51: 0.002
A52: 39845 | B52: 31.8 | C52: =B52-B51 -> 0.3 | I52: 0
A53: 39873 | B53: 32.9 | C53: =B53-B52 -> 1.1 | D53: -0.018 | I53: -0.003
A54: 39904 | B54: 34.6 | C54: =B54-B53 -> 1.7 | I54: -0.003
A55: 39934 | B55: 39.8 | C55: =B55-B54 -> 5.2 | I55: -0.004
A56: 39965 | B56: 42.8 | C56: =B56-B55 -> 3 | D56: -0.01 | I56: -0.003
A57: 39995 | B57: 47.3 | C57: =B57-B56 -> 4.5 | I57: -0.007
A58: 40026 | B58: 47.2 | C58: =B58-B57 -> -0.1 | I58: -0.005
A59: 40057 | B59: 45.8 | C59: =B59-B58 -> -1.4 | D59: -0.003 | I59: -0.001
A60: 40087 | B60: 46.3 | C60: =B60-B59 -> 0.5 | I60: 0.001
A61: 40118 | B61: 45.3 | C61: =B61-B60 -> -1
A62: 40148 | B62: 45.2 | C62: =B62-B61 -> -0.1 | D62: -0.001
A63: 40179 | B63: 45.3 | C63: =B63-B62 -> 0.1
A64: 40210 | B64: 49.1 | C64: =B64-B63 -> 3.8
A65: 40238 | B65: 51.8 | C65: =B65-B64 -> 2.7 | D65: 0.001
A66: 40269 | B66: 53.3 | C66: =B66-B65 -> 1.5
A67: 40299 | B67: 51.5 | C67: =B67-B66 -> -1.8
A68: 40330 | B68: 51.2 | C68: =B68-B67 -> -0.3 | D68: 0.002
A69: 40360 | B69: 51.6 | C69: =B69-B68 -> 0.4
A70: 40391 | B70: 51.2 | C70: =B70-B69 -> -0.4
A71: 40422 | B71: 49.6 | C71: =B71-B70 -> -1.6 | D71: 0
A72: 40452 | B72: 51.2 | C72: =B72-B71 -> 1.6
A73: 40483 | B73: 50 | C73: =B73-B72 -> -1.2
A74: 40513 | B74: 51.5 | C74: =B74-B73 -> 1.5 | D74: 0.002
A75: 40544 | B75: 52 | C75: =B75-B74 -> 0.5
A76: 40575 | B76: 52.1 | C76: =B76-B75 -> 0.1
A77: 40603 | B77: 51.6 | C77: =B77-B76 -> -0.5 | D77: 0.002
A78: 40634 | B78: 50.6 | C78: =B78-B77 -> -1
A79: 40664 | B79: 48.2 | C79: =B79-B78 -> -2.4
A80: 40695 | B80: 47.3 | C80: =B80-B79 -> -0.9 | D80: -0.001
A81: 40725 | B81: 45.6 | C81: =B81-B80 -> -1.7
A82: 40756 | B82: 45.3 | C82: =B82-B81 -> -0.3
A83: 40787 | B83: 43.7 | C83: =B83-B82 -> -1.6 | D83: -0.003
A84: 40817 | B84: 43.9 | C84: =B84-B83 -> 0.2
A85: 40848 | B85: 43.8 | C85: =B85-B84 -> -0.1 | H85: ES | I85: Spain
A86: 40878 | B86: 43.7 | C86: =B86-B85 -> -0.1 | D86: -0.004
A87: 40909 | B87: 45.1 | C87: =B87-B86 -> 1.4
A88: 40940 | B88: 45 | C88: =B88-B87 -> -0.1
A89: 40969 | B89: 44.5 | C89: =B89-B88 -> -0.5 | D89: -0.004
A90: 41000 | B90: 43.5 | C90: =B90-B89 -> -1
A91: 41030 | B91: 42 | C91: =B91-B90 -> -1.5
A92: 41061 | B92: 41.1 | C92: =B92-B91 -> -0.9 | D92: -0.005
A93: 41091 | B93: 42.3 | C93: =B93-B92 -> 1.2
A94: 41122 | B94: 44 | C94: =B94-B93 -> 1.7
A95: 41153 | B95: 44.5 | C95: =B95-B94 -> 0.5 | D95: -0.004
A96: 41183 | B96: 43.5 | C96: =B96-B95 -> -1
A97: 41214 | B97: 45.3 | C97: =B97-B96 -> 1.8
A98: 41244 | B98: 44.6 | C98: =B98-B97 -> -0.7 | D98: -0.008
A99: 41275 | B99: 46.1 | C99: =B99-B98 -> 1.5
A100: 41306 | B100: 46.8 | C100: =B100-B99 -> 0.7
A101: 41334 | B101: 44.2 | C101: =B101-B100 -> -2.6 | D101: -0.003
A102: 41365 | B102: 44.7 | C102: =B102-B101 -> 0.5
A103: 41395 | B103: 48.1 | C103: =B103-B102 -> 3.4
A104: 41426 | B104: 50 | C104: =B104-B103 -> 1.9 | D104: -0.001
A105: 41456 | B105: 49.8 | C105: =B105-B104 -> -0.2
A106: 41487 | B106: 51.1 | C106: =B106-B105 -> 1.3
A107: 41518 | B107: 50.7 | C107: =B107-B106 -> -0.4 | D107: 0.001
A108: 41548 | B108: 50.9 | C108: =B108-B107 -> 0.2
A109: 41579 | B109: 48.6 | C109: =B109-B108 -> -2.3
A110: 41609 | B110: 50.8 | C110: =B110-B109 -> 2.2 | D110: 0.002
A111: 41640 | B111: 52.2 | C111: =B111-B110 -> 1.4
A112: 41671 | B112: 52.5 | C112: =B112-B111 -> 0.3
A113: 41699 | B113: 52.8 | C113: =B113-B112 -> 0.3 | D113: 0.004
A114: 41730 | B114: 52.7 | C114: =B114-B113 -> -0.1
A115: 41760 | B115: 52.9 | C115: =B115-B114 -> 0.2
A116: 41791 | B116: 54.6 | C116: =B116-B115 -> 1.7 | D116: 0.006
A117: 41821 | B117: 53.9 | C117: =B117-B116 -> -0.7
A118: 41852 | B118: 52.8 | C118: =B118-B117 -> -1.1
A119: 41883 | B119: 52.6 | C119: =IFERROR(B119-B118,"") -> -0.2 | D119: =IF(VLOOKUP(I85,Data!$O$51:$V$152,7,FALSE)=A118,VLOOKUP(I85,Data!$O$51:$V$152,2,FALSE)/100,"") -> 0.005
A120: 41913 | B120: 52.6 | C120: 0
A121: 41944 | B121: =IF(A121=Data!$C$1,VLOOKUP($H$85,Data!$A$2:$C$36,3,FALSE),"N/A") -> 54.7 | C121: =B121-B120 -> 2.1
A122: 41974
A123: 42005
A124: 42036
...

Sheet EL
A71: Date | B71: Greece PMI | C71: Change | D71: Greece GDP Growth q/q | E71: Column1
A72: 40482 | B72: 43.6
A73: 40483 | B73: 43.9 | C73: =B73-B72 -> 0.3
A74: 40513 | B74: 43.1 | C74: =B74-B73 -> -0.8 | D74: -0.092
A75: 40544 | B75: 42.8 | C75: =B75-B74 -> -0.3
A76: 40575 | B76: 43.8 | C76: =B76-B75 -> 1
A77: 40603 | B77: 45.4 | C77: =B77-B76 -> 1.6 | D77: -0.083
A78: 40634 | B78: 46.8 | C78: =B78-B77 -> 1.4
A79: 40664 | B79: 44.5 | C79: =B79-B78 -> -2.3
A80: 40695 | B80: 45.5 | C80: =B80-B79 -> 1 | D80: -0.08
A81: 40725 | B81: 45.2 | C81: =B81-B80 -> -0.3
A82: 40756 | B82: 43.3 | C82: =B82-B81 -> -1.9
A83: 40787 | B83: 43.2 | C83: =B83-B82 -> -0.1 | D83: -0.043
A84: 40817 | B84: 40.5 | C84: =B84-B83 -> -2.7
A85: 40848 | B85: 40.9 | C85: =B85-B84 -> 0.4 | H85: EL | I85: Greece
A86: 40878 | B86: 42 | C86: =B86-B85 -> 1.1 | D86: -0.08
A87: 40909 | B87: 41 | C87: =B87-B86 -> -1
A88: 40940 | B88: 37.7 | C88: =B88-B87 -> -3.3
A89: 40969 | B89: 41.3 | C89: =B89-B88 -> 3.6 | D89: -0.078
A90: 41000 | B90: 40.7 | C90: =B90-B89 -> -0.6
A91: 41030 | B91: 43.1 | C91: =B91-B90 -> 2.4
A92: 41061 | B92: 40.1 | C92: =B92-B91 -> -3 | D92: -0.074
A93: 41091 | B93: 41.9 | C93: =B93-B92 -> 1.8
A94: 41122 | B94: 42.1 | C94: =B94-B93 -> 0.2
A95: 41153 | B95: 42.2 | C95: =B95-B94 -> 0.1 | D95: -0.077
A96: 41183 | B96: 41 | C96: =B96-B95 -> -1.2
A97: 41214 | B97: 41.8 | C97: =B97-B96 -> 0.8
A98: 41244 | B98: 41.4 | C98: =B98-B97 -> -0.4 | D98: -0.049
A99: 41275 | B99: 41.7 | C99: =B99-B98 -> 0.3
A100: 41306 | B100: 43 | C100: =B100-B99 -> 1.3
A101: 41334 | B101: 42.1 | C101: =B101-B100 -> -0.9 | D101: -0.06
A102: 41365 | B102: 45 | C102: =B102-B101 -> 2.9
A103: 41395 | B103: 45.3 | C103: =B103-B102 -> 0.3
A104: 41426 | B104: 45.4 | C104: =B104-B103 -> 0.1 | D104: -0.04
A105: 41456 | B105: 47 | C105: =B105-B104 -> 1.6
A106: 41487 | B106: 48.7 | C106: =B106-B105 -> 1.7
A107: 41518 | B107: 47.5 | C107: =B107-B106 -> -1.2 | D107: -0.032
A108: 41548 | B108: 47.3 | C108: =B108-B107 -> -0.2
A109: 41579 | B109: 49.2 | C109: =B109-B108 -> 1.9
A110: 41609 | B110: 49.6 | C110: =B110-B109 -> 0.4 | D110: -0.023
A111: 41640 | B111: 51.2 | C111: =B111-B110 -> 1.6
A112: 41671 | B112: 51.3 | C112: =B112-B111 -> 0.1
A113: 41699 | B113: 49.7 | C113: =B113-B112 -> -1.6 | D113: -0.011
A114: 41730 | B114: 51.1 | C114: =B114-B113 -> 1.4
A115: 41760 | B115: 51 | C115: =B115-B114 -> -0.1
A116: 41791 | B116: 49.4 | C116: =B116-B115 -> -1.6 | D116: 0.002
A117: 41821 | B117: 48.7 | C117: =B117-B116 -> -0.7
A118: 41852 | B118: 50.1 | C118: =B118-B117 -> 1.4
A119: 41883 | B119: 48.4 | C119: =IFERROR(B119-B118,"") -> -1.7 | D119: =IF(VLOOKUP(I85,Data!$O$51:$V$152,7,FALSE)=A118,VLOOKUP(I85,Data!$O$51:$V$152,2,FALSE)/100,"") -> 0.007
A120: 41913 | B120: 48.8 | C120: 0.4
A121: 41944 | B121: =IF(A121=Data!$C$1,VLOOKUP($H$85,Data!$A$2:$C$36,3,FALSE),"N/A") -> 49.1 | C121: =B121-B120 -> 0.3
A122: 41974
A123: 42005
A124: 42036
A125: 42064
A126: 42095
A127: 42125
A128: 42156
A129: 42186
A130: 42217
A131: 42248
A132: 42278
A133: 42309
... A154: 42948
A155: 46143 | B155: 53.3 | E155: gap 2015-Apr26: S&P Global licensed
A156: 46174 | B156: 53.8 | C156: 0.5

Sheet IR
A71: Date | B71: Ireland PMI | C71: Change | D71: Ireland GDP Growth q/q | E71: Column1
A72: 40452 | B72: 50.9
A73: 40483 | B73: 51.2 | C73: =B73-B72 -> 0.3
A74: 40513 | B74: 52.2 | C74: =B74-B73 -> 1
A75: 40544 | B75: 55.8 | C75: =B75-B74 -> 3.6
A76: 40575 | B76: 56.7 | C76: =B76-B75 -> 0.9
A77: 40603 | B77: 55.7 | C77: =B77-B76 -> -1
A78: 40634 | B78: 56 | C78: =B78-B77 -> 0.3
A79: 40664 | B79: 51.8 | C79: =B79-B78 -> -4.2
A80: 40695 | B80: 49.8 | C80: =B80-B79 -> -2
A81: 40725 | B81: 48.2 | C81: =B81-B80 -> -1.6
A82: 40756 | B82: 49.7 | C82: =B82-B81 -> 1.5
A83: 40787 | B83: 47.3 | C83: =B83-B82 -> -2.4 | D83: -0.002
A84: 40817 | B84: 50.1 | C84: =B84-B83 -> 2.8
A85: 40848 | B85: 48.5 | C85: =B85-B84 -> -1.6 | H85: IR | I85: Ireland
A86: 40878 | B86: 49.8 | C86: =B86-B85 -> 1.3 | D86: 0.011
A87: 40909 | B87: 49.3 | C87: =B87-B86 -> -0.5
A88: 40940 | B88: 49.7 | C88: =B88-B87 -> 0.4
A89: 40969 | B89: 51.5 | C89: =B89-B88 -> 1.8 | D89: -0.025
A90: 41000 | B90: 50.1 | C90: =B90-B89 -> -1.4
A91: 41030 | B91: 51.2 | C91: =B91-B90 -> 1.1
A92: 41061 | B92: 53.1 | C92: =B92-B91 -> 1.9 | D92: -0.001
A93: 41091 | B93: 53.9 | C93: =B93-B92 -> 0.8
A94: 41122 | B94: 50.9 | C94: =B94-B93 -> -3
A95: 41153 | B95: 51.8 | C95: =B95-B94 -> 0.9 | D95: 0.007
A96: 41183 | B96: 52.1 | C96: =B96-B95 -> 0.3
A97: 41214 | B97: 52.4 | C97: =B97-B96 -> 0.3
A98: 41244 | B98: 51.4 | C98: =B98-B97 -> -1 | D98: 0.028
A99: 41275 | B99: 50.3 | C99: =B99-B98 -> -1.1
A100: 41306 | B100: 51.5 | C100: =B100-B99 -> 1.2
A101: 41334 | B101: 48.6 | C101: =B101-B100 -> -2.9 | D101: -0.034
A102: 41365 | B102: 48 | C102: =B102-B101 -> -0.6
A103: 41395 | B103: 49.7 | C103: =B103-B102 -> 1.7
A104: 41426 | B104: 50.3 | C104: =B104-B103 -> 0.6 | D104: 0.001
A105: 41456 | B105: 51 | C105: =B105-B104 -> 0.7
A106: 41487 | B106: 52 | C106: =B106-B105 -> 1
A107: 41518 | B107: 52.7 | C107: =B107-B106 -> 0.7 | D107: 0.022
A108: 41548 | B108: 54.9 | C108: =B108-B107 -> 2.2
A109: 41579 | B109: 52.4 | C109: =B109-B108 -> -2.5
A110: 41609 | B110: 53.5 | C110: =B110-B109 -> 1.1 | D110: -0.001
A111: 41640 | B111: 52.8 | C111: =B111-B110 -> -0.7
A112: 41671 | B112: 52.9 | C112: =B112-B111 -> 0.1
A113: 41699 | B113: 55.5 | C113: =B113-B112 -> 2.6 | D113: 0.028
A114: 41730 | B114: 56.1 | C114: =B114-B113 -> 0.6
A115: 41760 | B115: 55 | C115: =B115-B114 -> -1.1
A116: 41791 | B116: 55.3 | C116: =B116-B115 -> 0.3 | D116: 0.015
A117: 41821 | B117: 55.4 | C117: =B117-B116 -> 0.1
A118: 41852 | B118: 57.3 | C118: =B118-B117 -> 1.9
A119: 41883 | B119: 55.7 | C119: =IFERROR(B119-B118,"") -> -1.6 | D119: =IF(VLOOKUP($I$85,Data!$O$51:$V$152,7,FALSE)=A118,VLOOKUP($I$85,Data!$O$51:$V$152,2,FALSE)/100,#N/A) -> #N/A
A120: 41913 | B120: 56.6 | C120: 0.9
A121: 41944 | B121: =IF(A121=Data!$C$1,VLOOKUP($H$85,Data!$A$2:$C$36,3,FALSE),"N/A") -> 56.2 | C121: =B121-B120 -> -0.4
A122: 41974
A123: 42005
A124: 42036
A125: 42064
A126: 42095
A127: 42125
A128: 42156
A129: 42186
A130: 42217
A131: 42248
A132: 42278
A133: 42309
... A154: 42948
A155: 46143 | B155: 55.9 | E155: gap 2015-Apr26: S&P Global licensed
A156: 46174 | B156: 54.9 | C156: -1

Sheet CH
A2: Date | B2: HSBC China PMI | C2: Change | D2: China GDP y/y % | E2: China GDP q/q
A3: 38353 | B3: 52.1
A4: 38384 | B4: 52.9 | C4: =B4-B3 -> 0.8
A5: 38412 | B5: 55.2 | C5: =B5-B4 -> 2.3 | D5: 0.105
A6: 38443 | B6: 54.4 | C6: =B6-B5 -> -0.8
A7: 38473 | B7: 53.3 | C7: =B7-B6 -> -1.1
A8: 38504 | B8: 51 | C8: =B8-B7 -> -2.3 | D8: 0.101
A9: 38534 | B9: 51.5 | C9: =B9-B8 -> 0.5
A10: 38565 | B10: 50.6 | C10: =B10-B9 -> -0.9
A11: 38596 | B11: 50.9 | C11: =B11-B10 -> 0.3 | D11: 0.0998
A12: 38626 | B12: 50.1 | C12: =B12-B11 -> -0.8
A13: 38657 | B13: 49.8 | C13: =B13-B12 -> -0.3
A14: 38687 | B14: 50.1 | C14: =B14-B13 -> 0.3 | D14: 0.099
A15: 38718 | B15: 50.2 | C15: =B15-B14 -> 0.1
A16: 38749 | B16: 50.7 | C16: =B16-B15 -> 0.5
A17: 38777 | B17: 51 | C17: =B17-B16 -> 0.3 | D17: 0.114
A18: 38808 | B18: 52.7 | C18: =B18-B17 -> 1.7
A19: 38838 | B19: 52.8 | C19: =B19-B18 -> 0.1
A20: 38869 | B20: 52.9 | C20: =B20-B19 -> 0.1 | D20: 0.115
A21: 38899 | B21: 53 | C21: =B21-B20 -> 0.1
A22: 38930 | B22: 52.6 | C22: =B22-B21 -> -0.4
A23: 38961 | B23: 52.4 | C23: =B23-B22 -> -0.2 | D23: 0.106
A24: 38991 | B24: 52.1 | C24: =B24-B23 -> -0.3
A25: 39022 | B25: 53 | C25: =B25-B24 -> 0.9
A26: 39052 | B26: 52.4 | C26: =B26-B25 -> -0.6 | D26: 0.104
A27: 39083 | B27: 52 | C27: =B27-B26 -> -0.4
A28: 39114 | B28: 53 | C28: =B28-B27 -> 1
A29: 39142 | B29: 52.3 | C29: =B29-B28 -> -0.7 | D29: 0.13
A30: 39173 | B30: 53.3 | C30: =B30-B29 -> 1
A31: 39203 | B31: 54.1 | C31: =B31-B30 -> 0.8
A32: 39234 | B32: 55 | C32: =B32-B31 -> 0.9 | D32: 0.126
A33: 39264 | B33: 53.2 | C33: =B33-B32 -> -1.8
A34: 39295 | B34: 53.4 | C34: =B34-B33 -> 0.2
A35: 39326 | B35: 55 | C35: =B35-B34 -> 1.6 | D35: 0.115
A36: 39356 | B36: 55.2 | C36: =B36-B35 -> 0.2
A37: 39387 | B37: 52.8 | C37: =B37-B36 -> -2.4
A38: 39417 | B38: 53.3 | C38: =B38-B37 -> 0.5 | D38: 0.112
A39: 39448 | B39: 53.2 | C39: =B39-B38 -> -0.1
A40: 39479 | B40: 52.8 | C40: =B40-B39 -> -0.4
A41: 39508 | B41: 54.4 | C41: =B41-B40 -> 1.6 | D41: 0.106
A42: 39539 | B42: 55.4 | C42: =B42-B41 -> 1
A43: 39569 | B43: 54.7 | C43: =B43-B42 -> -0.7
A44: 39600 | B44: 53.3 | C44: =B44-B43 -> -1.4 | D44: 0.101
A45: 39630 | B45: 53.3 | C45: =B45-B44 -> 0
A46: 39661 | B46: 49.2 | C46: =B46-B45 -> -4.1
A47: 39692 | B47: 47.7 | C47: =B47-B46 -> -1.5 | D47: 0.09
A48: 39722 | B48: 45.2 | C48: =B48-B47 -> -2.5
A49: 39753 | B49: 40.9 | C49: =B49-B48 -> -4.3
A50: 39783 | B50: 41.2 | C50: =B50-B49 -> 0.3 | D50: 0.068
A51: 39814 | B51: 42.2 | C51: =B51-B50 -> 1
A52: 39845 | B52: 45.1 | C52: =B52-B51 -> 2.9
A53: 39873 | B53: 44.8 | C53: =B53-B52 -> -0.3 | D53: 0.062
A54: 39904 | B54: 50.1 | C54: =B54-B53 -> 5.3
A55: 39934 | B55: 51.2 | C55: =B55-B54 -> 1.1
A56: 39965 | B56: 51.8 | C56: =B56-B55 -> 0.6 | D56: 0.079
A57: 39995 | B57: 52.8 | C57: =B57-B56 -> 1
A58: 40026 | B58: 55.1 | C58: =B58-B57 -> 2.3
A59: 40057 | B59: 55 | C59: =B59-B58 -> -0.1 | D59: 0.091
A60: 40087 | B60: 55.4 | C60: =B60-B59 -> 0.4
A61: 40118 | B61: 55.7 | C61: =B61-B60 -> 0.3
A62: 40148 | B62: 56.1 | C62: =B62-B61 -> 0.4 | D62: 0.107
A63: 40179 | B63: 57.4 | C63: =B63-B62 -> 1.3
A64: 40210 | B64: 55.8 | C64: =B64-B63 -> -1.6
A65: 40238 | B65: 57 | C65: =B65-B64 -> 1.2 | D65: 0.119
A66: 40269 | B66: 55.4 | C66: =B66-B65 -> -1.6
A67: 40299 | B67: 52.7 | C67: =B67-B66 -> -2.7
A68: 40330 | B68: 50.4 | C68: =B68-B67 -> -2.3 | D68: 0.103
A69: 40360 | B69: 49.4 | C69: =B69-B68 -> -1
A70: 40391 | B70: 51.9 | C70: =B70-B69 -> 2.5
A71: 40422 | B71: 52.9 | C71: =B71-B70 -> 1 | D71: 0.096
A72: 40452 | B72: 54.8 | C72: =B72-B71 -> 1.9
A73: 40483 | B73: 55.3 | C73: =B73-B72 -> 0.5
A74: 40513 | B74: 54.4 | C74: =B74-B73 -> -0.9 | D74: 0.098 | E74: 0.024
A75: 40544 | B75: 54.5 | C75: =B75-B74 -> 0.1
A76: 40575 | B76: 51.7 | C76: =B76-B75 -> -2.8
A77: 40603 | B77: 51.8 | C77: =B77-B76 -> 0.1 | D77: 0.097 | E77: 0.023
A78: 40634 | B78: 51.8 | C78: =B78-B77 -> 0
A79: 40664 | B79: 51.6 | C79: =B79-B78 -> -0.2
A80: 40695 | B80: 50.1 | C80: =B80-B79 -> -1.5 | D80: 0.095 | E80: 0.025
A81: 40725 | B81: 49.3 | C81: =B81-B80 -> -0.8
A82: 40756 | B82: 49.9 | C82: =B82-B81 -> 0.6
A83: 40787 | B83: 49.9 | C83: =B83-B82 -> 0 | D83: 0.091 | E83: 0.022
A84: 40817 | B84: 51 | C84: =B84-B83 -> 1.1
A85: 40848 | B85: 47.7 | C85: =B85-B84 -> -3.3 | H85: CH | I85: China
A86: 40878 | B86: 48.7 | C86: =B86-B85 -> 1 | D86: 0.089 | E86: 0.018
A87: 40909 | B87: 48.8 | C87: =B87-B86 -> 0.1
A88: 40940 | B88: 49.6 | C88: =B88-B87 -> 0.8
A89: 40969 | B89: 48.3 | C89: =B89-B88 -> -1.3 | D89: 0.081 | E89: 0.014
A90: 41000 | B90: 49.3 | C90: =B90-B89 -> 1
A91: 41031 | B91: 48.4 | C91: =B91-B90 -> -0.9
A92: 41063 | B92: 48.2 | C92: =B92-B91 -> -0.2 | D92: 0.076 | E92: 0.021
A93: 41094 | B93: 49.3 | C93: =B93-B92 -> 1.1
A94: 41126 | B94: 47.7 | C94: =B94-B93 -> -1.6
A95: 41158 | B95: 47.9 | C95: =B95-B94 -> 0.2 | D95: 0.074 | E95: 0.02
A96: 41189 | B96: 49.5 | C96: =B96-B95 -> 1.6
A97: 41221 | B97: 50.5 | C97: =B97-B96 -> 1
A98: 41252 | B98: 51.5 | C98: =B98-B97 -> 1 | D98: 0.079 | E98: 0.019
A99: 41275 | B99: 52.3 | C99: =B99-B98 -> 0.8
A100: 41307 | B100: 50.4 | C100: =B100-B99 -> -1.9
A101: 41336 | B101: 51.6 | C101: =B101-B100 -> 1.2 | D101: 0.077 | E101: 0.015
...

Sheet JP
A62: Date | B62: Japan PMI | C62: Change | D62: Japan GDP Growth q/q | E62: Column1
A63: 40179 | B63: 53.8
A64: 40210 | B64: 52.5 | C64: =B64-B63 -> -1.3
A65: 40238 | B65: 53.8 | C65: =B65-B64 -> 1.3 | D65: 0.014
A66: 40269 | B66: 53.5 | C66: =B66-B65 -> -0.3
A67: 40299 | B67: 54.7 | C67: =B67-B66 -> 1.2
A68: 40330 | B68: 53.9 | C68: =B68-B67 -> -0.8 | D68: 0.011
A69: 40360 | B69: 52.8 | C69: =B69-B68 -> -1.1
A70: 40391 | B70: 50.1 | C70: =B70-B69 -> -2.7
A71: 40422 | B71: 49.5 | C71: =B71-B70 -> -0.6 | D71: 0.014
A72: 40452 | B72: 47.2 | C72: =B72-B71 -> -2.3
A73: 40483 | B73: 47.3 | C73: =B73-B72 -> 0.1
A74: 40513 | B74: 48.3 | C74: =B74-B73 -> 1 | D74: -0.005
A75: 40544 | B75: 51.4 | C75: =B75-B74 -> 3.1
A76: 40575 | B76: 52.9 | C76: =B76-B75 -> 1.5
A77: 40603 | B77: 41.4 | C77: =B77-B76 -> -11.5 | D77: -0.018
A78: 40634 | B78: 45.7 | C78: =B78-B77 -> 4.3
A79: 40664 | B79: 51.3 | C79: =B79-B78 -> 5.6
A80: 40695 | B80: 50.7 | C80: =B80-B79 -> -0.6 | D80: -0.007
A81: 40725 | B81: 52.1 | C81: =B81-B80 -> 1.4
A82: 40756 | B82: 51.9 | C82: =B82-B81 -> -0.2
A83: 40787 | B83: 49.3 | C83: =B83-B82 -> -2.6 | D83: 0.026
A84: 40817 | B84: 50.6 | C84: =B84-B83 -> 1.3
A85: 40848 | B85: 49.1 | C85: =B85-B84 -> -1.5 | H85: JP | I85: Japan
A86: 40878 | B86: 50.2 | C86: =B86-B85 -> 1.1 | D86: 0.002
A87: 40909 | B87: 50.7 | C87: =B87-B86 -> 0.5
A88: 40940 | B88: 50.5 | C88: =B88-B87 -> -0.2
A89: 40969 | B89: 51.1 | C89: =B89-B88 -> 0.6 | D89: 0.009
A90: 41000 | B90: 50.7 | C90: =B90-B89 -> -0.4
A91: 41030 | B91: 50.7 | C91: =B91-B90 -> 0
A92: 41061 | B92: 52.6 | C92: =B92-B91 -> 1.9 | D92: -0.005
A93: 41091 | B93: 52 | C93: =B93-B92 -> -0.6
A94: 41122 | B94: 52.1 | C94: =B94-B93 -> 0.1
A95: 41153 | B95: 48 | C95: =B95-B94 -> -4.1 | D95: -0.008
A96: 41183 | B96: 46.9 | C96: =B96-B95 -> -1.1
A97: 41214 | B97: 46.5 | C97: =B97-B96 -> -0.4
A98: 41244 | B98: 45 | C98: =B98-B97 -> -1.5 | D98: 0.001
A99: 41275 | B99: 47.7 | C99: =B99-B98 -> 2.7
A100: 41306 | B100: 48.5 | C100: =B100-B99 -> 0.8
A101: 41334 | B101: 50.4 | C101: =B101-B100 -> 1.9 | D101: 0.012
A102: 41365 | B102: 51.1 | C102: =B102-B101 -> 0.7
A103: 41395 | B103: 51.5 | C103: =B103-B102 -> 0.4
A104: 41426 | B104: 52.3 | C104: =B104-B103 -> 0.8 | D104: 0.009
A105: 41456 | B105: 50.7 | C105: =B105-B104 -> -1.6
A106: 41487 | B106: 52.2 | C106: =B106-B105 -> 1.5
A107: 41518 | B107: 52.5 | C107: =B107-B106 -> 0.3 | D107: 0.003
A108: 41548 | B108: 54.2 | C108: =B108-B107 -> 1.7
A109: 41579 | B109: 55.1 | C109: =B109-B108 -> 0.9
A110: 41609 | B110: 55.2 | C110: =B110-B109 -> 0.1 | D110: 0.001
A111: 41640 | B111: 56.6 | C111: =B111-B110 -> 1.4
A112: 41671 | B112: 55.5 | C112: =B112-B111 -> -1.1
A113: 41699 | B113: 53.9 | C113: =B113-B112 -> -1.6 | D113: 0.016
A114: 41730 | B114: 49.4 | C114: =B114-B113 -> -4.5
A115: 41760 | B115: 49.9 | C115: =B115-B114 -> 0.5
A116: 41791 | B116: 51.5 | C116: =B116-B115 -> 1.6 | D116: -0.017
A117: 41821 | B117: 50.5 | C117: =B117-B116 -> -1
A118: 41852 | B118: 52.2 | C118: =B118-B117 -> 1.7
A119: 41883 | B119: 51.7 | C119: =IFERROR(B119-B118,"") -> -0.5 | D119: =IF(VLOOKUP(I85,Data!$O$51:$V$152,7,FALSE)=A118,VLOOKUP(I85,Data!$O$51:$V$152,2,FALSE)/100,"") -> -0.004
A120: 41913 | B120: 52.4 | C120: 0.7
A121: 41944 | B121: =IF(A121=Data!$C$1,VLOOKUP($H$85,Data!$A$2:$C$36,3,FALSE),"N/A") -> 52 | C121: =B121-B120 -> -0.4
A122: 41974
A123: 42005
A124: 42036
A125: 42064
A126: 42095
A127: 42125
A128: 42156
A129: 42186
A130: 42217
A131: 42248
A132: 42278
A133: 42309
... A154: 42948
A155: 46143 | B155: 54.5 | E155: gap 2015-Apr26: S&P Global licensed
A156: 46174 | B156: 54.8 | C156: 0.3

Sheet BRL
A71: Date | B71: Brasil PMI | C71: Change | D71: Brazil GDP Growth q/q | E71: Column1
A72: 40452 | B72: 49.5
A73: 40483 | B73: 49.9 | C73: =B73-B72 -> 0.4
A74: 40513 | B74: 52.4 | C74: =B74-B73 -> 2.5 | D74: 0.011
A75: 40544 | B75: 53.1 | C75: =B75-B74 -> 0.7
A76: 40575 | B76: 54.6 | C76: =B76-B75 -> 1.5
A77: 40603 | B77: 53.2 | C77: =B77-B76 -> -1.4 | D77: 0.006
A78: 40634 | B78: 52.5 | C78: =B78-B77 -> -0.7
A79: 40664 | B79: 53 | C79: =B79-B78 -> 0.5
A80: 40695 | B80: 49 | C80: =B80-B79 -> -4 | D80: 0.005
A81: 40725 | B81: 47.8 | C81: =B81-B80 -> -1.2
A82: 40756 | B82: 46 | C82: =B82-B81 -> -1.8
A83: 40787 | B83: 45.5 | C83: =B83-B82 -> -0.5 | D83: -0.001
A84: 40817 | B84: 46.5 | C84: =B84-B83 -> 1
A85: 40848 | B85: 48.7 | C85: =B85-B84 -> 2.2 | H85: BRL | I85: Brazil
A86: 40878 | B86: 49.3 | C86: =B86-B85 -> 0.6 | D86: 0.001
A87: 40909 | B87: 50.6 | C87: =B87-B86 -> 1.3
A88: 40940 | B88: 51.4 | C88: =B88-B87 -> 0.8
A89: 40969 | B89: 51.1 | C89: =B89-B88 -> -0.3 | D89: 0.001
A90: 41000 | B90: 49.3 | C90: =B90-B89 -> -1.8
A91: 41030 | B91: 49.3 | C91: =B91-B90 -> 0
A92: 41061 | B92: 48.5 | C92: =B92-B91 -> -0.8 | D92: 0.001
A93: 41091 | B93: 48.7 | C93: =B93-B92 -> 0.2
A94: 41122 | B94: 49.3 | C94: =B94-B93 -> 0.6
A95: 41153 | B95: 49.8 | C95: =B95-B94 -> 0.5 | D95: 0.006
A96: 41183 | B96: 50.2 | C96: =B96-B95 -> 0.4
A97: 41214 | B97: 52.2 | C97: =B97-B96 -> 2
A98: 41244 | B98: 51.1 | C98: =B98-B97 -> -1.1 | D98: 0.009
A99: 41275 | B99: 53.2 | C99: =B99-B98 -> 2.1
A100: 41306 | B100: 52.5 | C100: =B100-B99 -> -0.7
A101: 41334 | B101: 51.8 | C101: =B101-B100 -> -0.7 | D101: 0
A102: 41365 | B102: 50.8 | C102: =B102-B101 -> -1
A103: 41395 | B103: 50.4 | C103: =B103-B102 -> -0.4
A104: 41426 | B104: 50.4 | C104: =B104-B103 -> 0 | D104: 0.018
A105: 41456 | B105: 48.5 | C105: =B105-B104 -> -1.9
A106: 41487 | B106: 49.4 | C106: =B106-B105 -> 0.9
A107: 41518 | B107: 49.9 | C107: =B107-B106 -> 0.5 | D107: -0.005
A108: 41548 | B108: 50.2 | C108: =B108-B107 -> 0.3
A109: 41579 | B109: 49.7 | C109: =B109-B108 -> -0.5
A110: 41609 | B110: 50.5 | C110: =B110-B109 -> 0.8 | D110: 0.007
A111: 41640 | B111: 51.7 | C111: =B111-B110 -> 1.2
A112: 41671 | B112: 50.4 | C112: =B112-B111 -> -1.3
A113: 41699 | B113: 50.6 | C113: =B113-B112 -> 0.2 | D113: 0.002
A114: 41730 | B114: 49.3 | C114: =B114-B113 -> -1.3
A115: 41760 | B115: 48.8 | C115: =B115-B114 -> -0.5
A116: 41791 | B116: 48.7 | C116: =B116-B115 -> -0.1 | D116: -0.006
A117: 41821 | B117: 49.1 | C117: =B117-B116 -> 0.4
A118: 41852 | B118: 50.2 | C118: =B118-B117 -> 1.1
A119: 41883 | B119: 49.3 | C119: =IFERROR(B119-B118,"") -> -0.9 | D119: =IF(VLOOKUP(I85,Data!$O$51:$V$152,7,FALSE)=A118,VLOOKUP(I85,Data!$O$51:$V$152,2,FALSE)/100,"") -> 0.001
A120: 41913 | B120: 49.1 | C120: -0.2
A121: 41944 | B121: =IF(A121=Data!$C$1,VLOOKUP($H$85,Data!$A$2:$C$36,3,FALSE),"N/A") -> 48.7 | C121: =B121-B120 -> -0.4
A122: 41974
A123: 42005
A124: 42036
A125: 42064
A126: 42095
A127: 42125
A128: 42156
A129: 42186
A130: 42217
A131: 42248
A132: 42278
A133: 42309
... A154: 42948
A155: 46143 | B155: 49.1 | E155: gap 2015-Apr26: S&P Global licensed
A156: 46174 | B156: 50.8 | C156: 1.7

Sheet IND
A71: Date | B71: India PMI | C71: Change | D71: India GDP Growth q/q | E71: Column1
A72: 40452 | B72: 57.2
A73: 40483 | B73: 58.4 | C73: =B73-B72 -> 1.2
A74: 40513 | B74: 56.7 | C74: =B74-B73 -> -1.7 | D74: 0.023
A75: 40544 | B75: 56.8 | C75: =B75-B74 -> 0.1
A76: 40575 | B76: 57.9 | C76: =B76-B75 -> 1.1
A77: 40603 | B77: 57.9 | C77: =B77-B76 -> 0 | D77: 0.019
A78: 40634 | B78: 58 | C78: =B78-B77 -> 0.1
A79: 40664 | B79: 57.5 | C79: =B79-B78 -> -0.5
A80: 40695 | B80: 55.3 | C80: =B80-B79 -> -2.2 | D80: 0.016
A81: 40725 | B81: 56.3 | C81: =B81-B80 -> 1
A82: 40756 | B82: 52.6 | C82: =B82-B81 -> -3.7
A83: 40787 | B83: 50.4 | C83: =B83-B82 -> -2.2 | D83: 0.011
A84: 40817 | B84: 51 | C84: =B84-B83 -> 0.6
A85: 40848 | B85: 52 | C85: =B85-B84 -> 1 | H85: IND | I85: Indonesia
A86: 40878 | B86: 57 | C86: =B86-B85 -> 5 | D86: 0.011
A87: 40909 | B87: 57.5 | C87: =B87-B86 -> 0.5
A88: 40940 | B88: 56.6 | C88: =B88-B87 -> -0.9
A89: 40969 | B89: 54.7 | C89: =B89-B88 -> -1.9 | D89: 0.013
A90: 41000 | B90: 54.9 | C90: =B90-B89 -> 0.2
A91: 41030 | B91: 54.8 | C91: =B91-B90 -> -0.1
A92: 41061 | B92: 55 | C92: =B92-B91 -> 0.2 | D92: 0.014
A93: 41091 | B93: 52.9 | C93: =B93-B92 -> -2.1
A94: 41122 | B94: 52.8 | C94: =B94-B93 -> -0.1
A95: 41153 | B95: 52.8 | C95: =B95-B94 -> 0 | D95: 0.007
A96: 41183 | B96: 52.9 | C96: =B96-B95 -> 0.1
A97: 41214 | B97: 53.7 | C97: =B97-B96 -> 0.8
A98: 41244 | B98: 54.7 | C98: =B98-B97 -> 1 | D98: 0.015
A99: 41275 | B99: 53.2 | C99: =B99-B98 -> -1.5
A100: 41306 | B100: 54.2 | C100: =B100-B99 -> 1
A101: 41334 | B101: 52 | C101: =B101-B100 -> -2.2 | D101: 0.01
A102: 41365 | B102: 51 | C102: =B102-B101 -> -1
A103: 41395 | B103: 50.1 | C103: =B103-B102 -> -0.9
A104: 41426 | B104: 50.3 | C104: =B104-B103 -> 0.2 | D104: 0.007
A105: 41456 | B105: 50.1 | C105: =B105-B104 -> -0.2
A106: 41487 | B106: 48.5 | C106: =B106-B105 -> -1.6
A107: 41518 | B107: 49.6 | C107: =B107-B106 -> 1.1 | D107: 0.018
A108: 41548 | B108: 49.6 | C108: =B108-B107 -> 0
A109: 41579 | B109: 51.3 | C109: =B109-B108 -> 1.7
A110: 41609 | B110: 50.7 | C110: =B110-B109 -> -0.6 | D110: 0.011
A111: 41640 | B111: 51.4 | C111: =B111-B110 -> 0.7
A112: 41671 | B112: 52.5 | C112: =B112-B111 -> 1.1
A113: 41699 | B113: 51.3 | C113: =B113-B112 -> -1.2 | D113: 0.021
A114: 41730 | B114: 51.3 | C114: =B114-B113 -> 0
A115: 41760 | B115: 51.4 | C115: =B115-B114 -> 0.1
A116: 41791 | B116: 51.5 | C116: =B116-B115 -> 0.1 | D116: 0.0249
A117: 41821 | B117: 53 | C117: =B117-B116 -> 1.5
A118: 41852 | B118: 52.4 | C118: =B118-B117 -> -0.6
A119: 41883 | B119: 51 | C119: =IFERROR(B119-B118,"") -> -1.4 | D119: =IF(VLOOKUP(I85,Data!$O$51:$V$152,7,FALSE)=A118,VLOOKUP(I85,Data!$O$51:$V$152,2,FALSE)/100,"") -> 0.0296
A120: 41913 | B120: 51.6 | C120: 0.6
A121: 41944 | B121: =IF(A121=Data!$C$1,VLOOKUP($H$85,Data!$A$2:$C$36,3,FALSE),"N/A") -> 53.3 | C121: =B121-B120 -> 1.7
A122: 41974
A123: 42005
A124: 42036
A125: 42064
A126: 42095
A127: 42125
A128: 42156
A129: 42186
A130: 42217
A131: 42248
A132: 42278
A133: 42309
... A154: 42948
A155: 46143 | B155: 55 | E155: gap 2015-Apr26: S&P Global licensed
A156: 46174 | B156: 54.2 | C156: -0.8

Sheet RS
A71: Date | B71: Russia PMI | C71: Change | D71: Russian GDP Growth q/q | E71: Column1
A72: 40452 | B72: 51.8
A73: 40483 | B73: 51.1 | C73: =B73-B72 -> -0.7
A74: 40513 | B74: 53.5 | C74: =B74-B73 -> 2.4 | D74: 0.01
A75: 40544 | B75: 53.5 | C75: =B75-B74 -> 0
A76: 40575 | B76: 56.4 | C76: =B76-B75 -> 2.9
A77: 40603 | B77: 55.1 | C77: =B77-B76 -> -1.3 | D77: 0.009
A78: 40634 | B78: 52.1 | C78: =B78-B77 -> -3
A79: 40664 | B79: 50.9 | C79: =B79-B78 -> -1.2
A80: 40695 | B80: 50.6 | C80: =B80-B79 -> -0.3 | D80: 0.013
A81: 40725 | B81: 49.8 | C81: =B81-B80 -> -0.8
A82: 40756 | B82: 49.9 | C82: =B82-B81 -> 0.1
A83: 40787 | B83: 50 | C83: =B83-B82 -> 0.1 | D83: 0.014
A84: 40817 | B84: 50.4 | C84: =B84-B83 -> 0.4
A85: 40848 | B85: 52.6 | C85: =B85-B84 -> 2.2 | H85: RS | I85: Russia
A86: 40878 | B86: 51.6 | C86: =B86-B85 -> -1 | D86: 0.015
A87: 40909 | B87: 50.8 | C87: =B87-B86 -> -0.8
A88: 40940 | B88: 50.7 | C88: =B88-B87 -> -0.1
A89: 40969 | B89: 50.8 | C89: =B89-B88 -> 0.1 | D89: 0.008
A90: 41000 | B90: 52.9 | C90: =B90-B89 -> 2.1
A91: 41030 | B91: 53.2 | C91: =B91-B90 -> 0.3
A92: 41061 | B92: 51 | C92: =B92-B91 -> -2.2 | D92: 0.006
A93: 41091 | B93: 52 | C93: =B93-B92 -> 1
A94: 41122 | B94: 51 | C94: =B94-B93 -> -1
A95: 41153 | B95: 52.4 | C95: =B95-B94 -> 1.4 | D95: 0.003
A96: 41183 | B96: 52.9 | C96: =B96-B95 -> 0.5
A97: 41214 | B97: 52.2 | C97: =B97-B96 -> -0.7
A98: 41244 | B98: 50 | C98: =B98-B97 -> -2.2 | D98: -0.002
A99: 41275 | B99: 52 | C99: =B99-B98 -> 2
A100: 41306 | B100: 52 | C100: =B100-B99 -> 0
A101: 41334 | B101: 50.8 | C101: =B101-B100 -> -1.2 | D101: 0.005
A102: 41365 | B102: 50.6 | C102: =B102-B101 -> -0.2
A103: 41395 | B103: 50.4 | C103: =B103-B102 -> -0.2
A104: 41426 | B104: 51.7 | C104: =B104-B103 -> 1.3 | D104: 0.004
A105: 41456 | B105: 49.2 | C105: =B105-B104 -> -2.5
A106: 41487 | B106: 49.4 | C106: =B106-B105 -> 0.2
A107: 41518 | B107: 49.4 | C107: =B107-B106 -> 0 | D107: 0.003
A108: 41548 | B108: 51.8 | C108: =B108-B107 -> 2.4
A109: 41579 | B109: 49.4 | C109: =B109-B108 -> -2.4
A110: 41609 | B110: 48.8 | C110: =B110-B109 -> -0.6 | D110: 0.003
A111: 41640 | B111: 48 | C111: =B111-B110 -> -0.8
A112: 41671 | B112: 48.5 | C112: =B112-B111 -> 0.5
A113: 41699 | B113: 48.3 | C113: =B113-B112 -> -0.2 | D113: -0.003
A114: 41730 | B114: 48.5 | C114: =B114-B113 -> 0.2
A115: 41760 | B115: 48.9 | C115: =B115-B114 -> 0.4
A116: 41791 | B116: 49.1 | C116: =B116-B115 -> 0.2 | D116: 0.0025
A117: 41821 | B117: 51 | C117: =B117-B116 -> 1.9
A118: 41852 | B118: 51 | C118: =B118-B117 -> 0
A119: 41883 | B119: 50.4 | C119: =IFERROR(B119-B118,"") -> -0.6 | D119: =IF(VLOOKUP(I85,Data!$O$51:$V$152,7,FALSE)=A118,VLOOKUP(I85,Data!$O$51:$V$152,2,FALSE)/100,#N/A) -> #N/A
A120: 41913 | B120: 50.3 | C120: -0.1
A121: 41944 | B121: =IF(A121=Data!$C$1,VLOOKUP($H$85,Data!$A$2:$C$36,3,FALSE),"N/A") -> 51.7 | C121: =B121-B120 -> 1.4
A122: 41974
A123: 42005
A124: 42036
A125: 42064
A126: 42095
A127: 42125
A128: 42156
A129: 42186
A130: 42217
A131: 42248
A132: 42278
A133: 42309
... A154: 42948
A155: 46143 | B155: 48.8 | E155: gap 2015-Apr26: S&P Global licensed
A156: 46174 | B156: 50.3 | C156: 1.5

Sheet MX
A77: Date | B77: Mexico PMI | C77: Change | D77: Mexico GDP Growth q/q | E77: Column1
A78: 40634 | B78: 56.1
A79: 40664 | B79: 54.5 | C79: =B79-B78 -> -1.6
A80: 40695 | B80: 55.1 | C80: =B80-B79 -> 0.6 | D80: 0.009
A81: 40725 | B81: 54.8 | C81: =B81-B80 -> -0.3
A82: 40756 | B82: 51.7 | C82: =B82-B81 -> -3.1
A83: 40787 | B83: 53.2 | C83: =B83-B82 -> 1.5 | D83: 0.014
A84: 40817 | B84: 54.8 | C84: =B84-B83 -> 1.6
A85: 40848 | B85: 53.9 | C85: =B85-B84 -> -0.9 | H85: MX | I85: Mexico
A86: 40878 | B86: 53.1 | C86: =B86-B85 -> -0.8 | D86: 0.008
A87: 40909 | B87: 52.2 | C87: =B87-B86 -> -0.9
A88: 40940 | B88: 53.7 | C88: =B88-B87 -> 1.5
A89: 40969 | B89: 53.8 | C89: =B89-B88 -> 0.1 | D89: 0.007
A90: 41000 | B90: 56.3 | C90: =B90-B89 -> 2.5
A91: 41030 | B91: 55.2 | C91: =B91-B90 -> -1.1
A92: 41061 | B92: 55.9 | C92: =B92-B91 -> 0.7 | D92: 0.016
A93: 41091 | B93: 55.2 | C93: =B93-B92 -> -0.7
A94: 41122 | B94: 55.1 | C94: =B94-B93 -> -0.1
A95: 41153 | B95: 54.4 | C95: =B95-B94 -> -0.7 | D95: 0.001
A96: 41183 | B96: 55.5 | C96: =B96-B95 -> 1.1
A97: 41214 | B97: 55.6 | C97: =B97-B96 -> 0.1
A98: 41244 | B98: 57.1 | C98: =B98-B97 -> 1.5 | D98: 0.009
A99: 41275 | B99: 55 | C99: =B99-B98 -> -2.1
A100: 41306 | B100: 53.4 | C100: =B100-B99 -> -1.6
A101: 41334 | B101: 52.2 | C101: =B101-B100 -> -1.2 | D101: 0.002
A102: 41365 | B102: 51.7 | C102: =B102-B101 -> -0.5
A103: 41395 | B103: 51.8 | C103: =B103-B102 -> 0.1
A104: 41426 | B104: 51.3 | C104: =B104-B103 -> -0.5 | D104: -0.007
A105: 41456 | B105: 49.7 | C105: =B105-B104 -> -1.6
A106: 41487 | B106: 50.8 | C106: =B106-B105 -> 1.1
A107: 41518 | B107: 50 | C107: =B107-B106 -> -0.8 | D107: 0.009
A108: 41548 | B108: 50.2 | C108: =B108-B107 -> 0.2
A109: 41579 | B109: 51.9 | C109: =B109-B108 -> 1.7
A110: 41609 | B110: 52.6 | C110: =B110-B109 -> 0.7 | D110: 0.001
A111: 41640 | B111: 54 | C111: =B111-B110 -> 1.4
A112: 41671 | B112: 52 | C112: =B112-B111 -> -2
A113: 41699 | B113: 51.7 | C113: =B113-B112 -> -0.3 | D113: 0.002
A114: 41730 | B114: 51.8 | C114: =B114-B113 -> 0.1
A115: 41760 | B115: 51.9 | C115: =B115-B114 -> 0.1
A116: 41791 | B116: 51.8 | C116: =B116-B115 -> -0.1 | D116: 0.01
A117: 41821 | B117: 51.5 | C117: =B117-B116 -> -0.3
A118: 41852 | B118: 52.1 | C118: =B118-B117 -> 0.6
A119: 41883 | B119: 52.6 | C119: =IFERROR(B119-B118,"") -> 0.5 | D119: =IF(VLOOKUP(I85,Data!$O$51:$V$152,7,FALSE)=A118,VLOOKUP(I85,Data!$O$51:$V$152,2,FALSE)/100,"") -> 0.005
A120: 41913 | B120: 53.3 | C120: 0.7
A121: 41944 | B121: =IF(A121=Data!$C$1,VLOOKUP($H$85,Data!$A$2:$C$36,3,FALSE),"N/A") -> 54.3 | C121: =B121-B120 -> 1
A122: 41974
A123: 42005
A124: 42036
A125: 42064
A126: 42095
A127: 42125
A128: 42156
A129: 42186
A130: 42217
A131: 42248
A132: 42278
A133: 42309
... A154: 42948
A155: 46143 | B155: 49.6 | E155: gap 2015-Apr26: S&P Global licensed
A156: 46174 | B156: 51.3 | C156: 1.7

Sheet AU
A42: Date | B42: Australia PMI | C42: Change | D42: GDP Change y/y | E42: Column1
A43: 39569 | B43: 51.4
A44: 39600 | B44: 51.2 | C44: =B44-B43 -> -0.2 | D44: 0.001
A45: 39630 | B45: 52.7 | C45: =B45-B44 -> 1.5
A46: 39661 | B46: 51.2 | C46: =B46-B45 -> -1.5
A47: 39692 | B47: 47 | C47: =B47-B46 -> -4.2 | D47: 0.006
A48: 39722 | B48: 46.9 | C48: =B48-B47 -> -0.1
A49: 39753 | B49: 40.4 | C49: =B49-B48 -> -6.5
A50: 39783 | B50: 33.7 | C50: =B50-B49 -> -6.7 | D50: -0.007
A51: 39814 | B51: 36.6 | C51: =B51-B50 -> 2.9
A52: 39845 | B52: 31.7 | C52: =B52-B51 -> -4.9
A53: 39873 | B53: 33.4 | C53: =B53-B52 -> 1.7 | D53: 0.008
A54: 39904 | B54: 30.1 | C54: =B54-B53 -> -3.3
A55: 39934 | B55: 37.5 | C55: =B55-B54 -> 7.4
A56: 39965 | B56: 38.4 | C56: =B56-B55 -> 0.9 | D56: 0.001
A57: 39995 | B57: 44.5 | C57: =B57-B56 -> 6.1
A58: 40026 | B58: 51.7 | C58: =B58-B57 -> 7.2
A59: 40057 | B59: 52 | C59: =B59-B58 -> 0.3 | D59: 0.008
A60: 40087 | B60: 51.7 | C60: =B60-B59 -> -0.3
A61: 40118 | B61: 51.2 | C61: =B61-B60 -> -0.5
A62: 40148 | B62: 48.5 | C62: =B62-B61 -> -2.7 | D62: 0.008
A63: 40179 | B63: 51 | C63: =B63-B62 -> 2.5
A64: 40210 | B64: 53.8 | C64: =B64-B63 -> 2.8
A65: 40238 | B65: 50.2 | C65: =B65-B64 -> -3.6 | D65: 0.007
A66: 40269 | B66: 59.8 | C66: =B66-B65 -> 9.6
A67: 40299 | B67: 56.3 | C67: =B67-B66 -> -3.5
A68: 40330 | B68: 52.9 | C68: =B68-B67 -> -3.4 | D68: 0.006
A69: 40360 | B69: 54.4 | C69: =B69-B68 -> 1.5
A70: 40391 | B70: 51.7 | C70: =B70-B69 -> -2.7
A71: 40422 | B71: 47.3 | C71: =B71-B70 -> -4.4 | D71: 0.003
A72: 40452 | B72: 49.4 | C72: =B72-B71 -> 2.1
A73: 40483 | B73: 47.6 | C73: =B73-B72 -> -1.8
A74: 40513 | B74: 46.3 | C74: =B74-B73 -> -1.3 | D74: 0.006
A75: 40544 | B75: 46.7 | C75: =B75-B74 -> 0.4
A76: 40575 | B76: 51.1 | C76: =B76-B75 -> 4.4
A77: 40603 | B77: 47.9 | C77: =B77-B76 -> -3.2 | D77: -0.005
A78: 40634 | B78: 48.4 | C78: =B78-B77 -> 0.5
A79: 40664 | B79: 47.7 | C79: =B79-B78 -> -0.7
A80: 40695 | B80: 52.9 | C80: =B80-B79 -> 5.2 | D80: 0.012
A81: 40725 | B81: 43.4 | C81: =B81-B80 -> -9.5
A82: 40756 | B82: 43.3 | C82: =B82-B81 -> -0.1
A83: 40787 | B83: 42.3 | C83: =B83-B82 -> -1 | D83: 0.012
A84: 40817 | B84: 47.4 | C84: =B84-B83 -> 5.1
A85: 40848 | B85: 47.8 | C85: =B85-B84 -> 0.4 | H85: AU | I85: Australia
A86: 40878 | B86: 50.2 | C86: =B86-B85 -> 2.4 | D86: 0.006
A87: 40909 | B87: 51.6 | C87: =B87-B86 -> 1.4
A88: 40940 | B88: 51.3 | C88: =B88-B87 -> -0.3
A89: 40969 | B89: 49.5 | C89: =B89-B88 -> -1.8 | D89: 0.013
A90: 41000 | B90: 43.9 | C90: =B90-B89 -> -5.6
A91: 41030 | B91: 42.4 | C91: =B91-B90 -> -1.5
A92: 41061 | B92: 47.2 | C92: =B92-B91 -> 4.8 | D92: 0.005
A93: 41091 | B93: 40.3 | C93: =B93-B92 -> -6.9
A94: 41122 | B94: 45.3 | C94: =B94-B93 -> 5
A95: 41153 | B95: 44.1 | C95: =B95-B94 -> -1.2 | D95: 0.008
A96: 41183 | B96: 45.2 | C96: =B96-B95 -> 1.1
A97: 41214 | B97: 43.6 | C97: =B97-B96 -> -1.6
A98: 41244 | B98: 44.3 | C98: =B98-B97 -> 0.7 | D98: 0.007
A99: 41275 | B99: 40.2 | C99: =B99-B98 -> -4.1
A100: 41306 | B100: 45.6 | C100: =B100-B99 -> 5.4
A101: 41334 | B101: 44.4 | C101: =B101-B100 -> -1.2 | D101: 0.005
A102: 41365 | B102: 36.7 | C102: =B102-B101 -> -7.7
A103: 41395 | B103: 43.8 | C103: =B103-B102 -> 7.1
A104: 41426 | B104: 49.6 | C104: =B104-B103 -> 5.8 | D104: 0.007
A105: 41456 | B105: 42 | C105: =B105-B104 -> -7.6
A106: 41487 | B106: 46.4 | C106: =B106-B105 -> 4.4
A107: 41518 | B107: 51.7 | C107: =B107-B106 -> 5.3 | D107: 0.006
A108: 41548 | B108: 53.2 | C108: =B108-B107 -> 1.5
A109: 41579 | B109: 47.7 | C109: =B109-B108 -> -5.5
A110: 41609 | B110: 47.6 | C110: =B110-B109 -> -0.1 | D110: 0.008
A111: 41640 | B111: 46.7 | C111: =B111-B110 -> -0.9
A112: 41671 | B112: 48.6 | C112: =B112-B111 -> 1.9
A113: 41699 | B113: 49.7 | C113: =B113-B112 -> 1.1 | D113: 0.011
A114: 41730 | B114: 44.8 | C114: =B114-B113 -> -4.9
A115: 41760 | B115: 49.2 | C115: =B115-B114 -> 4.4
A116: 41791 | B116: 48.9 | C116: =B116-B115 -> -0.3 | D116: =IF(VLOOKUP(I85,Data!$O$51:$V$152,7,FALSE)=A115,VLOOKUP(I85,Data!$O$51:$V$152,2,FALSE)/100,"") -> 0.005
A117: 41821 | B117: 50.7 | C117: =B117-B116 -> 1.8
A118: 41852 | B118: 47.3 | C118: =B118-B117 -> -3.4
A119: 41883 | B119: 46.5 | C119: =IFERROR(B119-B118,"") -> -0.8 | D119: =IF(VLOOKUP(I85,Data!$O$51:$V$152,7,FALSE)=A118,VLOOKUP(I85,Data!$O$51:$V$152,2,FALSE)/100,#N/A) -> #N/A
A120: 41913 | B120: 49.42 | C120: 2.92
A121: 41944 | B121: =IF(A121=Data!$C$1,VLOOKUP($H$85,Data!$A$2:$C$36,3,FALSE),"N/A") -> 50.1 | C121: =B121-B120 -> 0.68
A122: 41974
A123: 42005
A124: 42036
A125: 42064
A126: 42095
A127: 42125
A128: 42156
A129: 42186
A130: 42217
A131: 42248
A132: 42278
A133: 42309
... A154: 42948
A155: 46143 | B155: 50.7 | E155: gap 2015-Apr26: S&P Global licensed
A156: 46174 | B156: 51.5 | C156: 0.8

Sheet SK
A73: Date | B73: S Korea PMI | C73: Change | D73: S Korea GDP Growth q/q | E73: Column1
A74: 40513 | B74: 53.9 | D74: 0.007
A75: 40544 | B75: 53.5 | C75: =B75-B74 -> -0.4
A76: 40575 | B76: 53.4 | C76: =B76-B75 -> -0.1
A77: 40603 | B77: 52.8 | C77: =B77-B76 -> -0.6 | D77: 0.006
A78: 40634 | B78: 51.7 | C78: =B78-B77 -> -1.1
A79: 40664 | B79: 51.2 | C79: =B79-B78 -> -0.5
A80: 40695 | B80: 51.2 | C80: =B80-B79 -> 0 | D80: 0.013
A81: 40725 | B81: 51.1 | C81: =B81-B80 -> -0.1
A82: 40756 | B82: 51.3 | C82: =B82-B81 -> 0.2
A83: 40787 | B83: 49.7 | C83: =B83-B82 -> -1.6 | D83: 0.008
A84: 40817 | B84: 47.4 | C84: =B84-B83 -> -2.3
A85: 40848 | B85: 48 | C85: =B85-B84 -> 0.6 | H85: SK | I85: South Korea
A86: 40878 | B86: 47.1 | C86: =B86-B85 -> -0.9 | D86: 0.004
A87: 40909 | B87: 49.2 | C87: =B87-B86 -> 2.1
A88: 40940 | B88: 50.7 | C88: =B88-B87 -> 1.5
A89: 40969 | B89: 52 | C89: =B89-B88 -> 1.3 | D89: 0.005
A90: 41000 | B90: 51.9 | C90: =B90-B89 -> -0.1
A91: 41030 | B91: 51 | C91: =B91-B90 -> -0.9
A92: 41061 | B92: 49.4 | C92: =B92-B91 -> -1.6 | D92: 0.005
A93: 41091 | B93: 47.2 | C93: =B93-B92 -> -2.2
A94: 41122 | B94: 47.5 | C94: =B94-B93 -> 0.3
A95: 41153 | B95: 45.7 | C95: =B95-B94 -> -1.8 | D95: 0.004
A96: 41183 | B96: 47.4 | C96: =B96-B95 -> 1.7
A97: 41214 | B97: 48.2 | C97: =B97-B96 -> 0.8
A98: 41244 | B98: 50.1 | C98: =B98-B97 -> 1.9 | D98: 0.006
A99: 41275 | B99: 49.9 | C99: =B99-B98 -> -0.2
A100: 41306 | B100: 50.9 | C100: =B100-B99 -> 1
A101: 41334 | B101: 52 | C101: =B101-B100 -> 1.1 | D101: 0.006
A102: 41365 | B102: 52.6 | C102: =B102-B101 -> 0.6
A103: 41395 | B103: 51.1 | C103: =B103-B102 -> -1.5
A104: 41426 | B104: 49.4 | C104: =B104-B103 -> -1.7 | D104: 0.01
A105: 41456 | B105: 47.2 | C105: =B105-B104 -> -2.2
A106: 41487 | B106: 47.5 | C106: =B106-B105 -> 0.3
A107: 41518 | B107: 49.7 | C107: =B107-B106 -> 2.2 | D107: 0.011
A108: 41548 | B108: 50.2 | C108: =B108-B107 -> 0.5
A109: 41579 | B109: 50.4 | C109: =B109-B108 -> 0.2
A110: 41609 | B110: 50.8 | C110: =B110-B109 -> 0.4 | D110: 0.009
A111: 41640 | B111: 50.9 | C111: =B111-B110 -> 0.1
A112: 41671 | B112: 49.8 | C112: =B112-B111 -> -1.1
A113: 41699 | B113: 50.4 | C113: =B113-B112 -> 0.6 | D113: 0.009
A114: 41730 | B114: 50.2 | C114: =B114-B113 -> -0.2
A115: 41760 | B115: 49.5 | C115: =B115-B114 -> -0.7
A116: 41791 | B116: 48.4 | C116: =B116-B115 -> -1.1 | D116: 0.005
A117: 41821 | B117: 48.506667 | C117: =B117-B116 -> 0.10666667
A118: 41852 | B118: 50.3 | C118: =B118-B117 -> 1.7933333
A119: 41883 | B119: 48.8 | C119: =IFERROR(B119-B118,"") -> -1.5 | D119: =IF(VLOOKUP(I85,Data!$O$51:$V$152,7,FALSE)=A118,VLOOKUP(I85,Data!$O$51:$V$152,2,FALSE)/100,#N/A) -> 0.009
A120: 41913 | B120: 48.7 | C120: -0.1
A121: 41944 | B121: =IF(A121=Data!$C$1,VLOOKUP($H$85,Data!$A$2:$C$36,3,FALSE),"N/A") -> 49 | C121: =B121-B120 -> 0.3
A122: 41974
A123: 42005
A124: 42036
A125: 42064
A126: 42095
A127: 42125
A128: 42156
A129: 42186
A130: 42217
A131: 42248
A132: 42278
A133: 42309
... A154: 42948
A155: 46143 | B155: 54.8 | E155: gap 2015-Apr26: S&P Global licensed
A156: 46174 | B156: 52.1 | C156: -2.7

Sheet INS
A73: Date | B73: Indonesia PMI | C73: Change | D73: GDP Growth q/q | E73: Column1
A74: 40513
A75: 40544
A76: 40575
A77: 40603
A78: 40634 | B78: 48.1
A79: 40664 | B79: 48 | C79: =B79-B78 -> -0.1
A80: 40695 | B80: 50.5 | C80: =B80-B79 -> 2.5
A81: 40725 | B81: 51 | C81: =B81-B80 -> 0.5 | D81: 0.029
A82: 40756 | B82: 50.9 | C82: =B82-B81 -> -0.1
A83: 40787 | B83: 49.8 | C83: =B83-B82 -> -1.1
A84: 40817 | B84: 51.3 | C84: =B84-B83 -> 1.5 | D84: 0.034
A85: 40848 | B85: 50.1 | C85: =B85-B84 -> -1.2 | H85: INS | I85: Indonesia
A86: 40878 | B86: 48.1 | C86: =B86-B85 -> -2
A87: 40909 | B87: 48.5 | C87: =B87-B86 -> 0.4 | D87: -0.013
A88: 40940 | B88: 50.6 | C88: =B88-B87 -> 2.1
A89: 40969 | B89: 50.8 | C89: =B89-B88 -> 0.2
A90: 41000 | B90: 50.5 | C90: =B90-B89 -> -0.3 | D90: 0.014
A91: 41030 | B91: 48.1 | C91: =B91-B90 -> -2.4
A92: 41061 | B92: 50.2 | C92: =B92-B91 -> 2.1
A93: 41091 | B93: 51.3 | C93: =B93-B92 -> 1.1 | D93: 0.028
A94: 41122 | B94: 51.4 | C94: =B94-B93 -> 0.1
A95: 41153 | B95: 51.6 | C95: =B95-B94 -> 0.2
A96: 41183 | B96: 50.5 | C96: =B96-B95 -> -1.1 | D96: 0.0318
A97: 41214 | B97: 51.9 | C97: =B97-B96 -> 1.4
A98: 41244 | B98: 51.5 | C98: =B98-B97 -> -0.4
A99: 41275 | B99: 49.7 | C99: =B99-B98 -> -1.8 | D99: -0.0145
A100: 41306 | B100: 50.5 | C100: =B100-B99 -> 0.8
A101: 41334 | B101: 51.3 | C101: =B101-B100 -> 0.8
A102: 41365 | B102: 51.7 | C102: =B102-B101 -> 0.4 | D102: 0.0142
A103: 41395 | B103: 51.6 | C103: =B103-B102 -> -0.1
A104: 41426 | B104: 51 | C104: =B104-B103 -> -0.6
A105: 41456 | B105: 50.7 | C105: =B105-B104 -> -0.3 | D105: 0.0261
A106: 41487 | B106: 48.5 | C106: =B106-B105 -> -2.2
A107: 41518 | B107: 50.2 | C107: =B107-B106 -> 1.7
A108: 41548 | B108: 50.9 | C108: =B108-B107 -> 0.7 | D108: 0.0296
A109: 41579 | B109: 50.3 | C109: =B109-B108 -> -0.6
A110: 41609 | B110: 50.9 | C110: =B110-B109 -> 0.6
A111: 41640 | B111: 51 | C111: =B111-B110 -> 0.1 | D111: -0.014
A112: 41671 | B112: 50.5 | C112: =B112-B111 -> -0.5
A113: 41699 | B113: 50.1 | C113: =B113-B112 -> -0.4
A114: 41730 | B114: 51.1 | C114: =B114-B113 -> 1 | D114: 0.0095
A115: 41760 | B115: 52.4 | C115: =B115-B114 -> 1.3
A116: 41791 | B116: 52.7 | C116: =B116-B115 -> 0.3
A117: 41821 | B117: 52.4 | C117: =B117-B116 -> -0.3
A118: 41852 | B118: 49.5 | C118: =B118-B117 -> -2.9
A119: 41883 | B119: 50.7 | C119: =IFERROR(B119-B118,"") -> 1.2 | D119: =IF(VLOOKUP(I85,Data!$O$51:$V$152,7,FALSE)=A118,VLOOKUP(I85,Data!$O$51:$V$152,2,FALSE)/100,#N/A) -> 0.0296
A120: 41913 | B120: 49.2 | C120: -1.5
A121: 41944 | B121: =IF(A121=Data!$C$1,VLOOKUP($H$85,Data!$A$2:$C$36,3,FALSE),"N/A") -> 48 | C121: =B121-B120 -> -1.2
A122: 41974
A123: 42005
A124: 42036
A125: 42064
A126: 42095
A127: 42125
A128: 42156
A129: 42186
A130: 42217
A131: 42248
A132: 42278
A133: 42309
... A154: 42948
A155: 46143 | B155: 50 | E155: gap 2015-Apr26: S&P Global licensed
A156: 46174 | B156: 46.9 | C156: -3.1

Sheet TW
A1: Date | B1: Taiwan | C1: Change | D1: Taiwan GDP Growth q/q
A71: Date | B71: Taiwan PMI | C71: Change | D71: GDP Growth q/q | E71: Column1
A72: 40452 | B72: 48.6
A73: 40483 | B73: 51.7 | C73: =B73-B72 -> 3.1
A74: 40513 | B74: 51.7 | C74: =B74-B73 -> 0 | D74: 0.006
A75: 40544 | B75: 54.6 | C75: =B75-B74 -> 2.9
A76: 40575 | B76: 55.8 | C76: =B76-B75 -> 1.2
A77: 40603 | B77: 55.6 | C77: =B77-B76 -> -0.2 | D77: 0.027
A78: 40634 | B78: 58.2 | C78: =B78-B77 -> 2.6
A79: 40664 | B79: 54.9 | C79: =B79-B78 -> -3.3
A80: 40695 | B80: 49.9 | C80: =B80-B79 -> -5 | D80: 0.005
A81: 40725 | B81: 46.1 | C81: =B81-B80 -> -3.8
A82: 40756 | B82: 45.2 | C82: =B82-B81 -> -0.9
A83: 40787 | B83: 44.5 | C83: =B83-B82 -> -0.7 | D83: -0.005
A84: 40817 | B84: 48 | C84: =B84-B83 -> 3.5
A85: 40848 | B85: 47.1 | C85: =B85-B84 -> -0.9 | H85: TW | I85: Taiwan
A86: 40878 | B86: 47.1 | C86: =B86-B85 -> 0 | D86: -0.013
A87: 40909 | B87: 47.1 | C87: =B87-B86 -> 0
A88: 40940 | B88: 48.9 | C88: =B88-B87 -> 1.8
A89: 40969 | B89: 52.7 | C89: =B89-B88 -> 3.8 | D89: 0.018
A90: 41000 | B90: 54.1 | C90: =B90-B89 -> 1.4
A91: 41030 | B91: 51.2 | C91: =B91-B90 -> -2.9
A92: 41061 | B92: 50.5 | C92: =B92-B91 -> -0.7 | D92: -0.001
A93: 41091 | B93: 49.2 | C93: =B93-B92 -> -1.3
A94: 41122 | B94: 47.5 | C94: =B94-B93 -> -1.7
A95: 41153 | B95: 46.1 | C95: =B95-B94 -> -1.4 | D95: 0.01
A96: 41183 | B96: 45.6 | C96: =B96-B95 -> -0.5
A97: 41214 | B97: 47.8 | C97: =B97-B96 -> 2.2
A98: 41244 | B98: 47.4 | C98: =B98-B97 -> -0.4 | D98: 0.012
A99: 41275 | B99: 51.5 | C99: =B99-B98 -> 4.1
A100: 41306 | B100: 51.5 | C100: =B100-B99 -> 0
A101: 41334 | B101: 50.2 | C101: =B101-B100 -> -1.3 | D101: -0.005
A102: 41365 | B102: 51.2 | C102: =B102-B101 -> 1
A103: 41395 | B103: 50.7 | C103: =B103-B102 -> -0.5
A104: 41426 | B104: 47.1 | C104: =B104-B103 -> -3.6 | D104: 0.009
A105: 41456 | B105: 49.5 | C105: =B105-B104 -> 2.4
A106: 41487 | B106: 48.6 | C106: =B106-B105 -> -0.9
A107: 41518 | B107: 50 | C107: =B107-B106 -> 1.4 | D107: 0
A108: 41548 | B108: 52 | C108: =B108-B107 -> 2
A109: 41579 | B109: 53 | C109: =B109-B108 -> 1
A110: 41609 | B110: 53.4 | C110: =B110-B109 -> 0.4 | D110: 0.018
A111: 41640 | B111: 55.5 | C111: =B111-B110 -> 2.1
A112: 41671 | B112: 54.7 | C112: =B112-B111 -> -0.8
A113: 41699 | B113: 52.7 | C113: =B113-B112 -> -2 | D113: 0.004
A114: 41730 | B114: 52.3 | C114: =B114-B113 -> -0.4
A115: 41760 | B115: 52.4 | C115: =B115-B114 -> 0.1
A116: 41791 | B116: 54 | C116: =B116-B115 -> 1.6 | D116: 0.0086
A117: 41821 | B117: 55.8 | C117: =B117-B116 -> 1.8
A118: 41852 | B118: 56.1 | C118: =B118-B117 -> 0.3
A119: 41883 | B119: 53.3 | C119: =IFERROR(B119-B118,"") -> -2.8 | D119: =IF(VLOOKUP(I85,Data!$O$51:$V$152,7,FALSE)=A118,VLOOKUP(I85,Data!$O$51:$V$152,2,FALSE)/100,#N/A) -> 0.0066
A120: 41913 | B120: 52 | C120: -1.3
A121: 41944 | B121: =IF(A121=Data!$C$1,VLOOKUP($H$85,Data!$A$2:$C$36,3,FALSE),"N/A") -> 51.4 | C121: =B121-B120 -> -0.6
A122: 41974
A123: 42005
A124: 42036
A125: 42064
A126: 42095
A127: 42125
A128: 42156
A129: 42186
A130: 42217
A131: 42248
A132: 42278
A133: 42309
... A154: 42948
A155: 46143 | B155: 56.1 | E155: gap 2015-Apr26: S&P Global licensed
A156: 46174 | B156: 55.2 | C156: -0.9

Sheet TUR
A71: Date | B71: Turkey PMI | C71: Change | D71: Turkey GDP Growth q/q | E71: Column1
A72: 40452 | B72: 54.3
A73: 40483 | B73: 56.4 | C73: =B73-B72 -> 2.1
A74: 40513 | B74: 56.4 | C74: =B74-B73 -> 0 | D74: 0.049
A75: 40544 | B75: 57.2 | C75: =B75-B74 -> 0.8
A76: 40575 | B76: 58.5 | C76: =B76-B75 -> 1.3
A77: 40603 | B77: 56.1 | C77: =B77-B76 -> -2.4 | D77: 0.022
A78: 40634 | B78: 52.7 | C78: =B78-B77 -> -3.4
A79: 40664 | B79: 50.6 | C79: =B79-B78 -> -2.1
A80: 40695 | B80: 52.3 | C80: =B80-B79 -> 1.7 | D80: 0.008
A81: 40725 | B81: 52.3 | C81: =B81-B80 -> 0
A82: 40756 | B82: 49.8 | C82: =B82-B81 -> -2.5
A83: 40787 | B83: 51.5 | C83: =B83-B82 -> 1.7 | D83: 0.013
A84: 40817 | B84: 53.3 | C84: =B84-B83 -> 1.8
A85: 40848 | B85: 52.3 | C85: =B85-B84 -> -1 | H85: TUR | I85: Turkey
A86: 40878 | B86: 52 | C86: =B86-B85 -> -0.3 | D86: 0.008
A87: 40909 | B87: 51.7 | C87: =B87-B86 -> -0.3
A88: 40940 | B88: 49.6 | C88: =B88-B87 -> -2.1
A89: 40969 | B89: 49.6 | C89: =B89-B88 -> 0 | D89: -0.005
A90: 41000 | B90: 52.3 | C90: =B90-B89 -> 2.7
A91: 41030 | B91: 50.2 | C91: =B91-B90 -> -2.1
A92: 41061 | B92: 51.4 | C92: =B92-B91 -> 1.2 | D92: 0.014
A93: 41091 | B93: 49.4 | C93: =B93-B92 -> -2
A94: 41122 | B94: 50 | C94: =B94-B93 -> 0.6
A95: 41153 | B95: 52.2 | C95: =B95-B94 -> 2.2 | D95: 0.003
A96: 41183 | B96: 52.5 | C96: =B96-B95 -> 0.3
A97: 41214 | B97: 51.6 | C97: =B97-B96 -> -0.9
A98: 41244 | B98: 53.1 | C98: =B98-B97 -> 1.5 | D98: 0.003
A99: 41275 | B99: 54 | C99: =B99-B98 -> 0.9
A100: 41306 | B100: 53.5 | C100: =B100-B99 -> -0.5
A101: 41334 | B101: 52.3 | C101: =B101-B100 -> -1.2 | D101: 0.014
A102: 41365 | B102: 51.3 | C102: =B102-B101 -> -1
A103: 41395 | B103: 51.1 | C103: =B103-B102 -> -0.2
A104: 41426 | B104: 51.2 | C104: =B104-B103 -> 0.1 | D104: 0.02
A105: 41456 | B105: 49.8 | C105: =B105-B104 -> -1.4
A106: 41487 | B106: 50.9 | C106: =B106-B105 -> 1.1
A107: 41518 | B107: 54 | C107: =B107-B106 -> 3.1 | D107: 0.004
A108: 41548 | B108: 53.3 | C108: =B108-B107 -> -0.7
A109: 41579 | B109: 55 | C109: =B109-B108 -> 1.7
A110: 41609 | B110: 53.5 | C110: =B110-B109 -> -1.5 | D110: 0.009
A111: 41640 | B111: 52.7 | C111: =B111-B110 -> -0.8
A112: 41671 | B112: 53.4 | C112: =B112-B111 -> 0.7
A113: 41699 | B113: 51.7 | C113: =B113-B112 -> -1.7 | D113: 0.017
A114: 41730 | B114: 51.1 | C114: =B114-B113 -> -0.6
A115: 41760 | B115: 50.1 | C115: =B115-B114 -> -1
A116: 41791 | B116: 48.8 | C116: =B116-B115 -> -1.3 | D116: =IF(VLOOKUP(I85,Data!$O$51:$V$152,7,FALSE)=A115,VLOOKUP(I85,Data!$O$51:$V$152,2,FALSE)/100,#N/A) -> -0.005
A117: 41821 | B117: 48.453571 | C117: =B117-B116 -> -0.34642857
A118: 41852 | B118: 50 | C118: =B118-B117 -> 1.5464286
A119: 41883 | B119: 50.4 | C119: =IFERROR(B119-B118,"") -> 0.4 | D119: =IF(VLOOKUP(I85,Data!$O$51:$V$152,7,FALSE)=A118,VLOOKUP(I85,Data!$O$51:$V$152,2,FALSE)/100,#N/A) -> #N/A
A120: 41913 | B120: 51.5 | C120: 1.1
A121: 41944 | B121: =IF(A121=Data!$C$1,VLOOKUP($H$85,Data!$A$2:$C$36,3,FALSE),"N/A") -> 52.2 | C121: =B121-B120 -> 0.7
A122: 41974
A123: 42005
A124: 42036
A125: 42064
A126: 42095
A127: 42125
A128: 42156
A129: 42186
A130: 42217
A131: 42248
A132: 42278
A133: 42309
... A154: 42948
A155: 46143 | B155: 49.8 | E155: gap 2015-Apr26: S&P Global licensed
A156: 46174 | B156: 47.1 | C156: -2.7

Sheet CZ
A71: Date | B71: Czech Manufacturing PMI | C71: Change | D71: Czech GDP Growth q/q | E71: Column1
A72: 40452 | B72: 57.2
A73: 40483 | B73: 57.3 | C73: =B73-B72 -> 0.1
A74: 40513 | B74: 58.4 | C74: =B74-B73 -> 1.1 | D74: 0.005
A75: 40544 | B75: 60.5 | C75: =B75-B74 -> 2.1
A76: 40575 | B76: 59.8 | C76: =B76-B75 -> -0.7
A77: 40603 | B77: 58.6 | C77: =B77-B76 -> -1.2 | D77: 0.009
A78: 40634 | B78: 59 | C78: =B78-B77 -> 0.4
A79: 40664 | B79: 55.9 | C79: =B79-B78 -> -3.1
A80: 40695 | B80: 55.1 | C80: =B80-B79 -> -0.8 | D80: 0.001
A81: 40725 | B81: 53.4 | C81: =B81-B80 -> -1.7
A82: 40756 | B82: 53.4 | C82: =B82-B81 -> 0
A83: 40787 | B83: 52.3 | C83: =B83-B82 -> -1.1 | D83: -0.001
A84: 40817 | B84: 51.7 | C84: =B84-B83 -> -0.6
A85: 40848 | B85: 48.6 | C85: =B85-B84 -> -3.1 | H85: CZ | I85: Czech Republic
A86: 40878 | B86: 49.2 | C86: =B86-B85 -> 0.6 | D86: -0.001
A87: 40909 | B87: 48.8 | C87: =B87-B86 -> -0.4
A88: 40940 | B88: 50.5 | C88: =B88-B87 -> 1.7
A89: 40969 | B89: 52.1 | C89: =B89-B88 -> 1.6 | D89: -0.005
A90: 41000 | B90: 49.7 | C90: =B90-B89 -> -2.4
A91: 41030 | B91: 47.6 | C91: =B91-B90 -> -2.1
A92: 41061 | B92: 49.4 | C92: =B92-B91 -> 1.8 | D92: -0.005
A93: 41091 | B93: 49.5 | C93: =B93-B92 -> 0.1
A94: 41122 | B94: 48.7 | C94: =B94-B93 -> -0.8
A95: 41153 | B95: 48 | C95: =B95-B94 -> -0.7 | D95: -0.004
A96: 41183 | B96: 47.2 | C96: =B96-B95 -> -0.8
A97: 41214 | B97: 48.2 | C97: =B97-B96 -> 1
A98: 41244 | B98: 46 | C98: =B98-B97 -> -2.2 | D98: -0.002
A99: 41275 | B99: 48.3 | C99: =B99-B98 -> 2.3
A100: 41306 | B100: 49.9 | C100: =B100-B99 -> 1.6
A101: 41334 | B101: 49.1 | C101: =B101-B100 -> -0.8 | D101: -0.013
A102: 41365 | B102: 49.5 | C102: =B102-B101 -> 0.4
A103: 41395 | B103: 50.1 | C103: =B103-B102 -> 0.6
A104: 41426 | B104: 51 | C104: =B104-B103 -> 0.9 | D104: 0.003
A105: 41456 | B105: 52 | C105: =B105-B104 -> 1
A106: 41487 | B106: 53.9 | C106: =B106-B105 -> 1.9
A107: 41518 | B107: 53.4 | C107: =B107-B106 -> -0.5 | D107: 0.003
A108: 41548 | B108: 54.5 | C108: =B108-B107 -> 1.1
A109: 41579 | B109: 55.4 | C109: =B109-B108 -> 0.9
A110: 41609 | B110: 54.9 | C110: =B110-B109 -> -0.5 | D110: 0.018
A111: 41640 | B111: 55.9 | C111: =B111-B110 -> 1
A112: 41671 | B112: 56.5 | C112: =B112-B111 -> 0.6
A113: 41699 | B113: 55.5 | C113: =B113-B112 -> -1 | D113: 0.008
A114: 41730 | B114: 56.5 | C114: =B114-B113 -> 1
A115: 41760 | B115: 57.3 | C115: =B115-B114 -> 0.8
A116: 41791 | B116: 54.7 | C116: =B116-B115 -> -2.6 | D116: 0.003
A117: 41821 | B117: 56.463889 | C117: =B117-B116 -> 1.7638889
A118: 41852 | B118: 54.3 | C118: =B118-B117 -> -2.1638889
A119: 41883 | B119: 55.6 | C119: =IFERROR(B119-B118,"") -> 1.3 | D119: =IF(VLOOKUP(I85,Data!$O$51:$V$152,7,FALSE)=A118,VLOOKUP(I85,Data!$O$51:$V$152,2,FALSE)/100,#N/A) -> 0.004
A120: 41913 | B120: 54.4 | C120: -1.2
A121: 41944 | B121: =IF(A121=Data!$C$1,VLOOKUP($H$85,Data!$A$2:$C$36,3,FALSE),"N/A") -> 55.6 | C121: =B121-B120 -> 1.2
A122: 41974
A123: 42005
A124: 42036
A125: 42064
A126: 42095
A127: 42125
A128: 42156
A129: 42186
A130: 42217
A131: 42248
A132: 42278
A133: 42309
... A154: 42948
A155: 46143 | B155: 52.2 | E155: gap 2015-Apr26: S&P Global licensed
A156: 46174 | B156: 53.9 | C156: 1.7

Sheet PL
A71: Date | B71: Poland Manufacturing PMI | C71: Change | D71: Poland GDP Growth q/q | E71: Column1
A72: 40452 | B72: 55.6
A73: 40483 | B73: 55.9 | C73: =B73-B72 -> 0.3
A74: 40513 | B74: 56.3 | C74: =B74-B73 -> 0.4 | D74: 0.008
A75: 40544 | B75: 55.6 | C75: =B75-B74 -> -0.7
A76: 40575 | B76: 53.8 | C76: =B76-B75 -> -1.8
A77: 40603 | B77: 54.8 | C77: =B77-B76 -> 1 | D77: 0.013
A78: 40634 | B78: 54.4 | C78: =B78-B77 -> -0.4
A79: 40664 | B79: 52.6 | C79: =B79-B78 -> -1.8
A80: 40695 | B80: 51.2 | C80: =B80-B79 -> -1.4 | D80: 0.014
A81: 40725 | B81: 52.9 | C81: =B81-B80 -> 1.7
A82: 40756 | B82: 51.8 | C82: =B82-B81 -> -1.1
A83: 40787 | B83: 50.2 | C83: =B83-B82 -> -1.6 | D83: 0.008
A84: 40817 | B84: 51.7 | C84: =B84-B83 -> 1.5
A85: 40848 | B85: 49.5 | C85: =B85-B84 -> -2.2 | H85: PL | I85: Poland
A86: 40878 | B86: 48.8 | C86: =B86-B85 -> -0.7 | D86: 0.01
A87: 40909 | B87: 52.2 | C87: =B87-B86 -> 3.4
A88: 40940 | B88: 50 | C88: =B88-B87 -> -2.2
A89: 40969 | B89: 50.1 | C89: =B89-B88 -> 0.1 | D89: 0.004
A90: 41000 | B90: 49.2 | C90: =B90-B89 -> -0.9
A91: 41030 | B91: 48.9 | C91: =B91-B90 -> -0.3
A92: 41061 | B92: 48 | C92: =B92-B91 -> -0.9 | D92: 0
A93: 41091 | B93: 49.7 | C93: =B93-B92 -> 1.7
A94: 41122 | B94: 48.3 | C94: =B94-B93 -> -1.4
A95: 41153 | B95: 47 | C95: =B95-B94 -> -1.3 | D95: 0.002
A96: 41183 | B96: 47.3 | C96: =B96-B95 -> 0.3
A97: 41214 | B97: 48.2 | C97: =B97-B96 -> 0.9
A98: 41244 | B98: 48.3 | C98: =B98-B97 -> 0.1 | D98: 0.002
A99: 41275 | B99: 48.6 | C99: =B99-B98 -> 0.3
A100: 41306 | B100: 48.9 | C100: =B100-B99 -> 0.3
A101: 41334 | B101: 48 | C101: =B101-B100 -> -0.9 | D101: 0.001
A102: 41365 | B102: 48 | C102: =B102-B101 -> 0
A103: 41395 | B103: 46.9 | C103: =B103-B102 -> -1.1
A104: 41426 | B104: 48 | C104: =B104-B103 -> 1.1 | D104: 0.008
A105: 41456 | B105: 49.3 | C105: =B105-B104 -> 1.3
A106: 41487 | B106: 51.1 | C106: =B106-B105 -> 1.8
A107: 41518 | B107: 52.6 | C107: =B107-B106 -> 1.5 | D107: 0.008
A108: 41548 | B108: 53.4 | C108: =B108-B107 -> 0.8
A109: 41579 | B109: 54.4 | C109: =B109-B108 -> 1
A110: 41609 | B110: 53.2 | C110: =B110-B109 -> -1.2 | D110: 0.007
A111: 41640 | B111: 55.4 | C111: =B111-B110 -> 2.2
A112: 41671 | B112: 55.9 | C112: =B112-B111 -> 0.5
A113: 41699 | B113: 54 | C113: =B113-B112 -> -1.9 | D113: 0.011
A114: 41730 | B114: 51.1 | C114: =B114-B113 -> -2.9
A115: 41760 | B115: 50.8 | C115: =B115-B114 -> -0.3
A116: 41791 | B116: 50.3 | C116: =B116-B115 -> -0.5 | D116: 0.006
A117: 41821 | B117: 49.4 | C117: =B117-B116 -> -0.9
A118: 41852 | B118: 49 | C118: =B118-B117 -> -0.4
A119: 41883 | B119: 49.5 | C119: =IFERROR(B119-B118,"") -> 0.5 | D119: =IF(VLOOKUP(I85,Data!$O$51:$V$152,7,FALSE)=A118,VLOOKUP(I85,Data!$O$51:$V$152,2,FALSE)/100,#N/A) -> 0.009
A120: 41913 | B120: 51.2 | C120: 1.7
A121: 41944 | B121: =IF(A121=Data!$C$1,VLOOKUP($H$85,Data!$A$2:$C$36,3,FALSE),"N/A") -> 53.2 | C121: =B121-B120 -> 2
A122: 41974
A123: 42005
A124: 42036
A125: 42064
A126: 42095
A127: 42125
A128: 42156
A129: 42186
A130: 42217
A131: 42248
A132: 42278
A133: 42309
... A154: 42948
A155: 46143 | B155: 49.4 | E155: gap 2015-Apr26: S&P Global licensed
A156: 46174 | B156: 46.1 | C156: -3.3

Sheet All
B2: Global | C2: US | D2: China | E2: EA | F2: Japan | G2: Germany | H2: France | I2: UK | J2: Italy | K2: Spain | L2: Brazil | M2: Mexico | N2: Russia | O2: India | P2: Canada | Q2: Australia | R2: Indonesia | S2: S Korea | T2: Taiwan | U2: Greece | V2: Ireland | W2: Turkey | X2: Czech | Y2: Poland
A3: 41244 | B3: =Global!B98 -> 50 | C3: =US!B98 -> 54 | D3: =CH!B98 -> 51.5 | E3: =EZ!B98 -> 46.1 | F3: =JP!B98 -> 45 | G3: =DE!B98 -> 46 | H3: =FR!B98 -> 44.6 | I3: =UK!B98 -> 50.7 | J3: =IT!B98 -> 46.7 | K3: =ES!B98 -> 44.6 | L3: =BRL!B98 -> 51.1 | M3: =MX!B98 -> 57.1 | N3: =RS!B98 -> 50 | O3: =IND!B98 -> 54.7 | P3: =CA!B98 -> 50.4 | Q3: =AU!B98 -> 44.3 | R3: =INS!B98 -> 51.5 | S3: =SK!B98 -> 50.1 | T3: =TW!B98 -> 47.4 | U3: =EL!B98 -> 41.4 | V3: =IR!B98 -> 51.4 | W3: =TUR!B98 -> 53.1 | X3: =CZ!B98 -> 46 | Y3: =PL!B98 -> 48.3
A4: 41275 | B4: =Global!B99 -> 51.5 | C4: =US!B99 -> 55.8 | D4: =CH!B99 -> 52.3 | E4: =EZ!B99 -> 47.9 | F4: =JP!B99 -> 47.7 | G4: =DE!B99 -> 49.8 | H4: =FR!B99 -> 42.9 | I4: =UK!B99 -> 50.9 | J4: =IT!B99 -> 47.8 | K4: =ES!B99 -> 46.1 | L4: =BRL!B99 -> 53.2 | M4: =MX!B99 -> 55 | N4: =RS!B99 -> 52 | O4: =IND!B99 -> 53.2 | P4: =CA!B99 -> 50.5 | Q4: =AU!B99 -> 40.2 | R4: =INS!B99 -> 49.7 | S4: =SK!B99 -> 49.9 | T4: =TW!B99 -> 51.5 | U4: =EL!B99 -> 41.7 | V4: =IR!B99 -> 50.3 | W4: =TUR!B99 -> 54 | X4: =CZ!B99 -> 48.3 | Y4: =PL!B99 -> 48.6
A5: 41306 | B5: =Global!B100 -> 50.9 | C5: =US!B100 -> 54.3 | D5: =CH!B100 -> 50.4 | E5: =EZ!B100 -> 47.9 | F5: =JP!B100 -> 48.5 | G5: =DE!B100 -> 50.3 | H5: =FR!B100 -> 43.9 | I5: =UK!B100 -> 48.2 | J5: =IT!B100 -> 45.8 | K5: =ES!B100 -> 46.8 | L5: =BRL!B100 -> 52.5 | M5: =MX!B100 -> 53.4 | N5: =RS!B100 -> 52 | O5: =IND!B100 -> 54.2 | P5: =CA!B100 -> 51.7 | Q5: =AU!B100 -> 45.6 | R5: =INS!B100 -> 50.5 | S5: =SK!B100 -> 50.9 | T5: =TW!B100 -> 51.5 | U5: =EL!B100 -> 43 | V5: =IR!B100 -> 51.5 | W5: =TUR!B100 -> 53.5 | X5: =CZ!B100 -> 49.9 | Y5: =PL!B100 -> 48.9
A6: 41334 | B6: =Global!B101 -> 51.2 | C6: =US!B101 -> 54.6 | D6: =CH!B101 -> 51.6 | E6: =EZ!B101 -> 46.8 | F6: =JP!B101 -> 50.4 | G6: =DE!B101 -> 49 | H6: =FR!B101 -> 44 | I6: =UK!B101 -> 49.3 | J6: =IT!B101 -> 44.5 | K6: =ES!B101 -> 44.2 | L6: =BRL!B101 -> 51.8 | M6: =MX!B101 -> 52.2 | N6: =RS!B101 -> 50.8 | O6: =IND!B101 -> 52 | P6: =CA!B101 -> 49.3 | Q6: =AU!B101 -> 44.4 | R6: =INS!B101 -> 51.3 | S6: =SK!B101 -> 52 | T6: =TW!B101 -> 50.2 | U6: =EL!B101 -> 42.1 | V6: =IR!B101 -> 48.6 | W6: =TUR!B101 -> 52.3 | X6: =CZ!B101 -> 49.1 | Y6: =PL!B101 -> 48
A7: 41365 | B7: =Global!B102 -> 50.4 | C7: =US!B102 -> 52.1 | D7: =CH!B102 -> 50.4 | E7: =EZ!B102 -> 46.7 | F7: =JP!B102 -> 51.1 | G7: =DE!B102 -> 48.1 | H7: =FR!B102 -> 44.4 | I7: =UK!B102 -> 50.6 | J7: =IT!B102 -> 45.5 | K7: =ES!B102 -> 44.7 | L7: =BRL!B102 -> 50.8 | M7: =MX!B102 -> 51.7 | N7: =RS!B102 -> 50.6 | O7: =IND!B102 -> 51 | P7: =CA!B102 -> 50.1 | Q7: =AU!B102 -> 36.7 | R7: =INS!B102 -> 51.7 | S7: =SK!B102 -> 52.6 | T7: =TW!B102 -> 51.2 | U7: =EL!B102 -> 45 | V7: =IR!B102 -> 48 | W7: =TUR!B102 -> 51.3 | X7: =CZ!B102 -> 49.5 | Y7: =PL!B102 -> 48
A8: 41395 | B8: =Global!B103 -> 50.6 | C8: =US!B103 -> 52.3 | D8: =CH!B103 -> 49.2 | E8: =EZ!B103 -> 48.3 | F8: =JP!B103 -> 51.5 | G8: =DE!B103 -> 49.4 | H8: =FR!B103 -> 46.4 | I8: =UK!B103 -> 52.1 | J8: =IT!B103 -> 47.3 | K8: =ES!B103 -> 48.1 | L8: =BRL!B103 -> 50.4 | M8: =MX!B103 -> 51.8 | N8: =RS!B103 -> 50.4 | O8: =IND!B103 -> 50.1 | P8: =CA!B103 -> 53.2 | Q8: =AU!B103 -> 43.8 | R8: =INS!B103 -> 51.6 | S8: =SK!B103 -> 51.1 | T8: =TW!B103 -> 50.7 | U8: =EL!B103 -> 45.3 | V8: =IR!B103 -> 49.7 | W8: =TUR!B103 -> 51.1 | X8: =CZ!B103 -> 50.1 | Y8: =PL!B103 -> 46.9
A9: 41426 | B9: =Global!B104 -> 50.6 | C9: =US!B104 -> 51.9 | D9: =CH!B104 -> 48.2 | E9: =EZ!B104 -> 48.8 | F9: =JP!B104 -> 52.3 | G9: =DE!B104 -> 48.6 | H9: =FR!B104 -> 48.4 | I9: =UK!B104 -> 53 | J9: =IT!B104 -> 49.1 | K9: =ES!B104 -> 50 | L9: =BRL!B104 -> 50.4 | M9: =MX!B104 -> 51.3 | N9: =RS!B104 -> 51.7 | O9: =IND!B104 -> 50.3 | P9: =CA!B104 -> 52.4 | Q9: =AU!B104 -> 49.6 | R9: =INS!B104 -> 51 | S9: =SK!B104 -> 49.4 | T9: =TW!B104 -> 47.1 | U9: =EL!B104 -> 45.4 | V9: =IR!B104 -> 50.3 | W9: =TUR!B104 -> 51.2 | X9: =CZ!B104 -> 51 | Y9: =PL!B104 -> 48
A10: 41456 | B10: =Global!B105 -> 50.8 | C10: =US!B105 -> 53.7 | D10: =CH!B105 -> 47.7 | E10: =EZ!B105 -> 50.3 | F10: =JP!B105 -> 50.7 | G10: =DE!B105 -> 50.7 | H10: =FR!B105 -> 49.7 | I10: =UK!B105 -> 54.7 | J10: =IT!B105 -> 50.4 | K10: =ES!B105 -> 49.8 | L10: =BRL!B105 -> 48.5 | M10: =MX!B105 -> 49.7 | N10: =RS!B105 -> 49.2 | O10: =IND!B105 -> 50.1 | P10: =CA!B105 -> 52 | Q10: =AU!B105 -> 42 | R10: =INS!B105 -> 50.7 | S10: =SK!B105 -> 47.2 | T10: =TW!B105 -> 49.5 | U10: =EL!B105 -> 47 | V10: =IR!B105 -> 51 | W10: =TUR!B105 -> 49.8 | X10: =CZ!B105 -> 52 | Y10: =PL!B105 -> 49.3
A11: 41487 | B11: =Global!B106 -> 51.6 | C11: =US!B106 -> 53.7 | D11: =CH!B106 -> 50.1 | E11: =EZ!B106 -> 51.4 | F11: =JP!B106 -> 52.2 | G11: =DE!B106 -> 51.8 | H11: =FR!B106 -> 49.7 | I11: =UK!B106 -> 57.3 | J11: =IT!B106 -> 51.3 | K11: =ES!B106 -> 51.1 | L11: =BRL!B106 -> 49.4 | M11: =MX!B106 -> 50.8 | N11: =RS!B106 -> 49.4 | O11: =IND!B106 -> 48.5 | P11: =CA!B106 -> 52.1 | Q11: =AU!B106 -> 46.4 | R11: =INS!B106 -> 48.5 | S11: =SK!B106 -> 47.5 | T11: =TW!B106 -> 48.6 | U11: =EL!B106 -> 48.7 | V11: =IR!B106 -> 52 | W11: =TUR!B106 -> 50.9 | X11: =CZ!B106 -> 53.9 | Y11: =PL!B106 -> 51.1
A12: 41518 | B12: =Global!B107 -> 51.8 | C12: =US!B107 -> 52.8 | D12: =CH!B107 -> 50.2 | E12: =EZ!B107 -> 51.1 | F12: =JP!B107 -> 52.5 | G12: =DE!B107 -> 51.1 | H12: =FR!B107 -> 49.8 | I12: =UK!B107 -> 56.7 | J12: =IT!B107 -> 50.8 | K12: =ES!B107 -> 50.7 | L12: =BRL!B107 -> 49.9 | M12: =MX!B107 -> 50 | N12: =RS!B107 -> 49.4 | O12: =IND!B107 -> 49.6 | P12: =CA!B107 -> 54.2 | Q12: =AU!B107 -> 51.7 | R12: =INS!B107 -> 50.2 | S12: =SK!B107 -> 49.7 | T12: =TW!B107 -> 50 | U12: =EL!B107 -> 47.5 | V12: =IR!B107 -> 52.7 | W12: =TUR!B107 -> 54 | X12: =CZ!B107 -> 53.4 | Y12: =PL!B107 -> 52.6
A13: 41548 | B13: =Global!B108 -> 52.1 | C13: =US!B108 -> 51.8 | D13: =CH!B108 -> 50.9 | E13: =EZ!B108 -> 51.3 | F13: =JP!B108 -> 54.2 | G13: =DE!B108 -> 51.7 | H13: =FR!B108 -> 49.1 | I13: =UK!B108 -> 56.5 | J13: =IT!B108 -> 50.7 | K13: =ES!B108 -> 50.9 | L13: =BRL!B108 -> 50.2 | M13: =MX!B108 -> 50.2 | N13: =RS!B108 -> 51.8 | O13: =IND!B108 -> 49.6 | P13: =CA!B108 -> 55.6 | Q13: =AU!B108 -> 53.2 | R13: =INS!B108 -> 50.9 | S13: =SK!B108 -> 50.2 | T13: =TW!B108 -> 52 | U13: =EL!B108 -> 47.3 | V13: =IR!B108 -> 54.9 | W13: =TUR!B108 -> 53.3 | X13: =CZ!B108 -> 54.5 | Y13: =PL!B108 -> 53.4
A14: 41579 | B14: =Global!B109 -> 53.1 | C14: =US!B109 -> 54.7 | D14: =CH!B109 -> 50.8 | E14: =EZ!B109 -> 51.6 | F14: =JP!B109 -> 55.1 | G14: =DE!B109 -> 52.7 | H14: =FR!B109 -> 48.4 | I14: =UK!B109 -> 58.1 | J14: =IT!B109 -> 51.4 | K14: =ES!B109 -> 48.6 | L14: =BRL!B109 -> 49.7 | M14: =MX!B109 -> 51.9 | N14: =RS!B109 -> 49.4 | O14: =IND!B109 -> 51.3 | P14: =CA!B109 -> 55.3 | Q14: =AU!B109 -> 47.7 | R14: =INS!B109 -> 50.3 | S14: =SK!B109 -> 50.4 | T14: =TW!B109 -> 53 | U14: =EL!B109 -> 49.2 | V14: =IR!B109 -> 52.4 | W14: =TUR!B109 -> 55 | X14: =CZ!B109 -> 55.4 | Y14: =PL!B109 -> 54.4
... A26: 41944 | B26: =Global!B121 -> 51.8 | C26: =US!B121 -> 54.8 | D26: =CH!B121 -> 50.3 | E26: =EZ!B121 -> 50.1 | F26: =JP!B121 -> 52 | G26: =DE!B121 -> 49.5 | H26: =FR!B121 -> 48.4 | I26: =UK!B121 -> 53.5 | J26: =IT!B121 -> 49 | K26: =ES!B121 -> 54.7 | L26: =BRL!B121 -> 48.7 | M26: =MX!B121 -> 54.3 | N26: =RS!B121 -> 51.7 | O26: =IND!B121 -> 53.3 | P26: =CA!B121 -> 55.3 | Q26: =AU!B121 -> 50.1 | R26: =INS!B121 -> 48 | S26: =SK!B121 -> 49 | T26: =TW!B121 -> 51.4 | U26: =EL!B121 -> 49.1 | V26: =IR!B121 -> 56.2 | W26: =TUR!B121 -> 52.2 | X26: =CZ!B121 -> 55.6 | Y26: =PL!B121 -> 53.2
A27: 41974
A28: 42005
A29: 42036
A30: 42064
A31: 42095
A32: 42125
A33: 42156
A34: 42186
A35: 42217
A36: 42248
A37: 42278
A38: 42309
... A59: 42948

Sheet Din
I3: =J4&" 2014 PMI numbers" -> Nov 2014 PMI numbers | N3: =O4&" 2014 PMI numbers" -> Nov 2014 PMI numbers
I4: Country | J4: Nov | K4: Oct | L4: Change | N4: Country | O4: Nov | P4: Oct | Q4: Change
I5: Ireland | J5: =Tabs!AP27 -> 54.9 | K5: =Tabs!AP26 -> 55.9 | L5: =J5-K5 -> -1 | N5: Spain | O5: 54.7 | P5: 52.6 | Q5: 2.1
I6: Czech | J6: =Tabs!CL27 -> 53.9 | K6: =Tabs!CL26 -> 52.2 | L6: =J6-K6 -> 1.7 | N6: Poland | O6: 53.2 | P6: 51.2 | Q6: 2
I7: Canada | J7: =Tabs!J27 -> 53 | K7: =Tabs!J26 -> 52.9 | L7: =J7-K7 -> 0.1 | N7: India | O7: 53.3 | P7: 51.6 | Q7: 1.7
I8: US | J8: =Tabs!F27 -> 53.9 | K8: =Tabs!F26 -> 55.1 | L8: =J8-K8 -> -1.2 | N8: Russia | O8: 51.7 | P8: 50.3 | Q8: 1.4
I9: Spain | J9: =Tabs!AH27 -> 49.7 | K9: =Tabs!AH26 -> 51.2 | L9: =J9-K9 -> -1.5 | N9: Czech | O9: 55.6 | P9: 54.4 | Q9: 1.2
I10: Mexico | J10: =Tabs!BN27 -> 51.3 | K10: =Tabs!BN26 -> 49.6 | L10: =J10-K10 -> 1.7 | N10: Mexico | O10: 54.3 | P10: 53.3 | Q10: 1
I11: UK | J11: =Tabs!R27 -> 52.5 | K11: =Tabs!R26 -> 53.9 | L11: =J11-K11 -> -1.4 | N11: Turkey | O11: 52.2 | P11: 51.5 | Q11: 0.7
I12: India | J12: =Tabs!BF27 -> 54.2 | K12: =Tabs!BF26 -> 55 | L12: =J12-K12 -> -0.8 | N12: Australia | O12: 50.1 | P12: 49.42 | Q12: 0.68
I13: Poland | J13: =Tabs!CP27 -> 46.1 | K13: =Tabs!CP26 -> 49.4 | L13: =J13-K13 -> -3.3 | N13: Greece | O13: 49.1 | P13: 48.8 | Q13: 0.3
I14: Turkey | J14: =Tabs!CH27 -> 47.1 | K14: =Tabs!CH26 -> 49.8 | L14: =J14-K14 -> -2.7 | N14: UK | O14: 53.5 | P14: 53.2 | Q14: 0.3
I15: Japan | J15: =Tabs!AX27 -> 54.8 | K15: =Tabs!AX26 -> 54.5 | L15: =J15-K15 -> 0.3 | N15: S Korea | O15: 49 | P15: 48.7 | Q15: 0.3
I16: Global | J16: =Tabs!B27 -> 52.2 | K16: =Tabs!B26 -> 52.7 | L16: =J16-K16 -> -0.5 | N16: Canada | O16: 55.3 | P16: 55.3 | Q16: 0
I17: Russia | J17: =Tabs!BJ27 -> 50.3 | K17: =Tabs!BJ26 -> 48.8 | L17: =J17-K17 -> 1.5 | N17: Italy | O17: 49 | P17: 49 | Q17: 0
I18: Taiwan | J18: =Tabs!CD27 -> 55.2 | K18: =Tabs!CD26 -> 56.1 | L18: =J18-K18 -> -0.9 | N18: France | O18: 48.4 | P18: 48.5 | Q18: -0.1
I19: China | J19: =Tabs!AT27 -> 51.7 | K19: =Tabs!AT26 -> 51.8 | L19: =J19-K19 -> -0.1 | N19: Ireland | O19: 56.2 | P19: 56.6 | Q19: -0.4
I20: Australia | J20: =Tabs!BR27 -> 51.5 | K20: =Tabs!BR26 -> 50.7 | L20: =J20-K20 -> 0.8 | N20: Japan | O20: 52 | P20: 52.4 | Q20: -0.4
I21: EA | J21: =Tabs!N27 -> 51.4 | K21: =Tabs!N26 -> 51.6 | L21: =J21-K21 -> -0.2 | N21: Brazil | O21: 48.7 | P21: 49.1 | Q21: -0.4
I22: Germany | J22: =Tabs!V27 -> 50.3 | K22: =Tabs!V26 -> 50.1 | L22: =J22-K22 -> 0.2 | N22: Global | O22: 51.8 | P22: 52.2 | Q22: -0.4
I23: Greece | J23: =Tabs!AL27 -> 53.8 | K23: =Tabs!AL26 -> 53.3 | L23: =J23-K23 -> 0.5 | N23: EA | O23: 50.1 | P23: 50.6 | Q23: -0.5
I24: S Korea | J24: =Tabs!BV27 -> 52.1 | K24: =Tabs!BV26 -> 54.8 | L24: =J24-K24 -> -2.7 | N24: China | O24: 50.3 | P24: 50.8 | Q24: -0.5
I25: Italy | J25: =Tabs!AD27 -> 52.2 | K25: =Tabs!AD26 -> 52.9 | L25: =J25-K25 -> -0.7 | N25: Taiwan | O25: 51.4 | P25: 52 | Q25: -0.6
I26: Brazil | J26: =Tabs!BB27 -> 50.8 | K26: =Tabs!BB26 -> 49.1 | L26: =J26-K26 -> 1.7 | N26: US | O26: 54.8 | P26: 55.9 | Q26: -1.1
I27: France | J27: =Tabs!Z27 -> 51.2 | K27: =Tabs!Z26 -> 49.7 | L27: =J27-K27 -> 1.5 | N27: Indonesia | O27: 48 | P27: 49.2 | Q27: -1.2
I28: Indonesia | J28: =Tabs!BZ27 -> 46.9 | K28: =Tabs!BZ26 -> 50 | L28: =J28-K28 -> -3.1 | N28: Germany | O28: 49.5 | P28: 51.4 | Q28: -1.9

Sheet Data
C1: 41944 | F1: Last | G1: Previous | H1: Highest | I1: Lowest | J1: Unit | K1: Reference | L1: Frequency
A2: US | B2: United States | C2: =IF(VLOOKUP(B2,$E$2:$L$49,7,FALSE)=$C$1,VLOOKUP(B2,$E$2:$L$49,2,FALSE),"") -> 54.8 | E2: Australia | F2: 50.1 | G2: 49.42 | H2: 62.13 | I2: 30.86 | K2: 41944 | L2: Monthly
A3: CA | B3: Canada | C3: =IF(VLOOKUP(B3,$E$2:$L$49,7,FALSE)=$C$1,VLOOKUP(B3,$E$2:$L$49,2,FALSE),"") -> 55.3 | E3: Austria | F3: 47.4 | G3: 46.9 | H3: 54.3 | I3: 46.9 | K3: 41944 | L3: Monthly
A4: UK | B4: United Kingdom | C4: =IF(VLOOKUP(B4,$E$2:$L$49,7,FALSE)=$C$1,VLOOKUP(B4,$E$2:$L$49,2,FALSE),"") -> 53.5 | E4: Brazil | F4: 48.7 | G4: 49.1 | H4: 53.2 | I4: 48.5 | K4: 41944 | L4: Monthly
A5: EZ | B5: Euro Area | C5: =IF(VLOOKUP(B5,$E$2:$L$49,7,FALSE)=$C$1,VLOOKUP(B5,$E$2:$L$49,2,FALSE),"") -> 50.1 | E5: Canada | F5: 55.3 | G5: 55.3 | H5: 56.3 | I5: 49.3 | K5: 41944 | L5: Monthly
A6: DE | B6: Germany | C6: =IF(VLOOKUP(B6,$E$2:$L$49,7,FALSE)=$C$1,VLOOKUP(B6,$E$2:$L$49,2,FALSE),"") -> 49.5 | E6: China | F6: 50.3 | G6: 50.8 | H6: 63.4 | I6: 38.8 | K6: 41944 | L6: Monthly
A7: FR | B7: France | C7: =IF(VLOOKUP(B7,$E$2:$L$49,7,FALSE)=$C$1,VLOOKUP(B7,$E$2:$L$49,2,FALSE),"") -> 48.4 | E7: Czech Republic | F7: 55.6 | G7: 54.4 | H7: 57.3 | I7: 46 | K7: 41944 | L7: Monthly
A8: IT | B8: Italy | C8: =IF(VLOOKUP(B8,$E$2:$L$49,7,FALSE)=$C$1,VLOOKUP(B8,$E$2:$L$49,2,FALSE),"") -> 49 | E8: Egypt | F8: 51 | G8: 52.4 | H8: 52.5 | I8: 37.1 | K8: 41913 | L8: Monthly
A9: ES | B9: Spain | C9: =IF(VLOOKUP(B9,$E$2:$L$49,7,FALSE)=$C$1,VLOOKUP(B9,$E$2:$L$49,2,FALSE),"") -> 54.7 | E9: Euro Area | F9: 50.1 | G9: 50.6 | H9: 59 | I9: 33.5 | K9: 41944 | L9: Monthly
A10: EL | B10: Greece | C10: =IF(VLOOKUP(B10,$E$2:$L$49,7,FALSE)=$C$1,VLOOKUP(B10,$E$2:$L$49,2,FALSE),"") -> 49.1 | E10: France | F10: 48.4 | G10: 48.5 | H10: 57.5 | I10: 42.7 | K10: 41944 | L10: Monthly
A11: IR | B11: Ireland | C11: =IF(VLOOKUP(B11,$E$2:$L$49,7,FALSE)=$C$1,VLOOKUP(B11,$E$2:$L$49,2,FALSE),"") -> 56.2 | E11: Germany | F11: 49.5 | G11: 51.4 | H11: 62.7 | I11: 32 | K11: 41944 | L11: Monthly
A12: CH | B12: China | C12: =IF(VLOOKUP(B12,$E$2:$L$49,7,FALSE)=$C$1,VLOOKUP(B12,$E$2:$L$49,2,FALSE),"") -> 50.3 | E12: Greece | F12: 49.1 | G12: 48.8 | H12: 51.3 | I12: 37.7 | K12: 41944 | L12: Monthly
A13: JP | B13: Japan | C13: =IF(VLOOKUP(B13,$E$2:$L$49,7,FALSE)=$C$1,VLOOKUP(B13,$E$2:$L$49,2,FALSE),"") -> 52 | E13: Hong Kong | F13: 47.7 | G13: 49.8 | H13: 53.3 | I13: 47.7 | K13: 41913 | L13: Monthly
... A24: PL | B24: Poland | C24: =IF(VLOOKUP(B24,$E$2:$L$49,7,FALSE)=$C$1,VLOOKUP(B24,$E$2:$L$49,2,FALSE),"") -> 53.2 | E24: Russia | F24: 51.7 | G24: 50.3 | H24: 53.2 | I24: 48 | K24: 41944 | L24: Monthly
E25: Saudi Arabia | F25: 59.1 | G25: 61.8 | H25: 61.8 | I25: 56.6 | K25: 41913 | L25: Monthly
E26: Singapore | F26: 51.8 | G26: 51.9 | H26: 51.9 | I26: 48.3 | K26: 41944 | L26: Monthly
E27: South Africa | F27: 50.1 | G27: 50.07 | H27: 63.71 | I27: 34.11 | K27: 41944 | L27: Monthly
E28: South Korea | F28: 49 | G28: 48.7 | H28: 52.6 | I28: 45.7 | K28: 41944 | L28: Monthly
E29: Spain | F29: 54.7 | G29: 52.6 | H29: 54.7 | I29: 41.1 | K29: 41944 | L29: Monthly
E30: Sweden | F30: 52.7 | G30: 52.1 | H30: 71.4 | I30: 32.7 | K30: 41944 | L30: Monthly
E31: Switzerland | F31: 52.1 | G31: 55.3 | H31: 66.9 | I31: 32.6 | K31: 41944 | L31: Monthly
E32: Taiwan | F32: 51.4 | G32: 52 | H32: 56.1 | I32: 45.6 | K32: 41944 | L32: Monthly
E33: Turkey | F33: 52.2 | G33: 51.5 | H33: 55 | I33: 48.5 | K33: 41944 | L33: Monthly
E34: United Arab Emirates | F34: 61.2 | G34: 57.6 | H34: 61.2 | I34: 51.7 | K34: 41913 | L34: Monthly
E35: United Kingdom | F35: 53.5 | G35: 53.3 | H35: 61.5 | I35: 34.4 | K35: 41944 | L35: Monthly
E36: United States | F36: 54.8 | G36: 55.9 | H36: 57.9 | I36: 51 | K36: 41944 | L36: Monthly
E37: Vietnam | F37: 51 | G37: 51.7 | H37: 53.1 | I37: 43.6 | K37: 41913 | L37: Monthly
A50: Names Tab | N50: REFRESHED 2026-07-03 for the 24 PMI-dashboard countries: GDP y/y + key rate + inflation = GMD 2026_06 2025 actuals (US/UK/AU/CN/EZ overridden with live FRED readings; Taiwan rate = 2023 latest). GDP q/q blanked (not tracked free). Other countries remain 2014-vintage. | O50: All Tabs GDP Growth
B51: GDP | C51: GDP YoY | D51: GDP QoQ | E51: Interest rate | F51: Inflation rate | G51: Jobless rate | H51: Gov. Budget | I51: Debt/GDP | J51: Current Account | K51: Currency | L51: Population | P51: Last | Q51: Previous | R51: Highest | S51: Lowest | T51: Unit | U51: Reference | V51: Frequency
O52: Albania | P52: 0.38 | Q52: 0.12 | R52: 6 | S52: -2.6 | T52: percent | U52: 41760 | V52: Quarterly | W52: [+]
A53: United States | B53: 16800 | C53: 0.022 | E53: 0.0363 | F53: 0.043 | G53: 0.058 | H53: -0.028 | I53: 1.0153 | J53: -2.3 | K53: 119.89 | L53: 317.3 | O53: Algeria | P53: 3.1 | Q53: 2.6 | R53: 6.7 | S53: 2 | T53: percent | U53: 41244 | V53: Yearly | W53: [+]
A54: Euro Area | B54: 12750 | C54: 0.003 | E54: 0.0193 | F54: 0.0314 | G54: 0.115 | H54: -0.029 | I54: 0.909 | J54: 2.4 | K54: 1.24 | L54: 332.88 | O54: Angola | P54: 7.4 | Q54: 5.2 | R54: 23.2 | S54: 2.4 | T54: percent | U54: 41609 | V54: Yearly | W54: [+]
A55: China | B55: 9240 | C55: 0.0446 | E55: 0.03 | F55: -0.001 | G55: 0.041 | H55: -0.021 | I55: 0.224 | J55: 2 | K55: 6.15 | L55: 1360.72 | O55: Argentina | P55: 0.9 | Q55: -0.5 | R55: 5.1 | S55: -5.7 | T55: percent | U55: 41760 | V55: Quarterly | W55: [+]
A56: Japan | B56: 4901 | C56: 0.0143 | E56: 0.0075 | F56: 0.0192 | G56: 0.035 | H56: -0.076 | I56: 2.272 | J56: 0.7 | K56: 119.12 | L56: 127.22 | O56: Australia | P56: 0.5 | Q56: 1.1 | R56: 4.5 | S56: -2 | T56: percent | U56: 41760 | V56: Quarterly | W56: [+]
A57: Germany | B57: 3635 | C57: 0.0072 | E57: 0.0238 | F57: 0.0202 | G57: 0.049 | H57: 0.001 | I57: 0.769 | J57: 7.5 | K57: 1.24 | L57: 80.52 | O57: Austria | P57: -0.3 | Q57: 0.1 | R57: 1.6 | S57: -1.8 | T57: percent | U57: 41852 | V57: Quarterly | W57: [+]
A58: France | B58: 2735 | C58: 0.009 | E58: 0.0238 | F58: 0.016 | G58: 0.102 | H58: -0.041 | I58: 0.922 | J58: -1.3 | K58: 1.24 | L58: 65.8 | O58: Bahrain | P58: 2.28 | Q58: 0.26 | R58: 2.8 | S58: -6.6 | T58: percent | U58: 41760 | V58: Quarterly | W58: [+]
A59: United Kingdom | B59: 2522 | C59: 0.0169 | E59: 0.0373 | F59: 0.028 | G59: 0.06 | H59: -0.058 | I59: 0.906 | J59: -4.4 | K59: 1.56 | L59: 63.9 | O59: Bangladesh | P59: 6.01 | Q59: 6.32 | R59: 6.71 | S59: 4.08 | T59: percent | U59: 41426 | V59: Yearly | W59: [+]
A60: Brazil | B60: 2246 | C60: 0.0233 | E60: 0.15 | F60: 0.0424 | G60: 0.047 | H60: 0.019 | I60: 0.568 | J60: -3.66 | K60: 2.57 | L60: 201.03 | O60: Belgium | P60: 0.3 | Q60: 0.1 | R60: 15.8 | S60: -2.2 | T60: percent | U60: 41852 | V60: Quarterly | W60: [+]
A61: Russia | B61: 2097 | C61: 0.0113 | E61: 0.16 | F61: 0.0704 | G61: 0.051 | H61: -0.005 | I61: 0.1341 | J61: 1.56 | K61: 53.92 | L61: 143.7 | O61: Belize | P61: 9.94 | Q61: -2.1 | R61: 13.45 | S61: -10.63 | T61: percent | U61: 41760 | V61: Quarterly | W61: [+]
A62: Italy | B62: 2071 | C62: 0.009 | E62: 0.0238 | F62: 0.0206 | G62: 0.132 | H62: -0.028 | I62: 1.326 | J62: 1 | K62: 1.24 | L62: 59.69 | O62: Bolivia | P62: -7.43 | Q62: 9.95 | R62: 17.6 | S62: -15.7 | T62: percent | U62: 41760 | V62: Quarterly | W62: [+]
A63: India | B63: 1877 | C63: 0.0667 | E63: 0.0525 | F63: 0.042 | G63: 0.052 | H63: -0.045 | I63: 0.6772 | J63: -1.7 | K63: 61.91 | L63: 1233 | O63: Bosnia And Herzegovina | P63: -1.2 | Q63: 1.3 | R63: 1.3 | S63: -1.6 | T63: percent | U63: 41760 | V63: Quarterly | W63: [+]
A64: Canada | B64: 1825 | C64: 0.0195 | E64: 0.0225 | F64: 0.0199 | G64: 0.065 | H64: -0.01 | I64: 0.891 | J64: -3.2 | K64: 1.13 | L64: 35.35 | O64: Botswana | P64: 1.6 | Q64: -0.7 | R64: 13.4 | S64: -14.4 | T64: percent | U64: 41760 | V64: Quarterly | W64: [+]
... A70: Turkey | B70: 820 | C70: 0.0259 | E70: 0.38 | F70: 0.3067 | G70: 0.101 | H70: -0.012 | I70: 0.3585 | J70: -7.9 | K70: 2.21 | L70: 76.67 | O70: China | P70: 1.9 | Q70: 2 | R70: 2.5 | S70: 1.4 | T70: percent | U70: 41852 | V70: Quarterly | W70: [+]
A71: Netherlands | B71: 800 | C71: 0.011 | D71: 0.002 | E71: 0.0005 | F71: 0.011 | G71: 0.08 | H71: -0.023 | I71: 0.735 | J71: 10.4 | K71: 1.24 | L71: 16.78 | O71: Colombia | P71: -0.1 | Q71: 2.5 | R71: 3.5 | S71: -0.9 | T71: percent | U71: 41760 | V71: Quarterly | W71: [+]
A72: Saudi Arabia | B72: 745 | C72: 0.038 | D72: 0.038 | E72: 0.02 | F72: 0.026 | G72: 0.055 | H72: 0.064 | I72: 0.0268 | J72: 18 | K72: 3.75 | L72: 29.99 | O72: Costa Rica | P72: 0.88 | Q72: 0.2 | R72: 9.33 | S72: -6.15 | T72: percent | U72: 41760 | V72: Quarterly | W72: [+]
A73: Switzerland | B73: 651 | C73: 0.019 | D73: 0.006 | E73: 0 | F73: 0 | G73: 0.031 | H73: 0 | I73: 0.354 | J73: 13.5 | K73: 0.96 | L73: 8.04 | O73: Croatia | P73: -0.3 | Q73: 0 | R73: 2.1 | S73: -5.5 | T73: percent | U73: 41760 | V73: Quarterly | W73: [+]
A74: Argentina | B74: 612 | C74: 0 | D74: 0.009 | E74: 0.2105 | F74: 0.109 | G74: 0.075 | H74: -0.026 | I74: 0.456 | J74: -0.9 | K74: 8.53 | L74: 41.45 | O74: Cyprus | P74: -0.4 | Q74: -0.3 | R74: 2 | S74: -1.8 | T74: percent | U74: 41852 | V74: Quarterly | W74: [+]
A75: Sweden | B75: 558 | C75: 0.021 | D75: 0.003 | E75: 0 | F75: -0.001 | G75: 0.075 | H75: -0.011 | I75: 0.406 | J75: 6.2 | K75: 7.44 | L75: 9.56 | O75: Czech Republic | P75: 0.4 | Q75: 0.3 | R75: 2.3 | S75: -3.3 | T75: percent | U75: 41852 | V75: Quarterly | W75: [+]
A76: Nigeria | B76: 523 | C76: 0.0623 | D76: 0.0867 | E76: 0.13 | F76: 0.081 | G76: 0.239 | H76: -0.018 | I76: 0.11 | J76: 7.1 | K76: 183.75 | L76: 166.21 | O76: Denmark | P76: 0.5 | Q76: 0.1 | R76: 3.89 | S76: -2.42 | T76: percent | U76: 41852 | V76: Quarterly | W76: [+]
A77: Poland | B77: 518 | C77: 0.0336 | E77: 0.04 | F77: 0.0503 | G77: 0.113 | H77: -0.043 | I77: 0.57 | J77: -1.3 | K77: 3.35 | L77: 38.49 | O77: Dominican Republic | P77: -13.44 | Q77: 13.17 | R77: 17.18 | S77: -13.44 | T77: percent | U77: 41671 | V77: Quarterly | W77: [+]
A78: Norway | B78: 513 | C78: 0.021 | D78: 0.005 | E78: 0.015 | F78: 0.02 | G78: 0.037 | H78: 0.111 | I78: 0.2952 | J78: 11 | K78: 6.94 | L78: 5.11 | O78: Ecuador | P78: 1 | Q78: 0.2 | R78: 3.4 | S78: -1.9 | T78: percent | U78: 41760 | V78: Quarterly | W78: [+]
A79: Belgium | B79: 508 | C79: 0.009 | D79: 0.003 | E79: 0.0005 | F79: -0.0011 | G79: 0.086 | H79: -0.026 | I79: 1.015 | J79: -1.6 | K79: 1.24 | L79: 11.16 | O79: Egypt | P79: 3.7 | Q79: 2.5 | R79: 7.3 | S79: -4.3 | T79: percent | U79: 41760 | V79: Quarterly | W79: [+]
A80: Taiwan | B80: 489 | C80: 0.087 | E80: 0.0111 | F80: 0.0166 | G80: 0.0387 | H80: -0.02 | I80: 0.4098 | J80: 11.73 | K80: 31.02 | L80: 23.37 | O80: El Salvador | P80: -0.06 | Q80: 0.22 | R80: 2.53 | S80: -2.78 | T80: percent | U80: 41760 | V80: Quarterly | W80: [+]
A81: Venezuela | B81: 438 | C81: 0.01 | D81: 0.068 | E81: 0.1839 | F81: 0.6342 | G81: 0.07 | H81: -0.115 | I81: 0.498 | J81: 7.1 | K81: 6.29 | L81: 29.72 | O81: Estonia | P81: 0.2 | Q81: 1.1 | R81: 4.9 | S81: -9.7 | T81: percent | U81: 41852 | V81: Quarterly | W81: [+]
A82: Austria | B82: 416 | C82: -0.001 | D82: -0.003 | E82: 0.0005 | F82: 0.016 | G82: 0.087 | H82: -0.015 | I82: 0.745 | J82: 2.7 | K82: 1.24 | L82: 8.45 | O82: Euro Area | P82: 0.2 | Q82: 0.1 | R82: 1.3 | S82: -2.8 | T82: percent | U82: 41852 | V82: Quarterly | W82: [+]
A83: Thailand | B83: 387 | C83: 0.006 | D83: 0.011 | E83: 0.02 | F83: 0.0126 | G83: 0.0075 | H83: -0.025 | I83: 0.457 | J83: -0.7 | K83: 32.77 | L83: 67.01 | O83: European Union | P83: 0.3 | Q83: 0.2 | R83: 1.3 | S83: -2.7 | T83: percent | U83: 41852 | V83: Quarterly | W83: [+]
A84: United Arab Emirates | B84: 384 | C84: 0.052 | D84: 0.052 | E84: 0.01 | F84: 0.031 | G84: 0.042 | H84: 0.1015 | I84: 0.167 | J84: 14.91 | K84: 3.67 | L84: 9.35 | O84: Finland | P84: 0.2 | Q84: 0.2 | R84: 5 | S84: -6.3 | T84: percent | U84: 41852 | V84: Quarterly | W84: [+]
A85: Colombia | B85: 378 | C85: 0.043 | D85: -0.001 | E85: 0.045 | F85: 0.0329 | G85: 0.079 | H85: -0.0241 | I85: 0.318 | J85: -3.4 | K85: 2238.3 | L85: 47.1 | O85: France | P85: 0.3 | Q85: -0.1 | R85: 1.6 | S85: -1.7 | T85: percent | U85: 41852 | V85: Quarterly | W85: [+]
A86: Iran | B86: 369 | C86: -0.011 | E86: 0.1415 | F86: 0.1438 | G86: 0.095 | H86: -0.0078 | I86: 0.1063 | J86: 8.12 | K86: 24797 | L86: 77.45 | O86: Germany | P86: 0.1 | Q86: -0.1 | R86: 2.1 | S86: -3.7 | T86: percent | U86: 41852 | V86: Quarterly | W86: [+]
A87: South Africa | B87: 351 | C87: 0.014 | D87: 0.014 | E87: 0.0575 | F87: 0.059 | G87: 0.254 | H87: -0.04 | I87: 0.461 | J87: -5.8 | K87: 11 | L87: 52.98 | O87: Ghana | P87: 3.3 | Q87: 2 | R87: 7.8 | S87: -5.9 | T87: percent | U87: 41760 | V87: Quarterly | W87: [+]
A88: Denmark | B88: 331 | C88: 0.009 | D88: 0.005 | E88: 0.002 | F88: 0.005 | G88: 0.04 | H88: -0.008 | I88: 0.445 | J88: 7.3 | K88: 5.97 | L88: 5.62 | O88: Greece | P88: 0.7 | Q88: 0.3 | R88: 3.3 | S88: -4.7 | T88: percent | U88: 41852 | V88: Quarterly | W88: [+]
A89: Malaysia | B89: 312 | C89: 0.056 | D89: 0.009 | E89: 0.0325 | F89: 0.028 | G89: 0.027 | H89: -0.039 | I89: 0.548 | J89: 4.7 | K89: 3.43 | L89: 29.95 | O89: Hong Kong | P89: 1.7 | Q89: -0.1 | R89: 6.3 | S89: -3.4 | T89: percent | U89: 41852 | V89: Quarterly | W89: [+]
A90: Singapore | B90: 298 | C90: 0.028 | D90: 0.031 | E90: 0.0012 | F90: 0.001 | G90: 0.019 | H90: 0.011 | I90: 1.055 | J90: 18 | K90: 1.31 | L90: 5.4 | O90: Hungary | P90: 0.5 | Q90: 0.8 | R90: 2.3 | S90: -3.3 | T90: percent | U90: 41852 | V90: Quarterly | W90: [+]
A91: Israel | B91: 291 | C91: 0.0189 | D91: -0.0009 | E91: 0.0025 | F91: -0.003 | G91: 0.057 | H91: -0.0315 | I91: 0.674 | J91: 2.47 | K91: 3.91 | L91: 8.13 | O91: Iceland | P91: -1.2 | Q91: -1 | R91: 10.4 | S91: -8 | T91: percent | U91: 41760 | V91: Quarterly | W91: [+]
A92: Chile | B92: 277 | C92: 0.008 | D92: 0.004 | E92: 0.03 | F92: 0.057 | G92: 0.064 | H92: -0.007 | I92: 0.128 | J92: -3.4 | K92: 612.1 | L92: 17.56 | O92: India | P92: 1.2 | Q92: 1.9 | R92: 5.8 | S92: -1.9 | T92: percent | U92: 41760 | V92: Quarterly | W92: [+]
A93: Hong Kong | B93: 274 | C93: 0.027 | D93: 0.017 | E93: 0.005 | F93: 0.052 | G93: 0.033 | H93: 0.006 | I93: 0.3384 | J93: 2.1 | K93: 7.76 | L93: 7.22 | O93: Indonesia | P93: 2.96 | Q93: 2.49 | R93: 3.82 | S93: -3.57 | T93: percent | U93: 41852 | V93: Quarterly | W93: [+]
A94: Egypt | B94: 272 | C94: 0.037 | D94: 0.037 | E94: 0.0925 | F94: 0.118 | G94: 0.131 | H94: -0.091 | I94: 0.871 | J94: -2.4 | K94: 7.13 | L94: 82.06 | O94: Ireland | P94: 1.5 | Q94: 2.8 | R94: 5.5 | S94: -4.3 | T94: percent | U94: 41760 | V94: Quarterly | W94: [+]
A95: Philippines | B95: 272 | C95: 0.053 | D95: 0.004 | E95: 0.04 | F95: 0.043 | G95: 0.067 | H95: -0.014 | I95: 0.492 | J95: 3.5 | K95: 44.73 | L95: 97.35 | O95: Israel | P95: -0.09 | Q95: 0.54 | R95: 7.4 | S95: -3.4 | T95: percent | U95: 41852 | V95: Quarterly | W95: [+]
A96: Finland | B96: 257 | C96: 0 | D96: 0.002 | E96: 0.0005 | F96: 0.01 | G96: 0.083 | H96: -0.02 | I96: 0.57 | J96: -1.1 | K96: 1.24 | L96: 5.45 | O96: Italy | P96: -0.1 | Q96: -0.2 | R96: 6 | S96: -3.5 | T96: percent | U96: 41852 | V96: Quarterly | W96: [+]
A97: Greece | B97: 242 | C97: 0.0217 | E97: 0.0238 | F97: 0.0274 | G97: 0.259 | H97: -0.122 | I97: 1.749 | J97: 0.7 | K97: 1.24 | L97: 11.06 | O97: Jamaica | P97: -0.5 | Q97: -0.3 | R97: 2.2 | S97: -1.9 | T97: percent | U97: 41671 | V97: Quarterly | W97: [+]
A98: Pakistan | B98: 237 | C98: 0.036 | D98: 0.05 | E98: 0.095 | F98: 0.0396 | G98: 0.06 | H98: -0.08 | I98: 0.633 | J98: -1.1 | K98: 101.75 | L98: 188.2 | O98: Japan | P98: -0.4 | Q98: -1.9 | R98: 3.2 | S98: -4 | T98: percent | U98: 41852 | V98: Quarterly | W98: [+]
A99: Kazakhstan | B99: 224 | C99: 0.04 | D99: 0.086 | E99: 0.055 | F99: 0.076 | G99: 0.05 | H99: -0.021 | I99: 0.1353 | J99: -0.05 | K99: 179.15 | L99: 16.91 | O99: Kazakhstan | P99: 8.6 | Q99: 2.1 | R99: 8.6 | S99: -8.9 | T99: percent | U99: 40118 | V99: Quarterly | W99: [+]
A100: Iraq | B100: 223 | C100: 0.0421 | E100: 0.06 | F100: 0.009 | G100: 0.151 | H100: -0.0555 | I100: 0.3134 | J100: 6.71 | K100: 1162 | L100: 33.42 | O100: Kenya | P100: 4 | Q100: 2.7 | R100: 4 | S100: -2.4 | T100: percent | U100: 41760 | V100: Quarterly | W100: [+]
A101: Portugal | B101: 220 | C101: 0.011 | D101: 0.003 | E101: 0.0005 | F101: 0 | G101: 0.131 | H101: -0.049 | I101: 1.29 | J101: 0.5 | K101: 1.24 | L101: 10.49 | O101: Latvia | P101: 0.5 | Q101: 0.8 | R101: 4.6 | S101: -12 | T101: percent | U101: 41852 | V101: Quarterly | W101: [+]
A102: Ireland | B102: 218 | C102: 0.0366 | E102: 0.0238 | F102: 0.0186 | G102: 0.11 | H102: -0.057 | I102: 1.233 | J102: 6.6 | K102: 1.24 | L102: 4.59 | O102: Lithuania | P102: 0.5 | Q102: 0.9 | R102: 4.2 | S102: -13.1 | T102: percent | U102: 41852 | V102: Quarterly | W102: [+]
A103: Algeria | B103: 210 | C103: 0.027 | D103: 0.031 | E103: 0.04 | F103: 0.068 | G103: 0.098 | H103: -0.002 | I103: 0.0921 | J103: 8 | K103: 85.61 | L103: 38.29 | O103: Luxembourg | P103: 0.7 | Q103: 0.8 | R103: 7.9 | S103: -5.5 | T103: percent | U103: 41760 | V103: Quarterly | W103: [+]
A104: Qatar | B104: 202 | C104: 0.057 | D104: -0.002 | E104: 0.045 | F104: 0.03 | G104: 0.003 | H104: 0.189 | I104: 0.3425 | J104: 30.9 | K104: 3.64 | L104: 2.17 | O104: Macedonia | P104: 3.2 | Q104: 3 | R104: 8.2 | S104: -2.4 | T104: percent | U104: 41579 | V104: Quarterly | W104: [+]
A105: Peru | B105: 202 | C105: 0.0176 | D105: 0.003 | E105: 0.035 | F105: 0.0316 | G105: 0.057 | H105: 0.009 | I105: 0.196 | J105: -4.6 | K105: 2.92 | L105: 30.38 | O105: Malaysia | P105: 0.9 | Q105: 1.9 | R105: 5.9 | S105: -7.6 | T105: percent | U105: 41852 | V105: Quarterly | W105: [+]
A106: Czech Republic | B106: 198 | C106: 0.0236 | E106: 0.035 | F106: 0.0233 | G106: 0.071 | H106: -0.015 | I106: 0.4604 | J106: -1.4 | K106: 22.11 | L106: 10.51 | O106: Malta | P106: 1.3 | Q106: 1.1 | R106: 4.1 | S106: -3.4 | T106: percent | U106: 41760 | V106: Quarterly | W106: [+]
A107: Romania | B107: 190 | C107: 0.032 | D107: 0.019 | E107: 0.0275 | F107: 0.014 | G107: 0.067 | H107: -0.009 | I107: 0.384 | J107: -1.1 | K107: 3.55 | L107: 20.02 | O107: Mauritius | P107: 2.4 | Q107: 0.8 | R107: 6.1 | S107: -1.7 | T107: percent | U107: 41760 | V107: Quarterly | W107: [+]
A108: New Zealand | B108: 183 | C108: 0.039 | D108: 0.007 | E108: 0.035 | F108: 0.01 | G108: 0.054 | H108: -0.021 | I108: 0.359 | J108: -3.4 | K108: 0.78 | L108: 4.5 | O108: Mexico | P108: 0.5 | Q108: 0.9 | R108: 2.9 | S108: -6.6 | T108: percent | U108: 41852 | V108: Quarterly | W108: [+]
A109: Kuwait | B109: 183 | C109: 0.0082 | E109: 0.02 | F109: 0.03 | G109: 0.0272 | H109: 0.2893 | I109: 0.0528 | J109: 38.8 | K109: 5.05 | L109: 3.82 | O109: Moldova | P109: 0.91 | Q109: 0.51 | R109: 5.2 | S109: -7.84 | T109: percent | U109: 40483 | V109: Quarterly | W109: [+]
A110: Ukraine | B110: 177 | C110: -0.051 | D110: -0.021 | E110: 0.14 | F110: 0.198 | G110: 0.086 | H110: -0.0448 | I110: 0.4103 | J110: -9.2 | K110: 14.81 | L110: 45.43 | O110: Mongolia | P110: 7.4 | Q110: 11.7 | R110: 17.5 | S110: -9.3 | T110: percent | U110: 41671 | V110: Quarterly | W110: [+]
A111: Vietnam | B111: 171 | C111: 0.0619 | D111: 0.0619 | E111: 0.065 | F111: 0.026 | G111: 0.0214 | H111: -0.071 | I111: 0.5498 | J111: 6.5 | K111: 21075 | L111: 89.71 | O111: Morocco | P111: 2.3 | Q111: 1.7 | R111: 9.3 | S111: 0.5 | T111: percent | U111: 41760 | V111: Quarterly | W111: [+]
A112: Bangladesh | B112: 130 | C112: 0.0601 | D112: 0.0601 | E112: 0.0725 | F112: 0.066 | G112: 0.045 | H112: -0.04 | I112: 0.18 | J112: 0.4 | K112: 75.86 | L112: 154.7 | O112: Mozambique | P112: 1 | Q112: 4.7 | R112: 7.7 | S112: -4.3 | T112: percent | U112: 41760 | V112: Quarterly | W112: [+]
A113: Hungary | B113: 126 | C113: 0.032 | D113: 0.005 | E113: 0.021 | F113: -0.004 | G113: 0.071 | H113: -0.022 | I113: 0.792 | J113: 3 | K113: 245.44 | L113: 9.91 | O113: Namibia | P113: 4.3 | Q113: -3.7 | R113: 13.3 | S113: -8.8 | T113: percent | U113: 41214 | V113: Quarterly | W113: [+]
A114: Angola | B114: 122 | C114: 0.051 | D114: 0.074 | E114: 0.09 | F114: 0.0748 | G114: 0.26 | H114: 0.024 | I114: 0.2929 | J114: 7.3 | K114: 100.95 | L114: 19.18 | O114: Netherlands | P114: 0.2 | Q114: 0.6 | R114: 2 | S114: -2.2 | T114: percent | U114: 41852 | V114: Quarterly | W114: [+]
A115: Morocco | B115: 104 | C115: 0.026 | D115: 0.023 | E115: 0.0275 | F115: 0.006 | G115: 0.096 | H115: -0.054 | I115: 0.617 | J115: -7.2 | K115: 8.82 | L115: 32.95 | O115: New Zealand | P115: 0.7 | Q115: 1 | R115: 2.9 | S115: -2.6 | T115: percent | U115: 41760 | V115: Quarterly | W115: [+]
A116: Puerto Rico | B116: 101 | C116: 0.003 | F116: 0.004 | G116: 0.14 | K116: 88.65 | L116: 3.67 | O116: Nigeria | P116: 8.67 | Q116: 4.18 | R116: 8.99 | S116: -9.88 | T116: percent | U116: 41852 | V116: Quarterly | W116: [+]
A117: Slovakia | B117: 92 | C117: 0.024 | D117: 0.006 | E117: 0.0005 | F117: 0 | G117: 0.1235 | H117: -0.0293 | I117: 0.5494 | J117: 2.1 | K117: 1.24 | L117: 5.41 | O117: Norway | P117: 0.5 | Q117: 1.1 | R117: 3.6 | S117: -2.6 | T117: percent | U117: 41852 | V117: Quarterly | W117: [+]
A118: Ecuador | B118: 90 | C118: 0.035 | D118: 0.01 | E118: 0.0834 | F118: 0.0398 | G118: 0.0571 | H118: -0.04 | I118: 0.244 | J118: -1.3 | K118: 216.3 | L118: 15.74 | O118: Pakistan | P118: 5 | Q118: 4.1 | R118: 10.22 | S118: -1.8 | T118: percent | U118: 41699 | V118: Yearly | W118: [+]
A119: Oman | B119: 81 | C119: 0.028 | E119: 0.01 | F119: 0.0102 | G119: 0.15 | H119: -0.003 | I119: 0.049 | J119: 6.4 | K119: 0.38 | L119: 3.63 | O119: Paraguay | P119: -0.6 | Q119: 2.2 | R119: 10.9 | S119: -5 | T119: percent | U119: 41760 | V119: Quarterly | W119: [+]
A120: Libya | B120: 75 | C120: -0.1206 | E120: 0.03 | F120: 0.011 | G120: 0.195 | H120: -0.093 | I120: 0.068 | J120: 50.3 | K120: 1.19 | L120: 6.2 | O120: Peru | P120: 0.3 | Q120: 1.7 | R120: 2.9 | S120: -1.3 | T120: percent | U120: 41671 | V120: Quarterly | W120: [+]
A121: Azerbaijan | B121: 74 | C121: 0.025 | E121: 0.035 | F121: 0.015 | G121: 0.052 | H121: 0.006 | I121: 0.1375 | J121: 16.7 | K121: 0.78 | L121: 9.36 | O121: Philippines | P121: 0.4 | Q121: 1.9 | R121: 3.2 | S121: -2.4 | T121: percent | U121: 41852 | V121: Quarterly | W121: [+]
A122: Syria | B122: 74 | C122: -0.023 | F122: 0.044 | G122: 0.149 | H122: -0.114 | I122: 0.3001 | J122: -0.62 | K122: 174.25 | L122: 22.85 | O122: Poland | P122: 0.9 | Q122: 0.7 | R122: 6.1 | S122: -3.1 | T122: percent | U122: 41852 | V122: Quarterly | W122: [+]
A123: Belarus | B123: 72 | C123: 0.005 | E123: 0.2 | F123: 0.1938 | G123: 0.005 | H123: -0.004 | I123: 0.3671 | J123: -9.8 | K123: 10900 | L123: 9.47 | O123: Portugal | P123: 0.3 | Q123: 0.3 | R123: 3.3 | S123: -2.6 | T123: percent | U123: 41852 | V123: Quarterly | W123: [+]
A124: Cuba | B124: 68 | C124: 0.027 | E124: 0.0225 | F124: 0.055 | G124: 0.033 | H124: -0.012 | I124: 0.211 | J124: 0.9 | K124: 1 | L124: 11.21 | O124: Qatar | P124: -0.2 | Q124: 2.3 | R124: 14.4 | S124: -23.2 | T124: percent | U124: 41760 | V124: Quarterly | W124: [+]
A125: Sri Lanka | B125: 67 | C125: 0.078 | D125: 0.078 | E125: 0.065 | F125: 0.015 | G125: 0.045 | H125: -0.059 | I125: 0.783 | J125: -3.9 | K125: 130.95 | L125: 20.48 | O125: Romania | P125: 1.9 | Q125: -0.3 | R125: 3.6 | S125: -4.8 | T125: percent | U125: 41852 | V125: Quarterly | W125: [+]
A126: Sudan | B126: 67 | C126: 0.036 | E126: 0.121 | F126: 0.282 | G126: 0.159 | H126: -0.017 | I126: 0.62 | J126: -9.6 | K126: 5.77 | L126: 37.96 | O126: Russia | P126: 0.25 | Q126: 0.07 | R126: 4.1 | S126: -5.4 | T126: percent | U126: 41760 | V126: Quarterly | W126: [+]
A127: Dominican Republic | B127: 61 | C127: 0.055 | D127: -0.1344 | E127: 0.0625 | F127: 0.0288 | G127: 0.149 | H127: -0.0287 | I127: 0.5177 | J127: -3.5 | K127: 44.09 | L127: 10.4 | O127: Rwanda | P127: 1.06 | Q127: -2.1 | R127: 13.4 | S127: 2.2 | T127: percent | U127: 41760 | V127: Quarterly | W127: [+]
...
