Workbook

Sheet Countries
A1: TBR - To be released
B4: Country Name | C4: % World GDP | D4: GDP y/y | E4: GDP q/q | F4: Key Rate | G4: Inflation | H4: Service PMI | I4: Summary | M4: Country Name | N4: % World GDP | O4: Nov | P4: Oct | Q4: Change | R4: Trend | S4: Summary
B5: United States | C5: =VLOOKUP($B5,Data!$K$30:$V$250,COLUMN(C5)-1,FALSE)/SUM(Data!$L$30:$L$250) -> 0.19182681 | D5: =VLOOKUP($B5,Data!$K$30:$V$250,COLUMN(D5)-1,FALSE) -> 0.024 | E5: =((1+VLOOKUP($B5,Data!$K$30:$V$250,COLUMN(E5)-1,FALSE))^(1/4))-1 -> 0.0096105657 | F5: =VLOOKUP($B5,Data!$K$30:$V$250,COLUMN(F5)-1,FALSE) -> 0.0025 | G5: =VLOOKUP($B5,Data!$K$30:$V$250,COLUMN(G5)-1,FALSE) -> 0.017 | H5: =Tabs!F28 -> 50.7 | I5: =VLOOKUP(B5,$M$5:$S$18,7,FALSE) -> Growing, slower | M5: Ireland | N5: =VLOOKUP(M5,$B$5:$C$18,2,FALSE) -> 0.0024891812 | O5: =Tabs!AH28 -> TBR | P5: =Tabs!AH27 -> TBR | Q5: =O5-P5 -> #VALUE! | R5: 26 | S5: Growing, faster
B6: Euro Area | C6: =VLOOKUP(B6,Data!$K$30:$V$250,COLUMN(C6)-1,FALSE)/SUM(Data!$L$30:$L$250) -> 0.14558285 | D6: =VLOOKUP($B6,Data!$K$30:$V$250,COLUMN(D6)-1,FALSE) -> 0.008 | E6: =VLOOKUP($B6,Data!$K$30:$V$250,COLUMN(E6)-1,FALSE) -> 0.002 | F6: =VLOOKUP($B6,Data!$K$30:$V$250,COLUMN(F6)-1,FALSE) -> 0.0005 | G6: =VLOOKUP($B6,Data!$K$30:$V$250,COLUMN(G6)-1,FALSE) -> 0.003 | H6: =Tabs!N28 -> 47.7 | I6: =VLOOKUP(B6,$M$5:$S$18,7,FALSE) -> Growing, slower | M6: United Kingdom | N6: =VLOOKUP(M6,$B$5:$C$18,2,FALSE) -> 0.028796858 | O6: 48.7 | P6: 49.3 | Q6: =O6-P6 -> -0.6 | R6: 32 | S6: Growing, faster
B7: China | C7: =VLOOKUP(B7,Data!$K$30:$V$250,COLUMN(C7)-1,FALSE)/SUM(Data!$L$30:$L$250) -> 0.10550474 | D7: =VLOOKUP($B7,Data!$K$30:$V$250,COLUMN(D7)-1,FALSE) -> 0.073 | E7: =VLOOKUP($B7,Data!$K$30:$V$250,COLUMN(E7)-1,FALSE) -> 0.019 | F7: =VLOOKUP($B7,Data!$K$30:$V$250,COLUMN(F7)-1,FALSE) -> 0.056 | G7: =VLOOKUP($B7,Data!$K$30:$V$250,COLUMN(G7)-1,FALSE) -> 0.016 | H7: =Tabs!AX28 -> TBR | I7: =VLOOKUP(B7,$M$5:$S$18,7,FALSE) -> Growing, faster | M7: United States | N7: =VLOOKUP(M7,$B$5:$C$18,2,FALSE) -> 0.19182681 | O7: =Tabs!F28 -> 50.7 | P7: =Tabs!F27 -> 51 | Q7: =O7-P7 -> -0.3 | R7: 11 | S7: Growing, slower
B8: Japan | C8: =VLOOKUP(B8,Data!$K$30:$V$250,COLUMN(C8)-1,FALSE)/SUM(Data!$L$30:$L$250) -> 0.055960904 | D8: =VLOOKUP($B8,Data!$K$30:$V$250,COLUMN(D8)-1,FALSE) -> -0.012 | E8: =VLOOKUP($B8,Data!$K$30:$V$250,COLUMN(E8)-1,FALSE) -> -0.004 | F8: =VLOOKUP($B8,Data!$K$30:$V$250,COLUMN(F8)-1,FALSE) -> 0 | G8: =VLOOKUP($B8,Data!$K$30:$V$250,COLUMN(G8)-1,FALSE) -> 0.029 | H8: =Tabs!AP28 -> 50 | I8: =VLOOKUP(B8,$M$5:$S$18,7,FALSE) -> Growing, from Contracting | M8: China | N8: =VLOOKUP(M8,$B$5:$C$18,2,FALSE) -> 0.10550474 | O8: =Tabs!AX28 -> TBR | P8: =Tabs!AX27 -> TBR | Q8: =O8-P8 -> #VALUE! | R8: 34 | S8: Growing, faster
B9: Germany | C9: =VLOOKUP(B9,Data!$K$30:$V$250,COLUMN(C9)-1,FALSE)/SUM(Data!$L$30:$L$250) -> 0.041505384 | D9: =VLOOKUP($B9,Data!$K$30:$V$250,COLUMN(D9)-1,FALSE) -> 0.012 | E9: =VLOOKUP($B9,Data!$K$30:$V$250,COLUMN(E9)-1,FALSE) -> 0.001 | F9: =VLOOKUP($B9,Data!$K$30:$V$250,COLUMN(F9)-1,FALSE) -> 0.0005 | G9: =VLOOKUP($B9,Data!$K$30:$V$250,COLUMN(G9)-1,FALSE) -> 0.006 | H9: =Tabs!R28 -> TBR | I9: =VLOOKUP(B9,$M$5:$S$18,7,FALSE) -> Growing, slower | M9: Spain | N9: =VLOOKUP(M9,$B$5:$C$18,2,FALSE) -> 0.015506 | O9: =Tabs!AD28 -> TBR | P9: =Tabs!AD27 -> TBR | Q9: =O9-P9 -> #VALUE! | R9: 11 | S9: Growing, slower
B10: France | C10: =VLOOKUP(B10,Data!$K$30:$V$250,COLUMN(C10)-1,FALSE)/SUM(Data!$L$30:$L$250) -> 0.031228948 | D10: =VLOOKUP($B10,Data!$K$30:$V$250,COLUMN(D10)-1,FALSE) -> 0.004 | E10: =VLOOKUP($B10,Data!$K$30:$V$250,COLUMN(E10)-1,FALSE) -> 0.003 | F10: =VLOOKUP($B10,Data!$K$30:$V$250,COLUMN(F10)-1,FALSE) -> 0.0005 | G10: =VLOOKUP($B10,Data!$K$30:$V$250,COLUMN(G10)-1,FALSE) -> 0.005 | H10: =Tabs!V28 -> TBR | I10: =VLOOKUP(B10,$M$5:$S$18,7,FALSE) -> Contracting, faster | M10: India | N10: =VLOOKUP(M10,$B$5:$C$18,2,FALSE) -> 0.021432078 | O10: =Tabs!BB28 -> 59.8 | P10: =Tabs!BB27 -> TBR | Q10: =O10-P10 -> #VALUE! | R10: 6 | S10: Growing, faster
B11: United Kingdom | C11: =VLOOKUP(B11,Data!$K$30:$V$250,COLUMN(C11)-1,FALSE)/SUM(Data!$L$30:$L$250) -> 0.028796858 | D11: =VLOOKUP($B11,Data!$K$30:$V$250,COLUMN(D11)-1,FALSE) -> 0.03 | E11: =VLOOKUP($B11,Data!$K$30:$V$250,COLUMN(E11)-1,FALSE) -> 0.007 | F11: =VLOOKUP($B11,Data!$K$30:$V$250,COLUMN(F11)-1,FALSE) -> 0.005 | G11: =VLOOKUP($B11,Data!$K$30:$V$250,COLUMN(G11)-1,FALSE) -> 0.013 | H11: 48.7 | I11: =VLOOKUP(B11,$M$5:$S$18,7,FALSE) -> Growing, faster | M11: Germany | N11: =VLOOKUP(M11,$B$5:$C$18,2,FALSE) -> 0.041505384 | O11: =Tabs!R28 -> TBR | P11: =Tabs!R27 -> TBR | Q11: =O11-P11 -> #VALUE! | R11: 17 | S11: Growing, slower
B12: Brazil | C12: =VLOOKUP(B12,Data!$K$30:$V$250,COLUMN(C12)-1,FALSE)/SUM(Data!$L$30:$L$250) -> 0.025645417 | D12: =VLOOKUP($B12,Data!$K$30:$V$250,COLUMN(D12)-1,FALSE) -> -0.002 | E12: =VLOOKUP($B12,Data!$K$30:$V$250,COLUMN(E12)-1,FALSE) -> 0.001 | F12: =VLOOKUP($B12,Data!$K$30:$V$250,COLUMN(F12)-1,FALSE) -> 0.1175 | G12: =VLOOKUP($B12,Data!$K$30:$V$250,COLUMN(G12)-1,FALSE) -> 0.0659 | H12: =Tabs!AT28 -> 50.4 | I12: =VLOOKUP(B12,$M$5:$S$18,7,FALSE) -> Contracting, slower | M12: Italy | N12: =VLOOKUP(M12,$B$5:$C$18,2,FALSE) -> 0.023647221 | O12: =Tabs!Z28 -> TBR | P12: =Tabs!Z27 -> TBR | Q12: =O12-P12 -> #VALUE! | R12: 1 | S12: Growing, faster
B13: Russia | C13: =VLOOKUP(B13,Data!$K$30:$V$250,COLUMN(C13)-1,FALSE)/SUM(Data!$L$30:$L$250) -> 0.023944096 | D13: =VLOOKUP($B13,Data!$K$30:$V$250,COLUMN(D13)-1,FALSE) -> 0.007 | E13: =VLOOKUP($B13,Data!$K$30:$V$250,COLUMN(E13)-1,FALSE) -> 0.0025 | F13: =VLOOKUP($B13,Data!$K$30:$V$250,COLUMN(F13)-1,FALSE) -> 0.095 | G13: =VLOOKUP($B13,Data!$K$30:$V$250,COLUMN(G13)-1,FALSE) -> 0.083 | H13: =Tabs!BF28 -> 48.7 | I13: =VLOOKUP(B13,$M$5:$S$18,7,FALSE) -> Contracting, faster | M13: Euro Area | N13: =VLOOKUP(M13,$B$5:$C$18,2,FALSE) -> 0.14558285 | O13: =Tabs!N28 -> 47.7 | P13: =Tabs!N27 -> 47.6 | Q13: =O13-P13 -> 0.1 | R13: 14 | S13: Growing, slower
B14: Italy | C14: =VLOOKUP(B14,Data!$K$30:$V$250,COLUMN(C14)-1,FALSE)/SUM(Data!$L$30:$L$250) -> 0.023647221 | D14: =VLOOKUP($B14,Data!$K$30:$V$250,COLUMN(D14)-1,FALSE) -> -0.005 | E14: =VLOOKUP($B14,Data!$K$30:$V$250,COLUMN(E14)-1,FALSE) -> -0.001 | F14: =VLOOKUP($B14,Data!$K$30:$V$250,COLUMN(F14)-1,FALSE) -> 0.0005 | G14: =VLOOKUP($B14,Data!$K$30:$V$250,COLUMN(G14)-1,FALSE) -> 0.0019 | H14: =Tabs!Z28 -> TBR | I14: =VLOOKUP(B14,$M$5:$S$18,7,FALSE) -> Growing, faster | M14: Japan | N14: =VLOOKUP(M14,$B$5:$C$18,2,FALSE) -> 0.055960904 | O14: =Tabs!AP28 -> 50 | P14: =Tabs!AP27 -> TBR | Q14: =O14-P14 -> #VALUE! | R14: 1 | S14: Growing, from Contracting
B15: India | C15: =VLOOKUP(B15,Data!$K$30:$V$250,COLUMN(C15)-1,FALSE)/SUM(Data!$L$30:$L$250) -> 0.021432078 | D15: =VLOOKUP($B15,Data!$K$30:$V$250,COLUMN(D15)-1,FALSE) -> 0.053 | E15: =VLOOKUP($B15,Data!$K$30:$V$250,COLUMN(E15)-1,FALSE) -> 0.012 | F15: =VLOOKUP($B15,Data!$K$30:$V$250,COLUMN(F15)-1,FALSE) -> 0.08 | G15: =VLOOKUP($B15,Data!$K$30:$V$250,COLUMN(G15)-1,FALSE) -> 0.0552 | H15: =Tabs!BB28 -> 59.8 | I15: =VLOOKUP(B15,$M$5:$S$18,7,FALSE) -> Growing, faster | M15: Brazil | N15: =VLOOKUP(M15,$B$5:$C$18,2,FALSE) -> 0.025645417 | O15: =Tabs!AT28 -> 50.4 | P15: =Tabs!AT27 -> TBR | Q15: =O15-P15 -> #VALUE! | R15: 1 | S15: Contracting, slower
B16: Australia | C16: =VLOOKUP(B16,Data!$K$30:$V$250,COLUMN(C16)-1,FALSE)/SUM(Data!$L$30:$L$250) -> 0.017823908 | D16: =VLOOKUP($B16,Data!$K$30:$V$250,COLUMN(D16)-1,FALSE) -> 0.027 | E16: =VLOOKUP($B16,Data!$K$30:$V$250,COLUMN(E16)-1,FALSE) -> 0.003 | F16: =VLOOKUP($B16,Data!$K$30:$V$250,COLUMN(F16)-1,FALSE) -> 0.025 | G16: =VLOOKUP($B16,Data!$K$30:$V$250,COLUMN(G16)-1,FALSE) -> 0.023 | H16: =Tabs!AL28 -> TBR | I16: =VLOOKUP(B16,$M$5:$S$18,7,FALSE) -> Contracting, slower | M16: France | N16: =VLOOKUP(M16,$B$5:$C$18,2,FALSE) -> 0.031228948 | O16: =Tabs!V28 -> TBR | P16: =Tabs!V27 -> TBR | Q16: =O16-P16 -> #VALUE! | R16: 3 | S16: Contracting, faster
B17: Spain | C17: =VLOOKUP(B17,Data!$K$30:$V$250,COLUMN(C17)-1,FALSE)/SUM(Data!$L$30:$L$250) -> 0.015506 | D17: =VLOOKUP($B17,Data!$K$30:$V$250,COLUMN(D17)-1,FALSE) -> 0.016 | E17: =VLOOKUP($B17,Data!$K$30:$V$250,COLUMN(E17)-1,FALSE) -> 0.005 | F17: =VLOOKUP($B17,Data!$K$30:$V$250,COLUMN(F17)-1,FALSE) -> 0.0005 | G17: =VLOOKUP($B17,Data!$K$30:$V$250,COLUMN(G17)-1,FALSE) -> -0.004 | H17: =Tabs!AD28 -> TBR | I17: =VLOOKUP(B17,$M$5:$S$18,7,FALSE) -> Growing, slower | M17: Russia | N17: =VLOOKUP(M17,$B$5:$C$18,2,FALSE) -> 0.023944096 | O17: =Tabs!BF28 -> 48.7 | P17: =Tabs!BF27 -> TBR | Q17: =O17-P17 -> #VALUE! | R17: 1 | S17: Contracting, faster
B18: Ireland | C18: =VLOOKUP(B18,Data!$K$30:$V$250,COLUMN(C18)-1,FALSE)/SUM(Data!$L$30:$L$250) -> 0.0024891812 | D18: =VLOOKUP($B18,Data!$K$30:$V$250,COLUMN(D18)-1,FALSE) -> 0.077 | E18: =VLOOKUP($B18,Data!$K$30:$V$250,COLUMN(E18)-1,FALSE) -> 0.015 | F18: =VLOOKUP($B18,Data!$K$30:$V$250,COLUMN(F18)-1,FALSE) -> 0.0005 | G18: =VLOOKUP($B18,Data!$K$30:$V$250,COLUMN(G18)-1,FALSE) -> 0.002 | H18: =Tabs!AH28 -> TBR | I18: =VLOOKUP(B18,$M$5:$S$18,7,FALSE) -> Growing, faster | M18: Australia | N18: =VLOOKUP(M18,$B$5:$C$18,2,FALSE) -> 0.017823908 | O18: =Tabs!AL28 -> TBR | P18: =Tabs!AL27 -> TBR | Q18: =O18-P18 -> #VALUE! | R18: 7 | S18: Contracting, slower

Sheet Tabs
A3: Global | E3: US | I3: UK | M3: EZ | Q3: DE | U3: FR | Y3: IT | AC3: ES | AG3: IR | AK3: AU | AO3: JP | AS3: BR | AW3: CH | BA3: IN | BE3: RS
A4: Date | B4: Index | C4: Change | E4: Date | F4: Index | G4: Change | I4: Date | J4: Index | K4: Change | M4: Date | N4: Index | O4: Change | Q4: Date | R4: Index | S4: Change | U4: Date | V4: Index | W4: Change | Y4: Date | Z4: Index | AA4: Change | AC4: Date | AD4: Index | AE4: Change | AG4: Date | AH4: Index | AI4: Change | AK4: Date | AL4: Index | AM4: Change | AO4: Date | AP4: Index | AQ4: Change | AS4: Date | AT4: Index | AU4: Change | AW4: Date | AX4: Index | AY4: Change | BA4: Date | BB4: Index | BC4: Change | BE4: Date | BF4: Index | BG4: Change
A5: =Global!A67 -> 41244 | B5: =Global!B67 -> 54.8 | C5: =Global!C67 -> 0 | E5: =US!A68 -> 41244 | F5: =US!B68 -> No data | G5: =US!C68 -> 0 | I5: =UK!A67 -> 41244 | J5: =UK!B67 -> 50.2 | K5: =UK!C67 -> -0.4 | M5: =EZ!A67 -> 41244 | N5: =EZ!B67 -> 47.2 | O5: =EZ!C67 -> 0.5 | Q5: =DE!A67 -> 41244 | R5: =DE!B67 -> 55.7 | S5: =DE!C67 -> 6 | U5: =FR!A67 -> 41244 | V5: =FR!B67 -> 44.1 | W5: =FR!C67 -> -1.7 | Y5: =IT!A67 -> 41244 | Z5: =IT!B67 -> 43.1 | AA5: =IT!C67 -> -1.5 | AC5: =ES!A67 -> 41244 | AD5: =ES!B67 -> 44.1 | AE5: =ES!C67 -> 1.7 | AG5: =IR!A67 -> 41244 | AH5: =IR!B67 -> 56.5 | AI5: =IR!C67 -> 0.4 | AK5: =AU!A67 -> 41244 | AL5: =AU!B67 -> 46.3 | AM5: =AU!C67 -> -0.8 | AO5: =JP!A67 -> 41244 | AP5: =JP!B67 -> 50.1 | AQ5: =JP!C67 -> 1 | AS5: =BR!A67 -> 41244 | AT5: =BR!B67 -> 53.2 | AU5: =BR!C67 -> 0.7 | AW5: =CH!A67 -> 41244 | AX5: =CH!B67 -> 53.5 | AY5: =CH!C67 -> 1.4 | BA5: =IN!A67 -> 41244 | BB5: =IN!B67 -> 52.1 | BC5: =IN!C67 -> -1.7 | BE5: =RS!A67 -> 41244 | BF5: =RS!B67 -> 56.1 | BG5: =RS!C67 -> -1
A6: =Global!A68 -> 41275 | B6: =Global!B68 -> 53.6 | C6: =Global!C68 -> -1.2 | E6: =US!A69 -> 41275 | F6: =US!B69 -> No data | G6: =US!C69 -> 0 | I6: =UK!A68 -> 41275 | J6: =UK!B68 -> 51.5 | K6: =UK!C68 -> 1.3 | M6: =EZ!A68 -> 41275 | N6: =EZ!B68 -> 48.6 | O6: =EZ!C68 -> 1.4 | Q6: =DE!A68 -> 41275 | R6: =DE!B68 -> 54.7 | S6: =DE!C68 -> -1 | U6: =FR!A68 -> 41275 | V6: =FR!B68 -> 43.6 | W6: =FR!C68 -> -0.5 | Y6: =IT!A68 -> 41275 | Z6: =IT!B68 -> 43.9 | AA6: =IT!C68 -> 0.8 | AC6: =ES!A68 -> 41275 | AD6: =ES!B68 -> 47 | AE6: =ES!C68 -> 2.9 | AG6: =IR!A68 -> 41275 | AH6: =IR!B68 -> 56.8 | AI6: =IR!C68 -> 0.3 | AK6: =AU!A68 -> 41275 | AL6: =AU!B68 -> 45.4 | AM6: =AU!C68 -> -0.9 | AO6: =JP!A68 -> 41275 | AP6: =JP!B68 -> 50.4 | AQ6: =JP!C68 -> 0.3 | AS6: =BR!A68 -> 41275 | AT6: =BR!B68 -> 54.5 | AU6: =BR!C68 -> 1.3 | AW6: =CH!A68 -> 41275 | AX6: =CH!B68 -> 54 | AY6: =CH!C68 -> 0.5 | BA6: =IN!A68 -> 41275 | BB6: =IN!B68 -> 57.5 | BC6: =IN!C68 -> 5.4 | BE6: =RS!A68 -> 41275 | BF6: =RS!B68 -> 55.7 | BG6: =RS!C68 -> -0.4
A7: =Global!A69 -> 41306 | B7: =Global!B69 -> 53.2 | C7: =Global!C69 -> -0.4 | E7: =US!A70 -> 41306 | F7: =US!B70 -> No data | G7: =US!C70 -> 0 | I7: =UK!A69 -> 41306 | J7: =UK!B69 -> 51.8 | K7: =UK!C69 -> 0.3 | M7: =EZ!A69 -> 41306 | N7: =EZ!B69 -> 47.9 | O7: =EZ!C69 -> -0.7 | Q7: =DE!A69 -> 41306 | R7: =DE!B69 -> 50.9 | S7: =DE!C69 -> -3.8 | U7: =FR!A69 -> 41306 | V7: =FR!B69 -> 43.7 | W7: =FR!C69 -> 0.1 | Y7: =IT!A69 -> 41306 | Z7: =IT!B69 -> 43.6 | AA7: =IT!C69 -> -0.3 | AC7: =ES!A69 -> 41306 | AD7: =ES!B69 -> 44.7 | AE7: =ES!C69 -> -2.3 | AG7: =IR!A69 -> 41306 | AH7: =IR!B69 -> 53.6 | AI7: =IR!C69 -> -3.2 | AK7: =AU!A69 -> 41306 | AL7: =AU!B69 -> 48.5 | AM7: =AU!C69 -> 3.1 | AO7: =JP!A69 -> 41306 | AP7: =JP!B69 -> 51.3 | AQ7: =JP!C69 -> 0.9 | AS7: =BR!A69 -> 41306 | AT7: =BR!B69 -> 52.1 | AU7: =BR!C69 -> -2.4 | AW7: =CH!A69 -> 41306 | AX7: =CH!B69 -> 52.1 | AY7: =CH!C69 -> -1.9 | BA7: =IN!A69 -> 41306 | BB7: =IN!B69 -> 54.2 | BC7: =IN!C69 -> -3.3 | BE7: =RS!A69 -> 41306 | BF7: =RS!B69 -> 56.1 | BG7: =RS!C69 -> 0.4
A8: =Global!A70 -> 41334 | B8: =Global!B70 -> 53.4 | C8: =Global!C70 -> 0.2 | E8: =US!A71 -> 41334 | F8: =US!B71 -> No data | G8: =US!C71 -> 0 | I8: =UK!A70 -> 41334 | J8: =UK!B70 -> 52.4 | K8: =UK!C70 -> 0.6 | M8: =EZ!A70 -> 41334 | N8: =EZ!B70 -> 46.4 | O8: =EZ!C70 -> -1.5 | Q8: =DE!A70 -> 41334 | R8: =DE!B70 -> 49.6 | S8: =DE!C70 -> -1.3 | U8: =FR!A70 -> 41334 | V8: =FR!B70 -> 41.3 | W8: =FR!C70 -> -2.4 | Y8: =IT!A70 -> 41334 | Z8: =IT!B70 -> 45.5 | AA8: =IT!C70 -> 1.9 | AC8: =ES!A70 -> 41334 | AD8: =ES!B70 -> 45.3 | AE8: =ES!C70 -> 0.6 | AG8: =IR!A70 -> 41334 | AH8: =IR!B70 -> 52.3 | AI8: =IR!C70 -> -1.3 | AK8: =AU!A70 -> 41334 | AL8: =AU!B70 -> 49.6 | AM8: =AU!C70 -> 1.1 | AO8: =JP!A70 -> 41334 | AP8: =JP!B70 -> 53.4 | AQ8: =JP!C70 -> 2.1 | AS8: =BR!A70 -> 41334 | AT8: =BR!B70 -> 50.3 | AU8: =BR!C70 -> -1.8 | AW8: =CH!A70 -> 41334 | AX8: =CH!B70 -> 54.3 | AY8: =CH!C70 -> 2.2 | BA8: =IN!A70 -> 41334 | BB8: =IN!B70 -> 51.4 | BC8: =IN!C70 -> -2.8 | BE8: =RS!A70 -> 41334 | BF8: =RS!B70 -> 54.6 | BG8: =RS!C70 -> -1.5
A9: =Global!A71 -> 41365 | B9: =Global!B71 -> 52.1 | C9: =Global!C71 -> -1.3 | E9: =US!A72 -> 41365 | F9: =US!B72 -> No data | G9: =US!C72 -> 0 | I9: =UK!A71 -> 41365 | J9: =UK!B71 -> 52.9 | K9: =UK!C71 -> 0.5 | M9: =EZ!A71 -> 41365 | N9: =EZ!B71 -> 47 | O9: =EZ!C71 -> 0.6 | Q9: =DE!A71 -> 41365 | R9: =DE!B71 -> 49.7 | S9: =DE!C71 -> 0.1 | U9: =FR!A71 -> 41365 | V9: =FR!B71 -> 44.3 | W9: =FR!C71 -> 3 | Y9: =IT!A71 -> 41365 | Z9: =IT!B71 -> 47 | AA9: =IT!C71 -> 1.5 | AC9: =ES!A71 -> 41365 | AD9: =ES!B71 -> 44.4 | AE9: =ES!C71 -> -0.9 | AG9: =IR!A71 -> 41365 | AH9: =IR!B71 -> 55.2 | AI9: =IR!C71 -> 2.9 | AK9: =AU!A71 -> 41365 | AL9: =AU!B71 -> 44.1 | AM9: =AU!C71 -> -5.5 | AO9: =JP!A71 -> 41365 | AP9: =JP!B71 -> 52.5 | AQ9: =JP!C71 -> -0.9 | AS9: =BR!A71 -> 41365 | AT9: =BR!B71 -> 51 | AU9: =BR!C71 -> 0.7 | AW9: =CH!A71 -> 41365 | AX9: =CH!B71 -> 51.1 | AY9: =CH!C71 -> -3.2 | BA9: =IN!A71 -> 41365 | BB9: =IN!B71 -> 50.7 | BC9: =IN!C71 -> -0.7 | BE9: =RS!A71 -> 41365 | BF9: =RS!B71 -> 53 | BG9: =RS!C71 -> -1.6
A10: =Global!A72 -> 41395 | B10: =Global!B72 -> 53.7 | C10: =Global!C72 -> 1.6 | E10: =US!A73 -> 41395 | F10: =US!B73 -> No data | G10: =US!C73 -> 0 | I10: =UK!A72 -> 41395 | J10: =UK!B72 -> 54.9 | K10: =UK!C72 -> 2 | M10: =EZ!A72 -> 41395 | N10: =EZ!B72 -> 47.2 | O10: =EZ!C72 -> 0.2 | Q10: =DE!A72 -> 41395 | R10: =DE!B72 -> 50.4 | S10: =DE!C72 -> 0.7 | U10: =FR!A72 -> 41395 | V10: =FR!B72 -> 44.3 | W10: =FR!C72 -> 0 | Y10: =IT!A72 -> 41395 | Z10: =IT!B72 -> 46.5 | AA10: =IT!C72 -> -0.5 | AC10: =ES!A72 -> 41395 | AD10: =ES!B72 -> 47.3 | AE10: =ES!C72 -> 2.9 | AG10: =IR!A72 -> 41395 | AH10: =IR!B72 -> 52.7 | AI10: =IR!C72 -> -2.5 | AK10: =AU!A72 -> 41395 | AL10: =AU!B72 -> 40.6 | AM10: =AU!C72 -> -3.5 | AO10: =JP!A72 -> 41395 | AP10: =JP!B72 -> 54.8 | AQ10: =JP!C72 -> 2.3 | AS10: =BR!A72 -> 41395 | AT10: =BR!B72 -> 51 | AU10: =BR!C72 -> 0 | AW10: =CH!A72 -> 41395 | AX10: =CH!B72 -> 51.2 | AY10: =CH!C72 -> 0.1 | BA10: =IN!A72 -> 41395 | BB10: =IN!B72 -> 53.6 | BC10: =IN!C72 -> 2.9 | BE10: =RS!A72 -> 41395 | BF10: =RS!B72 -> 51.4 | BG10: =RS!C72 -> -1.6
A11: =Global!A73 -> 41426 | B11: =Global!B73 -> 51.3 | C11: =Global!C73 -> -2.4 | E11: =US!A74 -> 41426 | F11: =US!B74 -> No data | G11: =US!C74 -> 0 | I11: =UK!A73 -> 41426 | J11: =UK!B73 -> 56.9 | K11: =UK!C73 -> 2 | M11: =EZ!A73 -> 41426 | N11: =EZ!B73 -> 48.3 | O11: =EZ!C73 -> 1.1 | Q11: =DE!A73 -> 41426 | R11: =DE!B73 -> 51.3 | S11: =DE!C73 -> 0.9 | U11: =FR!A73 -> 41426 | V11: =FR!B73 -> 47.2 | W11: =FR!C73 -> 2.9 | Y11: =IT!A73 -> 41426 | Z11: =IT!B73 -> 45.8 | AA11: =IT!C73 -> -0.7 | AC11: =ES!A73 -> 41426 | AD11: =ES!B73 -> 47.8 | AE11: =ES!C73 -> 0.5 | AG11: =IR!A73 -> 41426 | AH11: =IR!B73 -> 61.6 | AI11: =IR!C73 -> 8.9 | AK11: =AU!A73 -> 41426 | AL11: =AU!B73 -> 41.5 | AM11: =AU!C73 -> 0.9 | AO11: =JP!A73 -> 41426 | AP11: =JP!B73 -> 52.1 | AQ11: =JP!C73 -> -2.7 | AS11: =BR!A73 -> 41426 | AT11: =BR!B73 -> 50.3 | AU11: =BR!C73 -> -0.7 | AW11: =CH!A73 -> 41426 | AX11: =CH!B73 -> 51.3 | AY11: =CH!C73 -> 0.1 | BA11: =IN!A73 -> 41426 | BB11: =IN!B73 -> 51.7 | BC11: =IN!C73 -> -1.9 | BE11: =RS!A73 -> 41426 | BF11: =RS!B73 -> 48.8 | BG11: =RS!C73 -> -2.6
A12: =Global!A74 -> 41456 | B12: =Global!B74 -> 54.9 | C12: =Global!C74 -> 3.6 | E12: =US!A75 -> 41456 | F12: =US!B75 -> No data | G12: =US!C75 -> 0 | I12: =UK!A74 -> 41456 | J12: =UK!B74 -> 60.2 | K12: =UK!C74 -> 3.3 | M12: =EZ!A74 -> 41456 | N12: =EZ!B74 -> 49.8 | O12: =EZ!C74 -> 1.5 | Q12: =DE!A74 -> 41456 | R12: =DE!B74 -> 52.8 | S12: =DE!C74 -> 1.5 | U12: =FR!A74 -> 41456 | V12: =FR!B74 -> 48.6 | W12: =FR!C74 -> 1.4 | Y12: =IT!A74 -> 41456 | Z12: =IT!B74 -> 48.7 | AA12: =IT!C74 -> 2.9 | AC12: =ES!A74 -> 41456 | AD12: =ES!B74 -> 48.5 | AE12: =ES!C74 -> 0.7 | AG12: =IR!A74 -> 41456 | AH12: =IR!B74 -> 59.6 | AI12: =IR!C74 -> -2 | AK12: =AU!A74 -> 41456 | AL12: =AU!B74 -> 39.4 | AM12: =AU!C74 -> -2.1 | AO12: =JP!A74 -> 41456 | AP12: =JP!B74 -> 50.6 | AQ12: =JP!C74 -> -1.5 | AS12: =BR!A74 -> 41456 | AT12: =BR!B74 -> 49.7 | AU12: =BR!C74 -> -0.6 | AW12: =CH!A74 -> 41456 | AX12: =CH!B74 -> 51.3 | AY12: =CH!C74 -> 0 | BA12: =IN!A74 -> 41456 | BB12: =IN!B74 -> 47.9 | BC12: =IN!C74 -> -3.8 | BE12: =RS!A74 -> 41456 | BF12: =RS!B74 -> 48.7 | BG12: =RS!C74 -> -0.1
A13: =Global!A75 -> 41487 | B13: =Global!B75 -> 56 | C13: =Global!C75 -> 1.1 | E13: =US!A76 -> 41487 | F13: =US!B76 -> No data | G13: =US!C76 -> 0 | I13: =UK!A75 -> 41487 | J13: =UK!B75 -> 60.5 | K13: =UK!C75 -> 0.3 | M13: =EZ!A75 -> 41487 | N13: =EZ!B75 -> 50.7 | O13: =EZ!C75 -> 0.9 | Q13: =DE!A75 -> 41487 | R13: =DE!B75 -> 53.7 | S13: =DE!C75 -> 0.9 | U13: =FR!A75 -> 41487 | V13: =FR!B75 -> 48.9 | W13: =FR!C75 -> 0.3 | Y13: =IT!A75 -> 41487 | Z13: =IT!B75 -> 48.8 | AA13: =IT!C75 -> 0.1 | AC13: =ES!A75 -> 41487 | AD13: =ES!B75 -> 50.5 | AE13: =ES!C75 -> 2 | AG13: =IR!A75 -> 41487 | AH13: =IR!B75 -> 57.2 | AI13: =IR!C75 -> -2.4 | AK13: =AU!A75 -> 41487 | AL13: =AU!B75 -> 39 | AM13: =AU!C75 -> -0.4 | AO13: =JP!A75 -> 41487 | AP13: =JP!B75 -> 51.2 | AQ13: =JP!C75 -> 0.6 | AS13: =BR!A75 -> 41487 | AT13: =BR!B75 -> 50.7 | AU13: =BR!C75 -> 1 | AW13: =CH!A75 -> 41487 | AX13: =CH!B75 -> 52.8 | AY13: =CH!C75 -> 1.5 | BA13: =IN!A75 -> 41487 | BB13: =IN!B75 -> 47.6 | BC13: =IN!C75 -> -0.3 | BE13: =RS!A75 -> 41487 | BF13: =RS!B75 -> 51.8 | BG13: =RS!C75 -> 3.1
A14: =Global!A76 -> 41518 | B14: =Global!B76 -> 53.6 | C14: =Global!C76 -> -2.4 | E14: =US!A77 -> 41518 | F14: =US!B77 -> No data | G14: =US!C77 -> 0 | I14: =UK!A76 -> 41518 | J14: =UK!B76 -> 60.3 | K14: =UK!C76 -> -0.2 | M14: =EZ!A76 -> 41518 | N14: =EZ!B76 -> 52.2 | O14: =EZ!C76 -> 1.5 | Q14: =DE!A76 -> 41518 | R14: =DE!B76 -> 52.9 | S14: =DE!C76 -> -0.8 | U14: =FR!A76 -> 41518 | V14: =FR!B76 -> 51 | W14: =FR!C76 -> 2.1 | Y14: =IT!A76 -> 41518 | Z14: =IT!B76 -> 52.7 | AA14: =IT!C76 -> 3.9 | AC14: =ES!A76 -> 41518 | AD14: =ES!B76 -> 49 | AE14: =ES!C76 -> -1.5 | AG14: =IR!A76 -> 41518 | AH14: =IR!B76 -> 56.8 | AI14: =IR!C76 -> -0.4 | AK14: =AU!A76 -> 41518 | AL14: =AU!B76 -> 47.1 | AM14: =AU!C76 -> 8.1 | AO14: =JP!A76 -> 41518 | AP14: =JP!B76 -> 53 | AQ14: =JP!C76 -> 1.8 | AS14: =BR!A76 -> 41518 | AT14: =BR!B76 -> 52.1 | AU14: =BR!C76 -> 1.4 | AW14: =CH!A76 -> 41518 | AX14: =CH!B76 -> 52.4 | AY14: =CH!C76 -> -0.4 | BA14: =IN!A76 -> 41518 | BB14: =IN!B76 -> 44.6 | BC14: =IN!C76 -> -3 | BE14: =RS!A76 -> 41518 | BF14: =RS!B76 -> 51.5 | BG14: =RS!C76 -> -0.3
A15: =Global!A77 -> 41548 | B15: =Global!B77 -> 51.8 | C15: =Global!C77 -> -1.8 | E15: =US!A78 -> 41548 | F15: =US!B78 -> 49.3 | G15: =US!C78 -> 0 | I15: =UK!A77 -> 41548 | J15: =UK!B77 -> 62.5 | K15: =UK!C77 -> 2.2 | M15: =EZ!A77 -> 41548 | N15: =EZ!B77 -> 51.6 | O15: =EZ!C77 -> -0.6 | Q15: =DE!A77 -> 41548 | R15: =DE!B77 -> 55.7 | S15: =DE!C77 -> 2.8 | U15: =FR!A77 -> 41548 | V15: =FR!B77 -> 50.9 | W15: =FR!C77 -> -0.1 | Y15: =IT!A77 -> 41548 | Z15: =IT!B77 -> 50.5 | AA15: =IT!C77 -> -2.2 | AC15: =ES!A77 -> 41548 | AD15: =ES!B77 -> 49.6 | AE15: =ES!C77 -> 0.6 | AG15: =IR!A77 -> 41548 | AH15: =IR!B77 -> 60.1 | AI15: =IR!C77 -> 3.3 | AK15: =AU!A77 -> 41548 | AL15: =AU!B77 -> 47.9 | AM15: =AU!C77 -> 0.8 | AO15: =JP!A77 -> 41548 | AP15: =JP!B77 -> 55.3 | AQ15: =JP!C77 -> 2.3 | AS15: =BR!A77 -> 41548 | AT15: =BR!B77 -> 52.3 | AU15: =BR!C77 -> 0.2 | AW15: =CH!A77 -> 41548 | AX15: =CH!B77 -> 52.6 | AY15: =CH!C77 -> 0.2 | BA15: =IN!A77 -> 41548 | BB15: =IN!B77 -> 47.1 | BC15: =IN!C77 -> 2.5 | BE15: =RS!A77 -> 41548 | BF15: =RS!B77 -> 52.5 | BG15: =RS!C77 -> 1
A16: =Global!A78 -> 41579 | B16: =Global!B78 -> 53.9 | C16: =Global!C78 -> 2.1 | E16: =US!A79 -> 41579 | F16: =US!B79 -> 55.9 | G16: =US!C79 -> 6.6 | I16: =UK!A78 -> 41579 | J16: =UK!B78 -> 60 | K16: =UK!C78 -> -2.5 | M16: =EZ!A78 -> 41579 | N16: =EZ!B78 -> 51.2 | O16: =EZ!C78 -> -0.4 | Q16: =DE!A78 -> 41579 | R16: =DE!B78 -> 53.5 | S16: =DE!C78 -> -2.2 | U16: =FR!A78 -> 41579 | V16: =FR!B78 -> 48 | W16: =FR!C78 -> -2.9 | Y16: =IT!A78 -> 41579 | Z16: =IT!B78 -> 47.2 | AA16: =IT!C78 -> -3.3 | AC16: =ES!A78 -> 41579 | AD16: =ES!B78 -> 51.5 | AE16: =ES!C78 -> 1.9 | AG16: =IR!A78 -> 41579 | AH16: =IR!B78 -> 57.1 | AI16: =IR!C78 -> -3 | AK16: =AU!A78 -> 41579 | AL16: =AU!B78 -> 48.9 | AM16: =AU!C78 -> 1 | AO16: =JP!A78 -> 41579 | AP16: =JP!B78 -> 51.8 | AQ16: =JP!C78 -> -3.5 | AS16: =BR!A78 -> 41579 | AT16: =BR!B78 -> 51.7 | AU16: =BR!C78 -> -0.6 | AW16: =CH!A78 -> 41579 | AX16: =CH!B78 -> 52.5 | AY16: =CH!C78 -> -0.1 | BA16: =IN!A78 -> 41579 | BB16: =IN!B78 -> 47.2 | BC16: =IN!C78 -> 0.1 | BE16: =RS!A78 -> 41579 | BF16: =RS!B78 -> 52.9 | BG16: =RS!C78 -> 0.4
... A26: =Global!A88 -> 41883 | B26: =Global!B88 -> 55.3 | C26: =Global!C88 -> -0.2 | E26: =US!A89 -> 41883 | F26: =US!B89 -> 58.9 | G26: =US!C89 -> -0.6 | I26: =UK!A88 -> 41883 | J26: =UK!B88 -> 58.7 | K26: =UK!C88 -> -1.8 | M26: =EZ!A88 -> 41883 | N26: =EZ!B88 -> 52.4 | O26: =EZ!C88 -> -0.7 | Q26: =DE!A88 -> 41883 | R26: =DE!B88 -> 55.7 | S26: =DE!C88 -> 0.8 | U26: =FR!A88 -> 41883 | V26: =FR!B88 -> 48.4 | W26: =FR!C88 -> -1.9 | Y26: =IT!A88 -> 41883 | Z26: =IT!B88 -> 48.8 | AA26: =IT!C88 -> -1 | AC26: =ES!A88 -> 41883 | AD26: =ES!B88 -> 55.8 | AE26: =ES!C88 -> -2.3 | AG26: =IR!A88 -> 41883 | AH26: =IR!B88 -> 62.5 | AI26: =IR!C88 -> 0.1 | AK26: =AU!A88 -> 41883 | AL26: =AU!B88 -> 45.5 | AM26: =AU!C88 -> -3.9 | AO26: =JP!A88 -> 41883 | AP26: =JP!B88 -> 52.5 | AQ26: =JP!C88 -> 2.6 | AS26: =BR!A88 -> 41883 | AT26: =BR!B88 -> 51.2 | AU26: =BR!C88 -> 2 | AW26: =CH!A88 -> 41883 | AX26: =CH!B88 -> 53.5 | AY26: =CH!C88 -> -0.6 | BA26: =IN!A88 -> 41883 | BB26: =IN!B88 -> 51.6 | BC26: =IN!C88 -> 1 | BE26: =RS!A88 -> 41883 | BF26: =RS!B88 -> 50.5 | BG26: =RS!C88 -> 0.2
A27: =Global!A227 -> 46113 | B27: =Global!B227 -> TBR | C27: =Global!C227 | E27: =US!A363 -> 46113 | F27: =US!B363 -> 51 | G27: =US!C363 -> -2.8 | I27: =UK!A226 -> 46113 | J27: =UK!B226 -> 52.7 | K27: =UK!C226 -> 2.2 | M27: =EZ!A227 -> 46113 | N27: =EZ!B227 -> 47.6 | O27: =EZ!C227 | Q27: =DE!A227 -> 46113 | R27: =DE!B227 -> TBR | S27: =DE!C227 | U27: =FR!A227 -> 46113 | V27: =FR!B227 -> TBR | W27: =FR!C227 | Y27: =IT!A227 -> 46113 | Z27: =IT!B227 -> TBR | AA27: =IT!C227 | AC27: =ES!A227 -> 46113 | AD27: =ES!B227 -> TBR | AE27: =ES!C227 | AG27: =IR!A227 -> 46113 | AH27: =IR!B227 -> TBR | AI27: =IR!C227 | AK27: =AU!A227 -> 46113 | AL27: =AU!B227 -> TBR | AM27: =AU!C227 | AO27: =JP!A227 -> 46113 | AP27: =JP!B227 -> TBR | AQ27: =JP!C227 | AS27: =BR!A227 -> 46113 | AT27: =BR!B227 -> TBR | AU27: =BR!C227 | AW27: =CH!A227 -> 46113 | AX27: =CH!B227 -> TBR | AY27: =CH!C227 | BA27: =IN!A227 -> 46113 | BB27: =IN!B227 -> TBR | BC27: =IN!C227 | BE27: =RS!A227 -> 46113 | BF27: =RS!B227 -> TBR | BG27: =RS!C227
A28: =Global!A228 -> 46143 | B28: =Global!B228 -> TBR | C28: =Global!C228 | E28: =US!A364 -> 46143 | F28: =US!B364 -> 50.7 | G28: =US!C364 -> -0.3 | I28: =UK!A227 -> 46143 | J28: =UK!B227 -> 49.3 | K28: =UK!C227 -> -3.4 | M28: =EZ!A228 -> 46143 | N28: =EZ!B228 -> 47.7 | O28: =EZ!C228 -> 0.1 | Q28: =DE!A228 -> 46143 | R28: =DE!B228 -> TBR | S28: =DE!C228 | U28: =FR!A228 -> 46143 | V28: =FR!B228 -> TBR | W28: =FR!C228 | Y28: =IT!A228 -> 46143 | Z28: =IT!B228 -> TBR | AA28: =IT!C228 | AC28: =ES!A228 -> 46143 | AD28: =ES!B228 -> TBR | AE28: =ES!C228 | AG28: =IR!A228 -> 46143 | AH28: =IR!B228 -> TBR | AI28: =IR!C228 | AK28: =AU!A228 -> 46143 | AL28: =AU!B228 -> TBR | AM28: =AU!C228 | AO28: =JP!A228 -> 46143 | AP28: =JP!B228 -> 50 | AQ28: =JP!C228 | AS28: =BR!A228 -> 46143 | AT28: =BR!B228 -> 50.4 | AU28: =BR!C228 | AW28: =CH!A228 -> 46143 | AX28: =CH!B228 -> TBR | AY28: =CH!C228 | BA28: =IN!A228 -> 46143 | BB28: =IN!B228 -> 59.8 | BC28: =IN!C228 | BE28: =RS!A228 -> 46143 | BF28: =RS!B228 -> 48.7 | BG28: =RS!C228

Sheet Global
A40: Date | B40: Global Service PMI | C40: Change
A41: 40452 | B41: 54.6
A42: 40483 | B42: 54.8 | C42: =B42-B41 -> 0.2
A43: 40513 | B43: 56.3 | C43: =B43-B42 -> 1.5
A44: 40544 | B44: 57.1 | C44: =B44-B43 -> 0.8
A45: 40575 | B45: 59.3 | C45: =B45-B44 -> 2.2
A46: 40603 | B46: 54 | C46: =B46-B45 -> -5.3
A47: 40634 | B47: 51 | C47: =B47-B46 -> -3
A48: 40664 | B48: 52.5 | C48: =B48-B47 -> 1.5
A49: 40695 | B49: 52.1 | C49: =B49-B48 -> -0.4
A50: 40725 | B50: 53.1 | C50: =B50-B49 -> 1
A51: 40756 | B51: 52.4 | C51: =B51-B50 -> -0.7
A52: 40787 | B52: 52.6 | C52: =B52-B51 -> 0.2
A53: 40817 | B53: 51.8 | C53: =B53-B52 -> -0.8
... A90: 41944 | B90: 53.5 | C90: =B90-B89 -> -0.2
A91: 41974 | B91: TBR | C91: =IFERROR(B91-B90,"")
A92: 42005 | B92: TBR | C92: =IFERROR(B92-B91,"")
A93: 42036 | B93: TBR | C93: =IFERROR(B93-B92,"")
A94: 42064 | B94: TBR | C94: =IFERROR(B94-B93,"")
A95: 42095 | B95: TBR | C95: =IFERROR(B95-B94,"")
A96: 42125 | B96: TBR | C96: =IFERROR(B96-B95,"")
A97: 42156 | B97: TBR | C97: =IFERROR(B97-B96,"")
A98: 42186 | B98: TBR | C98: =IFERROR(B98-B97,"")
A99: 42217 | B99: TBR | C99: =IFERROR(B99-B98,"")
A100: 42248 | B100: TBR | C100: =IFERROR(B100-B99,"")
A101: 42278 | B101: TBR | C101: =IFERROR(B101-B100,"")
A102: 42309 | B102: TBR | C102: =IFERROR(B102-B101,"")
... A228: 46143 | B228: TBR | C228: =IFERROR(B228-B227,"")

Sheet US
A1: Date | B1: US Service PMI | C1: Change | D1: US GDP q/q
A41: Column1 | B41: Column2 | C41: Column3 | D41: Column4
A42: 40452 | B42: 54.3
A43: 40483 | B43: 55 | C43: =B43-B42 -> 0.7
A44: 40513 | C44: =B44-B43 -> -55
A45: 40544 | C45: =B45-B44 -> 0
A46: 40575 | B46: 59.7 | C46: =B46-B45 -> 59.7
A47: 40603 | B47: 57.3 | C47: =B47-B46 -> -2.4
A48: 40634 | B48: 52.8 | C48: =B48-B47 -> -4.5
A49: 40664 | B49: 53.6 | C49: =B49-B48 -> 0.8
A50: 40695 | B50: 53.3 | C50: =B50-B49 -> -0.3
A51: 40725 | B51: 52.7 | C51: =B51-B50 -> -0.6
A52: 40756 | C52: =B52-B51 -> -52.7
A53: 40787 | B53: 53 | C53: =B53-B52 -> 53
A54: 40817 | B54: 52.9 | C54: =B54-B53 -> -0.1
A55: 40848 | B55: 52 | C55: =B55-B54 -> -0.9
A56: 40878 | B56: 52.6 | C56: =B56-B55 -> 0.6
A57: 40909 | C57: =B57-B56 -> -52.6
A58: 40940 | C58: =B58-B57 -> 0
A59: 40969 | C59: =B59-B58 -> 0
A60: 41000 | C60: =B60-B59 -> 0
A61: 41030 | C61: =B61-B60 -> 0
A62: 41061 | B62: No data | C62: 0
A63: 41091 | B63: No data | C63: 0
A64: 41122 | B64: No data | C64: 0
A65: 41153 | B65: No data | C65: 0
A66: 41183 | B66: No data | C66: 0
A67: 41214 | B67: No data | C67: 0
A68: 41244 | B68: No data | C68: 0
A69: 41275 | B69: No data | C69: 0
A70: 41306 | B70: No data | C70: 0
A71: 41334 | B71: No data | C71: 0
A72: 41365 | B72: No data | C72: 0
A73: 41395 | B73: No data | C73: 0
... A77: 41518 | B77: No data | C77: 0
A78: 41548 | B78: 49.3 | C78: 0
A79: 41579 | B79: 55.9 | C79: =B79-B78 -> 6.6
A80: 41609 | B80: 55.7 | C80: =B80-B79 -> -0.2 | D80: 0.0065
A81: 41640 | B81: 56.7 | C81: =B81-B80 -> 1
A82: 41671 | B82: 53.3 | C82: =B82-B81 -> -3.4
A83: 41699 | B83: 55.3 | C83: =B83-B82 -> 2 | D83: -0.0075
A84: 41730 | B84: 55 | C84: =B84-B83 -> -0.3
A85: 41760 | B85: 58 | C85: =B85-B84 -> 3 | H85: US | I85: United States
A86: 41791 | B86: 61 | C86: 0 | D86: 0.0105
A87: 41821 | B87: 60.8 | C87: =B87-B86 -> -0.2
A88: 41852 | B88: 59.5 | C88: =B88-B87 -> -1.3
A89: 41883 | B89: 58.9 | C89: =IFERROR(B89-B88,"") -> -0.6 | D89: =IF(VLOOKUP(I85,Data!$A$30:$H$150,7,FALSE)=A88,((1+VLOOKUP(I85,Data!$A$30:$H$150,2,FALSE)/100)^(1/4))-1,#N/A) -> 0.0096105657
A90: 41913 | B90: 57.1 | C90: -1.8
A228: 42005 | B228: 56.7 | C228: =IFERROR(B228-#REF!,"")
A229: 42036 | B229: 56.7 | C229: =IFERROR(B229-B228,"") -> 0
A230: 42064 | B230: 56.7 | C230: =IFERROR(B230-B229,"") -> 0
A231: 42095 | B231: 57.5 | C231: =IFERROR(B231-B230,"") -> 0.8
A232: 42125 | B232: 55.9 | C232: =IFERROR(B232-B231,"") -> -1.6
A233: 42156 | B233: 56.2 | C233: =IFERROR(B233-B232,"") -> 0.3
A234: 42186 | B234: 59.6 | C234: =IFERROR(B234-B233,"") -> 3.4
A235: 42217 | B235: 59.6 | C235: =IFERROR(B235-B234,"") -> 0
A236: 42248 | B236: 56.7 | C236: =IFERROR(B236-B235,"") -> -2.9
A237: 42278 | B237: 58.3 | C237: =IFERROR(B237-B236,"") -> 1.6
A238: 42309 | B238: 58.3 | C238: =IFERROR(B238-B237,"") -> 0
A239: 42339 | B239: 55.8 | C239: =IFERROR(B239-B238,"") -> -2.5
A240: 42370 | B240: 53.5 | C240: =IFERROR(B240-B239,"") -> -2.3
... A364: 46143 | B364: 50.7 | C364: =IFERROR(B364-B363,"") -> -0.3

Sheet UK
A40: Date | B40: UK Service PMI | C40: Change | D40: UK GDP Growth q/q
A41: 40452 | B41: 53.2 | C41: =IF(AND(ISNUMBER(B41),ISNUMBER(B40)),B41-B40,"")
A42: 40483 | B42: 53 | C42: =IF(AND(ISNUMBER(B42),ISNUMBER(B41)),B42-B41,"") -> -0.2
A43: 40513 | B43: 53.9 | C43: =IF(AND(ISNUMBER(B43),ISNUMBER(B42)),B43-B42,"") -> 0.9 | D43: -0.002
A44: 40544 | B44: 54.5 | C44: =IF(AND(ISNUMBER(B44),ISNUMBER(B43)),B44-B43,"") -> 0.6
A45: 40575 | B45: 52.6 | C45: =IF(AND(ISNUMBER(B45),ISNUMBER(B44)),B45-B44,"") -> -1.9
A46: 40603 | B46: 57.1 | C46: =IF(AND(ISNUMBER(B46),ISNUMBER(B45)),B46-B45,"") -> 4.5 | D46: 0.005
A47: 40634 | B47: 54.3 | C47: =IF(AND(ISNUMBER(B47),ISNUMBER(B46)),B47-B46,"") -> -2.8
A48: 40664 | B48: 53.8 | C48: =IF(AND(ISNUMBER(B48),ISNUMBER(B47)),B48-B47,"") -> -0.5
A49: 40695 | B49: 53.9 | C49: =IF(AND(ISNUMBER(B49),ISNUMBER(B48)),B49-B48,"") -> 0.1 | D49: 0.001
A50: 40725 | B50: 55.4 | C50: =IF(AND(ISNUMBER(B50),ISNUMBER(B49)),B50-B49,"") -> 1.5
A51: 40756 | B51: 51.1 | C51: =IF(AND(ISNUMBER(B51),ISNUMBER(B50)),B51-B50,"") -> -4.3
A52: 40787 | B52: 52.9 | C52: =IF(AND(ISNUMBER(B52),ISNUMBER(B51)),B52-B51,"") -> 1.8 | D52: 0.006
A53: 40817 | B53: 51.3 | C53: =IF(AND(ISNUMBER(B53),ISNUMBER(B52)),B53-B52,"") -> -1.6
A54: 40848 | B54: 52.1 | C54: =IF(AND(ISNUMBER(B54),ISNUMBER(B53)),B54-B53,"") -> 0.8
A55: 40878 | B55: 54 | C55: =IF(AND(ISNUMBER(B55),ISNUMBER(B54)),B55-B54,"") -> 1.9 | D55: -0.001
A56: 40909 | B56: 56 | C56: =IF(AND(ISNUMBER(B56),ISNUMBER(B55)),B56-B55,"") -> 2
A57: 40940 | B57: 53.8 | C57: =IF(AND(ISNUMBER(B57),ISNUMBER(B56)),B57-B56,"") -> -2.2
A58: 40969 | B58: 55.3 | C58: =IF(AND(ISNUMBER(B58),ISNUMBER(B57)),B58-B57,"") -> 1.5 | D58: 0
A59: 41000 | B59: 53.3 | C59: =IF(AND(ISNUMBER(B59),ISNUMBER(B58)),B59-B58,"") -> -2
A60: 41030 | B60: 53.3 | C60: =IF(AND(ISNUMBER(B60),ISNUMBER(B59)),B60-B59,"") -> 0
A61: 41061 | B61: 51.3 | C61: =IF(AND(ISNUMBER(B61),ISNUMBER(B60)),B61-B60,"") -> -2 | D61: -0.004
A62: 41091 | B62: 51.3 | C62: =IF(AND(ISNUMBER(B62),ISNUMBER(B61)),B62-B61,"") -> 0
A63: 41122 | B63: 51 | C63: =IF(AND(ISNUMBER(B63),ISNUMBER(B62)),B63-B62,"") -> -0.3
A64: 41153 | B64: 53.7 | C64: =IF(AND(ISNUMBER(B64),ISNUMBER(B63)),B64-B63,"") -> 2.7 | D64: 0.008
A65: 41183 | B65: 52.2 | C65: =IF(AND(ISNUMBER(B65),ISNUMBER(B64)),B65-B64,"") -> -1.5
A66: 41214 | B66: 50.6 | C66: =IF(AND(ISNUMBER(B66),ISNUMBER(B65)),B66-B65,"") -> -1.6
A67: 41244 | B67: 50.2 | C67: =IF(AND(ISNUMBER(B67),ISNUMBER(B66)),B67-B66,"") -> -0.4 | D67: -0.001
A68: 41275 | B68: 51.5 | C68: =IF(AND(ISNUMBER(B68),ISNUMBER(B67)),B68-B67,"") -> 1.3
A69: 41306 | B69: 51.8 | C69: =IF(AND(ISNUMBER(B69),ISNUMBER(B68)),B69-B68,"") -> 0.3
A70: 41334 | B70: 52.4 | C70: =IF(AND(ISNUMBER(B70),ISNUMBER(B69)),B70-B69,"") -> 0.6 | D70: 0.005
A71: 41365 | B71: 52.9 | C71: =IF(AND(ISNUMBER(B71),ISNUMBER(B70)),B71-B70,"") -> 0.5
A72: 41395 | B72: 54.9 | C72: =IF(AND(ISNUMBER(B72),ISNUMBER(B71)),B72-B71,"") -> 2
A73: 41426 | B73: 56.9 | C73: =IF(AND(ISNUMBER(B73),ISNUMBER(B72)),B73-B72,"") -> 2 | D73: 0.008
A74: 41456 | B74: 60.2 | C74: =IF(AND(ISNUMBER(B74),ISNUMBER(B73)),B74-B73,"") -> 3.3
A75: 41487 | B75: 60.5 | C75: =IF(AND(ISNUMBER(B75),ISNUMBER(B74)),B75-B74,"") -> 0.3
A76: 41518 | B76: 60.3 | C76: =IF(AND(ISNUMBER(B76),ISNUMBER(B75)),B76-B75,"") -> -0.2 | D76: 0.008
A77: 41548 | B77: 62.5 | C77: =IF(AND(ISNUMBER(B77),ISNUMBER(B76)),B77-B76,"") -> 2.2
A78: 41579 | B78: 60 | C78: =IF(AND(ISNUMBER(B78),ISNUMBER(B77)),B78-B77,"") -> -2.5
A79: 41609 | B79: 58.8 | C79: =IF(AND(ISNUMBER(B79),ISNUMBER(B78)),B79-B78,"") -> -1.2 | D79: 0.007
A80: 41640 | B80: 58.3 | C80: =IF(AND(ISNUMBER(B80),ISNUMBER(B79)),B80-B79,"") -> -0.5
A81: 41671 | B81: 58.2 | C81: =IF(AND(ISNUMBER(B81),ISNUMBER(B80)),B81-B80,"") -> -0.1
A82: 41699 | B82: 57.6 | C82: =IF(AND(ISNUMBER(B82),ISNUMBER(B81)),B82-B81,"") -> -0.6 | D82: 0.008
A83: 41730 | B83: 58.7 | C83: =IF(AND(ISNUMBER(B83),ISNUMBER(B82)),B83-B82,"") -> 1.1
A84: 41760 | B84: 58.6 | C84: =IF(AND(ISNUMBER(B84),ISNUMBER(B83)),B84-B83,"") -> -0.1
A85: 41791 | B85: 57.7 | C85: =IF(AND(ISNUMBER(B85),ISNUMBER(B84)),B85-B84,"") -> -0.9 | D85: 0.008 | H85: UK | I85: United Kingdom
A86: 41821 | B86: 59.1 | C86: =IF(AND(ISNUMBER(B86),ISNUMBER(B85)),B86-B85,"") -> 1.4
A87: 41852 | B87: 60.5 | C87: =IF(AND(ISNUMBER(B87),ISNUMBER(B86)),B87-B86,"") -> 1.4
A88: 41883 | B88: 58.7 | C88: =IF(AND(ISNUMBER(B88),ISNUMBER(B87)),B88-B87,"") -> -1.8 | D88: =IF(VLOOKUP(I85,Data!$A$30:$H$150,7,FALSE)=A87,VLOOKUP(I85,Data!$A$30:$H$150,2,FALSE)/100,#N/A) -> 0.007
A89: 41913 | B89: 56.2 | C89: =IF(AND(ISNUMBER(B89),ISNUMBER(B88)),B89-B88,"") -> -2.5
A90: 41944 | B90: 58.6 | C90: =IF(AND(ISNUMBER(B90),ISNUMBER(B89)),B90-B89,"") -> 2.4
A91: 42005 | B91: 57.2 | C91: =IF(AND(ISNUMBER(B91),ISNUMBER(#REF!)),B91-#REF!,"")
A92: 42036 | B92: 56.7 | C92: =IF(AND(ISNUMBER(B92),ISNUMBER(B91)),B92-B91,"") -> -0.5
A93: 42064 | B93: 58.9 | C93: =IF(AND(ISNUMBER(B93),ISNUMBER(B92)),B93-B92,"") -> 2.2
A94: 42095 | B94: 59.5 | C94: =IF(AND(ISNUMBER(B94),ISNUMBER(B93)),B94-B93,"") -> 0.6
A95: 42125 | B95: 56.5 | C95: =IF(AND(ISNUMBER(B95),ISNUMBER(B94)),B95-B94,"") -> -3
A96: 42156 | B96: 58.5 | C96: =IF(AND(ISNUMBER(B96),ISNUMBER(B95)),B96-B95,"") -> 2
A97: 42186 | B97: 57.4 | C97: =IF(AND(ISNUMBER(B97),ISNUMBER(B96)),B97-B96,"") -> -1.1
A98: 42217 | B98: 55.6 | C98: =IF(AND(ISNUMBER(B98),ISNUMBER(B97)),B98-B97,"") -> -1.8
A99: 42248 | B99: 53.3 | C99: =IF(AND(ISNUMBER(B99),ISNUMBER(B98)),B99-B98,"") -> -2.3
A100: 42278 | B100: 54.9 | C100: =IF(AND(ISNUMBER(B100),ISNUMBER(B99)),B100-B99,"") -> 1.6
A101: 42309 | B101: 55.9 | C101: =IF(AND(ISNUMBER(B101),ISNUMBER(B100)),B101-B100,"") -> 1
A102: 42339 | B102: 55.5 | C102: =IF(AND(ISNUMBER(B102),ISNUMBER(B101)),B102-B101,"") -> -0.4
A103: 42370 | B103: 55.6 | C103: =IF(AND(ISNUMBER(B103),ISNUMBER(B102)),B103-B102,"") -> 0.1
... A227: 46143 | B227: 49.3 | C227: =IF(AND(ISNUMBER(B227),ISNUMBER(B226)),B227-B226,"") -> -3.4
A228: 46174 | B228: 48.8 | C228: =IF(AND(ISNUMBER(B228),ISNUMBER(B227)),B228-B227,"") -> -0.5 | D228: TBR

Sheet EZ
A1: Date | B1: Euro-Zone Service PMI | C1: Change | D1: Euro Zone GDP q/q %
A2: 39264 | B2: 58.3
A3: 39295 | B3: 58 | C3: =B3-B2 -> -0.3
A4: 39326 | B4: 54.2 | C4: =B4-B3 -> -3.8 | D4: 0.006
A5: 39356 | B5: 55.8 | C5: =B5-B4 -> 1.6
A6: 39387 | B6: 54.1 | C6: =B6-B5 -> -1.7
A7: 39417 | B7: 53.1 | C7: =B7-B6 -> -1 | D7: 0.004
A8: 39448 | B8: 50.6 | C8: =B8-B7 -> -2.5
A9: 39479 | B9: 51.7 | C9: =B9-B8 -> 1.1
A10: 39508 | B10: 51.6 | C10: =B10-B9 -> -0.1 | D10: 0.006
A11: 39539 | B11: 52 | C11: =B11-B10 -> 0.4
A12: 39569 | B12: 50.6 | C12: =B12-B11 -> -1.4
A13: 39600 | B13: 49.1 | C13: =B13-B12 -> -1.5 | D13: -0.004
A14: 39630 | B14: 48.3 | C14: =B14-B13 -> -0.8
A15: 39661 | B15: 48.5 | C15: =B15-B14 -> 0.2
A16: 39692 | B16: 48.4 | C16: =B16-B15 -> -0.1 | D16: -0.006
A17: 39722 | B17: 45.8 | C17: =B17-B16 -> -2.6
A18: 39753 | B18: 42.5 | C18: =B18-B17 -> -3.3
A19: 39783 | B19: 42.3 | C19: =B19-B18 -> -0.2 | D19: -0.017
A20: 39814 | B20: 42.2 | C20: =B20-B19 -> -0.1
A21: 39845 | B21: 39.2 | C21: =B21-B20 -> -3
A22: 39873 | B22: 40.9 | C22: =B22-B21 -> 1.7 | D22: -0.028
A23: 39904 | B23: 43.8 | C23: =B23-B22 -> 2.9
A24: 39934 | B24: 44.8 | C24: =B24-B23 -> 1
A25: 39965 | B25: 44.7 | C25: =B25-B24 -> -0.1 | D25: -0.003
A26: 39995 | B26: 45.7 | C26: =B26-B25 -> 1
A27: 40026 | B27: 49.9 | C27: =B27-B26 -> 4.2
A28: 40057 | B28: 50.9 | C28: =B28-B27 -> 1 | D28: 0.004
A29: 40087 | B29: 52.6 | C29: =B29-B28 -> 1.7
A30: 40118 | B30: 53 | C30: =B30-B29 -> 0.4
A31: 40148 | B31: 52.9 | C31: =B31-B30 -> -0.1 | D31: 0.005
A32: 40179 | B32: 52.5 | C32: =B32-B31 -> -0.4
A33: 40210 | B33: 51.8 | C33: =B33-B32 -> -0.7
A34: 40238 | B34: 54.1 | C34: =B34-B33 -> 2.3 | D34: 0.004
A35: 40269 | B35: 55.6 | C35: =B35-B34 -> 1.5
A36: 40299 | B36: 56.2 | C36: =B36-B35 -> 0.6
A37: 40330 | B37: 55.5 | C37: =B37-B36 -> -0.7 | D37: 0.009
A38: 40360 | B38: 55.8 | C38: =B38-B37 -> 0.3
A39: 40391 | B39: 55.9 | C39: =B39-B38 -> 0.1
A40: 40422 | B40: 54.1 | C40: =B40-B39 -> -1.8 | D40: 0.004
A41: 40452 | B41: 53.3 | C41: =B41-B40 -> -0.8
A42: 40483 | B42: 55.4 | C42: =B42-B41 -> 2.1
A43: 40513 | B43: 56.5 | C43: =B43-B42 -> 1.1 | D43: 0.005
A44: 40544 | B44: 55.9 | C44: =B44-B43 -> -0.6
A45: 40575 | B45: 56.8 | C45: =B45-B44 -> 0.9
A46: 40603 | B46: 57.2 | C46: =B46-B45 -> 0.4 | D46: 0.008
A47: 40634 | B47: 56.7 | C47: =B47-B46 -> -0.5
A48: 40664 | B48: 55.4 | C48: =B48-B47 -> -1.3
A49: 40695 | B49: 53.7 | C49: =B49-B48 -> -1.7 | D49: 0.002
A50: 40725 | B50: 51.6 | C50: =B50-B49 -> -2.1
A51: 40756 | B51: 51.5 | C51: =B51-B50 -> -0.1
A52: 40787 | B52: 48.8 | C52: =B52-B51 -> -2.7 | D52: 0.002
A53: 40817 | B53: 46.4 | C53: =B53-B52 -> -2.4
A54: 40848 | B54: 47.5 | C54: =B54-B53 -> 1.1
A55: 40878 | B55: 48.8 | C55: =B55-B54 -> 1.3 | D55: -0.002
A56: 40909 | B56: 50.4 | C56: =B56-B55 -> 1.6
A57: 40940 | B57: 48.8 | C57: =B57-B56 -> -1.6
A58: 40969 | B58: 47.9 | C58: =B58-B57 -> -0.9 | D58: -0.001
A59: 41000 | B59: 46.9 | C59: =B59-B58 -> -1
A60: 41030 | B60: 46.7 | C60: =B60-B59 -> -0.2
A61: 41061 | B61: 47.1 | C61: =B61-B60 -> 0.4 | D61: -0.003
A62: 41091 | B62: 47.9 | C62: =B62-B61 -> 0.8
A63: 41122 | B63: 47.2 | C63: =B63-B62 -> -0.7
A64: 41153 | B64: 46.1 | C64: =B64-B63 -> -1.1 | D64: -0.002
A65: 41183 | B65: 46 | C65: =B65-B64 -> -0.1
A66: 41214 | B66: 46.7 | C66: =B66-B65 -> 0.7
A67: 41244 | B67: 47.2 | C67: =B67-B66 -> 0.5 | D67: -0.005
A68: 41275 | B68: 48.6 | C68: =B68-B67 -> 1.4
A69: 41306 | B69: 47.9 | C69: =B69-B68 -> -0.7
A70: 41334 | B70: 46.4 | C70: =B70-B69 -> -1.5 | D70: -0.002
A71: 41365 | B71: 47 | C71: =B71-B70 -> 0.6
A72: 41395 | B72: 47.2 | C72: =B72-B71 -> 0.2
A73: 41426 | B73: 48.3 | C73: =B73-B72 -> 1.1 | D73: 0.003
A74: 41456 | B74: 49.8 | C74: =B74-B73 -> 1.5
A75: 41487 | B75: 50.7 | C75: =B75-B74 -> 0.9
A76: 41518 | B76: 52.2 | C76: =B76-B75 -> 1.5 | D76: 0.001
A77: 41548 | B77: 51.6 | C77: =B77-B76 -> -0.6
A78: 41579 | B78: 51.2 | C78: =B78-B77 -> -0.4
A79: 41609 | B79: 51 | C79: =B79-B78 -> -0.2 | D79: 0.002
A80: 41640 | B80: 51.6 | C80: =B80-B79 -> 0.6
A81: 41671 | B81: 52.6 | C81: =B81-B80 -> 1
A82: 41699 | B82: 52.2 | C82: =B82-B81 -> -0.4 | D82: 0.002
A83: 41730 | B83: 53.1 | C83: =B83-B82 -> 0.9
A84: 41760 | B84: 53.2 | C84: =B84-B83 -> 0.1
A85: 41791 | B85: 52.8 | C85: =B85-B84 -> -0.4 | D85: 0 | H85: EZ | I85: Euro Area
A86: 41821 | B86: 54.2 | C86: =B86-B85 -> 1.4
A87: 41852 | B87: 53.1 | C87: =B87-B86 -> -1.1
A88: 41883 | B88: 52.4 | C88: =IFERROR(B88-B87,"") -> -0.7 | D88: =IF(VLOOKUP(I85,Data!$A$30:$H$150,7,FALSE)=A87,VLOOKUP(I85,Data!$A$30:$H$150,2,FALSE)/100,#N/A) -> 0.002
A89: 41913 | B89: 52.3 | C89: -0.1
A90: 41944 | B90: =IF(A90=Data!$C$1,VLOOKUP($H$85,Data!$A$2:$C$36,3,FALSE),"N/A") -> N/A | C90: =IFERROR(B90-B89,"")
A91: 41974 | B91: TBR | C91: =IFERROR(B91-B90,"")
A92: 42005 | B92: TBR | C92: =IFERROR(B92-B91,"")
A93: 42036 | B93: TBR | C93: =IFERROR(B93-B92,"")
A94: 42064 | B94: TBR | C94: =IFERROR(B94-B93,"")
A95: 42095 | B95: TBR | C95: =IFERROR(B95-B94,"")
A96: 42125 | B96: TBR | C96: =IFERROR(B96-B95,"")
A97: 42156 | B97: TBR | C97: =IFERROR(B97-B96,"")
A98: 42186 | B98: TBR | C98: =IFERROR(B98-B97,"")
A99: 42217 | B99: TBR | C99: =IFERROR(B99-B98,"")
A100: 42248 | B100: TBR | C100: =IFERROR(B100-B99,"")
...

Sheet DE
A1: Date | B1: Germany Service PMI | C1: Change | D1: Germany GDP q/q
A2: 39264 | B2: 58.9
A3: 39295 | B3: 59.8 | C3: =B3-B2 -> 0.9
A4: 39326 | B4: 53.1 | C4: =B4-B3 -> -6.7 | D4: 0.008
A5: 39356 | B5: 55.1 | C5: =B5-B4 -> 2
A6: 39387 | B6: 53.1 | C6: =B6-B5 -> -2
A7: 39417 | B7: 51.5 | C7: =B7-B6 -> -1.6 | D7: 0.001
A8: 39448 | B8: 49.2 | C8: =B8-B7 -> -2.3
A9: 39479 | B9: 52.2 | C9: =B9-B8 -> 3
A10: 39508 | B10: 51.8 | C10: =B10-B9 -> -0.4 | D10: 0.016
A11: 39539 | B11: 54.9 | C11: =B11-B10 -> 3.1
A12: 39569 | B12: 53.8 | C12: =B12-B11 -> -1.1
A13: 39600 | B13: 52.1 | C13: =B13-B12 -> -1.7 | D13: -0.006
A14: 39630 | B14: 53.1 | C14: =B14-B13 -> 1
A15: 39661 | B15: 51.4 | C15: =B15-B14 -> -1.7
A16: 39692 | B16: 50.2 | C16: =B16-B15 -> -1.2 | D16: -0.003
A17: 39722 | B17: 48.3 | C17: =B17-B16 -> -1.9
A18: 39753 | B18: 45.1 | C18: =B18-B17 -> -3.2
A19: 39783 | B19: 43.1 | C19: =B19-B18 -> -2 | D19: -0.024
A20: 39814 | B20: 45.2 | C20: =B20-B19 -> 2.1
A21: 39845 | B21: 41.3 | C21: =B21-B20 -> -3.9
A22: 39873 | B22: 42.3 | C22: =B22-B21 -> 1 | D22: -0.037
A23: 39904 | B23: 43.8 | C23: =B23-B22 -> 1.5
A24: 39934 | B24: 45.2 | C24: =B24-B23 -> 1.4
A25: 39965 | B25: 45.2 | C25: =B25-B24 -> 0 | D25: 0.005
A26: 39995 | B26: 48.1 | C26: =B26-B25 -> 2.9
A27: 40026 | B27: 53.8 | C27: =B27-B26 -> 5.7
A28: 40057 | B28: 52.2 | C28: =B28-B27 -> -1.6 | D28: 0.008
A29: 40087 | B29: 50.7 | C29: =B29-B28 -> -1.5
A30: 40118 | B30: 51.4 | C30: =B30-B29 -> 0.7
A31: 40148 | B31: 52.1 | C31: =B31-B30 -> 0.7 | D31: 0.005
A32: 40179 | B32: 52.2 | C32: =B32-B31 -> 0.1
A33: 40210 | B33: 51.9 | C33: =B33-B32 -> -0.3
A34: 40238 | B34: 54.9 | C34: =B34-B33 -> 3 | D34: 0.005
A35: 40269 | B35: 53.7 | C35: =B35-B34 -> -1.2
A36: 40299 | B36: 54.8 | C36: =B36-B35 -> 1.1
A37: 40330 | B37: 54.8 | C37: =B37-B36 -> 0 | D37: 0.021
A38: 40360 | B38: 56.5 | C38: =B38-B37 -> 1.7
A39: 40391 | B39: 57.2 | C39: =B39-B38 -> 0.7
A40: 40422 | B40: 54.9 | C40: =B40-B39 -> -2.3 | D40: 0.008
A41: 40452 | B41: 56 | C41: =B41-B40 -> 1.1
A42: 40483 | B42: 59.2 | C42: =B42-B41 -> 3.2
A43: 40513 | B43: 59.5 | C43: =B43-B42 -> 0.3 | D43: 0.004
A44: 40544 | B44: 60.3 | C44: =B44-B43 -> 0.8
A45: 40575 | B45: 58.6 | C45: =B45-B44 -> -1.7
A46: 40603 | B46: 60.1 | C46: =B46-B45 -> 1.5 | D46: 0.015
A47: 40634 | B47: 56.8 | C47: =B47-B46 -> -3.3
A48: 40664 | B48: 56.1 | C48: =B48-B47 -> -0.7
A49: 40695 | B49: 56.7 | C49: =B49-B48 -> 0.6 | D49: 0.001
A50: 40725 | B50: 52.9 | C50: =B50-B49 -> -3.8
A51: 40756 | B51: 51.1 | C51: =B51-B50 -> -1.8
A52: 40787 | B52: 49.7 | C52: =B52-B51 -> -1.4 | D52: 0.004
A53: 40817 | B53: 50.6 | C53: =B53-B52 -> 0.9
A54: 40848 | B54: 50.3 | C54: =B54-B53 -> -0.3
A55: 40878 | B55: 52.4 | C55: =B55-B54 -> 2.1 | D55: 0.001
A56: 40909 | B56: 53.7 | C56: =B56-B55 -> 1.3
A57: 40940 | B57: 52.8 | C57: =B57-B56 -> -0.9
A58: 40969 | B58: 52.1 | C58: =B58-B57 -> -0.7 | D58: 0.007
A59: 41000 | B59: 52.2 | C59: =B59-B58 -> 0.1
A60: 41030 | B60: 51.8 | C60: =B60-B59 -> -0.4
A61: 41061 | B61: 49.9 | C61: =B61-B60 -> -1.9 | D61: -0.001
A62: 41091 | B62: 50.3 | C62: =B62-B61 -> 0.4
A63: 41122 | B63: 48.3 | C63: =B63-B62 -> -2
A64: 41153 | B64: 49.7 | C64: =B64-B63 -> 1.4 | D64: 0.002
A65: 41183 | B65: 48.4 | C65: =B65-B64 -> -1.3
A66: 41214 | B66: 49.7 | C66: =B66-B65 -> 1.3
A67: 41244 | B67: 55.7 | C67: =B67-B66 -> 6 | D67: -0.005
A68: 41275 | B68: 54.7 | C68: =B68-B67 -> -1
A69: 41306 | B69: 50.9 | C69: =B69-B68 -> -3.8
A70: 41334 | B70: 49.6 | C70: =B70-B69 -> -1.3 | D70: 0.001
A71: 41365 | B71: 49.7 | C71: =B71-B70 -> 0.1
A72: 41395 | B72: 50.4 | C72: =B72-B71 -> 0.7
A73: 41426 | B73: 51.3 | C73: =B73-B72 -> 0.9 | D73: 0.007
A74: 41456 | B74: 52.8 | C74: =B74-B73 -> 1.5
A75: 41487 | B75: 53.7 | C75: =B75-B74 -> 0.9
A76: 41518 | B76: 52.9 | C76: =B76-B75 -> -0.8 | D76: 0.003
A77: 41548 | B77: 55.7 | C77: =B77-B76 -> 2.8
A78: 41579 | B78: 53.5 | C78: =B78-B77 -> -2.2
A79: 41609 | B79: 53.1 | C79: =B79-B78 -> -0.4 | D79: 0.004
A80: 41640 | B80: 55.9 | C80: =B80-B79 -> 2.8
A81: 41671 | B81: 53 | C81: =B81-B80 -> -2.9
A82: 41699 | B82: 54.7 | C82: =B82-B81 -> 1.7 | D82: 0.008
A83: 41730 | B83: 56.4 | C83: =B83-B82 -> 1.7
A84: 41760 | B84: 56 | C84: =B84-B83 -> -0.4
A85: 41791 | B85: 54.6 | C85: =B85-B84 -> -1.4 | D85: -0.002 | H85: DE | I85: Germany
A86: 41821 | B86: 56.7 | C86: =B86-B85 -> 2.1
A87: 41852 | B87: 54.9 | C87: =B87-B86 -> -1.8
A88: 41883 | B88: 55.7 | C88: =IFERROR(B88-B87,"") -> 0.8 | D88: =IF(VLOOKUP(I85,Data!$A$30:$H$150,7,FALSE)=A87,VLOOKUP(I85,Data!$A$30:$H$150,2,FALSE)/100,#N/A) -> 0.001
A89: 41913 | B89: 54.4 | C89: -1.3
A90: 41944 | B90: =IF(A90=Data!$C$1,VLOOKUP($H$85,Data!$A$2:$C$36,3,FALSE),"N/A") -> N/A | C90: =IFERROR(B90-B89,"")
A91: 41974 | B91: TBR | C91: =IFERROR(B91-B90,"")
A92: 42005 | B92: TBR | C92: =IFERROR(B92-B91,"")
A93: 42036 | B93: TBR | C93: =IFERROR(B93-B92,"")
A94: 42064 | B94: TBR | C94: =IFERROR(B94-B93,"")
A95: 42095 | B95: TBR | C95: =IFERROR(B95-B94,"")
A96: 42125 | B96: TBR | C96: =IFERROR(B96-B95,"")
A97: 42156 | B97: TBR | C97: =IFERROR(B97-B96,"")
A98: 42186 | B98: TBR | C98: =IFERROR(B98-B97,"")
A99: 42217 | B99: TBR | C99: =IFERROR(B99-B98,"")
A100: 42248 | B100: TBR | C100: =IFERROR(B100-B99,"")
...

Sheet FR
A14: Date | B14: France Service PMI | C14: Change | D14: French GDP q/q
A15: 39661 | B15: 48
A16: 39692 | B16: 50.1 | C16: =B16-B15 -> 2.1 | D16: -0.004
A17: 39722 | B17: 47.5 | C17: =B17-B16 -> -2.6
A18: 39753 | B18: 46.2 | C18: =B18-B17 -> -1.3
A19: 39783 | B19: 44.2 | C19: =B19-B18 -> -2 | D19: -0.016
A20: 39814 | B20: 42.6 | C20: =B20-B19 -> -1.6
A21: 39845 | B21: 40.2 | C21: =B21-B20 -> -2.4
A22: 39873 | B22: 43.6 | C22: =B22-B21 -> 3.4 | D22: -0.017
A23: 39904 | B23: 46.5 | C23: =B23-B22 -> 2.9
A24: 39934 | B24: 48.3 | C24: =B24-B23 -> 1.8
A25: 39965 | B25: 47.2 | C25: =B25-B24 -> -1.1 | D25: 0
A26: 39995 | B26: 45.5 | C26: =B26-B25 -> -1.7
A27: 40026 | B27: 49.3 | C27: =B27-B26 -> 3.8
A28: 40057 | B28: 53.2 | C28: =B28-B27 -> 3.9 | D28: 0.001
A29: 40087 | B29: 57.7 | C29: =B29-B28 -> 4.5
A30: 40118 | B30: 60.9 | C30: =B30-B29 -> 3.2
A31: 40148 | B31: 58.2 | C31: =B31-B30 -> -2.7 | D31: 0.007
A32: 40179 | B32: 56.3 | C32: =B32-B31 -> -1.9
A33: 40210 | B33: 54.6 | C33: =B33-B32 -> -1.7
A34: 40238 | B34: 53.8 | C34: =B34-B33 -> -0.8 | D34: 0.003
A35: 40269 | B35: 59.2 | C35: =B35-B34 -> 5.4
A36: 40299 | B36: 61.4 | C36: =B36-B35 -> 2.2
A37: 40330 | B37: 60.8 | C37: =B37-B36 -> -0.6 | D37: 0.006
A38: 40360 | B38: 61.1 | C38: =B38-B37 -> 0.3
A39: 40391 | B39: 60.4 | C39: =B39-B38 -> -0.7
A40: 40422 | B40: 58.2 | C40: =B40-B39 -> -2.2 | D40: 0.005
A41: 40452 | B41: 54.8 | C41: =B41-B40 -> -3.4
A42: 40483 | B42: 55 | C42: =B42-B41 -> 0.2
A43: 40513 | B43: 57.1 | C43: =B43-B42 -> 2.1 | D43: 0.005
A44: 40544 | B44: 58.3 | C44: =B44-B43 -> 1.2
A45: 40575 | B45: 59.7 | C45: =B45-B44 -> 1.4
A46: 40603 | B46: 60.4 | C46: =B46-B45 -> 0.7 | D46: 0.011
A47: 40634 | B47: 62.9 | C47: =B47-B46 -> 2.5
A48: 40664 | B48: 62.5 | C48: =B48-B47 -> -0.4
A49: 40695 | B49: 56.1 | C49: =B49-B48 -> -6.4 | D49: -0.001
A50: 40725 | B50: 54.2 | C50: =B50-B49 -> -1.9
A51: 40756 | B51: 52.3 | C51: =B51-B50 -> -1.9
A52: 40787 | B52: 51.5 | C52: =B52-B51 -> -0.8 | D52: 0.003
A53: 40817 | B53: 44.6 | C53: =B53-B52 -> -6.9
A54: 40848 | B54: 49.6 | C54: =B54-B53 -> 5
A55: 40878 | B55: 50.3 | C55: =B55-B54 -> 0.7 | D55: 0.001
A56: 40909 | B56: 52.3 | C56: =B56-B55 -> 2
A57: 40940 | B57: 50 | C57: =B57-B56 -> -2.3
A58: 40969 | B58: 50.1 | C58: =B58-B57 -> 0.1 | D58: 0.001
A59: 41000 | B59: 45.2 | C59: =B59-B58 -> -4.9
A60: 41030 | B60: 45.1 | C60: =B60-B59 -> -0.1
A61: 41061 | B61: 47.9 | C61: =B61-B60 -> 2.8 | D61: -0.003
A62: 41091 | B62: 50 | C62: =B62-B61 -> 2.1
A63: 41122 | B63: 49.2 | C63: =B63-B62 -> -0.8
A64: 41153 | B64: 45 | C64: =B64-B63 -> -4.2 | D64: 0.002
A65: 41183 | B65: 44.6 | C65: =B65-B64 -> -0.4
A66: 41214 | B66: 45.8 | C66: =B66-B65 -> 1.2
A67: 41244 | B67: 44.1 | C67: =B67-B66 -> -1.7 | D67: -0.002
A68: 41275 | B68: 43.6 | C68: =B68-B67 -> -0.5
A69: 41306 | B69: 43.7 | C69: =B69-B68 -> 0.1
A70: 41334 | B70: 41.3 | C70: =B70-B69 -> -2.4 | D70: 0
A71: 41365 | B71: 44.3 | C71: =B71-B70 -> 3
A72: 41395 | B72: 44.3 | C72: =B72-B71 -> 0
A73: 41426 | B73: 47.2 | C73: =B73-B72 -> 2.9 | D73: 0.006
A74: 41456 | B74: 48.6 | C74: =B74-B73 -> 1.4
A75: 41487 | B75: 48.9 | C75: =B75-B74 -> 0.3
A76: 41518 | B76: 51 | C76: =B76-B75 -> 2.1 | D76: -0.001
A77: 41548 | B77: 50.9 | C77: =B77-B76 -> -0.1
A78: 41579 | B78: 48 | C78: =B78-B77 -> -2.9
A79: 41609 | B79: 48.1 | C79: =B79-B78 -> 0.1 | D79: 0.002
A80: 41640 | B80: 48.9 | C80: =B80-B79 -> 0.8
A81: 41671 | B81: 47.2 | C81: =B81-B80 -> -1.7
A82: 41699 | B82: 51.5 | C82: =B82-B81 -> 4.3 | D82: 0
A83: 41730 | B83: 50.4 | C83: =B83-B82 -> -1.1
A84: 41760 | B84: 49.1 | C84: =B84-B83 -> -1.3
A85: 41791 | B85: 48.2 | C85: =B85-B84 -> -0.9 | D85: 0 | H85: FR | I85: France
A86: 41821 | B86: 50.4 | C86: =B86-B85 -> 2.2
A87: 41852 | B87: 50.3 | C87: =B87-B86 -> -0.1
A88: 41883 | B88: 48.4 | C88: =IFERROR(B88-B87,"") -> -1.9 | D88: =IF(VLOOKUP(I85,Data!$A$30:$H$150,7,FALSE)=A87,VLOOKUP(I85,Data!$A$30:$H$150,2,FALSE)/100,#N/A) -> 0.003
A89: 41913 | B89: 48.3 | C89: -0.1
A90: 41944 | B90: =IF(A90=Data!$C$1,VLOOKUP($H$85,Data!$A$2:$C$36,3,FALSE),"N/A") -> N/A | C90: =IFERROR(B90-B89,"")
A91: 41974 | B91: TBR | C91: =IFERROR(B91-B90,"")
A92: 42005 | B92: TBR | C92: =IFERROR(B92-B91,"")
A93: 42036 | B93: TBR | C93: =IFERROR(B93-B92,"")
A94: 42064 | B94: TBR | C94: =IFERROR(B94-B93,"")
A95: 42095 | B95: TBR | C95: =IFERROR(B95-B94,"")
A96: 42125 | B96: TBR | C96: =IFERROR(B96-B95,"")
A97: 42156 | B97: TBR | C97: =IFERROR(B97-B96,"")
A98: 42186 | B98: TBR | C98: =IFERROR(B98-B97,"")
A99: 42217 | B99: TBR | C99: =IFERROR(B99-B98,"")
A100: 42248 | B100: TBR | C100: =IFERROR(B100-B99,"")
A101: 42278 | B101: TBR | C101: =IFERROR(B101-B100,"")
A102: 42309 | B102: TBR | C102: =IFERROR(B102-B101,"")
... A228: 46143 | B228: TBR | C228: =IFERROR(B228-B227,"")

Sheet IT
A40: Date | B40: Italy Service PMI | C40: Change | D40: Italy GDP q/q
A41: 40452 | B41: 51
A42: 40483 | B42: 54.4 | C42: =B42-B41 -> 3.4
A43: 40513 | B43: 52.1 | C43: =B43-B42 -> -2.3 | D43: 0.003
A44: 40544 | B44: 53.5 | C44: =B44-B43 -> 1.4
A45: 40575 | B45: 53.1 | C45: =B45-B44 -> -0.4
A46: 40603 | B46: 53.3 | C46: =B46-B45 -> 0.2 | D46: 0.001
A47: 40634 | B47: 52.2 | C47: =B47-B46 -> -1.1
A48: 40664 | B48: 50.1 | C48: =B48-B47 -> -2.1
A49: 40695 | B49: 47.4 | C49: =B49-B48 -> -2.7 | D49: 0.002
A50: 40725 | B50: 48.6 | C50: =B50-B49 -> 1.2
A51: 40756 | B51: 48.4 | C51: =B51-B50 -> -0.2
A52: 40787 | B52: 45.8 | C52: =B52-B51 -> -2.6 | D52: -0.002
A53: 40817 | B53: 43.9 | C53: =B53-B52 -> -1.9
A54: 40848 | B54: 45.8 | C54: =B54-B53 -> 1.9
A55: 40878 | B55: 44.5 | C55: =B55-B54 -> -1.3 | D55: -0.007
A56: 40909 | B56: 44.8 | C56: =B56-B55 -> 0.3
A57: 40940 | B57: 44.1 | C57: =B57-B56 -> -0.7
A58: 40969 | B58: 44.3 | C58: =B58-B57 -> 0.2 | D58: -0.011
A59: 41000 | B59: 42.3 | C59: =B59-B58 -> -2
A60: 41030 | B60: 42.8 | C60: =B60-B59 -> 0.5
A61: 41061 | B61: 43.1 | C61: =B61-B60 -> 0.3 | D61: 0.005
A62: 41091 | B62: 43 | C62: =B62-B61 -> -0.1
A63: 41122 | B63: 44 | C63: =B63-B62 -> 1
A64: 41153 | B64: 44.5 | C64: =B64-B63 -> 0.5 | D64: -0.004
A65: 41183 | B65: 46 | C65: =B65-B64 -> 1.5
A66: 41214 | B66: 44.6 | C66: =B66-B65 -> -1.4
A67: 41244 | B67: 43.1 | C67: =B67-B66 -> -1.5 | D67: -0.009
A68: 41275 | B68: 43.9 | C68: =B68-B67 -> 0.8
A69: 41306 | B69: 43.6 | C69: =B69-B68 -> -0.3
A70: 41334 | B70: 45.5 | C70: =B70-B69 -> 1.9 | D70: -0.006
A71: 41365 | B71: 47 | C71: =B71-B70 -> 1.5
A72: 41395 | B72: 46.5 | C72: =B72-B71 -> -0.5
A73: 41426 | B73: 45.8 | C73: =B73-B72 -> -0.7 | D73: -0.003
A74: 41456 | B74: 48.7 | C74: =B74-B73 -> 2.9
A75: 41487 | B75: 48.8 | C75: =B75-B74 -> 0.1
A76: 41518 | B76: 52.7 | C76: =B76-B75 -> 3.9 | D76: -0.001
A77: 41548 | B77: 50.5 | C77: =B77-B76 -> -2.2
A78: 41579 | B78: 47.2 | C78: =B78-B77 -> -3.3
A79: 41609 | B79: 48.6 | C79: =B79-B78 -> 1.4 | D79: 0.001
A80: 41640 | B80: 49.4 | C80: =B80-B79 -> 0.8
A81: 41671 | B81: 52.9 | C81: =B81-B80 -> 3.5
A82: 41699 | B82: 49.5 | C82: =B82-B81 -> -3.4 | D82: -0.001
A83: 41730 | B83: 51.1 | C83: =B83-B82 -> 1.6
A84: 41760 | B84: 51.6 | C84: =B84-B83 -> 0.5
A85: 41791 | B85: 53.6 | C85: =B85-B84 -> 2 | D85: -0.002 | H85: IT | I85: Italy
A86: 41821 | B86: 52.8 | C86: =B86-B85 -> -0.8
A87: 41852 | B87: 49.8 | C87: =B87-B86 -> -3
A88: 41883 | B88: 48.8 | C88: =IFERROR(B88-B87,"") -> -1 | D88: =IF(VLOOKUP(I85,Data!$A$30:$H$150,7,FALSE)=A87,VLOOKUP(I85,Data!$A$30:$H$150,2,FALSE)/100,#N/A) -> -0.001
A89: 41913 | B89: 50.8 | C89: 2
A90: 41944 | B90: =IF(A90=Data!$C$1,VLOOKUP($H$85,Data!$A$2:$C$36,3,FALSE),"N/A") -> N/A | C90: =IFERROR(B90-B89,"")
A91: 41974 | B91: TBR | C91: =IFERROR(B91-B90,"")
A92: 42005 | B92: TBR | C92: =IFERROR(B92-B91,"")
A93: 42036 | B93: TBR | C93: =IFERROR(B93-B92,"")
A94: 42064 | B94: TBR | C94: =IFERROR(B94-B93,"")
A95: 42095 | B95: TBR | C95: =IFERROR(B95-B94,"")
A96: 42125 | B96: TBR | C96: =IFERROR(B96-B95,"")
A97: 42156 | B97: TBR | C97: =IFERROR(B97-B96,"")
A98: 42186 | B98: TBR | C98: =IFERROR(B98-B97,"")
A99: 42217 | B99: TBR | C99: =IFERROR(B99-B98,"")
A100: 42248 | B100: TBR | C100: =IFERROR(B100-B99,"")
A101: 42278 | B101: TBR | C101: =IFERROR(B101-B100,"")
A102: 42309 | B102: TBR | C102: =IFERROR(B102-B101,"")
... A228: 46143 | B228: TBR | C228: =IFERROR(B228-B227,"")

Sheet ES
A40: Date | B40: Spain Service PMI | C40: Change | D40: Spanish GDP q/q
A41: 40452 | B41: 46.5
A42: 40483 | B42: 48.3 | C42: =B42-B41 -> 1.8
A43: 40513 | B43: 49.1 | C43: =B43-B42 -> 0.8 | D43: 0.002
A44: 40544 | B44: 50.1 | C44: =B44-B43 -> 1
A45: 40575 | B45: 50.8 | C45: =B45-B44 -> 0.7
A46: 40603 | B46: 48.7 | C46: =B46-B45 -> -2.1 | D46: 0.002
A47: 40634 | B47: 50.4 | C47: =B47-B46 -> 1.7
A48: 40664 | B48: 50.9 | C48: =B48-B47 -> 0.5
A49: 40695 | B49: 50.2 | C49: =B49-B48 -> -0.7 | D49: -0.001
A50: 40725 | B50: 46.5 | C50: =B50-B49 -> -3.7
A51: 40756 | B51: 45.2 | C51: =B51-B50 -> -1.3
A52: 40787 | B52: 44.8 | C52: =B52-B51 -> -0.4 | D52: -0.003
A53: 40817 | B53: 41.8 | C53: =B53-B52 -> -3
A54: 40848 | B54: 36.8 | C54: =B54-B53 -> -5
A55: 40878 | B55: 42.1 | C55: =B55-B54 -> 5.3 | D55: -0.004
A56: 40909 | B56: 46.1 | C56: =B56-B55 -> 4
A57: 40940 | B57: 41.9 | C57: =B57-B56 -> -4.2
A58: 40969 | B58: 46.3 | C58: =B58-B57 -> 4.4 | D58: -0.004
A59: 41000 | B59: 42.1 | C59: =B59-B58 -> -4.2
A60: 41030 | B60: 41.8 | C60: =B60-B59 -> -0.3
A61: 41061 | B61: 43.4 | C61: =B61-B60 -> 1.6 | D61: -0.005
A62: 41091 | B62: 43.7 | C62: =B62-B61 -> 0.3
A63: 41122 | B63: 44 | C63: =B63-B62 -> 0.3
A64: 41153 | B64: 40.2 | C64: =B64-B63 -> -3.8 | D64: -0.004
A65: 41183 | B65: 41.2 | C65: =B65-B64 -> 1
A66: 41214 | B66: 42.4 | C66: =B66-B65 -> 1.2
A67: 41244 | B67: 44.1 | C67: =B67-B66 -> 1.7 | D67: -0.008
A68: 41275 | B68: 47 | C68: =B68-B67 -> 2.9
A69: 41306 | B69: 44.7 | C69: =B69-B68 -> -2.3
A70: 41334 | B70: 45.3 | C70: =B70-B69 -> 0.6 | D70: -0.003
A71: 41365 | B71: 44.4 | C71: =B71-B70 -> -0.9
A72: 41395 | B72: 47.3 | C72: =B72-B71 -> 2.9
A73: 41426 | B73: 47.8 | C73: =B73-B72 -> 0.5 | D73: -0.001
A74: 41456 | B74: 48.5 | C74: =B74-B73 -> 0.7
A75: 41487 | B75: 50.5 | C75: =B75-B74 -> 2
A76: 41518 | B76: 49 | C76: =B76-B75 -> -1.5 | D76: 0.001
A77: 41548 | B77: 49.6 | C77: =B77-B76 -> 0.6
A78: 41579 | B78: 51.5 | C78: =B78-B77 -> 1.9
A79: 41609 | B79: 53.2 | C79: =B79-B78 -> 1.7 | D79: 0.002
A80: 41640 | B80: 54.9 | C80: =B80-B79 -> 1.7
A81: 41671 | B81: 53.7 | C81: =B81-B80 -> -1.2
A82: 41699 | B82: 54 | C82: =B82-B81 -> 0.3 | D82: 0.004
A83: 41730 | B83: 56.5 | C83: =B83-B82 -> 2.5
A84: 41760 | B84: 55.7 | C84: =B84-B83 -> -0.8
A85: 41791 | B85: 54.8 | C85: =B85-B84 -> -0.9 | D85: 0.006 | H85: ES | I85: Spain
A86: 41821 | B86: 56.2 | C86: =B86-B85 -> 1.4
A87: 41852 | B87: 58.1 | C87: =B87-B86 -> 1.9
A88: 41883 | B88: 55.8 | C88: =IFERROR(B88-B87,"") -> -2.3 | D88: =IF(VLOOKUP(I85,Data!$A$30:$H$150,7,FALSE)=A87,VLOOKUP(I85,Data!$A$30:$H$150,2,FALSE)/100,#N/A) -> 0.005
A89: 41913 | B89: 55.9 | C89: 0.1
A90: 41944 | B90: =IF(A90=Data!$C$1,VLOOKUP($H$85,Data!$A$2:$C$36,3,FALSE),"N/A") -> N/A | C90: =IFERROR(B90-B89,"")
A91: 41974 | B91: TBR | C91: =IFERROR(B91-B90,"")
A92: 42005 | B92: TBR | C92: =IFERROR(B92-B91,"")
A93: 42036 | B93: TBR | C93: =IFERROR(B93-B92,"")
A94: 42064 | B94: TBR | C94: =IFERROR(B94-B93,"")
A95: 42095 | B95: TBR | C95: =IFERROR(B95-B94,"")
A96: 42125 | B96: TBR | C96: =IFERROR(B96-B95,"")
A97: 42156 | B97: TBR | C97: =IFERROR(B97-B96,"")
A98: 42186 | B98: TBR | C98: =IFERROR(B98-B97,"")
A99: 42217 | B99: TBR | C99: =IFERROR(B99-B98,"")
A100: 42248 | B100: TBR | C100: =IFERROR(B100-B99,"")
A101: 42278 | B101: TBR | C101: =IFERROR(B101-B100,"")
A102: 42309 | B102: TBR | C102: =IFERROR(B102-B101,"")
... A228: 46143 | B228: TBR | C228: =IFERROR(B228-B227,"")

Sheet IR
A40: Date | B40: Ireland Service PMI | C40: Change | D40: Ireland GDP Growth q/q
A41: 40452 | B41: 50.9
A42: 40483 | B42: 50.8 | C42: =B42-B41 -> -0.1
A43: 40513 | B43: 52.1 | C43: =B43-B42 -> 1.3 | D43: -0.01
A44: 40544 | B44: 53.6 | C44: =B44-B43 -> 1.5
A45: 40575 | B45: 55.1 | C45: =B45-B44 -> 1.5
A46: 40603 | B46: 51.1 | C46: =B46-B45 -> -4 | D46: 0.015
A47: 40634 | B47: 50.2 | C47: =B47-B46 -> -0.9
A48: 40664 | B48: 50.5 | C48: =B48-B47 -> 0.3
A49: 40695 | B49: 52.4 | C49: =B49-B48 -> 1.9 | D49: 0.015
A50: 40725 | B50: 51.7 | C50: =B50-B49 -> -0.7
A51: 40756 | B51: 51.1 | C51: =B51-B50 -> -0.6
A52: 40787 | B52: 51.3 | C52: =B52-B51 -> 0.2 | D52: -0.01
A53: 40817 | B53: 51.5 | C53: =B53-B52 -> 0.2
A54: 40848 | B54: 52.7 | C54: =B54-B53 -> 1.2
A55: 40878 | B55: 48.4 | C55: =B55-B54 -> -4.3 | D55: 0.01
A56: 40909 | B56: 48.3 | C56: =B56-B55 -> -0.1
A57: 40940 | B57: 53.3 | C57: =B57-B56 -> 5
A58: 40969 | B58: 52.1 | C58: =B58-B57 -> -1.2 | D58: -0.005
A59: 41000 | B59: 52.2 | C59: =B59-B58 -> 0.1
A60: 41030 | B60: 48.9 | C60: =B60-B59 -> -3.3
A61: 41061 | B61: 49.7 | C61: =B61-B60 -> 0.8 | D61: 0.007
A62: 41091 | B62: 49.1 | C62: =B62-B61 -> -0.6
A63: 41122 | B63: 51.7 | C63: =B63-B62 -> 2.6
A64: 41153 | B64: 53.9 | C64: =B64-B63 -> 2.2 | D64: -0.019
A65: 41183 | B65: 56.1 | C65: =B65-B64 -> 2.2
A66: 41214 | B66: 56.1 | C66: =B66-B65 -> 0
A67: 41244 | B67: 56.5 | C67: =B67-B66 -> 0.4 | D67: 0.008
A68: 41275 | B68: 56.8 | C68: =B68-B67 -> 0.3
A69: 41306 | B69: 53.6 | C69: =B69-B68 -> -3.2
A70: 41334 | B70: 52.3 | C70: =B70-B69 -> -1.3 | D70: -0.014
A71: 41365 | B71: 55.2 | C71: =B71-B70 -> 2.9
A72: 41395 | B72: 52.7 | C72: =B72-B71 -> -2.5
A73: 41426 | B73: 61.6 | C73: =B73-B72 -> 8.9 | D73: 0.011
A74: 41456 | B74: 59.6 | C74: =B74-B73 -> -2
A75: 41487 | B75: 57.2 | C75: =B75-B74 -> -2.4
A76: 41518 | B76: 56.8 | C76: =B76-B75 -> -0.4 | D76: 0.021
A77: 41548 | B77: 60.1 | C77: =B77-B76 -> 3.3
A78: 41579 | B78: 57.1 | C78: =B78-B77 -> -3
A79: 41609 | B79: 59.3 | C79: =B79-B78 -> 2.2 | D79: -0.023
A80: 41640 | B80: 61.5 | C80: =B80-B79 -> 2.2
A81: 41671 | B81: 57.5 | C81: =B81-B80 -> -4
A82: 41699 | B82: 60.7 | C82: =B82-B81 -> 3.2 | D82: 0.027
A83: 41730 | B83: 61.9 | C83: =B83-B82 -> 1.2
A84: 41760 | B84: 61.7 | C84: =B84-B83 -> -0.2
A85: 41791 | B85: 62.6 | C85: =B85-B84 -> 0.9 | D85: 0.015 | H85: IR | I85: Ireland
A86: 41821 | B86: 61.3 | C86: =B86-B85 -> -1.3
A87: 41852 | B87: 62.4 | C87: =B87-B86 -> 1.1
A88: 41883 | B88: 62.5 | C88: =IFERROR(B88-B87,"") -> 0.1 | D88: =IF(VLOOKUP(I85,Data!$A$30:$H$150,7,FALSE)=A87,VLOOKUP(I85,Data!$A$30:$H$150,2,FALSE)/100,#N/A) -> #N/A
A89: 41913 | B89: 61.5 | C89: -1
A90: 41944 | B90: =IF(A90=Data!$C$1,VLOOKUP($H$85,Data!$A$2:$C$36,3,FALSE),"N/A") -> N/A | C90: =IFERROR(B90-B89,"")
A91: 41974 | B91: TBR | C91: =IFERROR(B91-B90,"")
A92: 42005 | B92: TBR | C92: =IFERROR(B92-B91,"")
A93: 42036 | B93: TBR | C93: =IFERROR(B93-B92,"")
A94: 42064 | B94: TBR | C94: =IFERROR(B94-B93,"")
A95: 42095 | B95: TBR | C95: =IFERROR(B95-B94,"")
A96: 42125 | B96: TBR | C96: =IFERROR(B96-B95,"")
A97: 42156 | B97: TBR | C97: =IFERROR(B97-B96,"")
A98: 42186 | B98: TBR | C98: =IFERROR(B98-B97,"")
A99: 42217 | B99: TBR | C99: =IFERROR(B99-B98,"")
A100: 42248 | B100: TBR | C100: =IFERROR(B100-B99,"")
A101: 42278 | B101: TBR | C101: =IFERROR(B101-B100,"")
A102: 42309 | B102: TBR | C102: =IFERROR(B102-B101,"")
... A228: 46143 | B228: TBR | C228: =IFERROR(B228-B227,"")

Sheet CH
A40: Date | B40: China Service PMI | C40: Change | D40: China GDP Growth q/q
A41: 40452 | B41: 60.5
A42: 40483 | B42: 53.2 | C42: =B42-B41 -> -7.3
A43: 40513 | B43: 48.1 | C43: =B43-B42 -> -5.1 | D43: 0.024
A44: 40544 | B44: 46.5 | C44: =B44-B43 -> -1.6
A45: 40575 | B45: 44.1 | C45: =B45-B44 -> -2.4
A46: 40603 | B46: 60.2 | C46: =B46-B45 -> 16.1 | D46: 0.023
A47: 40634 | B47: 62.5 | C47: =B47-B46 -> 2.3
A48: 40664 | B48: 61.9 | C48: =B48-B47 -> -0.6
A49: 40695 | B49: 57 | C49: =B49-B48 -> -4.9 | D49: 0.025
A50: 40725 | B50: 59.6 | C50: =B50-B49 -> 2.6
A51: 40756 | B51: 58.1 | C51: =B51-B50 -> -1.5
A52: 40787 | B52: 57 | C52: =B52-B51 -> -1.1 | D52: 0.022
A53: 40817 | B53: 54.6 | C53: =B53-B52 -> -2.4
A54: 40848 | B54: 49.7 | C54: =B54-B53 -> -4.9
A55: 40878 | B55: 56 | C55: =B55-B54 -> 6.3 | D55: 0.018
A56: 40909 | B56: 52.5 | C56: =B56-B55 -> -3.5
A57: 40940 | B57: 53.9 | C57: =B57-B56 -> 1.4
A58: 40969 | B58: 53.3 | C58: =B58-B57 -> -0.6 | D58: 0.014
A59: 41000 | B59: 54.1 | C59: =B59-B58 -> 0.8
A60: 41030 | B60: 54.7 | C60: =B60-B59 -> 0.6
A61: 41061 | B61: 52.3 | C61: =B61-B60 -> -2.4 | D61: 0.021
A62: 41091 | B62: 53.1 | C62: =B62-B61 -> 0.8
A63: 41122 | B63: 52 | C63: =B63-B62 -> -1.1
A64: 41153 | B64: 54.3 | C64: =B64-B63 -> 2.3 | D64: 0.02
A65: 41183 | B65: 53.5 | C65: =B65-B64 -> -0.8
A66: 41214 | B66: 52.1 | C66: =B66-B65 -> -1.4
A67: 41244 | B67: 53.5 | C67: =B67-B66 -> 1.4 | D67: 0.019
A68: 41275 | B68: 54 | C68: =B68-B67 -> 0.5
A69: 41306 | B69: 52.1 | C69: =B69-B68 -> -1.9
A70: 41334 | B70: 54.3 | C70: =B70-B69 -> 2.2 | D70: 0.015
A71: 41365 | B71: 51.1 | C71: =B71-B70 -> -3.2
A72: 41395 | B72: 51.2 | C72: =B72-B71 -> 0.1
A73: 41426 | B73: 51.3 | C73: =B73-B72 -> 0.1 | D73: 0.018
A74: 41456 | B74: 51.3 | C74: =B74-B73 -> 0
A75: 41487 | B75: 52.8 | C75: =B75-B74 -> 1.5
A76: 41518 | B76: 52.4 | C76: =B76-B75 -> -0.4 | D76: 0.023
A77: 41548 | B77: 52.6 | C77: =B77-B76 -> 0.2
A78: 41579 | B78: 52.5 | C78: =B78-B77 -> -0.1
A79: 41609 | B79: 51.4 | C79: =B79-B78 -> -1.1 | D79: 0.017
A80: 41640 | B80: 50.7 | C80: =B80-B79 -> -0.7
A81: 41671 | B81: 51 | C81: =B81-B80 -> 0.3
A82: 41699 | B82: 51.9 | C82: =B82-B81 -> 0.9 | D82: 0.014
A83: 41730 | B83: 51.4 | C83: =B83-B82 -> -0.5
A84: 41760 | B84: 50.7 | C84: =B84-B83 -> -0.7
A85: 41791 | B85: 53.1 | C85: =B85-B84 -> 2.4 | D85: 0.015 | H85: CH | I85: China
A86: 41821 | B86: 50 | C86: =B86-B85 -> -3.1
A87: 41852 | B87: 54.1 | C87: =B87-B86 -> 4.1
A88: 41883 | B88: 53.5 | C88: =IFERROR(B88-B87,"") -> -0.6 | D88: =IF(VLOOKUP(I85,Data!$A$30:$H$150,7,FALSE)=A87,VLOOKUP(I85,Data!$A$30:$H$150,2,FALSE)/100,#N/A) -> 0.019
A89: 41913 | B89: 52.9 | C89: -0.6
A90: 41944 | B90: =IF(A90=Data!$C$1,VLOOKUP($H$85,Data!$A$2:$C$36,3,FALSE),"N/A") -> N/A | C90: =IFERROR(B90-B89,"")
A91: 41974 | B91: TBR | C91: =IFERROR(B91-B90,"")
A92: 42005 | B92: TBR | C92: =IFERROR(B92-B91,"")
A93: 42036 | B93: TBR | C93: =IFERROR(B93-B92,"")
A94: 42064 | B94: TBR | C94: =IFERROR(B94-B93,"")
A95: 42095 | B95: TBR | C95: =IFERROR(B95-B94,"")
A96: 42125 | B96: TBR | C96: =IFERROR(B96-B95,"")
A97: 42156 | B97: TBR | C97: =IFERROR(B97-B96,"")
A98: 42186 | B98: TBR | C98: =IFERROR(B98-B97,"")
A99: 42217 | B99: TBR | C99: =IFERROR(B99-B98,"")
A100: 42248 | B100: TBR | C100: =IFERROR(B100-B99,"")
A101: 42278 | B101: TBR | C101: =IFERROR(B101-B100,"")
A102: 42309 | B102: TBR | C102: =IFERROR(B102-B101,"")
... A228: 46143 | B228: TBR | C228: =IFERROR(B228-B227,"")

Sheet AU
A40: Date | B40: Australia Service PMI | C40: Change | D40: GDP Change q/q
A41: 40452 | B41: 50.7
A42: 40483 | B42: 46.2 | C42: =B42-B41 -> -4.5
A43: 40513 | B43: 47.1 | C43: =B43-B42 -> 0.9 | D43: 0.006
A44: 40544 | B44: 45.5 | C44: =B44-B43 -> -1.6
A45: 40575 | B45: 48.7 | C45: =B45-B44 -> 3.2
A46: 40603 | B46: 46.5 | C46: =B46-B45 -> -2.2 | D46: -0.005
A47: 40634 | B47: 51.5 | C47: =B47-B46 -> 5
A48: 40664 | B48: 49.9 | C48: =B48-B47 -> -1.6
A49: 40695 | B49: 48.5 | C49: =B49-B48 -> -1.4 | D49: 0.012
A50: 40725 | B50: 48.8 | C50: =B50-B49 -> 0.3
A51: 40756 | B51: 52.1 | C51: =B51-B50 -> 3.3
A52: 40787 | B52: 50.3 | C52: =B52-B51 -> -1.8 | D52: 0.012
A53: 40817 | B53: 48.8 | C53: =B53-B52 -> -1.5
A54: 40848 | B54: 47.7 | C54: =B54-B53 -> -1.1
A55: 40878 | B55: 49 | C55: =B55-B54 -> 1.3 | D55: 0.006
A56: 40909 | B56: 51.9 | C56: =B56-B55 -> 2.9
A57: 40940 | B57: 46.7 | C57: =B57-B56 -> -5.2
A58: 40969 | B58: 47 | C58: =B58-B57 -> 0.3 | D58: 0.013
A59: 41000 | B59: 39.6 | C59: =B59-B58 -> -7.4
A60: 41030 | B60: 43.5 | C60: =B60-B59 -> 3.9
A61: 41061 | B61: 48.8 | C61: =B61-B60 -> 5.3 | D61: 0.005
A62: 41091 | B62: 46.5 | C62: =B62-B61 -> -2.3
A63: 41122 | B63: 42.4 | C63: =B63-B62 -> -4.1
A64: 41153 | B64: 41.9 | C64: =B64-B63 -> -0.5 | D64: 0.008
A65: 41183 | B65: 42.8 | C65: =B65-B64 -> 0.9
A66: 41214 | B66: 47.1 | C66: =B66-B65 -> 4.3
A67: 41244 | B67: 46.3 | C67: =B67-B66 -> -0.8 | D67: 0.007
A68: 41275 | B68: 45.4 | C68: =B68-B67 -> -0.9
A69: 41306 | B69: 48.5 | C69: =B69-B68 -> 3.1
A70: 41334 | B70: 49.6 | C70: =B70-B69 -> 1.1 | D70: 0.005
A71: 41365 | B71: 44.1 | C71: =B71-B70 -> -5.5
A72: 41395 | B72: 40.6 | C72: =B72-B71 -> -3.5
A73: 41426 | B73: 41.5 | C73: =B73-B72 -> 0.9 | D73: 0.007
A74: 41456 | B74: 39.4 | C74: =B74-B73 -> -2.1
A75: 41487 | B75: 39 | C75: =B75-B74 -> -0.4
A76: 41518 | B76: 47.1 | C76: =B76-B75 -> 8.1 | D76: 0.006
A77: 41548 | B77: 47.9 | C77: =B77-B76 -> 0.8
A78: 41579 | B78: 48.9 | C78: =B78-B77 -> 1
A79: 41609 | B79: 46.1 | C79: =B79-B78 -> -2.8 | D79: 0.008
A80: 41640 | B80: 49.3 | C80: =B80-B79 -> 3.2
A81: 41671 | B81: 55.2 | C81: =B81-B80 -> 5.9
A82: 41699 | B82: 48.9 | C82: =B82-B81 -> -6.3 | D82: 0.011
A83: 41730 | B83: 48.6 | C83: =B83-B82 -> -0.3
A84: 41760 | B84: 49.9 | C84: =B84-B83 -> 1.3
A85: 41791 | B85: 47.6 | C85: =B85-B84 -> -2.3 | D85: 0.005 | H85: AU | I85: Australia
A86: 41821 | B86: 49.3 | C86: =B86-B85 -> 1.7
A87: 41852 | B87: 49.4 | C87: =B87-B86 -> 0.1
A88: 41883 | B88: 45.5 | C88: =IFERROR(B88-B87,"") -> -3.9 | D88: =IF(VLOOKUP(I85,Data!$A$30:$H$150,7,FALSE)=A87,VLOOKUP(I85,Data!$A$30:$H$150,2,FALSE)/100,#N/A) -> 0.003
A89: 41913 | B89: 43.6 | C89: -1.9
A90: 41944 | B90: =IF(A90=Data!$C$1,VLOOKUP($H$85,Data!$A$2:$C$36,3,FALSE),"N/A") -> N/A | C90: =IFERROR(B90-B89,"")
A91: 41974 | B91: TBR | C91: =IFERROR(B91-B90,"")
A92: 42005 | B92: TBR | C92: =IFERROR(B92-B91,"")
A93: 42036 | B93: TBR | C93: =IFERROR(B93-B92,"")
A94: 42064 | B94: TBR | C94: =IFERROR(B94-B93,"")
A95: 42095 | B95: TBR | C95: =IFERROR(B95-B94,"")
A96: 42125 | B96: TBR | C96: =IFERROR(B96-B95,"")
A97: 42156 | B97: TBR | C97: =IFERROR(B97-B96,"")
A98: 42186 | B98: TBR | C98: =IFERROR(B98-B97,"")
A99: 42217 | B99: TBR | C99: =IFERROR(B99-B98,"")
A100: 42248 | B100: TBR | C100: =IFERROR(B100-B99,"")
A101: 42278 | B101: TBR | C101: =IFERROR(B101-B100,"")
A102: 42309 | B102: TBR | C102: =IFERROR(B102-B101,"")
... A228: 46143 | B228: TBR | C228: =IFERROR(B228-B227,"")

Sheet JP
A40: Date | B40: Japan Service PMI | C40: Change | D40: Japan GDP Growth q/q
A41: 40452 | B41: 47.2
A42: 40483 | B42: 49.5 | C42: =B42-B41 -> 2.3
A43: 40513 | B43: 50.1 | C43: =B43-B42 -> 0.6 | D43: -0.005
A44: 40544 | B44: 48.1 | C44: =B44-B43 -> -2
A45: 40575 | B45: 49.8 | C45: =B45-B44 -> 1.7
A46: 40603 | B46: 35.3 | C46: =B46-B45 -> -14.5 | D46: -0.018
A47: 40634 | B47: 35 | C47: =B47-B46 -> -0.3
A48: 40664 | B48: 43.8 | C48: =B48-B47 -> 8.8
A49: 40695 | B49: 45.4 | C49: =B49-B48 -> 1.6 | D49: -0.007
A50: 40725 | B50: 45.3 | C50: =B50-B49 -> -0.1
A51: 40756 | B51: 44.1 | C51: =B51-B50 -> -1.2
A52: 40787 | B52: 46.4 | C52: =B52-B51 -> 2.3 | D52: 0.026
A53: 40817 | B53: 52.3 | C53: =B53-B52 -> 5.9
A54: 40848 | B54: 49.5 | C54: =B54-B53 -> -2.8
A55: 40878 | B55: 50.4 | C55: =B55-B54 -> 0.9 | D55: 0.002
A56: 40909 | B56: 51 | C56: =B56-B55 -> 0.6
A57: 40940 | B57: 51.2 | C57: =B57-B56 -> 0.2
A58: 40969 | B58: 53.7 | C58: =B58-B57 -> 2.5 | D58: 0.009
A59: 41000 | B59: 51 | C59: =B59-B58 -> -2.7
A60: 41030 | B60: 50.5 | C60: =B60-B59 -> -0.5
A61: 41061 | B61: 49.5 | C61: =B61-B60 -> -1 | D61: -0.005
A62: 41091 | B62: 48.7 | C62: =B62-B61 -> -0.8
A63: 41122 | B63: 47.5 | C63: =B63-B62 -> -1.2
A64: 41153 | B64: 48.8 | C64: =B64-B63 -> 1.3 | D64: -0.008
A65: 41183 | B65: 49.7 | C65: =B65-B64 -> 0.9
A66: 41214 | B66: 49.1 | C66: =B66-B65 -> -0.6
A67: 41244 | B67: 50.1 | C67: =B67-B66 -> 1 | D67: 0.001
A68: 41275 | B68: 50.4 | C68: =B68-B67 -> 0.3
A69: 41306 | B69: 51.3 | C69: =B69-B68 -> 0.9
A70: 41334 | B70: 53.4 | C70: =B70-B69 -> 2.1 | D70: 0.012
A71: 41365 | B71: 52.5 | C71: =B71-B70 -> -0.9
A72: 41395 | B72: 54.8 | C72: =B72-B71 -> 2.3
A73: 41426 | B73: 52.1 | C73: =B73-B72 -> -2.7 | D73: 0.009
A74: 41456 | B74: 50.6 | C74: =B74-B73 -> -1.5
A75: 41487 | B75: 51.2 | C75: =B75-B74 -> 0.6
A76: 41518 | B76: 53 | C76: =B76-B75 -> 1.8 | D76: 0.003
A77: 41548 | B77: 55.3 | C77: =B77-B76 -> 2.3
A78: 41579 | B78: 51.8 | C78: =B78-B77 -> -3.5
A79: 41609 | B79: 52.1 | C79: =B79-B78 -> 0.3 | D79: 0.001
A80: 41640 | B80: 51.2 | C80: =B80-B79 -> -0.9
A81: 41671 | B81: 49.3 | C81: =B81-B80 -> -1.9
A82: 41699 | B82: 52.2 | C82: =B82-B81 -> 2.9 | D82: 0.015
A83: 41730 | B83: 46.4 | C83: =B83-B82 -> -5.8
A84: 41760 | B84: 49.3 | C84: =B84-B83 -> 2.9
A85: 41791 | B85: 49 | C85: =B85-B84 -> -0.3 | D85: -0.017 | H85: JP | I85: Japan
A86: 41821 | B86: 50.4 | C86: =B86-B85 -> 1.4
A87: 41852 | B87: 49.9 | C87: =B87-B86 -> -0.5
A88: 41883 | B88: 52.5 | C88: =IFERROR(B88-B87,"") -> 2.6 | D88: =IF(VLOOKUP(I85,Data!$A$30:$H$150,7,FALSE)=A87,VLOOKUP(I85,Data!$A$30:$H$150,2,FALSE)/100,#N/A) -> -0.004
A89: 41913 | B89: 48.7 | C89: -3.8
A90: 41944 | B90: =IF(A90=Data!$C$1,VLOOKUP($H$85,Data!$A$2:$C$36,3,FALSE),"N/A") -> N/A | C90: =IFERROR(B90-B89,"")
A91: 41974 | B91: TBR | C91: =IFERROR(B91-B90,"")
A92: 42005 | B92: TBR | C92: =IFERROR(B92-B91,"")
A93: 42036 | B93: TBR | C93: =IFERROR(B93-B92,"")
A94: 42064 | B94: TBR | C94: =IFERROR(B94-B93,"")
A95: 42095 | B95: TBR | C95: =IFERROR(B95-B94,"")
A96: 42125 | B96: TBR | C96: =IFERROR(B96-B95,"")
A97: 42156 | B97: TBR | C97: =IFERROR(B97-B96,"")
A98: 42186 | B98: TBR | C98: =IFERROR(B98-B97,"")
A99: 42217 | B99: TBR | C99: =IFERROR(B99-B98,"")
A100: 42248 | B100: TBR | C100: =IFERROR(B100-B99,"")
A101: 42278 | B101: TBR | C101: =IFERROR(B101-B100,"")
A102: 42309 | B102: TBR | C102: =IFERROR(B102-B101,"")
... A227: 46113 | B227: TBR | C227: =IFERROR(B227-B226,"")
A228: 46143 | B228: 50 | C228: =IFERROR(B228-B227,"")

Sheet BR
A40: Date | B40: Brazil Service PMI | C40: Change | D40: Brazil GDP Growth q/q
A41: 40452 | B41: 51.8
A42: 40483 | B42: 52.1 | C42: =B42-B41 -> 0.3
A43: 40513 | B43: 50.2 | C43: =B43-B42 -> -1.9 | D43: 0.011
A44: 40544 | B44: 51.2 | C44: =B44-B43 -> 1
A45: 40575 | B45: 52.7 | C45: =B45-B44 -> 1.5
A46: 40603 | B46: 53.5 | C46: =B46-B45 -> 0.8 | D46: 0.006
A47: 40634 | B47: 53.2 | C47: =B47-B46 -> -0.3
A48: 40664 | B48: 53.3 | C48: =B48-B47 -> 0.1
A49: 40695 | B49: 52.1 | C49: =B49-B48 -> -1.2 | D49: 0.005
A50: 40725 | B50: 53.7 | C50: =B50-B49 -> 1.6
A51: 40756 | B51: 52.1 | C51: =B51-B50 -> -1.6
A52: 40787 | B52: 50.5 | C52: =B52-B51 -> -1.6 | D52: -0.001
A53: 40817 | B53: 53.6 | C53: =B53-B52 -> 3.1
A54: 40848 | B54: 52.6 | C54: =B54-B53 -> -1
A55: 40878 | B55: 54.8 | C55: =B55-B54 -> 2.2 | D55: 0.001
A56: 40909 | B56: 55 | C56: =B56-B55 -> 0.2
A57: 40940 | B57: 57.1 | C57: =B57-B56 -> 2.1
A58: 40969 | B58: 53.8 | C58: =B58-B57 -> -3.3 | D58: 0.001
A59: 41000 | B59: 54.4 | C59: =B59-B58 -> 0.6
A60: 41030 | B60: 49.7 | C60: =B60-B59 -> -4.7
A61: 41061 | B61: 53 | C61: =B61-B60 -> 3.3 | D61: 0.001
A62: 41091 | B62: 48.9 | C62: =B62-B61 -> -4.1
A63: 41122 | B63: 48.1 | C63: =B63-B62 -> -0.8
A64: 41153 | B64: 52.8 | C64: =B64-B63 -> 4.7 | D64: 0.006
A65: 41183 | B65: 50.4 | C65: =B65-B64 -> -2.4
A66: 41214 | B66: 52.5 | C66: =B66-B65 -> 2.1
A67: 41244 | B67: 53.2 | C67: =B67-B66 -> 0.7 | D67: 0.009
A68: 41275 | B68: 54.5 | C68: =B68-B67 -> 1.3
A69: 41306 | B69: 52.1 | C69: =B69-B68 -> -2.4
A70: 41334 | B70: 50.3 | C70: =B70-B69 -> -1.8 | D70: 0
A71: 41365 | B71: 51 | C71: =B71-B70 -> 0.7
A72: 41395 | B72: 51 | C72: =B72-B71 -> 0
A73: 41426 | B73: 50.3 | C73: =B73-B72 -> -0.7 | D73: 0.018
A74: 41456 | B74: 49.7 | C74: =B74-B73 -> -0.6
A75: 41487 | B75: 50.7 | C75: =B75-B74 -> 1
A76: 41518 | B76: 52.1 | C76: =B76-B75 -> 1.4 | D76: -0.005
A77: 41548 | B77: 52.3 | C77: =B77-B76 -> 0.2
A78: 41579 | B78: 51.7 | C78: =B78-B77 -> -0.6
A79: 41609 | B79: 50.5 | C79: =B79-B78 -> -1.2 | D79: 0.007
A80: 41640 | B80: 49.6 | C80: =B80-B79 -> -0.9
A81: 41671 | B81: 50.8 | C81: =B81-B80 -> 1.2
A82: 41699 | B82: 51 | C82: =B82-B81 -> 0.2 | D82: 0.002
A83: 41730 | B83: 48.6 | C83: =B83-B82 -> -2.4
A84: 41760 | B84: 50.6 | C84: =B84-B83 -> 2
A85: 41791 | B85: 51.4 | C85: =B85-B84 -> 0.8 | D85: -0.006 | H85: BR | I85: Brazil
A86: 41821 | B86: 50.2 | C86: =B86-B85 -> -1.2
A87: 41852 | B87: 49.2 | C87: =B87-B86 -> -1
A88: 41883 | B88: 51.2 | C88: =IFERROR(B88-B87,"") -> 2 | D88: =IF(VLOOKUP(I85,Data!$A$30:$H$150,7,FALSE)=A87,VLOOKUP(I85,Data!$A$30:$H$150,2,FALSE)/100,#N/A) -> 0.001
A89: 41913 | B89: 48.2 | C89: -3
A90: 41944 | B90: =IF(A90=Data!$C$1,VLOOKUP($H$85,Data!$A$2:$C$36,3,FALSE),"N/A") -> N/A | C90: =IFERROR(B90-B89,"")
A91: 41974 | B91: TBR | C91: =IFERROR(B91-B90,"")
A92: 42005 | B92: TBR | C92: =IFERROR(B92-B91,"")
A93: 42036 | B93: TBR | C93: =IFERROR(B93-B92,"")
A94: 42064 | B94: TBR | C94: =IFERROR(B94-B93,"")
A95: 42095 | B95: TBR | C95: =IFERROR(B95-B94,"")
A96: 42125 | B96: TBR | C96: =IFERROR(B96-B95,"")
A97: 42156 | B97: TBR | C97: =IFERROR(B97-B96,"")
A98: 42186 | B98: TBR | C98: =IFERROR(B98-B97,"")
A99: 42217 | B99: TBR | C99: =IFERROR(B99-B98,"")
A100: 42248 | B100: TBR | C100: =IFERROR(B100-B99,"")
A101: 42278 | B101: TBR | C101: =IFERROR(B101-B100,"")
A102: 42309 | B102: TBR | C102: =IFERROR(B102-B101,"")
... A227: 46113 | B227: TBR | C227: =IFERROR(B227-B226,"")
A228: 46143 | B228: 50.4 | C228: =IFERROR(B228-B227,"")

Sheet IN
A40: Date | B40: India Service PMI | C40: Change | D40: India GDP Growth q/q
A41: 40452 | B41: 58.4
A42: 40483 | B42: 61.3 | C42: =B42-B41 -> 2.9
A43: 40513 | B43: 62.1 | C43: =B43-B42 -> 0.8 | D43: 0.023
A44: 40544 | B44: 59.4 | C44: =B44-B43 -> -2.7
A45: 40575 | B45: 61 | C45: =B45-B44 -> 1.6
A46: 40603 | B46: 60 | C46: =B46-B45 -> -1 | D46: 0.019
A47: 40634 | B47: 59.2 | C47: =B47-B46 -> -0.8
A48: 40664 | B48: 57.7 | C48: =B48-B47 -> -1.5
A49: 40695 | B49: 56.1 | C49: =B49-B48 -> -1.6 | D49: 0.016
A50: 40725 | B50: 58.2 | C50: =B50-B49 -> 2.1
A51: 40756 | B51: 56.7 | C51: =B51-B50 -> -1.5
A52: 40787 | B52: 49.8 | C52: =B52-B51 -> -6.9 | D52: 0.011
A53: 40817 | B53: 49.1 | C53: =B53-B52 -> -0.7
A54: 40848 | B54: 53.2 | C54: =B54-B53 -> 4.1
A55: 40878 | B55: 54.2 | C55: =B55-B54 -> 1 | D55: 0.011
A56: 40909 | B56: 55.1 | C56: =B56-B55 -> 0.9
A57: 40940 | B57: 53.4 | C57: =B57-B56 -> -1.7
A58: 40969 | B58: 54.1 | C58: =B58-B57 -> 0.7 | D58: 0.013
A59: 41000 | B59: 52.3 | C59: =B59-B58 -> -1.8
A60: 41030 | B60: 52.8 | C60: =B60-B59 -> 0.5
A61: 41061 | B61: 54.7 | C61: =B61-B60 -> 1.9 | D61: 0.014
A62: 41091 | B62: 54.3 | C62: =B62-B61 -> -0.4
A63: 41122 | B63: 54.2 | C63: =B63-B62 -> -0.1
A64: 41153 | B64: 55 | C64: =B64-B63 -> 0.8 | D64: 0.007
A65: 41183 | B65: 55.8 | C65: =B65-B64 -> 0.8
A66: 41214 | B66: 53.8 | C66: =B66-B65 -> -2
A67: 41244 | B67: 52.1 | C67: =B67-B66 -> -1.7 | D67: 0.015
A68: 41275 | B68: 57.5 | C68: =B68-B67 -> 5.4
A69: 41306 | B69: 54.2 | C69: =B69-B68 -> -3.3
A70: 41334 | B70: 51.4 | C70: =B70-B69 -> -2.8 | D70: 0.01
A71: 41365 | B71: 50.7 | C71: =B71-B70 -> -0.7
A72: 41395 | B72: 53.6 | C72: =B72-B71 -> 2.9
A73: 41426 | B73: 51.7 | C73: =B73-B72 -> -1.9 | D73: 0.007
A74: 41456 | B74: 47.9 | C74: =B74-B73 -> -3.8
A75: 41487 | B75: 47.6 | C75: =B75-B74 -> -0.3
A76: 41518 | B76: 44.6 | C76: =B76-B75 -> -3 | D76: 0.018
A77: 41548 | B77: 47.1 | C77: =B77-B76 -> 2.5
A78: 41579 | B78: 47.2 | C78: =B78-B77 -> 0.1
A79: 41609 | B79: 47.9 | C79: =B79-B78 -> 0.7 | D79: 0.01
A80: 41640 | B80: 48.3 | C80: =B80-B79 -> 0.4
A81: 41671 | B81: 48.8 | C81: =B81-B80 -> 0.5
A82: 41699 | B82: 47.5 | C82: =B82-B81 -> -1.3 | D82: 0.021
A83: 41730 | B83: 48.5 | C83: =B83-B82 -> 1
A84: 41760 | B84: 50.7 | C84: =B84-B83 -> 2.2
A85: 41791 | B85: 54.4 | C85: =B85-B84 -> 3.7 | D85: 0.0249 | H85: IN | I85: India
A86: 41821 | B86: 52.2 | C86: =B86-B85 -> -2.2
A87: 41852 | B87: 50.6 | C87: =B87-B86 -> -1.6
A88: 41883 | B88: 51.6 | C88: =IFERROR(B88-B87,"") -> 1 | D88: =IF(VLOOKUP(I85,Data!$A$30:$H$150,7,FALSE)=A87,VLOOKUP(I85,Data!$A$30:$H$150,2,FALSE)/100,#N/A) -> #N/A
A89: 41913 | B89: 50 | C89: -1.6
A90: 41944 | B90: =IF(A90=Data!$C$1,VLOOKUP($H$85,Data!$A$2:$C$36,3,FALSE),"N/A") -> N/A | C90: =IFERROR(B90-B89,"")
A91: 41974 | B91: TBR | C91: =IFERROR(B91-B90,"")
A92: 42005 | B92: TBR | C92: =IFERROR(B92-B91,"")
A93: 42036 | B93: TBR | C93: =IFERROR(B93-B92,"")
A94: 42064 | B94: TBR | C94: =IFERROR(B94-B93,"")
A95: 42095 | B95: TBR | C95: =IFERROR(B95-B94,"")
A96: 42125 | B96: TBR | C96: =IFERROR(B96-B95,"")
A97: 42156 | B97: TBR | C97: =IFERROR(B97-B96,"")
A98: 42186 | B98: TBR | C98: =IFERROR(B98-B97,"")
A99: 42217 | B99: TBR | C99: =IFERROR(B99-B98,"")
A100: 42248 | B100: TBR | C100: =IFERROR(B100-B99,"")
A101: 42278 | B101: TBR | C101: =IFERROR(B101-B100,"")
A102: 42309 | B102: TBR | C102: =IFERROR(B102-B101,"")
... A227: 46113 | B227: TBR | C227: =IFERROR(B227-B226,"")
A228: 46143 | B228: 59.8 | C228: =IFERROR(B228-B227,"")

Sheet RS
A40: Date | B40: Russia Service PMI | C40: Change | D40: Russian GDP Growth q/q
A41: 40452 | B41: 54.7
A42: 40483 | B42: 54.1 | C42: =B42-B41 -> -0.6
A43: 40513 | B43: 53.4 | C43: =B43-B42 -> -0.7 | D43: 0.01
A44: 40544 | B44: 52.4 | C44: =B44-B43 -> -1
A45: 40575 | B45: 53.4 | C45: =B45-B44 -> 1
A46: 40603 | B46: 53.3 | C46: =B46-B45 -> -0.1 | D46: 0.009
A47: 40634 | B47: 55.8 | C47: =B47-B46 -> 2.5
A48: 40664 | B48: 57.6 | C48: =B48-B47 -> 1.8
A49: 40695 | B49: 55.1 | C49: =B49-B48 -> -2.5 | D49: 0.013
A50: 40725 | B50: 56.9 | C50: =B50-B49 -> 1.8
A51: 40756 | B51: 55.1 | C51: =B51-B50 -> -1.8
A52: 40787 | B52: 53.3 | C52: =B52-B51 -> -1.8 | D52: 0.014
A53: 40817 | B53: 53.5 | C53: =B53-B52 -> 0.2
A54: 40848 | B54: 54.8 | C54: =B54-B53 -> 1.3
A55: 40878 | B55: 53.8 | C55: =B55-B54 -> -1 | D55: 0.015
A56: 40909 | B56: 56.5 | C56: =B56-B55 -> 2.7
A57: 40940 | B57: 55.3 | C57: =B57-B56 -> -1.2
A58: 40969 | B58: 54.4 | C58: =B58-B57 -> -0.9 | D58: 0.008
A59: 41000 | B59: 52.6 | C59: =B59-B58 -> -1.8
A60: 41030 | B60: 54.9 | C60: =B60-B59 -> 2.3
A61: 41061 | B61: 53.2 | C61: =B61-B60 -> -1.7 | D61: 0.006
A62: 41091 | B62: 52 | C62: =B62-B61 -> -1.2
A63: 41122 | B63: 52.6 | C63: =B63-B62 -> 0.6
A64: 41153 | B64: 54.5 | C64: =B64-B63 -> 1.9 | D64: 0.003
A65: 41183 | B65: 57.3 | C65: =B65-B64 -> 2.8
A66: 41214 | B66: 57.1 | C66: =B66-B65 -> -0.2
A67: 41244 | B67: 56.1 | C67: =B67-B66 -> -1 | D67: -0.001
A68: 41275 | B68: 55.7 | C68: =B68-B67 -> -0.4
A69: 41306 | B69: 56.1 | C69: =B69-B68 -> 0.4
A70: 41334 | B70: 54.6 | C70: =B70-B69 -> -1.5 | D70: 0.002
A71: 41365 | B71: 53 | C71: =B71-B70 -> -1.6
A72: 41395 | B72: 51.4 | C72: =B72-B71 -> -1.6
A73: 41426 | B73: 48.8 | C73: =B73-B72 -> -2.6 | D73: 0.004
A74: 41456 | B74: 48.7 | C74: =B74-B73 -> -0.1
A75: 41487 | B75: 51.8 | C75: =B75-B74 -> 3.1
A76: 41518 | B76: 51.5 | C76: =B76-B75 -> -0.3 | D76: 0.006
A77: 41548 | B77: 52.5 | C77: =B77-B76 -> 1
A78: 41579 | B78: 52.9 | C78: =B78-B77 -> 0.4
A79: 41609 | B79: 51.4 | C79: =B79-B78 -> -1.5 | D79: 0.009
A80: 41640 | B80: 50.2 | C80: =B80-B79 -> -1.2
A81: 41671 | B81: 50.8 | C81: =B81-B80 -> 0.6
A82: 41699 | B82: 47.7 | C82: =B82-B81 -> -3.1 | D82: -0.005
A83: 41730 | B83: 46.8 | C83: =B83-B82 -> -0.9
A84: 41760 | B84: 46.1 | C84: =B84-B83 -> -0.7
A85: 41791 | B85: 49.8 | C85: =B85-B84 -> 3.7 | D85: 0.0025 | H85: RS | I85: Russia
A86: 41821 | B86: 49.7 | C86: =B86-B85 -> -0.1
A87: 41852 | B87: 50.3 | C87: =B87-B86 -> 0.6
A88: 41883 | B88: 50.5 | C88: =IFERROR(B88-B87,"") -> 0.2 | D88: =IF(VLOOKUP(I85,Data!$A$30:$H$150,7,FALSE)=A87,VLOOKUP(I85,Data!$A$30:$H$150,2,FALSE)/100,#N/A) -> #N/A
A89: 41913 | B89: 47.4 | C89: =IFERROR(B89-B88,"") -> -3.1
A90: 41944 | B90: 44.5 | C90: =IFERROR(B90-B89,"") -> -2.9
A91: 41974 | B91: TBR | C91: =IFERROR(B91-B90,"")
A92: 42005 | B92: TBR | C92: =IFERROR(B92-B91,"")
A93: 42036 | B93: TBR | C93: =IFERROR(B93-B92,"")
A94: 42064 | B94: TBR | C94: =IFERROR(B94-B93,"")
A95: 42095 | B95: TBR | C95: =IFERROR(B95-B94,"")
A96: 42125 | B96: TBR | C96: =IFERROR(B96-B95,"")
A97: 42156 | B97: TBR | C97: =IFERROR(B97-B96,"")
A98: 42186 | B98: TBR | C98: =IFERROR(B98-B97,"")
A99: 42217 | B99: TBR | C99: =IFERROR(B99-B98,"")
A100: 42248 | B100: TBR | C100: =IFERROR(B100-B99,"")
A101: 42278 | B101: TBR | C101: =IFERROR(B101-B100,"")
A102: 42309 | B102: TBR | C102: =IFERROR(B102-B101,"")
... A227: 46113 | B227: TBR | C227: =IFERROR(B227-B226,"")
A228: 46143 | B228: 48.7 | C228: =IFERROR(B228-B227,"")

Sheet All
A1: Date | B1: Global | C1: US | D1: China | E1: EA | F1: Japan | G1: Germany | H1: France | I1: UK | J1: Italy | K1: Spain | L1: Brazil | M1: Russia | N1: India | O1: Australia | P1: Ireland
A2: 41091 | B2: =Global!B62 -> 49.2 | C2: =US!B63 -> No data | D2: =CH!B62 -> 53.1 | E2: =EZ!B62 -> 47.9 | F2: =JP!B62 -> 48.7 | G2: =DE!B62 -> 50.3 | H2: =FR!B62 -> 50 | I2: =UK!B62 -> 51.3 | J2: =IT!B62 -> 43 | K2: =ES!B62 -> 43.7 | L2: =BR!B62 -> 48.9 | M2: =RS!B62 -> 52 | N2: =IN!B62 -> 54.3 | O2: =AU!B62 -> 46.5 | P2: =IR!B62 -> 49.1
A3: 41122 | B3: =Global!B63 -> 52.4 | C3: =US!B64 -> No data | D3: =CH!B63 -> 52 | E3: =EZ!B63 -> 47.2 | F3: =JP!B63 -> 47.5 | G3: =DE!B63 -> 48.3 | H3: =FR!B63 -> 49.2 | I3: =UK!B63 -> 51 | J3: =IT!B63 -> 44 | K3: =ES!B63 -> 44 | L3: =BR!B63 -> 48.1 | M3: =RS!B63 -> 52.6 | N3: =IN!B63 -> 54.2 | O3: =AU!B63 -> 42.4 | P3: =IR!B63 -> 51.7
A4: 41153 | B4: =Global!B64 -> 53.1 | C4: =US!B65 -> No data | D4: =CH!B64 -> 54.3 | E4: =EZ!B64 -> 46.1 | F4: =JP!B64 -> 48.8 | G4: =DE!B64 -> 49.7 | H4: =FR!B64 -> 45 | I4: =UK!B64 -> 53.7 | J4: =IT!B64 -> 44.5 | K4: =ES!B64 -> 40.2 | L4: =BR!B64 -> 52.8 | M4: =RS!B64 -> 54.5 | N4: =IN!B64 -> 55 | O4: =AU!B64 -> 41.9 | P4: =IR!B64 -> 53.9
A5: 41183 | B5: =Global!B65 -> 53.6 | C5: =US!B66 -> No data | D5: =CH!B65 -> 53.5 | E5: =EZ!B65 -> 46 | F5: =JP!B65 -> 49.7 | G5: =DE!B65 -> 48.4 | H5: =FR!B65 -> 44.6 | I5: =UK!B65 -> 52.2 | J5: =IT!B65 -> 46 | K5: =ES!B65 -> 41.2 | L5: =BR!B65 -> 50.4 | M5: =RS!B65 -> 57.3 | N5: =IN!B65 -> 55.8 | O5: =AU!B65 -> 42.8 | P5: =IR!B65 -> 56.1
A6: 41214 | B6: =Global!B66 -> 54.8 | C6: =US!B67 -> No data | D6: =CH!B66 -> 52.1 | E6: =EZ!B66 -> 46.7 | F6: =JP!B66 -> 49.1 | G6: =DE!B66 -> 49.7 | H6: =FR!B66 -> 45.8 | I6: =UK!B66 -> 50.6 | J6: =IT!B66 -> 44.6 | K6: =ES!B66 -> 42.4 | L6: =BR!B66 -> 52.5 | M6: =RS!B66 -> 57.1 | N6: =IN!B66 -> 53.8 | O6: =AU!B66 -> 47.1 | P6: =IR!B66 -> 56.1
A7: 41244 | B7: =Global!B67 -> 54.8 | C7: =US!B68 -> No data | D7: =CH!B67 -> 53.5 | E7: =EZ!B67 -> 47.2 | F7: =JP!B67 -> 50.1 | G7: =DE!B67 -> 55.7 | H7: =FR!B67 -> 44.1 | I7: =UK!B67 -> 50.2 | J7: =IT!B67 -> 43.1 | K7: =ES!B67 -> 44.1 | L7: =BR!B67 -> 53.2 | M7: =RS!B67 -> 56.1 | N7: =IN!B67 -> 52.1 | O7: =AU!B67 -> 46.3 | P7: =IR!B67 -> 56.5
A8: 41275 | B8: =Global!B68 -> 53.6 | C8: =US!B69 -> No data | D8: =CH!B68 -> 54 | E8: =EZ!B68 -> 48.6 | F8: =JP!B68 -> 50.4 | G8: =DE!B68 -> 54.7 | H8: =FR!B68 -> 43.6 | I8: =UK!B68 -> 51.5 | J8: =IT!B68 -> 43.9 | K8: =ES!B68 -> 47 | L8: =BR!B68 -> 54.5 | M8: =RS!B68 -> 55.7 | N8: =IN!B68 -> 57.5 | O8: =AU!B68 -> 45.4 | P8: =IR!B68 -> 56.8
A9: 41306 | B9: =Global!B69 -> 53.2 | C9: =US!B70 -> No data | D9: =CH!B69 -> 52.1 | E9: =EZ!B69 -> 47.9 | F9: =JP!B69 -> 51.3 | G9: =DE!B69 -> 50.9 | H9: =FR!B69 -> 43.7 | I9: =UK!B69 -> 51.8 | J9: =IT!B69 -> 43.6 | K9: =ES!B69 -> 44.7 | L9: =BR!B69 -> 52.1 | M9: =RS!B69 -> 56.1 | N9: =IN!B69 -> 54.2 | O9: =AU!B69 -> 48.5 | P9: =IR!B69 -> 53.6
A10: 41334 | B10: =Global!B70 -> 53.4 | C10: =US!B71 -> No data | D10: =CH!B70 -> 54.3 | E10: =EZ!B70 -> 46.4 | F10: =JP!B70 -> 53.4 | G10: =DE!B70 -> 49.6 | H10: =FR!B70 -> 41.3 | I10: =UK!B70 -> 52.4 | J10: =IT!B70 -> 45.5 | K10: =ES!B70 -> 45.3 | L10: =BR!B70 -> 50.3 | M10: =RS!B70 -> 54.6 | N10: =IN!B70 -> 51.4 | O10: =AU!B70 -> 49.6 | P10: =IR!B70 -> 52.3
A11: 41365 | B11: =Global!B71 -> 52.1 | C11: =US!B72 -> No data | D11: =CH!B71 -> 51.1 | E11: =EZ!B71 -> 47 | F11: =JP!B71 -> 52.5 | G11: =DE!B71 -> 49.7 | H11: =FR!B71 -> 44.3 | I11: =UK!B71 -> 52.9 | J11: =IT!B71 -> 47 | K11: =ES!B71 -> 44.4 | L11: =BR!B71 -> 51 | M11: =RS!B71 -> 53 | N11: =IN!B71 -> 50.7 | O11: =AU!B71 -> 44.1 | P11: =IR!B71 -> 55.2
A12: 41395 | B12: =Global!B72 -> 53.7 | C12: =US!B73 -> No data | D12: =CH!B72 -> 51.2 | E12: =EZ!B72 -> 47.2 | F12: =JP!B72 -> 54.8 | G12: =DE!B72 -> 50.4 | H12: =FR!B72 -> 44.3 | I12: =UK!B72 -> 54.9 | J12: =IT!B72 -> 46.5 | K12: =ES!B72 -> 47.3 | L12: =BR!B72 -> 51 | M12: =RS!B72 -> 51.4 | N12: =IN!B72 -> 53.6 | O12: =AU!B72 -> 40.6 | P12: =IR!B72 -> 52.7
A13: 41426 | B13: =Global!B73 -> 51.3 | C13: =US!B74 -> No data | D13: =CH!B73 -> 51.3 | E13: =EZ!B73 -> 48.3 | F13: =JP!B73 -> 52.1 | G13: =DE!B73 -> 51.3 | H13: =FR!B73 -> 47.2 | I13: =UK!B73 -> 56.9 | J13: =IT!B73 -> 45.8 | K13: =ES!B73 -> 47.8 | L13: =BR!B73 -> 50.3 | M13: =RS!B73 -> 48.8 | N13: =IN!B73 -> 51.7 | O13: =AU!B73 -> 41.5 | P13: =IR!B73 -> 61.6
... A29: 41913 | B29: =Global!B89 -> 53.7 | C29: =US!B90 -> 57.1 | D29: =CH!B89 -> 52.9 | E29: =EZ!B89 -> 52.3 | F29: =JP!B89 -> 48.7 | G29: =DE!B89 -> 54.4 | H29: =FR!B89 -> 48.3 | I29: =UK!B89 -> 56.2 | J29: =IT!B89 -> 50.8 | K29: =ES!B89 -> 55.9 | L29: =BR!B89 -> 48.2 | M29: =RS!B89 -> 47.4 | N29: =IN!B89 -> 50 | O29: =AU!B89 -> 43.6 | P29: =IR!B89 -> 61.5
A30: 41944 | B30: =Global!B90 -> 53.5 | C30: =US!#REF! -> #REF! | D30: =CH!B90 -> N/A | E30: =EZ!B90 -> N/A | F30: =JP!B90 -> N/A | G30: =DE!B90 -> N/A | H30: =FR!B90 -> N/A | I30: =UK!B90 -> 58.6 | J30: =IT!B90 -> N/A | K30: =ES!B90 -> N/A | L30: =BR!B90 -> N/A | M30: =RS!B90 -> 44.5 | N30: =IN!B90 -> N/A | O30: =AU!B90 -> N/A | P30: =IR!B90 -> N/A
A31: 41974 | B31: =Global!B91 -> TBR | C31: =US!#REF! -> #REF! | D31: =CH!B91 -> TBR | E31: =EZ!B91 -> TBR | F31: =JP!B91 -> TBR | G31: =DE!B91 -> TBR | H31: =FR!B91 -> TBR | I31: =UK!#REF! -> #REF! | J31: =IT!B91 -> TBR | K31: =ES!B91 -> TBR | L31: =BR!B91 -> TBR | M31: =RS!B91 -> TBR | N31: =IN!B91 -> TBR | O31: =AU!B91 -> TBR | P31: =IR!B91 -> TBR
A32: 42005 | B32: =Global!B92 -> TBR | C32: =US!B228 -> 56.7 | D32: =CH!B92 -> TBR | E32: =EZ!B92 -> TBR | F32: =JP!B92 -> TBR | G32: =DE!B92 -> TBR | H32: =FR!B92 -> TBR | I32: =UK!B91 -> 57.2 | J32: =IT!B92 -> TBR | K32: =ES!B92 -> TBR | L32: =BR!B92 -> TBR | M32: =RS!B92 -> TBR | N32: =IN!B92 -> TBR | O32: =AU!B92 -> TBR | P32: =IR!B92 -> TBR
A33: 42036 | B33: =Global!B93 -> TBR | C33: =US!B229 -> 56.7 | D33: =CH!B93 -> TBR | E33: =EZ!B93 -> TBR | F33: =JP!B93 -> TBR | G33: =DE!B93 -> TBR | H33: =FR!B93 -> TBR | I33: =UK!B92 -> 56.7 | J33: =IT!B93 -> TBR | K33: =ES!B93 -> TBR | L33: =BR!B93 -> TBR | M33: =RS!B93 -> TBR | N33: =IN!B93 -> TBR | O33: =AU!B93 -> TBR | P33: =IR!B93 -> TBR
A34: 42064 | B34: =Global!B94 -> TBR | C34: =US!B230 -> 56.7 | D34: =CH!B94 -> TBR | E34: =EZ!B94 -> TBR | F34: =JP!B94 -> TBR | G34: =DE!B94 -> TBR | H34: =FR!B94 -> TBR | I34: =UK!B93 -> 58.9 | J34: =IT!B94 -> TBR | K34: =ES!B94 -> TBR | L34: =BR!B94 -> TBR | M34: =RS!B94 -> TBR | N34: =IN!B94 -> TBR | O34: =AU!B94 -> TBR | P34: =IR!B94 -> TBR
A35: 42095 | B35: =Global!B95 -> TBR | C35: =US!B231 -> 57.5 | D35: =CH!B95 -> TBR | E35: =EZ!B95 -> TBR | F35: =JP!B95 -> TBR | G35: =DE!B95 -> TBR | H35: =FR!B95 -> TBR | I35: =UK!B94 -> 59.5 | J35: =IT!B95 -> TBR | K35: =ES!B95 -> TBR | L35: =BR!B95 -> TBR | M35: =RS!B95 -> TBR | N35: =IN!B95 -> TBR | O35: =AU!B95 -> TBR | P35: =IR!B95 -> TBR
A36: 42125 | B36: =Global!B96 -> TBR | C36: =US!B232 -> 55.9 | D36: =CH!B96 -> TBR | E36: =EZ!B96 -> TBR | F36: =JP!B96 -> TBR | G36: =DE!B96 -> TBR | H36: =FR!B96 -> TBR | I36: =UK!B95 -> 56.5 | J36: =IT!B96 -> TBR | K36: =ES!B96 -> TBR | L36: =BR!B96 -> TBR | M36: =RS!B96 -> TBR | N36: =IN!B96 -> TBR | O36: =AU!B96 -> TBR | P36: =IR!B96 -> TBR
A37: 42156 | B37: =Global!B97 -> TBR | C37: =US!B233 -> 56.2 | D37: =CH!B97 -> TBR | E37: =EZ!B97 -> TBR | F37: =JP!B97 -> TBR | G37: =DE!B97 -> TBR | H37: =FR!B97 -> TBR | I37: =UK!B96 -> 58.5 | J37: =IT!B97 -> TBR | K37: =ES!B97 -> TBR | L37: =BR!B97 -> TBR | M37: =RS!B97 -> TBR | N37: =IN!B97 -> TBR | O37: =AU!B97 -> TBR | P37: =IR!B97 -> TBR
A38: 42186 | B38: =Global!B98 -> TBR | C38: =US!B234 -> 59.6 | D38: =CH!B98 -> TBR | E38: =EZ!B98 -> TBR | F38: =JP!B98 -> TBR | G38: =DE!B98 -> TBR | H38: =FR!B98 -> TBR | I38: =UK!B97 -> 57.4 | J38: =IT!B98 -> TBR | K38: =ES!B98 -> TBR | L38: =BR!B98 -> TBR | M38: =RS!B98 -> TBR | N38: =IN!B98 -> TBR | O38: =AU!B98 -> TBR | P38: =IR!B98 -> TBR
A39: 42217 | B39: =Global!B99 -> TBR | C39: =US!B235 -> 59.6 | D39: =CH!B99 -> TBR | E39: =EZ!B99 -> TBR | F39: =JP!B99 -> TBR | G39: =DE!B99 -> TBR | H39: =FR!B99 -> TBR | I39: =UK!B98 -> 55.6 | J39: =IT!B99 -> TBR | K39: =ES!B99 -> TBR | L39: =BR!B99 -> TBR | M39: =RS!B99 -> TBR | N39: =IN!B99 -> TBR | O39: =AU!B99 -> TBR | P39: =IR!B99 -> TBR
A40: 42248 | B40: =Global!B100 -> TBR | C40: =US!B236 -> 56.7 | D40: =CH!B100 -> TBR | E40: =EZ!B100 -> TBR | F40: =JP!B100 -> TBR | G40: =DE!B100 -> TBR | H40: =FR!B100 -> TBR | I40: =UK!B99 -> 53.3 | J40: =IT!B100 -> TBR | K40: =ES!B100 -> TBR | L40: =BR!B100 -> TBR | M40: =RS!B100 -> TBR | N40: =IN!B100 -> TBR | O40: =AU!B100 -> TBR | P40: =IR!B100 -> TBR
A41: 42278 | B41: =Global!B101 -> TBR | C41: =US!B237 -> 58.3 | D41: =CH!B101 -> TBR | E41: =EZ!B101 -> TBR | F41: =JP!B101 -> TBR | G41: =DE!B101 -> TBR | H41: =FR!B101 -> TBR | I41: =UK!B100 -> 54.9 | J41: =IT!B101 -> TBR | K41: =ES!B101 -> TBR | L41: =BR!B101 -> TBR | M41: =RS!B101 -> TBR | N41: =IN!B101 -> TBR | O41: =AU!B101 -> TBR | P41: =IR!B101 -> TBR
A42: 42309 | B42: =Global!B102 -> TBR | C42: =US!B238 -> 58.3 | D42: =CH!B102 -> TBR | E42: =EZ!B102 -> TBR | F42: =JP!B102 -> TBR | G42: =DE!B102 -> TBR | H42: =FR!B102 -> TBR | I42: =UK!B101 -> 55.9 | J42: =IT!B102 -> TBR | K42: =ES!B102 -> TBR | L42: =BR!B102 -> TBR | M42: =RS!B102 -> TBR | N42: =IN!B102 -> TBR | O42: =AU!B102 -> TBR | P42: =IR!B102 -> TBR
A43: 42339 | B43: =Global!B103 -> TBR | C43: =US!B239 -> 55.8 | D43: =CH!B103 -> TBR | E43: =EZ!B103 -> TBR | F43: =JP!B103 -> TBR | G43: =DE!B103 -> TBR | H43: =FR!B103 -> TBR | I43: =UK!B102 -> 55.5 | J43: =IT!B103 -> TBR | K43: =ES!B103 -> TBR | L43: =BR!B103 -> TBR | M43: =RS!B103 -> TBR | N43: =IN!B103 -> TBR | O43: =AU!B103 -> TBR | P43: =IR!B103 -> TBR
... A168: 46143 | B168: =Global!B228 -> TBR | C168: =US!B364 -> 50.7 | D168: =CH!B228 -> TBR | E168: =EZ!B228 -> 47.7 | F168: =JP!B228 -> 50 | G168: =DE!B228 -> TBR | H168: =FR!B228 -> TBR | I168: =UK!B227 -> 49.3 | J168: =IT!B228 -> TBR | K168: =ES!B228 -> TBR | L168: =BR!B228 -> 50.4 | M168: =RS!B228 -> 48.7 | N168: =IN!B228 -> 59.8 | O168: =AU!B228 -> TBR | P168: =IR!B228 -> TBR

Sheet Din
F3: ="Service PMI "&G4&" 2014 " -> Service PMI Nov 2014 | K3: ="Service PMI "&L4&" 2014 " -> Service PMI Nov 2014
F4: Country | G4: Nov | H4: Oct | I4: Change | K4: Country | L4: Nov | M4: Oct | N4: Change
F5: Ireland | G5: =Tabs!AH28 -> TBR | H5: =Tabs!AH27 -> TBR | I5: =G5-H5 -> #VALUE! | K5: India | L5: 52.6 | M5: 50 | N5: 2.6
F6: UK | G6: =Tabs!J28 -> 49.3 | H6: =Tabs!J27 -> 52.7 | I6: =G6-H6 -> -3.4 | K6: UK | L6: 58.6 | M6: 56.2 | N6: 2.4
F7: US | G7: =Tabs!F28 -> 50.7 | H7: =Tabs!F27 -> 51 | I7: =G7-H7 -> -0.3 | K7: Japan | L7: 50.6 | M7: 48.7 | N7: 1.9
F8: Global | G8: =Tabs!B28 -> TBR | H8: =Tabs!B27 -> TBR | I8: =G8-H8 -> #VALUE! | K8: Italy | L8: 51.8 | M8: 50.8 | N8: 1
F9: China | G9: =Tabs!AX28 -> TBR | H9: =Tabs!AX27 -> TBR | I9: =G9-H9 -> #VALUE! | K9: Brazil | L9: 48.5 | M9: 48.2 | N9: 0.3
F10: Spain | G10: =Tabs!AD28 -> TBR | H10: =Tabs!AD27 -> TBR | I10: =G10-H10 -> #VALUE! | K10: Australia | L10: 43.8 | M10: 43.6 | N10: 0.2
F11: India | G11: =Tabs!BB28 -> 59.8 | H11: =Tabs!BB27 -> TBR | I11: =G11-H11 -> #VALUE! | K11: Ireland | L11: 61.6 | M11: 61.5 | N11: 0.1
F12: Germany | G12: =Tabs!R28 -> TBR | H12: =Tabs!R27 -> TBR | I12: =G12-H12 -> #VALUE! | K12: China | L12: 53 | M12: 52.9 | N12: 0.1
F13: Italy | G13: =Tabs!Z28 -> TBR | H13: =Tabs!Z27 -> TBR | I13: =G13-H13 -> #VALUE! | K13: Global | L13: 53.5 | M13: 53.7 | N13: -0.2
F14: EA | G14: =Tabs!N28 -> 47.7 | H14: =Tabs!N27 -> 47.6 | I14: =G14-H14 -> 0.1 | K14: France | L14: 47.9 | M14: 48.3 | N14: -0.4
F15: Japan | G15: =Tabs!AP28 -> 50 | H15: =Tabs!AP27 -> TBR | I15: =G15-H15 -> #VALUE! | K15: US | L15: 56.2 | M15: 57.1 | N15: -0.9
F16: Brazil | G16: =Tabs!AT28 -> 50.4 | H16: =Tabs!AT27 -> TBR | I16: =G16-H16 -> #VALUE! | K16: EA | L16: 51.1 | M16: 52.3 | N16: -1.2
F17: France | G17: =Tabs!V28 -> TBR | H17: =Tabs!V27 -> TBR | I17: =G17-H17 -> #VALUE! | K17: Germany | L17: 52.1 | M17: 54.4 | N17: -2.3
F18: Russia | G18: =Tabs!BF28 -> 48.7 | H18: =Tabs!BF27 -> TBR | I18: =G18-H18 -> #VALUE! | K18: Russia | L18: 44.5 | M18: 47.4 | N18: -2.9
F19: Australia | G19: =Tabs!AL28 -> TBR | H19: =Tabs!AL27 -> TBR | I19: =G19-H19 -> #VALUE! | K19: Spain | L19: 52.7 | M19: 55.9 | N19: -3.2

Sheet Data
C1: 46143 | F1: Last | G1: Previous | H1: Highest | I1: Lowest | J1: Unit | K1: Reference | L1: Frequency
A2: US | B2: United States | C2: =IF(VLOOKUP(B2,$E$2:$L$52,7,FALSE)=$C$1,VLOOKUP(B2,$E$2:$L$52,2,FALSE),"") | E2: Australia | F2: 43.8 | G2: 43.6 | H2: 55.2 | I2: 39 | J2: Index Points | K2: 41944 | L2: Monthly
A3: UK | B3: United Kingdom | C3: =IF(VLOOKUP(B3,$E$2:$L$52,7,FALSE)=$C$1,VLOOKUP(B3,$E$2:$L$52,2,FALSE),"") | E3: Brazil | F3: 48.5 | G3: 48.2 | H3: 57.1 | I3: 48.1 | J3: Index Points | K3: 41944 | L3: Monthly
A4: EZ | B4: Euro Area | C4: =IF(VLOOKUP(B4,$E$2:$L$52,7,FALSE)=$C$1,VLOOKUP(B4,$E$2:$L$52,2,FALSE),"") | E4: China | F4: 53 | G4: 52.9 | H4: 54.7 | I4: 50 | J4: Index Points | K4: 41944 | L4: Monthly
A5: DE | B5: Germany | C5: =IF(VLOOKUP(B5,$E$2:$L$52,7,FALSE)=$C$1,VLOOKUP(B5,$E$2:$L$52,2,FALSE),"") | E5: Euro Area | F5: 51.1 | G5: 52.3 | H5: 58.3 | I5: 39.2 | J5: Index Points | K5: 41944 | L5: Monthly
A6: FR | B6: France | C6: =IF(VLOOKUP(B6,$E$2:$L$52,7,FALSE)=$C$1,VLOOKUP(B6,$E$2:$L$52,2,FALSE),"") | E6: France | F6: 47.9 | G6: 48.3 | H6: 62.9 | I6: 40.2 | J6: Index Points | K6: 41944 | L6: Monthly
A7: IT | B7: Italy | C7: =IF(VLOOKUP(B7,$E$2:$L$52,7,FALSE)=$C$1,VLOOKUP(B7,$E$2:$L$52,2,FALSE),"") | E7: Germany | F7: 52.1 | G7: 54.4 | H7: 60.3 | I7: 41.3 | J7: Index Points | K7: 41944 | L7: Monthly
A8: ES | B8: Spain | C8: =IF(VLOOKUP(B8,$E$2:$L$52,7,FALSE)=$C$1,VLOOKUP(B8,$E$2:$L$52,2,FALSE),"") | E8: India | F8: 52.6 | G8: 50 | H8: 57.5 | I8: 44.6 | J8: Index Points | K8: 41944 | L8: Monthly
A9: IR | B9: Ireland | C9: =IF(VLOOKUP(B9,$E$2:$L$52,7,FALSE)=$C$1,VLOOKUP(B9,$E$2:$L$52,2,FALSE),"") | E9: Ireland | F9: 61.6 | G9: 61.5 | H9: 62.6 | I9: 48.3 | J9: Index Points | K9: 41944 | L9: Monthly
A10: AU | B10: Australia | C10: =IF(VLOOKUP(B10,$E$2:$L$52,7,FALSE)=$C$1,VLOOKUP(B10,$E$2:$L$52,2,FALSE),"") | E10: Italy | F10: 51.8 | G10: 50.8 | H10: 53.9 | I10: 42.3 | J10: Index Points | K10: 41944 | L10: Monthly
A11: CH | B11: China | C11: =IF(VLOOKUP(B11,$E$2:$L$52,7,FALSE)=$C$1,VLOOKUP(B11,$E$2:$L$52,2,FALSE),"") | E11: Japan | F11: 50.6 | G11: 48.7 | H11: 55.3 | I11: 46.4 | J11: Index Points | K11: 41944 | L11: Monthly
A12: JP | B12: Japan | C12: =IF(VLOOKUP(B12,$E$2:$L$52,7,FALSE)=$C$1,VLOOKUP(B12,$E$2:$L$52,2,FALSE),"") | E12: Russia | F12: 44.5 | G12: 47.4 | H12: 57.6 | I12: 46.1 | J12: Index Points | K12: 41944 | L12: Monthly
A13: BR | B13: Brazil | C13: =IF(VLOOKUP(B13,$E$2:$L$52,7,FALSE)=$C$1,VLOOKUP(B13,$E$2:$L$52,2,FALSE),"") | E13: Spain | F13: 52.7 | G13: 55.9 | H13: 58.1 | I13: 36.8 | J13: Index Points | K13: 41944 | L13: Monthly
... A15: RS | B15: Russia | C15: =IF(VLOOKUP(B15,$E$2:$L$52,7,FALSE)=$C$1,VLOOKUP(B15,$E$2:$L$52,2,FALSE),"") | E15: United Kingdom | F15: 58.6 | G15: 56.2 | H15: 62.5 | I15: 40.1 | J15: Index Points | K15: 41944 | L15: Monthly
E16: United States | F16: 56.2 | G16: 57.1 | H16: 61 | I16: 49.3 | J16: Index Points | K16: 41944 | L16: Monthly
A29: GDP Growth
B30: Last | C30: Previous | D30: Highest | E30: Lowest | F30: Unit | G30: Reference | H30: Frequency | L30: GDP | M30: GDP YoY | N30: GDP QoQ | O30: Interest rate | P30: Inflation rate | Q30: Jobless rate | R30: Gov. Budget | S30: Debt/GDP | T30: Current Account | U30: Currency | V30: Population
A31: Albania | B31: 0.38 | C31: 0.12 | D31: 6 | E31: -2.6 | F31: percent | G31: 41760 | H31: Quarterly
A32: Algeria | B32: 3.1 | C32: 2.6 | D32: 6.7 | E32: 2 | F32: percent | G32: 41244 | H32: Yearly | K32: United States | L32: 16800 | M32: 0.024 | N32: 0.039 | O32: 0.0025 | P32: 0.017 | Q32: 0.058 | R32: -0.028 | S32: 1.0153 | T32: -2.3 | U32: 119.89 | V32: 317.3
A33: Angola | B33: 7.4 | C33: 5.2 | D33: 23.2 | E33: 2.4 | F33: percent | G33: 41609 | H33: Yearly | K33: Euro Area | L33: 12750 | M33: 0.008 | N33: 0.002 | O33: 0.0005 | P33: 0.003 | Q33: 0.115 | R33: -0.029 | S33: 0.909 | T33: 2.4 | U33: 1.23 | V33: 332.88
A34: Argentina | B34: 0.9 | C34: -0.5 | D34: 5.1 | E34: -5.7 | F34: percent | G34: 41760 | H34: Quarterly | K34: China | L34: 9240 | M34: 0.073 | N34: 0.019 | O34: 0.056 | P34: 0.016 | Q34: 0.041 | R34: -0.021 | S34: 0.224 | T34: 2 | U34: 6.15 | V34: 1360.72
A35: Australia | B35: 0.3 | C35: 0.5 | D35: 4.5 | E35: -2 | F35: percent | G35: 41852 | H35: Quarterly | K35: Japan | L35: 4901 | M35: -0.012 | N35: -0.004 | O35: 0 | P35: 0.029 | Q35: 0.035 | R35: -0.076 | S35: 2.272 | T35: 0.7 | U35: 119.65 | V35: 127.22
A36: Austria | B36: -0.3 | C36: 0.1 | D36: 1.6 | E36: -1.8 | F36: percent | G36: 41852 | H36: Quarterly | K36: Germany | L36: 3635 | M36: 0.012 | N36: 0.001 | O36: 0.0005 | P36: 0.006 | Q36: 0.049 | R36: 0.001 | S36: 0.769 | T36: 7.5 | U36: 1.23 | V36: 80.52
A37: Bahrain | B37: 2.28 | C37: 0.26 | D37: 2.8 | E37: -6.6 | F37: percent | G37: 41760 | H37: Quarterly | K37: France | L37: 2735 | M37: 0.004 | N37: 0.003 | O37: 0.0005 | P37: 0.005 | Q37: 0.104 | R37: -0.041 | S37: 0.922 | T37: -1.3 | U37: 1.23 | V37: 65.8
A38: Bangladesh | B38: 6.01 | C38: 6.32 | D38: 6.71 | E38: 4.08 | F38: percent | G38: 41426 | H38: Yearly | K38: United Kingdom | L38: 2522 | M38: 0.03 | N38: 0.007 | O38: 0.005 | P38: 0.013 | Q38: 0.06 | R38: -0.058 | S38: 0.906 | T38: -4.4 | U38: 1.57 | V38: 63.9
A39: Belgium | B39: 0.3 | C39: 0.1 | D39: 15.8 | E39: -2.2 | F39: percent | G39: 41852 | H39: Quarterly | K39: Brazil | L39: 2246 | M39: -0.002 | N39: 0.001 | O39: 0.1175 | P39: 0.0659 | Q39: 0.047 | R39: 0.019 | S39: 0.568 | T39: -3.66 | U39: 2.55 | V39: 201.03
A40: Belize | B40: 9.94 | C40: -2.1 | D40: 13.45 | E40: -10.63 | F40: percent | G40: 41760 | H40: Quarterly | K40: Russia | L40: 2097 | M40: 0.007 | N40: 0.0025 | O40: 0.095 | P40: 0.083 | Q40: 0.051 | R40: -0.005 | S40: 0.1341 | T40: 1.56 | U40: 52.89 | V40: 143.7
A41: Bolivia | B41: -7.43 | C41: 9.95 | D41: 17.6 | E41: -15.7 | F41: percent | G41: 41760 | H41: Quarterly | K41: Italy | L41: 2071 | M41: -0.005 | N41: -0.001 | O41: 0.0005 | P41: 0.0019 | Q41: 0.132 | R41: -0.028 | S41: 1.326 | T41: 1 | U41: 1.23 | V41: 59.69
A42: Bosnia And Herzegovina | B42: -1.2 | C42: 1.3 | D42: 1.3 | E42: -1.6 | F42: percent | G42: 41760 | H42: Quarterly | K42: India | L42: 1877 | M42: 0.053 | N42: 0.012 | O42: 0.08 | P42: 0.0552 | Q42: 0.052 | R42: -0.045 | S42: 0.6772 | T42: -1.7 | U42: 61.85 | V42: 1233
A43: Botswana | B43: 1.6 | C43: -0.7 | D43: 13.4 | E43: -14.4 | F43: percent | G43: 41760 | H43: Quarterly | K43: Canada | L43: 1825 | M43: 0.0259 | N43: 0.007 | O43: 0.01 | P43: 0.024 | Q43: 0.065 | R43: -0.01 | S43: 0.891 | T43: -3.2 | U43: 1.13 | V43: 35.35
... A64: France | B64: 0.3 | C64: -0.1 | D64: 1.6 | E64: -1.7 | F64: percent | G64: 41852 | H64: Quarterly | K64: Colombia | L64: 378 | M64: 0.043 | N64: -0.001 | O64: 0.045 | P64: 0.0329 | Q64: 0.079 | R64: -0.0241 | S64: 0.318 | T64: -3.4 | U64: 2235.3 | V64: 47.1
A65: Germany | B65: 0.1 | C65: -0.1 | D65: 2.1 | E65: -3.7 | F65: percent | G65: 41852 | H65: Quarterly | K65: Iran | L65: 369 | M65: -0.011 | O65: 0.1415 | P65: 0.1438 | Q65: 0.095 | R65: -0.0078 | S65: 0.1063 | T65: 8.12 | U65: 24797 | V65: 77.45
A66: Ghana | B66: 3.3 | C66: 2 | D66: 7.8 | E66: -5.9 | F66: percent | G66: 41760 | H66: Quarterly | K66: South Africa | L66: 351 | M66: 0.014 | N66: 0.014 | O66: 0.0575 | P66: 0.059 | Q66: 0.254 | R66: -0.04 | S66: 0.461 | T66: -5.8 | U66: 11.12 | V66: 52.98
A67: Greece | B67: 0.7 | C67: 0.3 | D67: 3.3 | E67: -4.7 | F67: percent | G67: 41852 | H67: Quarterly | K67: Denmark | L67: 331 | M67: 0.009 | N67: 0.005 | O67: 0.002 | P67: 0.005 | Q67: 0.04 | R67: -0.008 | S67: 0.445 | T67: 7.3 | U67: 6.01 | V67: 5.62
A68: Hong Kong | B68: 1.7 | C68: -0.1 | D68: 6.3 | E68: -3.4 | F68: percent | G68: 41852 | H68: Quarterly | K68: Malaysia | L68: 312 | M68: 0.056 | N68: 0.009 | O68: 0.0325 | P68: 0.028 | Q68: 0.027 | R68: -0.039 | S68: 0.548 | T68: 4.7 | U68: 3.43 | V68: 29.95
A69: Hungary | B69: 0.5 | C69: 0.8 | D69: 2.3 | E69: -3.3 | F69: percent | G69: 41852 | H69: Quarterly | K69: Singapore | L69: 298 | M69: 0.028 | N69: 0.031 | O69: 0.0012 | P69: 0.001 | Q69: 0.019 | R69: 0.011 | S69: 1.055 | T69: 18 | U69: 1.31 | V69: 5.4
A70: Iceland | B70: -1.2 | C70: -1 | D70: 10.4 | E70: -8 | F70: percent | G70: 41760 | H70: Quarterly | K70: Israel | L70: 291 | M70: 0.0189 | N70: -0.0009 | O70: 0.0025 | P70: -0.003 | Q70: 0.057 | R70: -0.0315 | S70: 0.674 | T70: 2.47 | U70: 3.98 | V70: 8.13
A71: India | B71: 1.2 | C71: 1.9 | D71: 5.8 | E71: -1.9 | F71: percent | G71: 41760 | H71: Quarterly | K71: Chile | L71: 277 | M71: 0.008 | N71: 0.004 | O71: 0.03 | P71: 0.057 | Q71: 0.064 | R71: -0.007 | S71: 0.128 | T71: -3.4 | U71: 613.9 | V71: 17.56
A72: Indonesia | B72: 2.96 | C72: 2.49 | D72: 3.82 | E72: -3.57 | F72: percent | G72: 41852 | H72: Quarterly | K72: Hong Kong | L72: 274 | M72: 0.027 | N72: 0.017 | O72: 0.005 | P72: 0.052 | Q72: 0.033 | R72: 0.006 | S72: 0.3384 | T72: 2.1 | U72: 7.75 | V72: 7.22
A73: Ireland | B73: 1.5 | C73: 2.8 | D73: 5.5 | E73: -4.3 | F73: percent | G73: 41760 | H73: Quarterly | K73: Egypt | L73: 272 | M73: 0.037 | N73: 0.037 | O73: 0.0925 | P73: 0.118 | Q73: 0.131 | R73: -0.091 | S73: 0.871 | T73: -2.4 | U73: 7.13 | V73: 82.06
A74: Israel | B74: -0.09 | C74: 0.54 | D74: 7.4 | E74: -3.4 | F74: percent | G74: 41852 | H74: Quarterly | K74: Philippines | L74: 272 | M74: 0.053 | N74: 0.004 | O74: 0.04 | P74: 0.043 | Q74: 0.067 | R74: -0.014 | S74: 0.492 | T74: 3.5 | U74: 44.69 | V74: 97.35
A75: Italy | B75: -0.1 | C75: -0.2 | D75: 6 | E75: -3.5 | F75: percent | G75: 41852 | H75: Quarterly | K75: Finland | L75: 257 | M75: 0 | N75: 0.002 | O75: 0.0005 | P75: 0.01 | Q75: 0.083 | R75: -0.02 | S75: 0.57 | T75: -1.1 | U75: 1.23 | V75: 5.45
A76: Jamaica | B76: -0.5 | C76: -0.3 | D76: 2.2 | E76: -1.9 | F76: percent | G76: 41671 | H76: Quarterly | K76: Greece | L76: 242 | M76: 0.019 | N76: 0.007 | O76: 0.0005 | P76: -0.017 | Q76: 0.259 | R76: -0.122 | S76: 1.749 | T76: 0.7 | U76: 1.23 | V76: 11.06
A77: Japan | B77: -0.4 | C77: -1.9 | D77: 3.2 | E77: -4 | F77: percent | G77: 41852 | H77: Quarterly | K77: Pakistan | L77: 237 | M77: 0.036 | N77: 0.05 | O77: 0.095 | P77: 0.0396 | Q77: 0.06 | R77: -0.08 | S77: 0.633 | T77: -1.1 | U77: 100.79 | V77: 188.2
A78: Kazakhstan | B78: 8.6 | C78: 2.1 | D78: 8.6 | E78: -8.9 | F78: percent | G78: 40118 | H78: Quarterly | K78: Kazakhstan | L78: 224 | M78: 0.04 | N78: 0.086 | O78: 0.055 | P78: 0.076 | Q78: 0.05 | R78: -0.021 | S78: 0.1353 | T78: -0.05 | U78: 180.08 | V78: 16.91
A79: Kenya | B79: 4 | C79: 2.7 | D79: 4 | E79: -2.4 | F79: percent | G79: 41760 | H79: Quarterly | K79: Iraq | L79: 223 | M79: 0.0421 | O79: 0.06 | P79: 0.009 | Q79: 0.151 | R79: -0.0555 | S79: 0.3134 | T79: 6.71 | U79: 1162 | V79: 33.42
A80: Latvia | B80: 0.5 | C80: 0.8 | D80: 4.6 | E80: -12 | F80: percent | G80: 41852 | H80: Quarterly | K80: Portugal | L80: 220 | M80: 0.011 | N80: 0.003 | O80: 0.0005 | P80: 0 | Q80: 0.131 | R80: -0.049 | S80: 1.29 | T80: 0.5 | U80: 1.23 | V80: 10.49
A81: Lithuania | B81: 0.5 | C81: 0.9 | D81: 4.2 | E81: -13.1 | F81: percent | G81: 41852 | H81: Quarterly | K81: Ireland | L81: 218 | M81: 0.077 | N81: 0.015 | O81: 0.0005 | P81: 0.002 | Q81: 0.107 | R81: -0.057 | S81: 1.233 | T81: 6.6 | U81: 1.23 | V81: 4.59
A82: Luxembourg | B82: 0.7 | C82: 0.8 | D82: 7.9 | E82: -5.5 | F82: percent | G82: 41760 | H82: Quarterly | K82: Algeria | L82: 210 | M82: 0.027 | N82: 0.031 | O82: 0.04 | P82: 0.068 | Q82: 0.098 | R82: -0.002 | S82: 0.0921 | T82: 8 | U82: 85.69 | V82: 38.29
A83: Macedonia | B83: 3.2 | C83: 3 | D83: 8.2 | E83: -2.4 | F83: percent | G83: 41579 | H83: Quarterly | K83: Qatar | L83: 202 | M83: 0.057 | N83: -0.002 | O83: 0.045 | P83: 0.03 | Q83: 0.003 | R83: 0.189 | S83: 0.3425 | T83: 30.9 | U83: 3.64 | V83: 2.17
A84: Malaysia | B84: 0.9 | C84: 1.9 | D84: 5.9 | E84: -7.6 | F84: percent | G84: 41852 | H84: Quarterly | K84: Peru | L84: 202 | M84: 0.0176 | N84: 0.003 | O84: 0.035 | P84: 0.0316 | Q84: 0.057 | R84: 0.009 | S84: 0.196 | T84: -4.6 | U84: 2.88 | V84: 30.38
A85: Malta | B85: 1.3 | C85: 1.1 | D85: 4.1 | E85: -3.4 | F85: percent | G85: 41760 | H85: Quarterly | K85: Czech Republic | L85: 198 | M85: 0.024 | N85: 0.004 | O85: 0.0005 | P85: 0.007 | Q85: 0.071 | R85: -0.015 | S85: 0.4604 | T85: -1.4 | U85: 22.28 | V85: 10.51
A86: Mauritius | B86: 2.4 | C86: 0.8 | D86: 6.1 | E86: -1.7 | F86: percent | G86: 41760 | H86: Quarterly | K86: Romania | L86: 190 | M86: 0.032 | N86: 0.018 | O86: 0.0275 | P86: 0.014 | Q86: 0.067 | R86: -0.009 | S86: 0.384 | T86: -1.1 | U86: 3.57 | V86: 20.02
A87: Mexico | B87: 0.5 | C87: 0.9 | D87: 2.9 | E87: -6.6 | F87: percent | G87: 41852 | H87: Quarterly | K87: New Zealand | L87: 183 | M87: 0.039 | N87: 0.007 | O87: 0.035 | P87: 0.01 | Q87: 0.054 | R87: -0.021 | S87: 0.359 | T87: -3.4 | U87: 0.77 | V87: 4.5
A88: Moldova | B88: 0.91 | C88: 0.51 | D88: 5.2 | E88: -7.84 | F88: percent | G88: 40483 | H88: Quarterly | K88: Kuwait | L88: 183 | M88: 0.0082 | O88: 0.02 | P88: 0.03 | Q88: 0.0272 | R88: 0.2893 | S88: 0.0528 | T88: 38.8 | U88: 5.05 | V88: 3.82
A89: Mongolia | B89: 7.4 | C89: 11.7 | D89: 17.5 | E89: -9.3 | F89: percent | G89: 41671 | H89: Quarterly | K89: Ukraine | L89: 177 | M89: -0.051 | N89: -0.021 | O89: 0.14 | P89: 0.198 | Q89: 0.086 | R89: -0.0448 | S89: 0.4103 | T89: -9.2 | U89: 14.93 | V89: 45.43
A90: Morocco | B90: 2.3 | C90: 1.7 | D90: 9.3 | E90: 0.5 | F90: percent | G90: 41760 | H90: Quarterly | K90: Vietnam | L90: 171 | M90: 0.0619 | N90: 0.0619 | O90: 0.065 | P90: 0.026 | Q90: 0.0214 | R90: -0.071 | S90: 0.5498 | T90: 6.5 | U90: 21158 | V90: 89.71
A91: Mozambique | B91: 1 | C91: 4.7 | D91: 7.7 | E91: -4.3 | F91: percent | G91: 41760 | H91: Quarterly | K91: Bangladesh | L91: 130 | M91: 0.0601 | N91: 0.0601 | O91: 0.0725 | P91: 0.066 | Q91: 0.045 | R91: -0.04 | S91: 0.18 | T91: 0.4 | U91: 76.22 | V91: 154.7
A92: Namibia | B92: 4.3 | C92: -3.7 | D92: 13.3 | E92: -8.8 | F92: percent | G92: 41214 | H92: Quarterly | K92: Hungary | L92: 126 | M92: 0.032 | N92: 0.005 | O92: 0.021 | P92: -0.004 | Q92: 0.071 | R92: -0.022 | S92: 0.792 | T92: 3 | U92: 247.79 | V92: 9.91
A93: Netherlands | B93: 0.2 | C93: 0.6 | D93: 2 | E93: -2.2 | F93: percent | G93: 41852 | H93: Quarterly | K93: Angola | L93: 122 | M93: 0.051 | N93: 0.074 | O93: 0.09 | P93: 0.0748 | Q93: 0.26 | R93: 0.024 | S93: 0.2929 | T93: 7.3 | U93: 100.95 | V93: 19.18
A94: New Zealand | B94: 0.7 | C94: 1 | D94: 2.9 | E94: -2.6 | F94: percent | G94: 41760 | H94: Quarterly | K94: Morocco | L94: 104 | M94: 0.026 | N94: 0.023 | O94: 0.0275 | P94: 0.006 | Q94: 0.096 | R94: -0.054 | S94: 0.617 | T94: -7.2 | U94: 8.86 | V94: 32.95
A95: Nigeria | B95: 8.67 | C95: 4.18 | D95: 8.99 | E95: -9.88 | F95: percent | G95: 41852 | H95: Quarterly | K95: Puerto Rico | L95: 101 | M95: 0.003 | P95: 0.004 | Q95: 0.14 | U95: 88.96 | V95: 3.67
A96: Norway | B96: 0.5 | C96: 1.1 | D96: 3.6 | E96: -2.6 | F96: percent | G96: 41852 | H96: Quarterly | K96: Slovakia | L96: 92 | M96: 0.024 | N96: 0.006 | O96: 0.0005 | P96: 0 | Q96: 0.1235 | R96: -0.0293 | S96: 0.5494 | T96: 2.1 | U96: 1.23 | V96: 5.41
A97: Pakistan | B97: 5 | C97: 4.1 | D97: 10.22 | E97: -1.8 | F97: percent | G97: 41699 | H97: Yearly | K97: Ecuador | L97: 90 | M97: 0.035 | N97: 0.01 | O97: 0.0834 | P97: 0.0398 | Q97: 0.0571 | R97: -0.04 | S97: 0.244 | T97: -1.3 | U97: 216.3 | V97: 15.74
A98: Paraguay | B98: -0.6 | C98: 2.2 | D98: 10.9 | E98: -5 | F98: percent | G98: 41760 | H98: Quarterly | K98: Oman | L98: 81 | M98: 0.028 | O98: 0.01 | P98: 0.0102 | Q98: 0.15 | R98: -0.003 | S98: 0.049 | T98: 6.4 | U98: 0.38 | V98: 3.63
A99: Peru | B99: 0.3 | C99: 1.7 | D99: 2.9 | E99: -1.3 | F99: percent | G99: 41671 | H99: Quarterly | K99: Libya | L99: 75 | M99: -0.1206 | O99: 0.03 | P99: 0.011 | Q99: 0.195 | R99: -0.093 | S99: 0.068 | T99: 50.3 | U99: 1.19 | V99: 6.2
A100: Philippines | B100: 0.4 | C100: 1.9 | D100: 3.2 | E100: -2.4 | F100: percent | G100: 41852 | H100: Quarterly | K100: Azerbaijan | L100: 74 | M100: 0.025 | O100: 0.035 | P100: 0.015 | Q100: 0.052 | R100: 0.006 | S100: 0.1375 | T100: 16.7 | U100: 0.78 | V100: 9.36
A101: Poland | B101: 0.9 | C101: 0.7 | D101: 6.1 | E101: -3.1 | F101: percent | G101: 41852 | H101: Quarterly | K101: Syria | L101: 74 | M101: -0.023 | P101: 0.044 | Q101: 0.149 | R101: -0.114 | S101: 0.3001 | T101: -0.62 | U101: 174.2 | V101: 22.85
A102: Portugal | B102: 0.3 | C102: 0.3 | D102: 3.3 | E102: -2.6 | F102: percent | G102: 41852 | H102: Quarterly | K102: Belarus | L102: 72 | M102: 0.005 | O102: 0.2 | P102: 0.1938 | Q102: 0.005 | R102: -0.004 | S102: 0.3671 | T102: -9.8 | U102: 10900 | V102: 9.47
A103: Qatar | B103: -0.2 | C103: 2.3 | D103: 14.4 | E103: -23.2 | F103: percent | G103: 41760 | H103: Quarterly | K103: Cuba | L103: 68 | M103: 0.027 | O103: 0.0225 | P103: 0.055 | Q103: 0.033 | R103: -0.012 | S103: 0.211 | T103: 0.9 | U103: 1 | V103: 11.21
A104: Romania | B104: 1.8 | C104: -0.4 | D104: 3.6 | E104: -4.8 | F104: percent | G104: 41852 | H104: Quarterly | K104: Sri Lanka | L104: 67 | M104: 0.078 | N104: 0.078 | O104: 0.065 | P104: 0.015 | Q104: 0.045 | R104: -0.059 | S104: 0.783 | T104: -3.9 | U104: 130.93 | V104: 20.48
A105: Russia | B105: 0.25 | C105: 0.07 | D105: 4.1 | E105: -5.4 | F105: percent | G105: 41760 | H105: Quarterly | K105: Sudan | L105: 67 | M105: 0.036 | O105: 0.121 | P105: 0.282 | Q105: 0.159 | R105: -0.017 | S105: 0.62 | T105: -9.6 | U105: 5.77 | V105: 37.96
A106: Rwanda | B106: 1.06 | C106: -2.1 | D106: 13.4 | E106: 2.2 | F106: percent | G106: 41760 | H106: Quarterly | K106: Dominican Republic | L106: 61 | M106: 0.055 | N106: -0.1344 | O106: 0.0625 | P106: 0.0288 | Q106: 0.149 | R106: -0.0287 | S106: 0.5177 | T106: -3.5 | U106: 44.12 | V106: 10.4
A107: Saudi Arabia | B107: 3.8 | C107: 5.1 | D107: 27.49 | E107: -11.1 | F107: percent | G107: 41760 | H107: Quarterly | K107: Luxembourg | L107: 60 | M107: 0.032 | N107: 0.007 | O107: 0.0005 | P107: 0.0031 | Q107: 0.071 | R107: 0.001 | S107: 0.231 | T107: 5.2 | U107: 1.23 | V107: 0.53
A108: Senegal | B108: 2.1 | C108: -14.8 | D108: 25 | E108: -14.8 | F108: percent | G108: 41760 | H108: Quarterly | K108: Croatia | L108: 58 | M108: -0.005 | N108: -0.003 | O108: 0.05 | P108: 0.0037 | Q108: 0.187 | R108: -0.049 | S108: 0.671 | T108: 1.2 | U108: 6.19 | V108: 4.26
A109: Serbia | B109: -0.3 | C109: -0.5 | D109: 5.2 | E109: -2.7 | F109: percent | G109: 41671 | H109: Quarterly | K109: Uzbekistan | L109: 57 | M109: 0.081 | O109: 0.1 | P109: 0.068 | Q109: 0.048 | R109: -0.009 | S109: 0.0858 | T109: 3.7 | U109: 2401.09 | V109: 30.49
A110: Singapore | B110: 3.1 | C110: -0.3 | D110: 36.4 | E110: -13 | F110: percent | G110: 41852 | H110: Quarterly | K110: Uruguay | L110: 56 | M110: 0.037 | N110: 0.02 | O110: 0.0925 | P110: 0.0805 | Q110: 0.067 | R110: 0.0032 | S110: 0.594 | T110: -5.9 | U110: 23.37 | V110: 3.39
A111: Slovakia | B111: 0.6 | C111: 0.6 | D111: 9 | E111: -7.6 | F111: percent | G111: 41852 | H111: Quarterly | K111: Guatemala | L111: 54 | M111: 0.043 | O111: 0.045 | P111: 0.0364 | Q111: 0.029 | R111: -0.022 | S111: 0.3064 | T111: -2.7 | U111: 7.62 | V111: 15.44
A112: Slovenia | B112: 0.7 | C112: 1 | D112: 4.19 | E112: -6.04 | F112: percent | G112: 41852 | H112: Quarterly | K112: Bulgaria | L112: 53 | M112: 0.015 | N112: 0.004 | O112: 0.0002 | P112: -0.004 | Q112: 0.108 | R112: -0.015 | S112: 0.189 | T112: 1.9 | U112: 1.58 | V112: 7.25
A113: South Africa | B113: 1.4 | C113: 0.5 | D113: 7.6 | E113: -6.1 | F113: percent | G113: 41852 | H113: Quarterly | K113: Myanmar | L113: 53 | M113: 0.065 | O113: 0.1 | P113: 0.0417 | Q113: 0.0402 | R113: -0.049 | S113: 0.4266 | T113: -4.8 | U113: 1038 | V113: 53.26
A114: South Korea | B114: 0.9 | C114: 0.5 | D114: 6.8 | E114: -7 | F114: percent | G114: 41852 | H114: Quarterly | K114: Macao | L114: 52 | M114: -0.021 | O114: 0.005 | P114: 0.0582 | Q114: 0.017 | T114: 42.93 | U114: 7.98 | V114: 0.6
A115: Spain | B115: 0.5 | C115: 0.5 | D115: 1.53 | E115: -1.6 | F115: percent | G115: 41852 | H115: Quarterly | K115: Costa Rica | L115: 50 | M115: 0.0382 | N115: 0.0088 | O115: 0.0525 | P115: 0.057 | Q115: 0.09 | R115: -0.054 | S115: 0.5545 | T115: -5.1 | U115: 535.75 | V115: 4.71
A116: Sri Lanka | B116: 7.8 | C116: 7.6 | D116: 8.6 | E116: 1.5 | F116: percent | G116: 41760 | H116: Quarterly | K116: Ghana | L116: 48 | M116: 0.053 | N116: 0.033 | O116: 0.21 | P116: 0.169 | Q116: 0.129 | R116: -0.101 | S116: 0.449 | T116: -12.3 | U116: 3.2 | V116: 25.91
A117: Sweden | B117: 0.3 | C117: 0.5 | D117: 2.8 | E117: -3.8 | F117: percent | G117: 41852 | H117: Quarterly | K117: Ethiopia | L117: 47 | M117: 0.104 | O117: 0.05 | P117: 0.054 | Q117: 0.175 | R117: -0.02 | S117: 0.257 | T117: -3 | U117: 20.34 | V117: 94.1
A118: Switzerland | B118: 0.6 | C118: 0.3 | D118: 1.9 | E118: -2.2 | F118: percent | G118: 41852 | H118: Quarterly | K118: Tunisia | L118: 47 | M118: 0.02 | N118: 0.002 | O118: 0.0475 | P118: 0.054 | Q118: 0.152 | R118: -0.062 | S118: 0.4438 | T118: -8.2 | U118: 1.85 | V118: 10.89
A119: Taiwan | B119: 0.66 | C119: 0.86 | D119: 5.64 | E119: -5.07 | F119: percent | G119: 41852 | H119: Quarterly | K119: Slovenia | L119: 45 | M119: 0.032 | N119: 0.007 | O119: 0.0005 | P119: -0.002 | Q119: 0.123 | R119: -0.147 | S119: 0.717 | T119: 6.3 | U119: 1.23 | V119: 2.06
A120: Tanzania | B120: 1.5 | C120: 1.6 | D120: 12.4 | E120: -14 | F120: percent | G120: 40391 | H120: Quarterly | K120: Lebanon | L120: 44 | M120: 0.01 | O120: 0.1 | P120: 0.0147 | Q120: 0.0889 | R120: 0.0621 | S120: 1.459 | T120: -16.18 | U120: 1512.5 | V120: 4.47
A121: Thailand | B121: 1.1 | C121: 1.1 | D121: 11.4 | E121: -11.1 | F121: percent | G121: 41852 | H121: Quarterly | K121: Kenya | L121: 44 | M121: 0.058 | N121: 0.04 | O121: 0.085 | P121: 0.0609 | Q121: 0.4 | R121: -0.048 | S121: 0.517 | T121: -8.2 | U121: 88.76 | V121: 44.35
A122: Tunisia | B122: 0.2 | C122: 0.6 | D122: 4.6 | E122: -7.8 | F122: percent | G122: 41760 | H122: Quarterly | K122: Panama | L122: 43 | M122: 0.063 | O122: 0.0094 | P122: 0.021 | Q122: 0.041 | R122: -0.044 | S122: 0.413 | T122: -11.9 | U122: 0.98 | V122: 3.86
A123: Turkey | B123: -0.5 | C123: 1.8 | D123: 6.69 | E123: -7.57 | F123: percent | G123: 41760 | H123: Quarterly | K123: Serbia | L123: 43 | M123: -0.036 | N123: -0.003 | O123: 0.08 | P123: 0.018 | Q123: 0.176 | R123: -0.048 | S123: 0.638 | T123: -5 | U123: 96.96 | V123: 7.18
A124: Uganda | B124: 2.37 | C124: 0.47 | D124: 6.22 | E124: -2.79 | F124: percent | G124: 41671 | H124: Quarterly | K124: Lithuania | L124: 42 | M124: 0.026 | N124: 0.005 | O124: 0.003 | P124: 0.001 | Q124: 0.124 | R124: -0.022 | S124: 0.394 | T124: 1.5 | U124: 2.75 | V124: 2.94
A125: Ukraine | B125: -2.1 | C125: -2.3 | D125: 3.9 | E125: -2.3 | F125: percent | G125: 41852 | H125: Quarterly | K125: Turkmenistan | L125: 42 | M125: 0.103 | P125: 0.06 | Q125: 0.026 | R125: 0.015 | S125: 0.2065 | T125: 0.5 | U125: 2.85 | V125: 5.24
A126: United Arab Emirates | B126: 5.2 | C126: 4.4 | D126: 9.8 | E126: -4.8 | F126: percent | G126: 41609 | H126: Yearly | K126: Yemen | L126: 36 | M126: 0.044 | O126: 0.15 | P126: 0.1 | Q126: 0.29 | R126: -0.058 | S126: 0.4995 | T126: -4.5 | U126: 214.75 | V126: 24.41
A127: United Kingdom | B127: 0.7 | C127: 0.9 | D127: 5 | E127: -2.7 | F127: percent | G127: 41852 | H127: Quarterly | K127: Jordan | L127: 34 | M127: 0.028 | O127: 0.0425 | P127: 0.027 | Q127: 0.12 | R127: -0.055 | S127: 0.8775 | T127: -12.1 | U127: 0.7 | V127: 6.53
A128: United States | B128: 3.9 | C128: 4.6 | D128: 16.9 | E128: -10 | F128: percent | G128: 41852 | H128: Quarterly | K128: Bahrain | L128: 33 | M128: 0.0562 | N128: 0.0228 | O128: 0.0225 | P128: 0.026 | Q128: 0.037 | R128: -0.055 | S128: 0.4387 | T128: 7.8 | U128: 0.37 | V128: 1.33
A129: Uruguay | B129: 2 | C129: -0.4 | D129: 3.3 | E129: -2.1 | F129: percent | G129: 41760 | H129: Quarterly | K129: Tanzania | L129: 33 | M129: 0.069 | N129: 0.015 | O129: 0.12 | P129: 0.059 | Q129: 0.107 | R129: -0.089 | S129: 0.399 | T129: -10.1 | U129: 1713.5 | V129: 49.25
A130: Venezuela | B130: 6.8 | C130: 0 | D130: 22.7 | E130: -15.3 | F130: percent | G130: 41579 | H130: Quarterly | K130: Congo | L130: 31 | M130: 0.087 | O130: 0.02 | P130: 0.0148 | Q130: 0.461 | R130: -0.037 | S130: 0.47 | T130: -9.1 | U130: 925 | V130: 67.51
A131: Vietnam | B131: 6.19 | C131: 5.42 | D131: 8.46 | E131: 3.14 | F131: percent | G131: 41852 | H131: Quarterly | K131: Bolivia | L131: 31 | M131: 0.0465 | N131: -0.0743 | O131: 0.0306 | P131: 0.0364 | Q131: 0.075 | R131: 0.0083 | S131: 0.3309 | T131: 3.3 | U131: 6.78 | V131: 10.67
K132: Ivory Coast | L132: 31 | M132: 0.099 | O132: 0.035 | P132: 0.006 | Q132: 0.157 | R132: -0.02 | S132: 0.541 | T132: -1.7 | U132: 532.36 | V132: 20.32
K133: Paraguay | L133: 30 | M133: 0.03 | N133: -0.006 | O133: 0.0675 | P133: 0.035 | Q133: 0.079 | R133: -0.004 | S133: 0.1516 | T133: 0.8 | U133: 4539.7 | V133: 6.7
...
